Workbook
Name Limite_descuento: #REF!

Sheet Ventas
A1: Referencia de la orden | B1: Fecha de la orden | C1: Cliente | D1: Vendedor | E1: Términos de pago | F1: Lista de precios/ID | G1: Lista de precios/Nombre de la lista de precios | H1: Líneas de la orden/Producto/Categoría del producto | I1: Líneas de la orden/Producto/Referencia interna | J1: Líneas de la orden/Producto/Nombre en pantalla | K1: Líneas de la orden/Precio unitario | L1: Líneas de la orden/Subtotal | M1: Líneas de la orden/Cantidad | N1: Líneas de la orden/Descuento (%) | O1: Subtotal Orden | P1: Total Orden | Q1: Factura Nro | R1: Factura Fecha | S1: Factura Producto | T1: Factura Precio Unitario $ | U1: Factura Cantidad | V1: Factura Descuento % | W1: Factura Total $ | X1: Pago Nro | Y1: Pago ID | Z1: Pago Fecha | AA1: Pago Moneda | AB1: Pago Importe Firmado | AC1: Pago Método / Diario | AD1: Descuento Diferencial % | AE1: Descuento Pronto Pago % | AF1: Otros Descuentos % | AG1: Descuento Total Aplicado % | AH1: Total Orden con Descuentos | AI1: Total Factura con Descuentos | AJ1: Monto Pagado Total USD | AK1: Saldo Deudor sobre Orden | AL1: Saldo Deudor sobre Factura | AM1: Diferencia de Totales Orden vs Factura | AN1: ID Número de Orden | AO1: Validación Diferencial | AP1: Validación Pronto Pago | AQ1: Validación Descuento Previo | AR1: Validación General
A2: =IF('Ordenes_Odoo'!A2="","",'Ordenes_Odoo'!A2) | B2: =IF('Ordenes_Odoo'!B2="","",'Ordenes_Odoo'!B2) | C2: =IF('Ordenes_Odoo'!C2="","",'Ordenes_Odoo'!C2) | D2: =IF('Ordenes_Odoo'!D2="","",'Ordenes_Odoo'!D2) | E2: =IF('Ordenes_Odoo'!E2="","",'Ordenes_Odoo'!E2) | F2: =IF('Ordenes_Odoo'!F2="","",'Ordenes_Odoo'!F2) | G2: =IF('Ordenes_Odoo'!G2="","",'Ordenes_Odoo'!G2) | H2: =IF('Ordenes_Odoo'!H2="","",'Ordenes_Odoo'!H2) | ... P2: =IF('Ordenes_Odoo'!P2="","",'Ordenes_Odoo'!P2) | Q2: =IF(A2="","",IFERROR(INDEX(Facturas_Odoo!$B:$B, MATCH(A2, Facturas_Odoo!$D:$D, 0)), "Sin Factura")) | R2: =IF(Q2="Sin Factura","",IFERROR(INDEX(Facturas_Odoo!$A:$A, MATCH(Q2, Facturas_Odoo!$B:$B, 0)), "")) | S2: =IF(Q2="Sin Factura","",IFERROR(_xlfn.XLOOKUP(1, (Facturas_Odoo!$D:$D=A2) * (Facturas_Odoo!$K:$K=I2), Facturas_Odoo!$L:$L, ""), "")) | T2: =IF(Q2="Sin Factura",0,IFERROR(_xlfn.XLOOKUP(1, (Facturas_Odoo!$D:$D=A2) * (Facturas_Odoo!$K:$K=I2), Facturas_Odoo!$M:$M, 0), 0)) | U2: =IF(Q2="Sin Factura",0,IFERROR(_xlfn.XLOOKUP(1, (Facturas_Odoo!$D:$D=A2) * (Facturas_Odoo!$K:$K=I2), Facturas_Odoo!$N:$N, 0), 0)) | V2: =IF(Q2="Sin Factura",0,IFERROR(_xlfn.XLOOKUP(1, (Facturas_Odoo!$D:$D=A2) * (Facturas_Odoo!$K:$K=I2), Facturas_Odoo!$O:$O, 0), 0)) | W2: =IF(Q2="Sin Factura",0,IFERROR(_xlfn.XLOOKUP(1, (Facturas_Odoo!$D:$D=A2) * (Facturas_Odoo!$K:$K=I2), Facturas_Odoo!$Q:$Q, 0), 0)) | X2: =IF(OR(Q2="Sin Factura",Q2=""),"",IFERROR(INDEX(Pagos_Odoo!$B:$B, MATCH(Q2, Pagos_Odoo!$I:$I, 0)), "Sin Pago")) | Y2: =IF(X2="Sin Pago","",IFERROR(INDEX(Pagos_Odoo!$C:$C, MATCH(X2, Pagos_Odoo!$B:$B, 0)), "")) | Z2: =IF(X2="Sin Pago","",IFERROR(INDEX(Pagos_Odoo!$A:$A, MATCH(X2, Pagos_Odoo!$B:$B, 0)), "")) | AA2: =IF(X2="Sin Pago","",IFERROR(INDEX(Pagos_Odoo!$F:$F, MATCH(X2, Pagos_Odoo!$B:$B, 0)), "")) | AB2: =IF(X2="Sin Pago",0,IFERROR(INDEX(Pagos_Odoo!$E:$E, MATCH(X2, Pagos_Odoo!$B:$B, 0)), 0)) | AC2: =IF(X2="Sin Pago","",IFERROR(INDEX(Pagos_Odoo!$G:$G, MATCH(X2, Pagos_Odoo!$B:$B, 0)), "")) | AD2: 0 | AG2: =IF(AN2="","",AD2+AE2+AF2) | AH2: =IF(AN2="","",P2*(1-AG2)) | AI2: =IF(AN2="","",IF(Q2="Sin Factura",0,IFERROR(INDEX(Facturas_Odoo!$H:$H, MATCH(Q2, Facturas_Odoo!$B:$B, 0)), 0)*(1-AG2))) | AJ2: =IF(AN2="","",_xlfn.LET(idVenta, AN2&"", pagos, IFERROR(SUMIF(Aux_Datos!$B:$B, idVenta, Aux_Datos!$L:$L), 0), retenciones, IFERROR(SUMIF(Aux_Datos!$O:$O, idVenta, Aux_Datos!$S:$S), 0), pagos_manuales, IFERROR(SUMIF('Asignación Pagos'!$G:$G, idVenta, 'Asignación Pagos'!$F:$F), 0), pagos+retenciones+pagos_manuales)) | AK2: =IF(AN2="","",AH2-AJ2) | AL2: =IF(AN2="","",IF(Q2="Sin Factura","",AI2-AJ2)) | AM2: =IF(AN2="","",IF(Q2="Sin Factura",0,P2-IFERROR(INDEX(Facturas_Odoo!$H:$H, MATCH(Q2, Facturas_Odoo!$B:$B, 0)), 0))) | AN2: =VALUE(MID(A2,2,LEN(A2))) | AO2: =IF(AN2="","",IF(AD2=0,"OK",_xlfn.LET(monedaPago, IF(AA2="","USD",AA2), limitePermitido, IFERROR(VLOOKUP(monedaPago, Configuración!$A$2:$B$3, 2, FALSE), 0.15), IF(AD2>limitePermitido, "ALERTA: EXCESO (" & TEXT(limitePermitido, "0%") & " máx)", "OK")))) | AP2: =IF(AN2="","",IF(AE2=0,"OK",_xlfn.LET(fechaPago, Z2, fechaFactura, R2, diasCredito, IF(E2="Pago inmediato", 0, IFERROR(VALUE(MID(E2, 1, SEARCH(" ", E2)-1)), 0)), tolerancia, Configuración!$E$2, limiteDias, diasCredito + tolerancia, IF(OR(fechaPago="", fechaFactura=""), "REVISAR: SIN FECHA", IF(fechaPago - fechaFactura > limiteDias, "ALERTA: PAGO FUERA DE PLAZO (" & (fechaPago - fechaFactura) & " días)", "OK"))))) | AQ2: =IF(AN2="","",IF(AND(N2>0, AG2>0), IF(Configuración!$K$2="NO", "ALERTA: DESCUENTO DOBLE NO PERMITIDO", "OK"), "OK")) | AR2: =IF(AN2="","",IF(OR(AO2<>"OK", AP2<>"OK", AQ2<>"OK"), "⚠️ REVISAR", "OK"))
A3: =IF('Ordenes_Odoo'!A3="","",'Ordenes_Odoo'!A3) | B3: =IF('Ordenes_Odoo'!B3="","",'Ordenes_Odoo'!B3) | C3: =IF('Ordenes_Odoo'!C3="","",'Ordenes_Odoo'!C3) | D3: =IF('Ordenes_Odoo'!D3="","",'Ordenes_Odoo'!D3) | E3: =IF('Ordenes_Odoo'!E3="","",'Ordenes_Odoo'!E3) | F3: =IF('Ordenes_Odoo'!F3="","",'Ordenes_Odoo'!F3) | G3: =IF('Ordenes_Odoo'!G3="","",'Ordenes_Odoo'!G3) | H3: =IF('Ordenes_Odoo'!H3="","",'Ordenes_Odoo'!H3) | ... P3: =IF('Ordenes_Odoo'!P3="","",'Ordenes_Odoo'!P3) | Q3: =IF(A3="","",IFERROR(INDEX(Facturas_Odoo!$B:$B, MATCH(A3, Facturas_Odoo!$D:$D, 0)), "Sin Factura")) | R3: =IF(Q3="Sin Factura","",IFERROR(INDEX(Facturas_Odoo!$A:$A, MATCH(Q3, Facturas_Odoo!$B:$B, 0)), "")) | S3: =IF(Q3="Sin Factura","",IFERROR(_xlfn.XLOOKUP(1, (Facturas_Odoo!$D:$D=A3) * (Facturas_Odoo!$K:$K=I3), Facturas_Odoo!$L:$L, ""), "")) | T3: =IF(Q3="Sin Factura",0,IFERROR(_xlfn.XLOOKUP(1, (Facturas_Odoo!$D:$D=A3) * (Facturas_Odoo!$K:$K=I3), Facturas_Odoo!$M:$M, 0), 0)) | U3: =IF(Q3="Sin Factura",0,IFERROR(_xlfn.XLOOKUP(1, (Facturas_Odoo!$D:$D=A3) * (Facturas_Odoo!$K:$K=I3), Facturas_Odoo!$N:$N, 0), 0)) | V3: =IF(Q3="Sin Factura",0,IFERROR(_xlfn.XLOOKUP(1, (Facturas_Odoo!$D:$D=A3) * (Facturas_Odoo!$K:$K=I3), Facturas_Odoo!$O:$O, 0), 0)) | W3: =IF(Q3="Sin Factura",0,IFERROR(_xlfn.XLOOKUP(1, (Facturas_Odoo!$D:$D=A3) * (Facturas_Odoo!$K:$K=I3), Facturas_Odoo!$Q:$Q, 0), 0)) | X3: =IF(OR(Q3="Sin Factura",Q3=""),"",IFERROR(INDEX(Pagos_Odoo!$B:$B, MATCH(Q3, Pagos_Odoo!$I:$I, 0)), "Sin Pago")) | Y3: =IF(X3="Sin Pago","",IFERROR(INDEX(Pagos_Odoo!$C:$C, MATCH(X3, Pagos_Odoo!$B:$B, 0)), "")) | Z3: =IF(X3="Sin Pago","",IFERROR(INDEX(Pagos_Odoo!$A:$A, MATCH(X3, Pagos_Odoo!$B:$B, 0)), "")) | AA3: =IF(X3="Sin Pago","",IFERROR(INDEX(Pagos_Odoo!$F:$F, MATCH(X3, Pagos_Odoo!$B:$B, 0)), "")) | AB3: =IF(X3="Sin Pago",0,IFERROR(INDEX(Pagos_Odoo!$E:$E, MATCH(X3, Pagos_Odoo!$B:$B, 0)), 0)) | AC3: =IF(X3="Sin Pago","",IFERROR(INDEX(Pagos_Odoo!$G:$G, MATCH(X3, Pagos_Odoo!$B:$B, 0)), "")) | AD3: 0 | AG3: =IF(AN3="","",AD3+AE3+AF3) | AH3: =IF(AN3="","",P3*(1-AG3)) | AI3: =IF(AN3="","",IF(Q3="Sin Factura",0,IFERROR(INDEX(Facturas_Odoo!$H:$H, MATCH(Q3, Facturas_Odoo!$B:$B, 0)), 0)*(1-AG3))) | AJ3: =IF(AN3="","",_xlfn.LET(idVenta, AN3&"", pagos, IFERROR(SUMIF(Aux_Datos!$B:$B, idVenta, Aux_Datos!$L:$L), 0), retenciones, IFERROR(SUMIF(Aux_Datos!$O:$O, idVenta, Aux_Datos!$S:$S), 0), pagos_manuales, IFERROR(SUMIF('Asignación Pagos'!$G:$G, idVenta, 'Asignación Pagos'!$F:$F), 0), pagos+retenciones+pagos_manuales)) | AK3: =IF(AN3="","",AH3-AJ3) | AL3: =IF(AN3="","",IF(Q3="Sin Factura","",AI3-AJ3)) | AM3: =IF(AN3="","",IF(Q3="Sin Factura",0,P3-IFERROR(INDEX(Facturas_Odoo!$H:$H, MATCH(Q3, Facturas_Odoo!$B:$B, 0)), 0))) | AN3: =IF(AND(A3="", J3=""), "", IF(A3<>"", VALUE(MID(A3,2,LEN(A3))), AN2)) | AO3: =IF(AN3="","",IF(AD3=0,"OK",_xlfn.LET(monedaPago, IF(AA3="","USD",AA3), limitePermitido, IFERROR(VLOOKUP(monedaPago, Configuración!$A$2:$B$3, 2, FALSE), 0.15), IF(AD3>limitePermitido, "ALERTA: EXCESO (" & TEXT(limitePermitido, "0%") & " máx)", "OK")))) | AP3: =IF(AN3="","",IF(AE3=0,"OK",_xlfn.LET(fechaPago, Z3, fechaFactura, R3, diasCredito, IF(E3="Pago inmediato", 0, IFERROR(VALUE(MID(E3, 1, SEARCH(" ", E3)-1)), 0)), tolerancia, Configuración!$E$2, limiteDias, diasCredito + tolerancia, IF(OR(fechaPago="", fechaFactura=""), "REVISAR: SIN FECHA", IF(fechaPago - fechaFactura > limiteDias, "ALERTA: PAGO FUERA DE PLAZO (" & (fechaPago - fechaFactura) & " días)", "OK"))))) | AQ3: =IF(AN3="","",IF(AND(N3>0, AG3>0), IF(Configuración!$K$2="NO", "ALERTA: DESCUENTO DOBLE NO PERMITIDO", "OK"), "OK")) | AR3: =IF(AN3="","",IF(OR(AO3<>"OK", AP3<>"OK", AQ3<>"OK"), "⚠️ REVISAR", "OK"))
A4: =IF('Ordenes_Odoo'!A4="","",'Ordenes_Odoo'!A4) | B4: =IF('Ordenes_Odoo'!B4="","",'Ordenes_Odoo'!B4) | C4: =IF('Ordenes_Odoo'!C4="","",'Ordenes_Odoo'!C4) | D4: =IF('Ordenes_Odoo'!D4="","",'Ordenes_Odoo'!D4) | E4: =IF('Ordenes_Odoo'!E4="","",'Ordenes_Odoo'!E4) | F4: =IF('Ordenes_Odoo'!F4="","",'Ordenes_Odoo'!F4) | G4: =IF('Ordenes_Odoo'!G4="","",'Ordenes_Odoo'!G4) | H4: =IF('Ordenes_Odoo'!H4="","",'Ordenes_Odoo'!H4) | ... P4: =IF('Ordenes_Odoo'!P4="","",'Ordenes_Odoo'!P4) | Q4: =IF(A4="","",IFERROR(INDEX(Facturas_Odoo!$B:$B, MATCH(A4, Facturas_Odoo!$D:$D, 0)), "Sin Factura")) | R4: =IF(Q4="Sin Factura","",IFERROR(INDEX(Facturas_Odoo!$A:$A, MATCH(Q4, Facturas_Odoo!$B:$B, 0)), "")) | S4: =IF(Q4="Sin Factura","",IFERROR(_xlfn.XLOOKUP(1, (Facturas_Odoo!$D:$D=A4) * (Facturas_Odoo!$K:$K=I4), Facturas_Odoo!$L:$L, ""), "")) | T4: =IF(Q4="Sin Factura",0,IFERROR(_xlfn.XLOOKUP(1, (Facturas_Odoo!$D:$D=A4) * (Facturas_Odoo!$K:$K=I4), Facturas_Odoo!$M:$M, 0), 0)) | U4: =IF(Q4="Sin Factura",0,IFERROR(_xlfn.XLOOKUP(1, (Facturas_Odoo!$D:$D=A4) * (Facturas_Odoo!$K:$K=I4), Facturas_Odoo!$N:$N, 0), 0)) | V4: =IF(Q4="Sin Factura",0,IFERROR(_xlfn.XLOOKUP(1, (Facturas_Odoo!$D:$D=A4) * (Facturas_Odoo!$K:$K=I4), Facturas_Odoo!$O:$O, 0), 0)) | W4: =IF(Q4="Sin Factura",0,IFERROR(_xlfn.XLOOKUP(1, (Facturas_Odoo!$D:$D=A4) * (Facturas_Odoo!$K:$K=I4), Facturas_Odoo!$Q:$Q, 0), 0)) | X4: =IF(OR(Q4="Sin Factura",Q4=""),"",IFERROR(INDEX(Pagos_Odoo!$B:$B, MATCH(Q4, Pagos_Odoo!$I:$I, 0)), "Sin Pago")) | Y4: =IF(X4="Sin Pago","",IFERROR(INDEX(Pagos_Odoo!$C:$C, MATCH(X4, Pagos_Odoo!$B:$B, 0)), "")) | Z4: =IF(X4="Sin Pago","",IFERROR(INDEX(Pagos_Odoo!$A:$A, MATCH(X4, Pagos_Odoo!$B:$B, 0)), "")) | AA4: =IF(X4="Sin Pago","",IFERROR(INDEX(Pagos_Odoo!$F:$F, MATCH(X4, Pagos_Odoo!$B:$B, 0)), "")) | AB4: =IF(X4="Sin Pago",0,IFERROR(INDEX(Pagos_Odoo!$E:$E, MATCH(X4, Pagos_Odoo!$B:$B, 0)), 0)) | AC4: =IF(X4="Sin Pago","",IFERROR(INDEX(Pagos_Odoo!$G:$G, MATCH(X4, Pagos_Odoo!$B:$B, 0)), "")) | AD4: 0 | AG4: =IF(AN4="","",AD4+AE4+AF4) | AH4: =IF(AN4="","",P4*(1-AG4)) | AI4: =IF(AN4="","",IF(Q4="Sin Factura",0,IFERROR(INDEX(Facturas_Odoo!$H:$H, MATCH(Q4, Facturas_Odoo!$B:$B, 0)), 0)*(1-AG4))) | AJ4: =IF(AN4="","",_xlfn.LET(idVenta, AN4&"", pagos, IFERROR(SUMIF(Aux_Datos!$B:$B, idVenta, Aux_Datos!$L:$L), 0), retenciones, IFERROR(SUMIF(Aux_Datos!$O:$O, idVenta, Aux_Datos!$S:$S), 0), pagos_manuales, IFERROR(SUMIF('Asignación Pagos'!$G:$G, idVenta, 'Asignación Pagos'!$F:$F), 0), pagos+retenciones+pagos_manuales)) | AK4: =IF(AN4="","",AH4-AJ4) | AL4: =IF(AN4="","",IF(Q4="Sin Factura","",AI4-AJ4)) | AM4: =IF(AN4="","",IF(Q4="Sin Factura",0,P4-IFERROR(INDEX(Facturas_Odoo!$H:$H, MATCH(Q4, Facturas_Odoo!$B:$B, 0)), 0))) | AN4: =IF(AND(A4="", J4=""), "", IF(A4<>"", VALUE(MID(A4,2,LEN(A4))), AN3)) | AO4: =IF(AN4="","",IF(AD4=0,"OK",_xlfn.LET(monedaPago, IF(AA4="","USD",AA4), limitePermitido, IFERROR(VLOOKUP(monedaPago, Configuración!$A$2:$B$3, 2, FALSE), 0.15), IF(AD4>limitePermitido, "ALERTA: EXCESO (" & TEXT(limitePermitido, "0%") & " máx)", "OK")))) | AP4: =IF(AN4="","",IF(AE4=0,"OK",_xlfn.LET(fechaPago, Z4, fechaFactura, R4, diasCredito, IF(E4="Pago inmediato", 0, IFERROR(VALUE(MID(E4, 1, SEARCH(" ", E4)-1)), 0)), tolerancia, Configuración!$E$2, limiteDias, diasCredito + tolerancia, IF(OR(fechaPago="", fechaFactura=""), "REVISAR: SIN FECHA", IF(fechaPago - fechaFactura > limiteDias, "ALERTA: PAGO FUERA DE PLAZO (" & (fechaPago - fechaFactura) & " días)", "OK"))))) | AQ4: =IF(AN4="","",IF(AND(N4>0, AG4>0), IF(Configuración!$K$2="NO", "ALERTA: DESCUENTO DOBLE NO PERMITIDO", "OK"), "OK")) | AR4: =IF(AN4="","",IF(OR(AO4<>"OK", AP4<>"OK", AQ4<>"OK"), "⚠️ REVISAR", "OK"))
A5: =IF('Ordenes_Odoo'!A5="","",'Ordenes_Odoo'!A5) | B5: =IF('Ordenes_Odoo'!B5="","",'Ordenes_Odoo'!B5) | C5: =IF('Ordenes_Odoo'!C5="","",'Ordenes_Odoo'!C5) | D5: =IF('Ordenes_Odoo'!D5="","",'Ordenes_Odoo'!D5) | E5: =IF('Ordenes_Odoo'!E5="","",'Ordenes_Odoo'!E5) | F5: =IF('Ordenes_Odoo'!F5="","",'Ordenes_Odoo'!F5) | G5: =IF('Ordenes_Odoo'!G5="","",'Ordenes_Odoo'!G5) | H5: =IF('Ordenes_Odoo'!H5="","",'Ordenes_Odoo'!H5) | ... P5: =IF('Ordenes_Odoo'!P5="","",'Ordenes_Odoo'!P5) | Q5: =IF(A5="","",IFERROR(INDEX(Facturas_Odoo!$B:$B, MATCH(A5, Facturas_Odoo!$D:$D, 0)), "Sin Factura")) | R5: =IF(Q5="Sin Factura","",IFERROR(INDEX(Facturas_Odoo!$A:$A, MATCH(Q5, Facturas_Odoo!$B:$B, 0)), "")) | S5: =IF(Q5="Sin Factura","",IFERROR(_xlfn.XLOOKUP(1, (Facturas_Odoo!$D:$D=A5) * (Facturas_Odoo!$K:$K=I5), Facturas_Odoo!$L:$L, ""), "")) | T5: =IF(Q5="Sin Factura",0,IFERROR(_xlfn.XLOOKUP(1, (Facturas_Odoo!$D:$D=A5) * (Facturas_Odoo!$K:$K=I5), Facturas_Odoo!$M:$M, 0), 0)) | U5: =IF(Q5="Sin Factura",0,IFERROR(_xlfn.XLOOKUP(1, (Facturas_Odoo!$D:$D=A5) * (Facturas_Odoo!$K:$K=I5), Facturas_Odoo!$N:$N, 0), 0)) | V5: =IF(Q5="Sin Factura",0,IFERROR(_xlfn.XLOOKUP(1, (Facturas_Odoo!$D:$D=A5) * (Facturas_Odoo!$K:$K=I5), Facturas_Odoo!$O:$O, 0), 0)) | W5: =IF(Q5="Sin Factura",0,IFERROR(_xlfn.XLOOKUP(1, (Facturas_Odoo!$D:$D=A5) * (Facturas_Odoo!$K:$K=I5), Facturas_Odoo!$Q:$Q, 0), 0)) | X5: =IF(OR(Q5="Sin Factura",Q5=""),"",IFERROR(INDEX(Pagos_Odoo!$B:$B, MATCH(Q5, Pagos_Odoo!$I:$I, 0)), "Sin Pago")) | Y5: =IF(X5="Sin Pago","",IFERROR(INDEX(Pagos_Odoo!$C:$C, MATCH(X5, Pagos_Odoo!$B:$B, 0)), "")) | Z5: =IF(X5="Sin Pago","",IFERROR(INDEX(Pagos_Odoo!$A:$A, MATCH(X5, Pagos_Odoo!$B:$B, 0)), "")) | AA5: =IF(X5="Sin Pago","",IFERROR(INDEX(Pagos_Odoo!$F:$F, MATCH(X5, Pagos_Odoo!$B:$B, 0)), "")) | AB5: =IF(X5="Sin Pago",0,IFERROR(INDEX(Pagos_Odoo!$E:$E, MATCH(X5, Pagos_Odoo!$B:$B, 0)), 0)) | AC5: =IF(X5="Sin Pago","",IFERROR(INDEX(Pagos_Odoo!$G:$G, MATCH(X5, Pagos_Odoo!$B:$B, 0)), "")) | AD5: 0 | AG5: =IF(AN5="","",AD5+AE5+AF5) | AH5: =IF(AN5="","",P5*(1-AG5)) | AI5: =IF(AN5="","",IF(Q5="Sin Factura",0,IFERROR(INDEX(Facturas_Odoo!$H:$H, MATCH(Q5, Facturas_Odoo!$B:$B, 0)), 0)*(1-AG5))) | AJ5: =IF(AN5="","",_xlfn.LET(idVenta, AN5&"", pagos, IFERROR(SUMIF(Aux_Datos!$B:$B, idVenta, Aux_Datos!$L:$L), 0), retenciones, IFERROR(SUMIF(Aux_Datos!$O:$O, idVenta, Aux_Datos!$S:$S), 0), pagos_manuales, IFERROR(SUMIF('Asignación Pagos'!$G:$G, idVenta, 'Asignación Pagos'!$F:$F), 0), pagos+retenciones+pagos_manuales)) | AK5: =IF(AN5="","",AH5-AJ5) | AL5: =IF(AN5="","",IF(Q5="Sin Factura","",AI5-AJ5)) | AM5: =IF(AN5="","",IF(Q5="Sin Factura",0,P5-IFERROR(INDEX(Facturas_Odoo!$H:$H, MATCH(Q5, Facturas_Odoo!$B:$B, 0)), 0))) | AN5: =IF(AND(A5="", J5=""), "", IF(A5<>"", VALUE(MID(A5,2,LEN(A5))), AN4)) | AO5: =IF(AN5="","",IF(AD5=0,"OK",_xlfn.LET(monedaPago, IF(AA5="","USD",AA5), limitePermitido, IFERROR(VLOOKUP(monedaPago, Configuración!$A$2:$B$3, 2, FALSE), 0.15), IF(AD5>limitePermitido, "ALERTA: EXCESO (" & TEXT(limitePermitido, "0%") & " máx)", "OK")))) | AP5: =IF(AN5="","",IF(AE5=0,"OK",_xlfn.LET(fechaPago, Z5, fechaFactura, R5, diasCredito, IF(E5="Pago inmediato", 0, IFERROR(VALUE(MID(E5, 1, SEARCH(" ", E5)-1)), 0)), tolerancia, Configuración!$E$2, limiteDias, diasCredito + tolerancia, IF(OR(fechaPago="", fechaFactura=""), "REVISAR: SIN FECHA", IF(fechaPago - fechaFactura > limiteDias, "ALERTA: PAGO FUERA DE PLAZO (" & (fechaPago - fechaFactura) & " días)", "OK"))))) | AQ5: =IF(AN5="","",IF(AND(N5>0, AG5>0), IF(Configuración!$K$2="NO", "ALERTA: DESCUENTO DOBLE NO PERMITIDO", "OK"), "OK")) | AR5: =IF(AN5="","",IF(OR(AO5<>"OK", AP5<>"OK", AQ5<>"OK"), "⚠️ REVISAR", "OK"))
A6: =IF('Ordenes_Odoo'!A6="","",'Ordenes_Odoo'!A6) | B6: =IF('Ordenes_Odoo'!B6="","",'Ordenes_Odoo'!B6) | C6: =IF('Ordenes_Odoo'!C6="","",'Ordenes_Odoo'!C6) | D6: =IF('Ordenes_Odoo'!D6="","",'Ordenes_Odoo'!D6) | E6: =IF('Ordenes_Odoo'!E6="","",'Ordenes_Odoo'!E6) | F6: =IF('Ordenes_Odoo'!F6="","",'Ordenes_Odoo'!F6) | G6: =IF('Ordenes_Odoo'!G6="","",'Ordenes_Odoo'!G6) | H6: =IF('Ordenes_Odoo'!H6="","",'Ordenes_Odoo'!H6) | ... P6: =IF('Ordenes_Odoo'!P6="","",'Ordenes_Odoo'!P6) | Q6: =IF(A6="","",IFERROR(INDEX(Facturas_Odoo!$B:$B, MATCH(A6, Facturas_Odoo!$D:$D, 0)), "Sin Factura")) | R6: =IF(Q6="Sin Factura","",IFERROR(INDEX(Facturas_Odoo!$A:$A, MATCH(Q6, Facturas_Odoo!$B:$B, 0)), "")) | S6: =IF(Q6="Sin Factura","",IFERROR(_xlfn.XLOOKUP(1, (Facturas_Odoo!$D:$D=A6) * (Facturas_Odoo!$K:$K=I6), Facturas_Odoo!$L:$L, ""), "")) | T6: =IF(Q6="Sin Factura",0,IFERROR(_xlfn.XLOOKUP(1, (Facturas_Odoo!$D:$D=A6) * (Facturas_Odoo!$K:$K=I6), Facturas_Odoo!$M:$M, 0), 0)) | U6: =IF(Q6="Sin Factura",0,IFERROR(_xlfn.XLOOKUP(1, (Facturas_Odoo!$D:$D=A6) * (Facturas_Odoo!$K:$K=I6), Facturas_Odoo!$N:$N, 0), 0)) | V6: =IF(Q6="Sin Factura",0,IFERROR(_xlfn.XLOOKUP(1, (Facturas_Odoo!$D:$D=A6) * (Facturas_Odoo!$K:$K=I6), Facturas_Odoo!$O:$O, 0), 0)) | W6: =IF(Q6="Sin Factura",0,IFERROR(_xlfn.XLOOKUP(1, (Facturas_Odoo!$D:$D=A6) * (Facturas_Odoo!$K:$K=I6), Facturas_Odoo!$Q:$Q, 0), 0)) | X6: =IF(OR(Q6="Sin Factura",Q6=""),"",IFERROR(INDEX(Pagos_Odoo!$B:$B, MATCH(Q6, Pagos_Odoo!$I:$I, 0)), "Sin Pago")) | Y6: =IF(X6="Sin Pago","",IFERROR(INDEX(Pagos_Odoo!$C:$C, MATCH(X6, Pagos_Odoo!$B:$B, 0)), "")) | Z6: =IF(X6="Sin Pago","",IFERROR(INDEX(Pagos_Odoo!$A:$A, MATCH(X6, Pagos_Odoo!$B:$B, 0)), "")) | AA6: =IF(X6="Sin Pago","",IFERROR(INDEX(Pagos_Odoo!$F:$F, MATCH(X6, Pagos_Odoo!$B:$B, 0)), "")) | AB6: =IF(X6="Sin Pago",0,IFERROR(INDEX(Pagos_Odoo!$E:$E, MATCH(X6, Pagos_Odoo!$B:$B, 0)), 0)) | AC6: =IF(X6="Sin Pago","",IFERROR(INDEX(Pagos_Odoo!$G:$G, MATCH(X6, Pagos_Odoo!$B:$B, 0)), "")) | AD6: 0 | AG6: =IF(AN6="","",AD6+AE6+AF6) | AH6: =IF(AN6="","",P6*(1-AG6)) | AI6: =IF(AN6="","",IF(Q6="Sin Factura",0,IFERROR(INDEX(Facturas_Odoo!$H:$H, MATCH(Q6, Facturas_Odoo!$B:$B, 0)), 0)*(1-AG6))) | AJ6: =IF(AN6="","",_xlfn.LET(idVenta, AN6&"", pagos, IFERROR(SUMIF(Aux_Datos!$B:$B, idVenta, Aux_Datos!$L:$L), 0), retenciones, IFERROR(SUMIF(Aux_Datos!$O:$O, idVenta, Aux_Datos!$S:$S), 0), pagos_manuales, IFERROR(SUMIF('Asignación Pagos'!$G:$G, idVenta, 'Asignación Pagos'!$F:$F), 0), pagos+retenciones+pagos_manuales)) | AK6: =IF(AN6="","",AH6-AJ6) | AL6: =IF(AN6="","",IF(Q6="Sin Factura","",AI6-AJ6)) | AM6: =IF(AN6="","",IF(Q6="Sin Factura",0,P6-IFERROR(INDEX(Facturas_Odoo!$H:$H, MATCH(Q6, Facturas_Odoo!$B:$B, 0)), 0))) | AN6: =IF(AND(A6="", J6=""), "", IF(A6<>"", VALUE(MID(A6,2,LEN(A6))), AN5)) | AO6: =IF(AN6="","",IF(AD6=0,"OK",_xlfn.LET(monedaPago, IF(AA6="","USD",AA6), limitePermitido, IFERROR(VLOOKUP(monedaPago, Configuración!$A$2:$B$3, 2, FALSE), 0.15), IF(AD6>limitePermitido, "ALERTA: EXCESO (" & TEXT(limitePermitido, "0%") & " máx)", "OK")))) | AP6: =IF(AN6="","",IF(AE6=0,"OK",_xlfn.LET(fechaPago, Z6, fechaFactura, R6, diasCredito, IF(E6="Pago inmediato", 0, IFERROR(VALUE(MID(E6, 1, SEARCH(" ", E6)-1)), 0)), tolerancia, Configuración!$E$2, limiteDias, diasCredito + tolerancia, IF(OR(fechaPago="", fechaFactura=""), "REVISAR: SIN FECHA", IF(fechaPago - fechaFactura > limiteDias, "ALERTA: PAGO FUERA DE PLAZO (" & (fechaPago - fechaFactura) & " días)", "OK"))))) | AQ6: =IF(AN6="","",IF(AND(N6>0, AG6>0), IF(Configuración!$K$2="NO", "ALERTA: DESCUENTO DOBLE NO PERMITIDO", "OK"), "OK")) | AR6: =IF(AN6="","",IF(OR(AO6<>"OK", AP6<>"OK", AQ6<>"OK"), "⚠️ REVISAR", "OK"))
A7: =IF('Ordenes_Odoo'!A7="","",'Ordenes_Odoo'!A7) | B7: =IF('Ordenes_Odoo'!B7="","",'Ordenes_Odoo'!B7) | C7: =IF('Ordenes_Odoo'!C7="","",'Ordenes_Odoo'!C7) | D7: =IF('Ordenes_Odoo'!D7="","",'Ordenes_Odoo'!D7) | E7: =IF('Ordenes_Odoo'!E7="","",'Ordenes_Odoo'!E7) | F7: =IF('Ordenes_Odoo'!F7="","",'Ordenes_Odoo'!F7) | G7: =IF('Ordenes_Odoo'!G7="","",'Ordenes_Odoo'!G7) | H7: =IF('Ordenes_Odoo'!H7="","",'Ordenes_Odoo'!H7) | ... P7: =IF('Ordenes_Odoo'!P7="","",'Ordenes_Odoo'!P7) | Q7: =IF(A7="","",IFERROR(INDEX(Facturas_Odoo!$B:$B, MATCH(A7, Facturas_Odoo!$D:$D, 0)), "Sin Factura")) | R7: =IF(Q7="Sin Factura","",IFERROR(INDEX(Facturas_Odoo!$A:$A, MATCH(Q7, Facturas_Odoo!$B:$B, 0)), "")) | S7: =IF(Q7="Sin Factura","",IFERROR(_xlfn.XLOOKUP(1, (Facturas_Odoo!$D:$D=A7) * (Facturas_Odoo!$K:$K=I7), Facturas_Odoo!$L:$L, ""), "")) | T7: =IF(Q7="Sin Factura",0,IFERROR(_xlfn.XLOOKUP(1, (Facturas_Odoo!$D:$D=A7) * (Facturas_Odoo!$K:$K=I7), Facturas_Odoo!$M:$M, 0), 0)) | U7: =IF(Q7="Sin Factura",0,IFERROR(_xlfn.XLOOKUP(1, (Facturas_Odoo!$D:$D=A7) * (Facturas_Odoo!$K:$K=I7), Facturas_Odoo!$N:$N, 0), 0)) | V7: =IF(Q7="Sin Factura",0,IFERROR(_xlfn.XLOOKUP(1, (Facturas_Odoo!$D:$D=A7) * (Facturas_Odoo!$K:$K=I7), Facturas_Odoo!$O:$O, 0), 0)) | W7: =IF(Q7="Sin Factura",0,IFERROR(_xlfn.XLOOKUP(1, (Facturas_Odoo!$D:$D=A7) * (Facturas_Odoo!$K:$K=I7), Facturas_Odoo!$Q:$Q, 0), 0)) | X7: =IF(OR(Q7="Sin Factura",Q7=""),"",IFERROR(INDEX(Pagos_Odoo!$B:$B, MATCH(Q7, Pagos_Odoo!$I:$I, 0)), "Sin Pago")) | Y7: =IF(X7="Sin Pago","",IFERROR(INDEX(Pagos_Odoo!$C:$C, MATCH(X7, Pagos_Odoo!$B:$B, 0)), "")) | Z7: =IF(X7="Sin Pago","",IFERROR(INDEX(Pagos_Odoo!$A:$A, MATCH(X7, Pagos_Odoo!$B:$B, 0)), "")) | AA7: =IF(X7="Sin Pago","",IFERROR(INDEX(Pagos_Odoo!$F:$F, MATCH(X7, Pagos_Odoo!$B:$B, 0)), "")) | AB7: =IF(X7="Sin Pago",0,IFERROR(INDEX(Pagos_Odoo!$E:$E, MATCH(X7, Pagos_Odoo!$B:$B, 0)), 0)) | AC7: =IF(X7="Sin Pago","",IFERROR(INDEX(Pagos_Odoo!$G:$G, MATCH(X7, Pagos_Odoo!$B:$B, 0)), "")) | AD7: 0 | AG7: =IF(AN7="","",AD7+AE7+AF7) | AH7: =IF(AN7="","",P7*(1-AG7)) | AI7: =IF(AN7="","",IF(Q7="Sin Factura",0,IFERROR(INDEX(Facturas_Odoo!$H:$H, MATCH(Q7, Facturas_Odoo!$B:$B, 0)), 0)*(1-AG7))) | AJ7: =IF(AN7="","",_xlfn.LET(idVenta, AN7&"", pagos, IFERROR(SUMIF(Aux_Datos!$B:$B, idVenta, Aux_Datos!$L:$L), 0), retenciones, IFERROR(SUMIF(Aux_Datos!$O:$O, idVenta, Aux_Datos!$S:$S), 0), pagos_manuales, IFERROR(SUMIF('Asignación Pagos'!$G:$G, idVenta, 'Asignación Pagos'!$F:$F), 0), pagos+retenciones+pagos_manuales)) | AK7: =IF(AN7="","",AH7-AJ7) | AL7: =IF(AN7="","",IF(Q7="Sin Factura","",AI7-AJ7)) | AM7: =IF(AN7="","",IF(Q7="Sin Factura",0,P7-IFERROR(INDEX(Facturas_Odoo!$H:$H, MATCH(Q7, Facturas_Odoo!$B:$B, 0)), 0))) | AN7: =IF(AND(A7="", J7=""), "", IF(A7<>"", VALUE(MID(A7,2,LEN(A7))), AN6)) | AO7: =IF(AN7="","",IF(AD7=0,"OK",_xlfn.LET(monedaPago, IF(AA7="","USD",AA7), limitePermitido, IFERROR(VLOOKUP(monedaPago, Configuración!$A$2:$B$3, 2, FALSE), 0.15), IF(AD7>limitePermitido, "ALERTA: EXCESO (" & TEXT(limitePermitido, "0%") & " máx)", "OK")))) | AP7: =IF(AN7="","",IF(AE7=0,"OK",_xlfn.LET(fechaPago, Z7, fechaFactura, R7, diasCredito, IF(E7="Pago inmediato", 0, IFERROR(VALUE(MID(E7, 1, SEARCH(" ", E7)-1)), 0)), tolerancia, Configuración!$E$2, limiteDias, diasCredito + tolerancia, IF(OR(fechaPago="", fechaFactura=""), "REVISAR: SIN FECHA", IF(fechaPago - fechaFactura > limiteDias, "ALERTA: PAGO FUERA DE PLAZO (" & (fechaPago - fechaFactura) & " días)", "OK"))))) | AQ7: =IF(AN7="","",IF(AND(N7>0, AG7>0), IF(Configuración!$K$2="NO", "ALERTA: DESCUENTO DOBLE NO PERMITIDO", "OK"), "OK")) | AR7: =IF(AN7="","",IF(OR(AO7<>"OK", AP7<>"OK", AQ7<>"OK"), "⚠️ REVISAR", "OK"))
A8: =IF('Ordenes_Odoo'!A8="","",'Ordenes_Odoo'!A8) | B8: =IF('Ordenes_Odoo'!B8="","",'Ordenes_Odoo'!B8) | C8: =IF('Ordenes_Odoo'!C8="","",'Ordenes_Odoo'!C8) | D8: =IF('Ordenes_Odoo'!D8="","",'Ordenes_Odoo'!D8) | E8: =IF('Ordenes_Odoo'!E8="","",'Ordenes_Odoo'!E8) | F8: =IF('Ordenes_Odoo'!F8="","",'Ordenes_Odoo'!F8) | G8: =IF('Ordenes_Odoo'!G8="","",'Ordenes_Odoo'!G8) | H8: =IF('Ordenes_Odoo'!H8="","",'Ordenes_Odoo'!H8) | ... P8: =IF('Ordenes_Odoo'!P8="","",'Ordenes_Odoo'!P8) | Q8: =IF(A8="","",IFERROR(INDEX(Facturas_Odoo!$B:$B, MATCH(A8, Facturas_Odoo!$D:$D, 0)), "Sin Factura")) | R8: =IF(Q8="Sin Factura","",IFERROR(INDEX(Facturas_Odoo!$A:$A, MATCH(Q8, Facturas_Odoo!$B:$B, 0)), "")) | S8: =IF(Q8="Sin Factura","",IFERROR(_xlfn.XLOOKUP(1, (Facturas_Odoo!$D:$D=A8) * (Facturas_Odoo!$K:$K=I8), Facturas_Odoo!$L:$L, ""), "")) | T8: =IF(Q8="Sin Factura",0,IFERROR(_xlfn.XLOOKUP(1, (Facturas_Odoo!$D:$D=A8) * (Facturas_Odoo!$K:$K=I8), Facturas_Odoo!$M:$M, 0), 0)) | U8: =IF(Q8="Sin Factura",0,IFERROR(_xlfn.XLOOKUP(1, (Facturas_Odoo!$D:$D=A8) * (Facturas_Odoo!$K:$K=I8), Facturas_Odoo!$N:$N, 0), 0)) | V8: =IF(Q8="Sin Factura",0,IFERROR(_xlfn.XLOOKUP(1, (Facturas_Odoo!$D:$D=A8) * (Facturas_Odoo!$K:$K=I8), Facturas_Odoo!$O:$O, 0), 0)) | W8: =IF(Q8="Sin Factura",0,IFERROR(_xlfn.XLOOKUP(1, (Facturas_Odoo!$D:$D=A8) * (Facturas_Odoo!$K:$K=I8), Facturas_Odoo!$Q:$Q, 0), 0)) | X8: =IF(OR(Q8="Sin Factura",Q8=""),"",IFERROR(INDEX(Pagos_Odoo!$B:$B, MATCH(Q8, Pagos_Odoo!$I:$I, 0)), "Sin Pago")) | Y8: =IF(X8="Sin Pago","",IFERROR(INDEX(Pagos_Odoo!$C:$C, MATCH(X8, Pagos_Odoo!$B:$B, 0)), "")) | Z8: =IF(X8="Sin Pago","",IFERROR(INDEX(Pagos_Odoo!$A:$A, MATCH(X8, Pagos_Odoo!$B:$B, 0)), "")) | AA8: =IF(X8="Sin Pago","",IFERROR(INDEX(Pagos_Odoo!$F:$F, MATCH(X8, Pagos_Odoo!$B:$B, 0)), "")) | AB8: =IF(X8="Sin Pago",0,IFERROR(INDEX(Pagos_Odoo!$E:$E, MATCH(X8, Pagos_Odoo!$B:$B, 0)), 0)) | AC8: =IF(X8="Sin Pago","",IFERROR(INDEX(Pagos_Odoo!$G:$G, MATCH(X8, Pagos_Odoo!$B:$B, 0)), "")) | AD8: 0 | AG8: =IF(AN8="","",AD8+AE8+AF8) | AH8: =IF(AN8="","",P8*(1-AG8)) | AI8: =IF(AN8="","",IF(Q8="Sin Factura",0,IFERROR(INDEX(Facturas_Odoo!$H:$H, MATCH(Q8, Facturas_Odoo!$B:$B, 0)), 0)*(1-AG8))) | AJ8: =IF(AN8="","",_xlfn.LET(idVenta, AN8&"", pagos, IFERROR(SUMIF(Aux_Datos!$B:$B, idVenta, Aux_Datos!$L:$L), 0), retenciones, IFERROR(SUMIF(Aux_Datos!$O:$O, idVenta, Aux_Datos!$S:$S), 0), pagos_manuales, IFERROR(SUMIF('Asignación Pagos'!$G:$G, idVenta, 'Asignación Pagos'!$F:$F), 0), pagos+retenciones+pagos_manuales)) | AK8: =IF(AN8="","",AH8-AJ8) | AL8: =IF(AN8="","",IF(Q8="Sin Factura","",AI8-AJ8)) | AM8: =IF(AN8="","",IF(Q8="Sin Factura",0,P8-IFERROR(INDEX(Facturas_Odoo!$H:$H, MATCH(Q8, Facturas_Odoo!$B:$B, 0)), 0))) | AN8: =IF(AND(A8="", J8=""), "", IF(A8<>"", VALUE(MID(A8,2,LEN(A8))), AN7)) | AO8: =IF(AN8="","",IF(AD8=0,"OK",_xlfn.LET(monedaPago, IF(AA8="","USD",AA8), limitePermitido, IFERROR(VLOOKUP(monedaPago, Configuración!$A$2:$B$3, 2, FALSE), 0.15), IF(AD8>limitePermitido, "ALERTA: EXCESO (" & TEXT(limitePermitido, "0%") & " máx)", "OK")))) | AP8: =IF(AN8="","",IF(AE8=0,"OK",_xlfn.LET(fechaPago, Z8, fechaFactura, R8, diasCredito, IF(E8="Pago inmediato", 0, IFERROR(VALUE(MID(E8, 1, SEARCH(" ", E8)-1)), 0)), tolerancia, Configuración!$E$2, limiteDias, diasCredito + tolerancia, IF(OR(fechaPago="", fechaFactura=""), "REVISAR: SIN FECHA", IF(fechaPago - fechaFactura > limiteDias, "ALERTA: PAGO FUERA DE PLAZO (" & (fechaPago - fechaFactura) & " días)", "OK"))))) | AQ8: =IF(AN8="","",IF(AND(N8>0, AG8>0), IF(Configuración!$K$2="NO", "ALERTA: DESCUENTO DOBLE NO PERMITIDO", "OK"), "OK")) | AR8: =IF(AN8="","",IF(OR(AO8<>"OK", AP8<>"OK", AQ8<>"OK"), "⚠️ REVISAR", "OK"))
A9: =IF('Ordenes_Odoo'!A9="","",'Ordenes_Odoo'!A9) | B9: =IF('Ordenes_Odoo'!B9="","",'Ordenes_Odoo'!B9) | C9: =IF('Ordenes_Odoo'!C9="","",'Ordenes_Odoo'!C9) | D9: =IF('Ordenes_Odoo'!D9="","",'Ordenes_Odoo'!D9) | E9: =IF('Ordenes_Odoo'!E9="","",'Ordenes_Odoo'!E9) | F9: =IF('Ordenes_Odoo'!F9="","",'Ordenes_Odoo'!F9) | G9: =IF('Ordenes_Odoo'!G9="","",'Ordenes_Odoo'!G9) | H9: =IF('Ordenes_Odoo'!H9="","",'Ordenes_Odoo'!H9) | ... P9: =IF('Ordenes_Odoo'!P9="","",'Ordenes_Odoo'!P9) | Q9: =IF(A9="","",IFERROR(INDEX(Facturas_Odoo!$B:$B, MATCH(A9, Facturas_Odoo!$D:$D, 0)), "Sin Factura")) | R9: =IF(Q9="Sin Factura","",IFERROR(INDEX(Facturas_Odoo!$A:$A, MATCH(Q9, Facturas_Odoo!$B:$B, 0)), "")) | S9: =IF(Q9="Sin Factura","",IFERROR(_xlfn.XLOOKUP(1, (Facturas_Odoo!$D:$D=A9) * (Facturas_Odoo!$K:$K=I9), Facturas_Odoo!$L:$L, ""), "")) | T9: =IF(Q9="Sin Factura",0,IFERROR(_xlfn.XLOOKUP(1, (Facturas_Odoo!$D:$D=A9) * (Facturas_Odoo!$K:$K=I9), Facturas_Odoo!$M:$M, 0), 0)) | U9: =IF(Q9="Sin Factura",0,IFERROR(_xlfn.XLOOKUP(1, (Facturas_Odoo!$D:$D=A9) * (Facturas_Odoo!$K:$K=I9), Facturas_Odoo!$N:$N, 0), 0)) | V9: =IF(Q9="Sin Factura",0,IFERROR(_xlfn.XLOOKUP(1, (Facturas_Odoo!$D:$D=A9) * (Facturas_Odoo!$K:$K=I9), Facturas_Odoo!$O:$O, 0), 0)) | W9: =IF(Q9="Sin Factura",0,IFERROR(_xlfn.XLOOKUP(1, (Facturas_Odoo!$D:$D=A9) * (Facturas_Odoo!$K:$K=I9), Facturas_Odoo!$Q:$Q, 0), 0)) | X9: =IF(OR(Q9="Sin Factura",Q9=""),"",IFERROR(INDEX(Pagos_Odoo!$B:$B, MATCH(Q9, Pagos_Odoo!$I:$I, 0)), "Sin Pago")) | Y9: =IF(X9="Sin Pago","",IFERROR(INDEX(Pagos_Odoo!$C:$C, MATCH(X9, Pagos_Odoo!$B:$B, 0)), "")) | Z9: =IF(X9="Sin Pago","",IFERROR(INDEX(Pagos_Odoo!$A:$A, MATCH(X9, Pagos_Odoo!$B:$B, 0)), "")) | AA9: =IF(X9="Sin Pago","",IFERROR(INDEX(Pagos_Odoo!$F:$F, MATCH(X9, Pagos_Odoo!$B:$B, 0)), "")) | AB9: =IF(X9="Sin Pago",0,IFERROR(INDEX(Pagos_Odoo!$E:$E, MATCH(X9, Pagos_Odoo!$B:$B, 0)), 0)) | AC9: =IF(X9="Sin Pago","",IFERROR(INDEX(Pagos_Odoo!$G:$G, MATCH(X9, Pagos_Odoo!$B:$B, 0)), "")) | AD9: 0 | AG9: =IF(AN9="","",AD9+AE9+AF9) | AH9: =IF(AN9="","",P9*(1-AG9)) | AI9: =IF(AN9="","",IF(Q9="Sin Factura",0,IFERROR(INDEX(Facturas_Odoo!$H:$H, MATCH(Q9, Facturas_Odoo!$B:$B, 0)), 0)*(1-AG9))) | AJ9: =IF(AN9="","",_xlfn.LET(idVenta, AN9&"", pagos, IFERROR(SUMIF(Aux_Datos!$B:$B, idVenta, Aux_Datos!$L:$L), 0), retenciones, IFERROR(SUMIF(Aux_Datos!$O:$O, idVenta, Aux_Datos!$S:$S), 0), pagos_manuales, IFERROR(SUMIF('Asignación Pagos'!$G:$G, idVenta, 'Asignación Pagos'!$F:$F), 0), pagos+retenciones+pagos_manuales)) | AK9: =IF(AN9="","",AH9-AJ9) | AL9: =IF(AN9="","",IF(Q9="Sin Factura","",AI9-AJ9)) | AM9: =IF(AN9="","",IF(Q9="Sin Factura",0,P9-IFERROR(INDEX(Facturas_Odoo!$H:$H, MATCH(Q9, Facturas_Odoo!$B:$B, 0)), 0))) | AN9: =IF(AND(A9="", J9=""), "", IF(A9<>"", VALUE(MID(A9,2,LEN(A9))), AN8)) | AO9: =IF(AN9="","",IF(AD9=0,"OK",_xlfn.LET(monedaPago, IF(AA9="","USD",AA9), limitePermitido, IFERROR(VLOOKUP(monedaPago, Configuración!$A$2:$B$3, 2, FALSE), 0.15), IF(AD9>limitePermitido, "ALERTA: EXCESO (" & TEXT(limitePermitido, "0%") & " máx)", "OK")))) | AP9: =IF(AN9="","",IF(AE9=0,"OK",_xlfn.LET(fechaPago, Z9, fechaFactura, R9, diasCredito, IF(E9="Pago inmediato", 0, IFERROR(VALUE(MID(E9, 1, SEARCH(" ", E9)-1)), 0)), tolerancia, Configuración!$E$2, limiteDias, diasCredito + tolerancia, IF(OR(fechaPago="", fechaFactura=""), "REVISAR: SIN FECHA", IF(fechaPago - fechaFactura > limiteDias, "ALERTA: PAGO FUERA DE PLAZO (" & (fechaPago - fechaFactura) & " días)", "OK"))))) | AQ9: =IF(AN9="","",IF(AND(N9>0, AG9>0), IF(Configuración!$K$2="NO", "ALERTA: DESCUENTO DOBLE NO PERMITIDO", "OK"), "OK")) | AR9: =IF(AN9="","",IF(OR(AO9<>"OK", AP9<>"OK", AQ9<>"OK"), "⚠️ REVISAR", "OK"))
A10: =IF('Ordenes_Odoo'!A10="","",'Ordenes_Odoo'!A10) | B10: =IF('Ordenes_Odoo'!B10="","",'Ordenes_Odoo'!B10) | C10: =IF('Ordenes_Odoo'!C10="","",'Ordenes_Odoo'!C10) | D10: =IF('Ordenes_Odoo'!D10="","",'Ordenes_Odoo'!D10) | E10: =IF('Ordenes_Odoo'!E10="","",'Ordenes_Odoo'!E10) | F10: =IF('Ordenes_Odoo'!F10="","",'Ordenes_Odoo'!F10) | G10: =IF('Ordenes_Odoo'!G10="","",'Ordenes_Odoo'!G10) | H10: =IF('Ordenes_Odoo'!H10="","",'Ordenes_Odoo'!H10) | ... P10: =IF('Ordenes_Odoo'!P10="","",'Ordenes_Odoo'!P10) | Q10: =IF(A10="","",IFERROR(INDEX(Facturas_Odoo!$B:$B, MATCH(A10, Facturas_Odoo!$D:$D, 0)), "Sin Factura")) | R10: =IF(Q10="Sin Factura","",IFERROR(INDEX(Facturas_Odoo!$A:$A, MATCH(Q10, Facturas_Odoo!$B:$B, 0)), "")) | S10: =IF(Q10="Sin Factura","",IFERROR(_xlfn.XLOOKUP(1, (Facturas_Odoo!$D:$D=A10) * (Facturas_Odoo!$K:$K=I10), Facturas_Odoo!$L:$L, ""), "")) | T10: =IF(Q10="Sin Factura",0,IFERROR(_xlfn.XLOOKUP(1, (Facturas_Odoo!$D:$D=A10) * (Facturas_Odoo!$K:$K=I10), Facturas_Odoo!$M:$M, 0), 0)) | U10: =IF(Q10="Sin Factura",0,IFERROR(_xlfn.XLOOKUP(1, (Facturas_Odoo!$D:$D=A10) * (Facturas_Odoo!$K:$K=I10), Facturas_Odoo!$N:$N, 0), 0)) | V10: =IF(Q10="Sin Factura",0,IFERROR(_xlfn.XLOOKUP(1, (Facturas_Odoo!$D:$D=A10) * (Facturas_Odoo!$K:$K=I10), Facturas_Odoo!$O:$O, 0), 0)) | W10: =IF(Q10="Sin Factura",0,IFERROR(_xlfn.XLOOKUP(1, (Facturas_Odoo!$D:$D=A10) * (Facturas_Odoo!$K:$K=I10), Facturas_Odoo!$Q:$Q, 0), 0)) | X10: =IF(OR(Q10="Sin Factura",Q10=""),"",IFERROR(INDEX(Pagos_Odoo!$B:$B, MATCH(Q10, Pagos_Odoo!$I:$I, 0)), "Sin Pago")) | Y10: =IF(X10="Sin Pago","",IFERROR(INDEX(Pagos_Odoo!$C:$C, MATCH(X10, Pagos_Odoo!$B:$B, 0)), "")) | Z10: =IF(X10="Sin Pago","",IFERROR(INDEX(Pagos_Odoo!$A:$A, MATCH(X10, Pagos_Odoo!$B:$B, 0)), "")) | AA10: =IF(X10="Sin Pago","",IFERROR(INDEX(Pagos_Odoo!$F:$F, MATCH(X10, Pagos_Odoo!$B:$B, 0)), "")) | AB10: =IF(X10="Sin Pago",0,IFERROR(INDEX(Pagos_Odoo!$E:$E, MATCH(X10, Pagos_Odoo!$B:$B, 0)), 0)) | AC10: =IF(X10="Sin Pago","",IFERROR(INDEX(Pagos_Odoo!$G:$G, MATCH(X10, Pagos_Odoo!$B:$B, 0)), "")) | AD10: 0 | AG10: =IF(AN10="","",AD10+AE10+AF10) | AH10: =IF(AN10="","",P10*(1-AG10)) | AI10: =IF(AN10="","",IF(Q10="Sin Factura",0,IFERROR(INDEX(Facturas_Odoo!$H:$H, MATCH(Q10, Facturas_Odoo!$B:$B, 0)), 0)*(1-AG10))) | AJ10: =IF(AN10="","",_xlfn.LET(idVenta, AN10&"", pagos, IFERROR(SUMIF(Aux_Datos!$B:$B, idVenta, Aux_Datos!$L:$L), 0), retenciones, IFERROR(SUMIF(Aux_Datos!$O:$O, idVenta, Aux_Datos!$S:$S), 0), pagos_manuales, IFERROR(SUMIF('Asignación Pagos'!$G:$G, idVenta, 'Asignación Pagos'!$F:$F), 0), pagos+retenciones+pagos_manuales)) | AK10: =IF(AN10="","",AH10-AJ10) | AL10: =IF(AN10="","",IF(Q10="Sin Factura","",AI10-AJ10)) | AM10: =IF(AN10="","",IF(Q10="Sin Factura",0,P10-IFERROR(INDEX(Facturas_Odoo!$H:$H, MATCH(Q10, Facturas_Odoo!$B:$B, 0)), 0))) | AN10: =IF(AND(A10="", J10=""), "", IF(A10<>"", VALUE(MID(A10,2,LEN(A10))), AN9)) | AO10: =IF(AN10="","",IF(AD10=0,"OK",_xlfn.LET(monedaPago, IF(AA10="","USD",AA10), limitePermitido, IFERROR(VLOOKUP(monedaPago, Configuración!$A$2:$B$3, 2, FALSE), 0.15), IF(AD10>limitePermitido, "ALERTA: EXCESO (" & TEXT(limitePermitido, "0%") & " máx)", "OK")))) | AP10: =IF(AN10="","",IF(AE10=0,"OK",_xlfn.LET(fechaPago, Z10, fechaFactura, R10, diasCredito, IF(E10="Pago inmediato", 0, IFERROR(VALUE(MID(E10, 1, SEARCH(" ", E10)-1)), 0)), tolerancia, Configuración!$E$2, limiteDias, diasCredito + tolerancia, IF(OR(fechaPago="", fechaFactura=""), "REVISAR: SIN FECHA", IF(fechaPago - fechaFactura > limiteDias, "ALERTA: PAGO FUERA DE PLAZO (" & (fechaPago - fechaFactura) & " días)", "OK"))))) | AQ10: =IF(AN10="","",IF(AND(N10>0, AG10>0), IF(Configuración!$K$2="NO", "ALERTA: DESCUENTO DOBLE NO PERMITIDO", "OK"), "OK")) | AR10: =IF(AN10="","",IF(OR(AO10<>"OK", AP10<>"OK", AQ10<>"OK"), "⚠️ REVISAR", "OK"))
A11: =IF('Ordenes_Odoo'!A11="","",'Ordenes_Odoo'!A11) | B11: =IF('Ordenes_Odoo'!B11="","",'Ordenes_Odoo'!B11) | C11: =IF('Ordenes_Odoo'!C11="","",'Ordenes_Odoo'!C11) | D11: =IF('Ordenes_Odoo'!D11="","",'Ordenes_Odoo'!D11) | E11: =IF('Ordenes_Odoo'!E11="","",'Ordenes_Odoo'!E11) | F11: =IF('Ordenes_Odoo'!F11="","",'Ordenes_Odoo'!F11) | G11: =IF('Ordenes_Odoo'!G11="","",'Ordenes_Odoo'!G11) | H11: =IF('Ordenes_Odoo'!H11="","",'Ordenes_Odoo'!H11) | ... P11: =IF('Ordenes_Odoo'!P11="","",'Ordenes_Odoo'!P11) | Q11: =IF(A11="","",IFERROR(INDEX(Facturas_Odoo!$B:$B, MATCH(A11, Facturas_Odoo!$D:$D, 0)), "Sin Factura")) | R11: =IF(Q11="Sin Factura","",IFERROR(INDEX(Facturas_Odoo!$A:$A, MATCH(Q11, Facturas_Odoo!$B:$B, 0)), "")) | S11: =IF(Q11="Sin Factura","",IFERROR(_xlfn.XLOOKUP(1, (Facturas_Odoo!$D:$D=A11) * (Facturas_Odoo!$K:$K=I11), Facturas_Odoo!$L:$L, ""), "")) | T11: =IF(Q11="Sin Factura",0,IFERROR(_xlfn.XLOOKUP(1, (Facturas_Odoo!$D:$D=A11) * (Facturas_Odoo!$K:$K=I11), Facturas_Odoo!$M:$M, 0), 0)) | U11: =IF(Q11="Sin Factura",0,IFERROR(_xlfn.XLOOKUP(1, (Facturas_Odoo!$D:$D=A11) * (Facturas_Odoo!$K:$K=I11), Facturas_Odoo!$N:$N, 0), 0)) | V11: =IF(Q11="Sin Factura",0,IFERROR(_xlfn.XLOOKUP(1, (Facturas_Odoo!$D:$D=A11) * (Facturas_Odoo!$K:$K=I11), Facturas_Odoo!$O:$O, 0), 0)) | W11: =IF(Q11="Sin Factura",0,IFERROR(_xlfn.XLOOKUP(1, (Facturas_Odoo!$D:$D=A11) * (Facturas_Odoo!$K:$K=I11), Facturas_Odoo!$Q:$Q, 0), 0)) | X11: =IF(OR(Q11="Sin Factura",Q11=""),"",IFERROR(INDEX(Pagos_Odoo!$B:$B, MATCH(Q11, Pagos_Odoo!$I:$I, 0)), "Sin Pago")) | Y11: =IF(X11="Sin Pago","",IFERROR(INDEX(Pagos_Odoo!$C:$C, MATCH(X11, Pagos_Odoo!$B:$B, 0)), "")) | Z11: =IF(X11="Sin Pago","",IFERROR(INDEX(Pagos_Odoo!$A:$A, MATCH(X11, Pagos_Odoo!$B:$B, 0)), "")) | AA11: =IF(X11="Sin Pago","",IFERROR(INDEX(Pagos_Odoo!$F:$F, MATCH(X11, Pagos_Odoo!$B:$B, 0)), "")) | AB11: =IF(X11="Sin Pago",0,IFERROR(INDEX(Pagos_Odoo!$E:$E, MATCH(X11, Pagos_Odoo!$B:$B, 0)), 0)) | AC11: =IF(X11="Sin Pago","",IFERROR(INDEX(Pagos_Odoo!$G:$G, MATCH(X11, Pagos_Odoo!$B:$B, 0)), "")) | AD11: 0 | AG11: =IF(AN11="","",AD11+AE11+AF11) | AH11: =IF(AN11="","",P11*(1-AG11)) | AI11: =IF(AN11="","",IF(Q11="Sin Factura",0,IFERROR(INDEX(Facturas_Odoo!$H:$H, MATCH(Q11, Facturas_Odoo!$B:$B, 0)), 0)*(1-AG11))) | AJ11: =IF(AN11="","",_xlfn.LET(idVenta, AN11&"", pagos, IFERROR(SUMIF(Aux_Datos!$B:$B, idVenta, Aux_Datos!$L:$L), 0), retenciones, IFERROR(SUMIF(Aux_Datos!$O:$O, idVenta, Aux_Datos!$S:$S), 0), pagos_manuales, IFERROR(SUMIF('Asignación Pagos'!$G:$G, idVenta, 'Asignación Pagos'!$F:$F), 0), pagos+retenciones+pagos_manuales)) | AK11: =IF(AN11="","",AH11-AJ11) | AL11: =IF(AN11="","",IF(Q11="Sin Factura","",AI11-AJ11)) | AM11: =IF(AN11="","",IF(Q11="Sin Factura",0,P11-IFERROR(INDEX(Facturas_Odoo!$H:$H, MATCH(Q11, Facturas_Odoo!$B:$B, 0)), 0))) | AN11: =IF(AND(A11="", J11=""), "", IF(A11<>"", VALUE(MID(A11,2,LEN(A11))), AN10)) | AO11: =IF(AN11="","",IF(AD11=0,"OK",_xlfn.LET(monedaPago, IF(AA11="","USD",AA11), limitePermitido, IFERROR(VLOOKUP(monedaPago, Configuración!$A$2:$B$3, 2, FALSE), 0.15), IF(AD11>limitePermitido, "ALERTA: EXCESO (" & TEXT(limitePermitido, "0%") & " máx)", "OK")))) | AP11: =IF(AN11="","",IF(AE11=0,"OK",_xlfn.LET(fechaPago, Z11, fechaFactura, R11, diasCredito, IF(E11="Pago inmediato", 0, IFERROR(VALUE(MID(E11, 1, SEARCH(" ", E11)-1)), 0)), tolerancia, Configuración!$E$2, limiteDias, diasCredito + tolerancia, IF(OR(fechaPago="", fechaFactura=""), "REVISAR: SIN FECHA", IF(fechaPago - fechaFactura > limiteDias, "ALERTA: PAGO FUERA DE PLAZO (" & (fechaPago - fechaFactura) & " días)", "OK"))))) | AQ11: =IF(AN11="","",IF(AND(N11>0, AG11>0), IF(Configuración!$K$2="NO", "ALERTA: DESCUENTO DOBLE NO PERMITIDO", "OK"), "OK")) | AR11: =IF(AN11="","",IF(OR(AO11<>"OK", AP11<>"OK", AQ11<>"OK"), "⚠️ REVISAR", "OK"))
A12: =IF('Ordenes_Odoo'!A12="","",'Ordenes_Odoo'!A12) | B12: =IF('Ordenes_Odoo'!B12="","",'Ordenes_Odoo'!B12) | C12: =IF('Ordenes_Odoo'!C12="","",'Ordenes_Odoo'!C12) | D12: =IF('Ordenes_Odoo'!D12="","",'Ordenes_Odoo'!D12) | E12: =IF('Ordenes_Odoo'!E12="","",'Ordenes_Odoo'!E12) | F12: =IF('Ordenes_Odoo'!F12="","",'Ordenes_Odoo'!F12) | G12: =IF('Ordenes_Odoo'!G12="","",'Ordenes_Odoo'!G12) | H12: =IF('Ordenes_Odoo'!H12="","",'Ordenes_Odoo'!H12) | ... P12: =IF('Ordenes_Odoo'!P12="","",'Ordenes_Odoo'!P12) | Q12: =IF(A12="","",IFERROR(INDEX(Facturas_Odoo!$B:$B, MATCH(A12, Facturas_Odoo!$D:$D, 0)), "Sin Factura")) | R12: =IF(Q12="Sin Factura","",IFERROR(INDEX(Facturas_Odoo!$A:$A, MATCH(Q12, Facturas_Odoo!$B:$B, 0)), "")) | S12: =IF(Q12="Sin Factura","",IFERROR(_xlfn.XLOOKUP(1, (Facturas_Odoo!$D:$D=A12) * (Facturas_Odoo!$K:$K=I12), Facturas_Odoo!$L:$L, ""), "")) | T12: =IF(Q12="Sin Factura",0,IFERROR(_xlfn.XLOOKUP(1, (Facturas_Odoo!$D:$D=A12) * (Facturas_Odoo!$K:$K=I12), Facturas_Odoo!$M:$M, 0), 0)) | U12: =IF(Q12="Sin Factura",0,IFERROR(_xlfn.XLOOKUP(1, (Facturas_Odoo!$D:$D=A12) * (Facturas_Odoo!$K:$K=I12), Facturas_Odoo!$N:$N, 0), 0)) | V12: =IF(Q12="Sin Factura",0,IFERROR(_xlfn.XLOOKUP(1, (Facturas_Odoo!$D:$D=A12) * (Facturas_Odoo!$K:$K=I12), Facturas_Odoo!$O:$O, 0), 0)) | W12: =IF(Q12="Sin Factura",0,IFERROR(_xlfn.XLOOKUP(1, (Facturas_Odoo!$D:$D=A12) * (Facturas_Odoo!$K:$K=I12), Facturas_Odoo!$Q:$Q, 0), 0)) | X12: =IF(OR(Q12="Sin Factura",Q12=""),"",IFERROR(INDEX(Pagos_Odoo!$B:$B, MATCH(Q12, Pagos_Odoo!$I:$I, 0)), "Sin Pago")) | Y12: =IF(X12="Sin Pago","",IFERROR(INDEX(Pagos_Odoo!$C:$C, MATCH(X12, Pagos_Odoo!$B:$B, 0)), "")) | Z12: =IF(X12="Sin Pago","",IFERROR(INDEX(Pagos_Odoo!$A:$A, MATCH(X12, Pagos_Odoo!$B:$B, 0)), "")) | AA12: =IF(X12="Sin Pago","",IFERROR(INDEX(Pagos_Odoo!$F:$F, MATCH(X12, Pagos_Odoo!$B:$B, 0)), "")) | AB12: =IF(X12="Sin Pago",0,IFERROR(INDEX(Pagos_Odoo!$E:$E, MATCH(X12, Pagos_Odoo!$B:$B, 0)), 0)) | AC12: =IF(X12="Sin Pago","",IFERROR(INDEX(Pagos_Odoo!$G:$G, MATCH(X12, Pagos_Odoo!$B:$B, 0)), "")) | AD12: 0 | AG12: =IF(AN12="","",AD12+AE12+AF12) | AH12: =IF(AN12="","",P12*(1-AG12)) | AI12: =IF(AN12="","",IF(Q12="Sin Factura",0,IFERROR(INDEX(Facturas_Odoo!$H:$H, MATCH(Q12, Facturas_Odoo!$B:$B, 0)), 0)*(1-AG12))) | AJ12: =IF(AN12="","",_xlfn.LET(idVenta, AN12&"", pagos, IFERROR(SUMIF(Aux_Datos!$B:$B, idVenta, Aux_Datos!$L:$L), 0), retenciones, IFERROR(SUMIF(Aux_Datos!$O:$O, idVenta, Aux_Datos!$S:$S), 0), pagos_manuales, IFERROR(SUMIF('Asignación Pagos'!$G:$G, idVenta, 'Asignación Pagos'!$F:$F), 0), pagos+retenciones+pagos_manuales)) | AK12: =IF(AN12="","",AH12-AJ12) | AL12: =IF(AN12="","",IF(Q12="Sin Factura","",AI12-AJ12)) | AM12: =IF(AN12="","",IF(Q12="Sin Factura",0,P12-IFERROR(INDEX(Facturas_Odoo!$H:$H, MATCH(Q12, Facturas_Odoo!$B:$B, 0)), 0))) | AN12: =IF(AND(A12="", J12=""), "", IF(A12<>"", VALUE(MID(A12,2,LEN(A12))), AN11)) | AO12: =IF(AN12="","",IF(AD12=0,"OK",_xlfn.LET(monedaPago, IF(AA12="","USD",AA12), limitePermitido, IFERROR(VLOOKUP(monedaPago, Configuración!$A$2:$B$3, 2, FALSE), 0.15), IF(AD12>limitePermitido, "ALERTA: EXCESO (" & TEXT(limitePermitido, "0%") & " máx)", "OK")))) | AP12: =IF(AN12="","",IF(AE12=0,"OK",_xlfn.LET(fechaPago, Z12, fechaFactura, R12, diasCredito, IF(E12="Pago inmediato", 0, IFERROR(VALUE(MID(E12, 1, SEARCH(" ", E12)-1)), 0)), tolerancia, Configuración!$E$2, limiteDias, diasCredito + tolerancia, IF(OR(fechaPago="", fechaFactura=""), "REVISAR: SIN FECHA", IF(fechaPago - fechaFactura > limiteDias, "ALERTA: PAGO FUERA DE PLAZO (" & (fechaPago - fechaFactura) & " días)", "OK"))))) | AQ12: =IF(AN12="","",IF(AND(N12>0, AG12>0), IF(Configuración!$K$2="NO", "ALERTA: DESCUENTO DOBLE NO PERMITIDO", "OK"), "OK")) | AR12: =IF(AN12="","",IF(OR(AO12<>"OK", AP12<>"OK", AQ12<>"OK"), "⚠️ REVISAR", "OK"))
A13: =IF('Ordenes_Odoo'!A13="","",'Ordenes_Odoo'!A13) | B13: =IF('Ordenes_Odoo'!B13="","",'Ordenes_Odoo'!B13) | C13: =IF('Ordenes_Odoo'!C13="","",'Ordenes_Odoo'!C13) | D13: =IF('Ordenes_Odoo'!D13="","",'Ordenes_Odoo'!D13) | E13: =IF('Ordenes_Odoo'!E13="","",'Ordenes_Odoo'!E13) | F13: =IF('Ordenes_Odoo'!F13="","",'Ordenes_Odoo'!F13) | G13: =IF('Ordenes_Odoo'!G13="","",'Ordenes_Odoo'!G13) | H13: =IF('Ordenes_Odoo'!H13="","",'Ordenes_Odoo'!H13) | ... P13: =IF('Ordenes_Odoo'!P13="","",'Ordenes_Odoo'!P13) | Q13: =IF(A13="","",IFERROR(INDEX(Facturas_Odoo!$B:$B, MATCH(A13, Facturas_Odoo!$D:$D, 0)), "Sin Factura")) | R13: =IF(Q13="Sin Factura","",IFERROR(INDEX(Facturas_Odoo!$A:$A, MATCH(Q13, Facturas_Odoo!$B:$B, 0)), "")) | S13: =IF(Q13="Sin Factura","",IFERROR(_xlfn.XLOOKUP(1, (Facturas_Odoo!$D:$D=A13) * (Facturas_Odoo!$K:$K=I13), Facturas_Odoo!$L:$L, ""), "")) | T13: =IF(Q13="Sin Factura",0,IFERROR(_xlfn.XLOOKUP(1, (Facturas_Odoo!$D:$D=A13) * (Facturas_Odoo!$K:$K=I13), Facturas_Odoo!$M:$M, 0), 0)) | U13: =IF(Q13="Sin Factura",0,IFERROR(_xlfn.XLOOKUP(1, (Facturas_Odoo!$D:$D=A13) * (Facturas_Odoo!$K:$K=I13), Facturas_Odoo!$N:$N, 0), 0)) | V13: =IF(Q13="Sin Factura",0,IFERROR(_xlfn.XLOOKUP(1, (Facturas_Odoo!$D:$D=A13) * (Facturas_Odoo!$K:$K=I13), Facturas_Odoo!$O:$O, 0), 0)) | W13: =IF(Q13="Sin Factura",0,IFERROR(_xlfn.XLOOKUP(1, (Facturas_Odoo!$D:$D=A13) * (Facturas_Odoo!$K:$K=I13), Facturas_Odoo!$Q:$Q, 0), 0)) | X13: =IF(OR(Q13="Sin Factura",Q13=""),"",IFERROR(INDEX(Pagos_Odoo!$B:$B, MATCH(Q13, Pagos_Odoo!$I:$I, 0)), "Sin Pago")) | Y13: =IF(X13="Sin Pago","",IFERROR(INDEX(Pagos_Odoo!$C:$C, MATCH(X13, Pagos_Odoo!$B:$B, 0)), "")) | Z13: =IF(X13="Sin Pago","",IFERROR(INDEX(Pagos_Odoo!$A:$A, MATCH(X13, Pagos_Odoo!$B:$B, 0)), "")) | AA13: =IF(X13="Sin Pago","",IFERROR(INDEX(Pagos_Odoo!$F:$F, MATCH(X13, Pagos_Odoo!$B:$B, 0)), "")) | AB13: =IF(X13="Sin Pago",0,IFERROR(INDEX(Pagos_Odoo!$E:$E, MATCH(X13, Pagos_Odoo!$B:$B, 0)), 0)) | AC13: =IF(X13="Sin Pago","",IFERROR(INDEX(Pagos_Odoo!$G:$G, MATCH(X13, Pagos_Odoo!$B:$B, 0)), "")) | AD13: 0 | AG13: =IF(AN13="","",AD13+AE13+AF13) | AH13: =IF(AN13="","",P13*(1-AG13)) | AI13: =IF(AN13="","",IF(Q13="Sin Factura",0,IFERROR(INDEX(Facturas_Odoo!$H:$H, MATCH(Q13, Facturas_Odoo!$B:$B, 0)), 0)*(1-AG13))) | AJ13: =IF(AN13="","",_xlfn.LET(idVenta, AN13&"", pagos, IFERROR(SUMIF(Aux_Datos!$B:$B, idVenta, Aux_Datos!$L:$L), 0), retenciones, IFERROR(SUMIF(Aux_Datos!$O:$O, idVenta, Aux_Datos!$S:$S), 0), pagos_manuales, IFERROR(SUMIF('Asignación Pagos'!$G:$G, idVenta, 'Asignación Pagos'!$F:$F), 0), pagos+retenciones+pagos_manuales)) | AK13: =IF(AN13="","",AH13-AJ13) | AL13: =IF(AN13="","",IF(Q13="Sin Factura","",AI13-AJ13)) | AM13: =IF(AN13="","",IF(Q13="Sin Factura",0,P13-IFERROR(INDEX(Facturas_Odoo!$H:$H, MATCH(Q13, Facturas_Odoo!$B:$B, 0)), 0))) | AN13: =IF(AND(A13="", J13=""), "", IF(A13<>"", VALUE(MID(A13,2,LEN(A13))), AN12)) | AO13: =IF(AN13="","",IF(AD13=0,"OK",_xlfn.LET(monedaPago, IF(AA13="","USD",AA13), limitePermitido, IFERROR(VLOOKUP(monedaPago, Configuración!$A$2:$B$3, 2, FALSE), 0.15), IF(AD13>limitePermitido, "ALERTA: EXCESO (" & TEXT(limitePermitido, "0%") & " máx)", "OK")))) | AP13: =IF(AN13="","",IF(AE13=0,"OK",_xlfn.LET(fechaPago, Z13, fechaFactura, R13, diasCredito, IF(E13="Pago inmediato", 0, IFERROR(VALUE(MID(E13, 1, SEARCH(" ", E13)-1)), 0)), tolerancia, Configuración!$E$2, limiteDias, diasCredito + tolerancia, IF(OR(fechaPago="", fechaFactura=""), "REVISAR: SIN FECHA", IF(fechaPago - fechaFactura > limiteDias, "ALERTA: PAGO FUERA DE PLAZO (" & (fechaPago - fechaFactura) & " días)", "OK"))))) | AQ13: =IF(AN13="","",IF(AND(N13>0, AG13>0), IF(Configuración!$K$2="NO", "ALERTA: DESCUENTO DOBLE NO PERMITIDO", "OK"), "OK")) | AR13: =IF(AN13="","",IF(OR(AO13<>"OK", AP13<>"OK", AQ13<>"OK"), "⚠️ REVISAR", "OK"))
A14: =IF('Ordenes_Odoo'!A14="","",'Ordenes_Odoo'!A14) | B14: =IF('Ordenes_Odoo'!B14="","",'Ordenes_Odoo'!B14) | C14: =IF('Ordenes_Odoo'!C14="","",'Ordenes_Odoo'!C14) | D14: =IF('Ordenes_Odoo'!D14="","",'Ordenes_Odoo'!D14) | E14: =IF('Ordenes_Odoo'!E14="","",'Ordenes_Odoo'!E14) | F14: =IF('Ordenes_Odoo'!F14="","",'Ordenes_Odoo'!F14) | G14: =IF('Ordenes_Odoo'!G14="","",'Ordenes_Odoo'!G14) | H14: =IF('Ordenes_Odoo'!H14="","",'Ordenes_Odoo'!H14) | ... P14: =IF('Ordenes_Odoo'!P14="","",'Ordenes_Odoo'!P14) | Q14: =IF(A14="","",IFERROR(INDEX(Facturas_Odoo!$B:$B, MATCH(A14, Facturas_Odoo!$D:$D, 0)), "Sin Factura")) | R14: =IF(Q14="Sin Factura","",IFERROR(INDEX(Facturas_Odoo!$A:$A, MATCH(Q14, Facturas_Odoo!$B:$B, 0)), "")) | S14: =IF(Q14="Sin Factura","",IFERROR(_xlfn.XLOOKUP(1, (Facturas_Odoo!$D:$D=A14) * (Facturas_Odoo!$K:$K=I14), Facturas_Odoo!$L:$L, ""), "")) | T14: =IF(Q14="Sin Factura",0,IFERROR(_xlfn.XLOOKUP(1, (Facturas_Odoo!$D:$D=A14) * (Facturas_Odoo!$K:$K=I14), Facturas_Odoo!$M:$M, 0), 0)) | U14: =IF(Q14="Sin Factura",0,IFERROR(_xlfn.XLOOKUP(1, (Facturas_Odoo!$D:$D=A14) * (Facturas_Odoo!$K:$K=I14), Facturas_Odoo!$N:$N, 0), 0)) | V14: =IF(Q14="Sin Factura",0,IFERROR(_xlfn.XLOOKUP(1, (Facturas_Odoo!$D:$D=A14) * (Facturas_Odoo!$K:$K=I14), Facturas_Odoo!$O:$O, 0), 0)) | W14: =IF(Q14="Sin Factura",0,IFERROR(_xlfn.XLOOKUP(1, (Facturas_Odoo!$D:$D=A14) * (Facturas_Odoo!$K:$K=I14), Facturas_Odoo!$Q:$Q, 0), 0)) | X14: =IF(OR(Q14="Sin Factura",Q14=""),"",IFERROR(INDEX(Pagos_Odoo!$B:$B, MATCH(Q14, Pagos_Odoo!$I:$I, 0)), "Sin Pago")) | Y14: =IF(X14="Sin Pago","",IFERROR(INDEX(Pagos_Odoo!$C:$C, MATCH(X14, Pagos_Odoo!$B:$B, 0)), "")) | Z14: =IF(X14="Sin Pago","",IFERROR(INDEX(Pagos_Odoo!$A:$A, MATCH(X14, Pagos_Odoo!$B:$B, 0)), "")) | AA14: =IF(X14="Sin Pago","",IFERROR(INDEX(Pagos_Odoo!$F:$F, MATCH(X14, Pagos_Odoo!$B:$B, 0)), "")) | AB14: =IF(X14="Sin Pago",0,IFERROR(INDEX(Pagos_Odoo!$E:$E, MATCH(X14, Pagos_Odoo!$B:$B, 0)), 0)) | AC14: =IF(X14="Sin Pago","",IFERROR(INDEX(Pagos_Odoo!$G:$G, MATCH(X14, Pagos_Odoo!$B:$B, 0)), "")) | AD14: 0 | AG14: =IF(AN14="","",AD14+AE14+AF14) | AH14: =IF(AN14="","",P14*(1-AG14)) | AI14: =IF(AN14="","",IF(Q14="Sin Factura",0,IFERROR(INDEX(Facturas_Odoo!$H:$H, MATCH(Q14, Facturas_Odoo!$B:$B, 0)), 0)*(1-AG14))) | AJ14: =IF(AN14="","",_xlfn.LET(idVenta, AN14&"", pagos, IFERROR(SUMIF(Aux_Datos!$B:$B, idVenta, Aux_Datos!$L:$L), 0), retenciones, IFERROR(SUMIF(Aux_Datos!$O:$O, idVenta, Aux_Datos!$S:$S), 0), pagos_manuales, IFERROR(SUMIF('Asignación Pagos'!$G:$G, idVenta, 'Asignación Pagos'!$F:$F), 0), pagos+retenciones+pagos_manuales)) | AK14: =IF(AN14="","",AH14-AJ14) | AL14: =IF(AN14="","",IF(Q14="Sin Factura","",AI14-AJ14)) | AM14: =IF(AN14="","",IF(Q14="Sin Factura",0,P14-IFERROR(INDEX(Facturas_Odoo!$H:$H, MATCH(Q14, Facturas_Odoo!$B:$B, 0)), 0))) | AN14: =IF(AND(A14="", J14=""), "", IF(A14<>"", VALUE(MID(A14,2,LEN(A14))), AN13)) | AO14: =IF(AN14="","",IF(AD14=0,"OK",_xlfn.LET(monedaPago, IF(AA14="","USD",AA14), limitePermitido, IFERROR(VLOOKUP(monedaPago, Configuración!$A$2:$B$3, 2, FALSE), 0.15), IF(AD14>limitePermitido, "ALERTA: EXCESO (" & TEXT(limitePermitido, "0%") & " máx)", "OK")))) | AP14: =IF(AN14="","",IF(AE14=0,"OK",_xlfn.LET(fechaPago, Z14, fechaFactura, R14, diasCredito, IF(E14="Pago inmediato", 0, IFERROR(VALUE(MID(E14, 1, SEARCH(" ", E14)-1)), 0)), tolerancia, Configuración!$E$2, limiteDias, diasCredito + tolerancia, IF(OR(fechaPago="", fechaFactura=""), "REVISAR: SIN FECHA", IF(fechaPago - fechaFactura > limiteDias, "ALERTA: PAGO FUERA DE PLAZO (" & (fechaPago - fechaFactura) & " días)", "OK"))))) | AQ14: =IF(AN14="","",IF(AND(N14>0, AG14>0), IF(Configuración!$K$2="NO", "ALERTA: DESCUENTO DOBLE NO PERMITIDO", "OK"), "OK")) | AR14: =IF(AN14="","",IF(OR(AO14<>"OK", AP14<>"OK", AQ14<>"OK"), "⚠️ REVISAR", "OK"))
... A389: =IF('Ordenes_Odoo'!A389="","",'Ordenes_Odoo'!A389) | B389: =IF('Ordenes_Odoo'!B389="","",'Ordenes_Odoo'!B389) | C389: =IF('Ordenes_Odoo'!C389="","",'Ordenes_Odoo'!C389) | D389: =IF('Ordenes_Odoo'!D389="","",'Ordenes_Odoo'!D389) | E389: =IF('Ordenes_Odoo'!E389="","",'Ordenes_Odoo'!E389) | F389: =IF('Ordenes_Odoo'!F389="","",'Ordenes_Odoo'!F389) | G389: =IF('Ordenes_Odoo'!G389="","",'Ordenes_Odoo'!G389) | H389: =IF('Ordenes_Odoo'!H389="","",'Ordenes_Odoo'!H389) | ... P389: =IF('Ordenes_Odoo'!P389="","",'Ordenes_Odoo'!P389) | Q389: =IF(A389="","",IFERROR(INDEX(Facturas_Odoo!$B:$B, MATCH(A389, Facturas_Odoo!$D:$D, 0)), "Sin Factura")) | R389: =IF(Q389="Sin Factura","",IFERROR(INDEX(Facturas_Odoo!$A:$A, MATCH(Q389, Facturas_Odoo!$B:$B, 0)), "")) | S389: =IF(Q389="Sin Factura","",IFERROR(_xlfn.XLOOKUP(1, (Facturas_Odoo!$D:$D=A389) * (Facturas_Odoo!$K:$K=I389), Facturas_Odoo!$L:$L, ""), "")) | T389: =IF(Q389="Sin Factura",0,IFERROR(_xlfn.XLOOKUP(1, (Facturas_Odoo!$D:$D=A389) * (Facturas_Odoo!$K:$K=I389), Facturas_Odoo!$M:$M, 0), 0)) | U389: =IF(Q389="Sin Factura",0,IFERROR(_xlfn.XLOOKUP(1, (Facturas_Odoo!$D:$D=A389) * (Facturas_Odoo!$K:$K=I389), Facturas_Odoo!$N:$N, 0), 0)) | V389: =IF(Q389="Sin Factura",0,IFERROR(_xlfn.XLOOKUP(1, (Facturas_Odoo!$D:$D=A389) * (Facturas_Odoo!$K:$K=I389), Facturas_Odoo!$O:$O, 0), 0)) | W389: =IF(Q389="Sin Factura",0,IFERROR(_xlfn.XLOOKUP(1, (Facturas_Odoo!$D:$D=A389) * (Facturas_Odoo!$K:$K=I389), Facturas_Odoo!$Q:$Q, 0), 0)) | X389: =IF(OR(Q389="Sin Factura",Q389=""),"",IFERROR(INDEX(Pagos_Odoo!$B:$B, MATCH(Q389, Pagos_Odoo!$I:$I, 0)), "Sin Pago")) | Y389: =IF(X389="Sin Pago","",IFERROR(INDEX(Pagos_Odoo!$C:$C, MATCH(X389, Pagos_Odoo!$B:$B, 0)), "")) | Z389: =IF(X389="Sin Pago","",IFERROR(INDEX(Pagos_Odoo!$A:$A, MATCH(X389, Pagos_Odoo!$B:$B, 0)), "")) | AA389: =IF(X389="Sin Pago","",IFERROR(INDEX(Pagos_Odoo!$F:$F, MATCH(X389, Pagos_Odoo!$B:$B, 0)), "")) | AB389: =IF(X389="Sin Pago",0,IFERROR(INDEX(Pagos_Odoo!$E:$E, MATCH(X389, Pagos_Odoo!$B:$B, 0)), 0)) | AC389: =IF(X389="Sin Pago","",IFERROR(INDEX(Pagos_Odoo!$G:$G, MATCH(X389, Pagos_Odoo!$B:$B, 0)), "")) | AD389: 0 | AG389: =IF(AN389="","",AD389+AE389+AF389) | AH389: =IF(AN389="","",P389*(1-AG389)) | AI389: =IF(AN389="","",IF(Q389="Sin Factura",0,IFERROR(INDEX(Facturas_Odoo!$H:$H, MATCH(Q389, Facturas_Odoo!$B:$B, 0)), 0)*(1-AG389))) | AJ389: =IF(AN389="","",_xlfn.LET(idVenta, AN389&"", pagos, IFERROR(SUMIF(Aux_Datos!$B:$B, idVenta, Aux_Datos!$L:$L), 0), retenciones, IFERROR(SUMIF(Aux_Datos!$O:$O, idVenta, Aux_Datos!$S:$S), 0), pagos_manuales, IFERROR(SUMIF('Asignación Pagos'!$G:$G, idVenta, 'Asignación Pagos'!$F:$F), 0), pagos+retenciones+pagos_manuales)) | AK389: =IF(AN389="","",AH389-AJ389) | AL389: =IF(AN389="","",IF(Q389="Sin Factura","",AI389-AJ389)) | AM389: =IF(AN389="","",IF(Q389="Sin Factura",0,P389-IFERROR(INDEX(Facturas_Odoo!$H:$H, MATCH(Q389, Facturas_Odoo!$B:$B, 0)), 0))) | AN389: =IF(AND(A389="", J389=""), "", IF(A389<>"", VALUE(MID(A389,2,LEN(A389))), AN388)) | AO389: =IF(AN389="","",IF(AD389=0,"OK",_xlfn.LET(monedaPago, IF(AA389="","USD",AA389), limitePermitido, IFERROR(VLOOKUP(monedaPago, Configuración!$A$2:$B$3, 2, FALSE), 0.15), IF(AD389>limitePermitido, "ALERTA: EXCESO (" & TEXT(limitePermitido, "0%") & " máx)", "OK")))) | AP389: =IF(AN389="","",IF(AE389=0,"OK",_xlfn.LET(fechaPago, Z389, fechaFactura, R389, diasCredito, IF(E389="Pago inmediato", 0, IFERROR(VALUE(MID(E389, 1, SEARCH(" ", E389)-1)), 0)), tolerancia, Configuración!$E$2, limiteDias, diasCredito + tolerancia, IF(OR(fechaPago="", fechaFactura=""), "REVISAR: SIN FECHA", IF(fechaPago - fechaFactura > limiteDias, "ALERTA: PAGO FUERA DE PLAZO (" & (fechaPago - fechaFactura) & " días)", "OK"))))) | AQ389: =IF(AN389="","",IF(AND(N389>0, AG389>0), IF(Configuración!$K$2="NO", "ALERTA: DESCUENTO DOBLE NO PERMITIDO", "OK"), "OK")) | AR389: =IF(AN389="","",IF(OR(AO389<>"OK", AP389<>"OK", AQ389<>"OK"), "⚠️ REVISAR", "OK"))
A390: =IF('Ordenes_Odoo'!A390="","",'Ordenes_Odoo'!A390) | B390: =IF('Ordenes_Odoo'!B390="","",'Ordenes_Odoo'!B390) | C390: =IF('Ordenes_Odoo'!C390="","",'Ordenes_Odoo'!C390) | D390: =IF('Ordenes_Odoo'!D390="","",'Ordenes_Odoo'!D390) | E390: =IF('Ordenes_Odoo'!E390="","",'Ordenes_Odoo'!E390) | F390: =IF('Ordenes_Odoo'!F390="","",'Ordenes_Odoo'!F390) | G390: =IF('Ordenes_Odoo'!G390="","",'Ordenes_Odoo'!G390) | H390: =IF('Ordenes_Odoo'!H390="","",'Ordenes_Odoo'!H390) | ... P390: =IF('Ordenes_Odoo'!P390="","",'Ordenes_Odoo'!P390) | Q390: =IF(A390="","",IFERROR(INDEX(Facturas_Odoo!$B:$B, MATCH(A390, Facturas_Odoo!$D:$D, 0)), "Sin Factura")) | R390: =IF(Q390="Sin Factura","",IFERROR(INDEX(Facturas_Odoo!$A:$A, MATCH(Q390, Facturas_Odoo!$B:$B, 0)), "")) | S390: =IF(Q390="Sin Factura","",IFERROR(_xlfn.XLOOKUP(1, (Facturas_Odoo!$D:$D=A390) * (Facturas_Odoo!$K:$K=I390), Facturas_Odoo!$L:$L, ""), "")) | T390: =IF(Q390="Sin Factura",0,IFERROR(_xlfn.XLOOKUP(1, (Facturas_Odoo!$D:$D=A390) * (Facturas_Odoo!$K:$K=I390), Facturas_Odoo!$M:$M, 0), 0)) | U390: =IF(Q390="Sin Factura",0,IFERROR(_xlfn.XLOOKUP(1, (Facturas_Odoo!$D:$D=A390) * (Facturas_Odoo!$K:$K=I390), Facturas_Odoo!$N:$N, 0), 0)) | V390: =IF(Q390="Sin Factura",0,IFERROR(_xlfn.XLOOKUP(1, (Facturas_Odoo!$D:$D=A390) * (Facturas_Odoo!$K:$K=I390), Facturas_Odoo!$O:$O, 0), 0)) | W390: =IF(Q390="Sin Factura",0,IFERROR(_xlfn.XLOOKUP(1, (Facturas_Odoo!$D:$D=A390) * (Facturas_Odoo!$K:$K=I390), Facturas_Odoo!$Q:$Q, 0), 0)) | X390: =IF(OR(Q390="Sin Factura",Q390=""),"",IFERROR(INDEX(Pagos_Odoo!$B:$B, MATCH(Q390, Pagos_Odoo!$I:$I, 0)), "Sin Pago")) | Y390: =IF(X390="Sin Pago","",IFERROR(INDEX(Pagos_Odoo!$C:$C, MATCH(X390, Pagos_Odoo!$B:$B, 0)), "")) | Z390: =IF(X390="Sin Pago","",IFERROR(INDEX(Pagos_Odoo!$A:$A, MATCH(X390, Pagos_Odoo!$B:$B, 0)), "")) | AA390: =IF(X390="Sin Pago","",IFERROR(INDEX(Pagos_Odoo!$F:$F, MATCH(X390, Pagos_Odoo!$B:$B, 0)), "")) | AB390: =IF(X390="Sin Pago",0,IFERROR(INDEX(Pagos_Odoo!$E:$E, MATCH(X390, Pagos_Odoo!$B:$B, 0)), 0)) | AC390: =IF(X390="Sin Pago","",IFERROR(INDEX(Pagos_Odoo!$G:$G, MATCH(X390, Pagos_Odoo!$B:$B, 0)), "")) | AD390: 0 | AE390: 0.0509 | AG390: =IF(AN390="","",AD390+AE390+AF390) | AH390: =IF(AN390="","",P390*(1-AG390)) | AI390: =IF(AN390="","",IF(Q390="Sin Factura",0,IFERROR(INDEX(Facturas_Odoo!$H:$H, MATCH(Q390, Facturas_Odoo!$B:$B, 0)), 0)*(1-AG390))) | AJ390: =IF(AN390="","",_xlfn.LET(idVenta, AN390&"", pagos, IFERROR(SUMIF(Aux_Datos!$B:$B, idVenta, Aux_Datos!$L:$L), 0), retenciones, IFERROR(SUMIF(Aux_Datos!$O:$O, idVenta, Aux_Datos!$S:$S), 0), pagos_manuales, IFERROR(SUMIF('Asignación Pagos'!$G:$G, idVenta, 'Asignación Pagos'!$F:$F), 0), pagos+retenciones+pagos_manuales)) | AK390: =IF(AN390="","",AH390-AJ390) | AL390: =IF(AN390="","",IF(Q390="Sin Factura","",AI390-AJ390)) | AM390: =IF(AN390="","",IF(Q390="Sin Factura",0,P390-IFERROR(INDEX(Facturas_Odoo!$H:$H, MATCH(Q390, Facturas_Odoo!$B:$B, 0)), 0))) | AN390: =IF(AND(A390="", J390=""), "", IF(A390<>"", VALUE(MID(A390,2,LEN(A390))), AN389)) | AO390: =IF(AN390="","",IF(AD390=0,"OK",_xlfn.LET(monedaPago, IF(AA390="","USD",AA390), limitePermitido, IFERROR(VLOOKUP(monedaPago, Configuración!$A$2:$B$3, 2, FALSE), 0.15), IF(AD390>limitePermitido, "ALERTA: EXCESO (" & TEXT(limitePermitido, "0%") & " máx)", "OK")))) | AP390: =IF(AN390="","",IF(AE390=0,"OK",_xlfn.LET(fechaPago, Z390, fechaFactura, R390, diasCredito, IF(E390="Pago inmediato", 0, IFERROR(VALUE(MID(E390, 1, SEARCH(" ", E390)-1)), 0)), tolerancia, Configuración!$E$2, limiteDias, diasCredito + tolerancia, IF(OR(fechaPago="", fechaFactura=""), "REVISAR: SIN FECHA", IF(fechaPago - fechaFactura > limiteDias, "ALERTA: PAGO FUERA DE PLAZO (" & (fechaPago - fechaFactura) & " días)", "OK"))))) | AQ390: =IF(AN390="","",IF(AND(N390>0, AG390>0), IF(Configuración!$K$2="NO", "ALERTA: DESCUENTO DOBLE NO PERMITIDO", "OK"), "OK")) | AR390: =IF(AN390="","",IF(OR(AO390<>"OK", AP390<>"OK", AQ390<>"OK"), "⚠️ REVISAR", "OK"))
A391: =IF('Ordenes_Odoo'!A391="","",'Ordenes_Odoo'!A391) | B391: =IF('Ordenes_Odoo'!B391="","",'Ordenes_Odoo'!B391) | C391: =IF('Ordenes_Odoo'!C391="","",'Ordenes_Odoo'!C391) | D391: =IF('Ordenes_Odoo'!D391="","",'Ordenes_Odoo'!D391) | E391: =IF('Ordenes_Odoo'!E391="","",'Ordenes_Odoo'!E391) | F391: =IF('Ordenes_Odoo'!F391="","",'Ordenes_Odoo'!F391) | G391: =IF('Ordenes_Odoo'!G391="","",'Ordenes_Odoo'!G391) | H391: =IF('Ordenes_Odoo'!H391="","",'Ordenes_Odoo'!H391) | ... P391: =IF('Ordenes_Odoo'!P391="","",'Ordenes_Odoo'!P391) | Q391: =IF(A391="","",IFERROR(INDEX(Facturas_Odoo!$B:$B, MATCH(A391, Facturas_Odoo!$D:$D, 0)), "Sin Factura")) | R391: =IF(Q391="Sin Factura","",IFERROR(INDEX(Facturas_Odoo!$A:$A, MATCH(Q391, Facturas_Odoo!$B:$B, 0)), "")) | S391: =IF(Q391="Sin Factura","",IFERROR(_xlfn.XLOOKUP(1, (Facturas_Odoo!$D:$D=A391) * (Facturas_Odoo!$K:$K=I391), Facturas_Odoo!$L:$L, ""), "")) | T391: =IF(Q391="Sin Factura",0,IFERROR(_xlfn.XLOOKUP(1, (Facturas_Odoo!$D:$D=A391) * (Facturas_Odoo!$K:$K=I391), Facturas_Odoo!$M:$M, 0), 0)) | U391: =IF(Q391="Sin Factura",0,IFERROR(_xlfn.XLOOKUP(1, (Facturas_Odoo!$D:$D=A391) * (Facturas_Odoo!$K:$K=I391), Facturas_Odoo!$N:$N, 0), 0)) | V391: =IF(Q391="Sin Factura",0,IFERROR(_xlfn.XLOOKUP(1, (Facturas_Odoo!$D:$D=A391) * (Facturas_Odoo!$K:$K=I391), Facturas_Odoo!$O:$O, 0), 0)) | W391: =IF(Q391="Sin Factura",0,IFERROR(_xlfn.XLOOKUP(1, (Facturas_Odoo!$D:$D=A391) * (Facturas_Odoo!$K:$K=I391), Facturas_Odoo!$Q:$Q, 0), 0)) | X391: =IF(OR(Q391="Sin Factura",Q391=""),"",IFERROR(INDEX(Pagos_Odoo!$B:$B, MATCH(Q391, Pagos_Odoo!$I:$I, 0)), "Sin Pago")) | Y391: =IF(X391="Sin Pago","",IFERROR(INDEX(Pagos_Odoo!$C:$C, MATCH(X391, Pagos_Odoo!$B:$B, 0)), "")) | Z391: =IF(X391="Sin Pago","",IFERROR(INDEX(Pagos_Odoo!$A:$A, MATCH(X391, Pagos_Odoo!$B:$B, 0)), "")) | AA391: =IF(X391="Sin Pago","",IFERROR(INDEX(Pagos_Odoo!$F:$F, MATCH(X391, Pagos_Odoo!$B:$B, 0)), "")) | AB391: =IF(X391="Sin Pago",0,IFERROR(INDEX(Pagos_Odoo!$E:$E, MATCH(X391, Pagos_Odoo!$B:$B, 0)), 0)) | AC391: =IF(X391="Sin Pago","",IFERROR(INDEX(Pagos_Odoo!$G:$G, MATCH(X391, Pagos_Odoo!$B:$B, 0)), "")) | AD391: 0 | AG391: =IF(AN391="","",AD391+AE391+AF391) | AH391: =IF(AN391="","",P391*(1-AG391)) | AI391: =IF(AN391="","",IF(Q391="Sin Factura",0,IFERROR(INDEX(Facturas_Odoo!$H:$H, MATCH(Q391, Facturas_Odoo!$B:$B, 0)), 0)*(1-AG391))) | AJ391: =IF(AN391="","",_xlfn.LET(idVenta, AN391&"", pagos, IFERROR(SUMIF(Aux_Datos!$B:$B, idVenta, Aux_Datos!$L:$L), 0), retenciones, IFERROR(SUMIF(Aux_Datos!$O:$O, idVenta, Aux_Datos!$S:$S), 0), pagos_manuales, IFERROR(SUMIF('Asignación Pagos'!$G:$G, idVenta, 'Asignación Pagos'!$F:$F), 0), pagos+retenciones+pagos_manuales)) | AK391: =IF(AN391="","",AH391-AJ391) | AL391: =IF(AN391="","",IF(Q391="Sin Factura","",AI391-AJ391)) | AM391: =IF(AN391="","",IF(Q391="Sin Factura",0,P391-IFERROR(INDEX(Facturas_Odoo!$H:$H, MATCH(Q391, Facturas_Odoo!$B:$B, 0)), 0))) | AN391: =IF(AND(A391="", J391=""), "", IF(A391<>"", VALUE(MID(A391,2,LEN(A391))), AN390)) | AO391: =IF(AN391="","",IF(AD391=0,"OK",_xlfn.LET(monedaPago, IF(AA391="","USD",AA391), limitePermitido, IFERROR(VLOOKUP(monedaPago, Configuración!$A$2:$B$3, 2, FALSE), 0.15), IF(AD391>limitePermitido, "ALERTA: EXCESO (" & TEXT(limitePermitido, "0%") & " máx)", "OK")))) | AP391: =IF(AN391="","",IF(AE391=0,"OK",_xlfn.LET(fechaPago, Z391, fechaFactura, R391, diasCredito, IF(E391="Pago inmediato", 0, IFERROR(VALUE(MID(E391, 1, SEARCH(" ", E391)-1)), 0)), tolerancia, Configuración!$E$2, limiteDias, diasCredito + tolerancia, IF(OR(fechaPago="", fechaFactura=""), "REVISAR: SIN FECHA", IF(fechaPago - fechaFactura > limiteDias, "ALERTA: PAGO FUERA DE PLAZO (" & (fechaPago - fechaFactura) & " días)", "OK"))))) | AQ391: =IF(AN391="","",IF(AND(N391>0, AG391>0), IF(Configuración!$K$2="NO", "ALERTA: DESCUENTO DOBLE NO PERMITIDO", "OK"), "OK")) | AR391: =IF(AN391="","",IF(OR(AO391<>"OK", AP391<>"OK", AQ391<>"OK"), "⚠️ REVISAR", "OK"))
A392: =IF('Ordenes_Odoo'!A392="","",'Ordenes_Odoo'!A392) | B392: =IF('Ordenes_Odoo'!B392="","",'Ordenes_Odoo'!B392) | C392: =IF('Ordenes_Odoo'!C392="","",'Ordenes_Odoo'!C392) | D392: =IF('Ordenes_Odoo'!D392="","",'Ordenes_Odoo'!D392) | E392: =IF('Ordenes_Odoo'!E392="","",'Ordenes_Odoo'!E392) | F392: =IF('Ordenes_Odoo'!F392="","",'Ordenes_Odoo'!F392) | G392: =IF('Ordenes_Odoo'!G392="","",'Ordenes_Odoo'!G392) | H392: =IF('Ordenes_Odoo'!H392="","",'Ordenes_Odoo'!H392) | ... P392: =IF('Ordenes_Odoo'!P392="","",'Ordenes_Odoo'!P392) | Q392: =IF(A392="","",IFERROR(INDEX(Facturas_Odoo!$B:$B, MATCH(A392, Facturas_Odoo!$D:$D, 0)), "Sin Factura")) | R392: =IF(Q392="Sin Factura","",IFERROR(INDEX(Facturas_Odoo!$A:$A, MATCH(Q392, Facturas_Odoo!$B:$B, 0)), "")) | S392: =IF(Q392="Sin Factura","",IFERROR(_xlfn.XLOOKUP(1, (Facturas_Odoo!$D:$D=A392) * (Facturas_Odoo!$K:$K=I392), Facturas_Odoo!$L:$L, ""), "")) | T392: =IF(Q392="Sin Factura",0,IFERROR(_xlfn.XLOOKUP(1, (Facturas_Odoo!$D:$D=A392) * (Facturas_Odoo!$K:$K=I392), Facturas_Odoo!$M:$M, 0), 0)) | U392: =IF(Q392="Sin Factura",0,IFERROR(_xlfn.XLOOKUP(1, (Facturas_Odoo!$D:$D=A392) * (Facturas_Odoo!$K:$K=I392), Facturas_Odoo!$N:$N, 0), 0)) | V392: =IF(Q392="Sin Factura",0,IFERROR(_xlfn.XLOOKUP(1, (Facturas_Odoo!$D:$D=A392) * (Facturas_Odoo!$K:$K=I392), Facturas_Odoo!$O:$O, 0), 0)) | W392: =IF(Q392="Sin Factura",0,IFERROR(_xlfn.XLOOKUP(1, (Facturas_Odoo!$D:$D=A392) * (Facturas_Odoo!$K:$K=I392), Facturas_Odoo!$Q:$Q, 0), 0)) | X392: =IF(OR(Q392="Sin Factura",Q392=""),"",IFERROR(INDEX(Pagos_Odoo!$B:$B, MATCH(Q392, Pagos_Odoo!$I:$I, 0)), "Sin Pago")) | Y392: =IF(X392="Sin Pago","",IFERROR(INDEX(Pagos_Odoo!$C:$C, MATCH(X392, Pagos_Odoo!$B:$B, 0)), "")) | Z392: =IF(X392="Sin Pago","",IFERROR(INDEX(Pagos_Odoo!$A:$A, MATCH(X392, Pagos_Odoo!$B:$B, 0)), "")) | AA392: =IF(X392="Sin Pago","",IFERROR(INDEX(Pagos_Odoo!$F:$F, MATCH(X392, Pagos_Odoo!$B:$B, 0)), "")) | AB392: =IF(X392="Sin Pago",0,IFERROR(INDEX(Pagos_Odoo!$E:$E, MATCH(X392, Pagos_Odoo!$B:$B, 0)), 0)) | AC392: =IF(X392="Sin Pago","",IFERROR(INDEX(Pagos_Odoo!$G:$G, MATCH(X392, Pagos_Odoo!$B:$B, 0)), "")) | AD392: 0 | AG392: =IF(AN392="","",AD392+AE392+AF392) | AH392: =IF(AN392="","",P392*(1-AG392)) | AI392: =IF(AN392="","",IF(Q392="Sin Factura",0,IFERROR(INDEX(Facturas_Odoo!$H:$H, MATCH(Q392, Facturas_Odoo!$B:$B, 0)), 0)*(1-AG392))) | AJ392: =IF(AN392="","",_xlfn.LET(idVenta, AN392&"", pagos, IFERROR(SUMIF(Aux_Datos!$B:$B, idVenta, Aux_Datos!$L:$L), 0), retenciones, IFERROR(SUMIF(Aux_Datos!$O:$O, idVenta, Aux_Datos!$S:$S), 0), pagos_manuales, IFERROR(SUMIF('Asignación Pagos'!$G:$G, idVenta, 'Asignación Pagos'!$F:$F), 0), pagos+retenciones+pagos_manuales)) | AK392: =IF(AN392="","",AH392-AJ392) | AL392: =IF(AN392="","",IF(Q392="Sin Factura","",AI392-AJ392)) | AM392: =IF(AN392="","",IF(Q392="Sin Factura",0,P392-IFERROR(INDEX(Facturas_Odoo!$H:$H, MATCH(Q392, Facturas_Odoo!$B:$B, 0)), 0))) | AN392: =IF(AND(A392="", J392=""), "", IF(A392<>"", VALUE(MID(A392,2,LEN(A392))), AN391)) | AO392: =IF(AN392="","",IF(AD392=0,"OK",_xlfn.LET(monedaPago, IF(AA392="","USD",AA392), limitePermitido, IFERROR(VLOOKUP(monedaPago, Configuración!$A$2:$B$3, 2, FALSE), 0.15), IF(AD392>limitePermitido, "ALERTA: EXCESO (" & TEXT(limitePermitido, "0%") & " máx)", "OK")))) | AP392: =IF(AN392="","",IF(AE392=0,"OK",_xlfn.LET(fechaPago, Z392, fechaFactura, R392, diasCredito, IF(E392="Pago inmediato", 0, IFERROR(VALUE(MID(E392, 1, SEARCH(" ", E392)-1)), 0)), tolerancia, Configuración!$E$2, limiteDias, diasCredito + tolerancia, IF(OR(fechaPago="", fechaFactura=""), "REVISAR: SIN FECHA", IF(fechaPago - fechaFactura > limiteDias, "ALERTA: PAGO FUERA DE PLAZO (" & (fechaPago - fechaFactura) & " días)", "OK"))))) | AQ392: =IF(AN392="","",IF(AND(N392>0, AG392>0), IF(Configuración!$K$2="NO", "ALERTA: DESCUENTO DOBLE NO PERMITIDO", "OK"), "OK")) | AR392: =IF(AN392="","",IF(OR(AO392<>"OK", AP392<>"OK", AQ392<>"OK"), "⚠️ REVISAR", "OK"))
A393: =IF('Ordenes_Odoo'!A393="","",'Ordenes_Odoo'!A393) | B393: =IF('Ordenes_Odoo'!B393="","",'Ordenes_Odoo'!B393) | C393: =IF('Ordenes_Odoo'!C393="","",'Ordenes_Odoo'!C393) | D393: =IF('Ordenes_Odoo'!D393="","",'Ordenes_Odoo'!D393) | E393: =IF('Ordenes_Odoo'!E393="","",'Ordenes_Odoo'!E393) | F393: =IF('Ordenes_Odoo'!F393="","",'Ordenes_Odoo'!F393) | G393: =IF('Ordenes_Odoo'!G393="","",'Ordenes_Odoo'!G393) | H393: =IF('Ordenes_Odoo'!H393="","",'Ordenes_Odoo'!H393) | ... P393: =IF('Ordenes_Odoo'!P393="","",'Ordenes_Odoo'!P393) | Q393: =IF(A393="","",IFERROR(INDEX(Facturas_Odoo!$B:$B, MATCH(A393, Facturas_Odoo!$D:$D, 0)), "Sin Factura")) | R393: =IF(Q393="Sin Factura","",IFERROR(INDEX(Facturas_Odoo!$A:$A, MATCH(Q393, Facturas_Odoo!$B:$B, 0)), "")) | S393: =IF(Q393="Sin Factura","",IFERROR(_xlfn.XLOOKUP(1, (Facturas_Odoo!$D:$D=A393) * (Facturas_Odoo!$K:$K=I393), Facturas_Odoo!$L:$L, ""), "")) | T393: =IF(Q393="Sin Factura",0,IFERROR(_xlfn.XLOOKUP(1, (Facturas_Odoo!$D:$D=A393) * (Facturas_Odoo!$K:$K=I393), Facturas_Odoo!$M:$M, 0), 0)) | U393: =IF(Q393="Sin Factura",0,IFERROR(_xlfn.XLOOKUP(1, (Facturas_Odoo!$D:$D=A393) * (Facturas_Odoo!$K:$K=I393), Facturas_Odoo!$N:$N, 0), 0)) | V393: =IF(Q393="Sin Factura",0,IFERROR(_xlfn.XLOOKUP(1, (Facturas_Odoo!$D:$D=A393) * (Facturas_Odoo!$K:$K=I393), Facturas_Odoo!$O:$O, 0), 0)) | W393: =IF(Q393="Sin Factura",0,IFERROR(_xlfn.XLOOKUP(1, (Facturas_Odoo!$D:$D=A393) * (Facturas_Odoo!$K:$K=I393), Facturas_Odoo!$Q:$Q, 0), 0)) | X393: =IF(OR(Q393="Sin Factura",Q393=""),"",IFERROR(INDEX(Pagos_Odoo!$B:$B, MATCH(Q393, Pagos_Odoo!$I:$I, 0)), "Sin Pago")) | Y393: =IF(X393="Sin Pago","",IFERROR(INDEX(Pagos_Odoo!$C:$C, MATCH(X393, Pagos_Odoo!$B:$B, 0)), "")) | Z393: =IF(X393="Sin Pago","",IFERROR(INDEX(Pagos_Odoo!$A:$A, MATCH(X393, Pagos_Odoo!$B:$B, 0)), "")) | AA393: =IF(X393="Sin Pago","",IFERROR(INDEX(Pagos_Odoo!$F:$F, MATCH(X393, Pagos_Odoo!$B:$B, 0)), "")) | AB393: =IF(X393="Sin Pago",0,IFERROR(INDEX(Pagos_Odoo!$E:$E, MATCH(X393, Pagos_Odoo!$B:$B, 0)), 0)) | AC393: =IF(X393="Sin Pago","",IFERROR(INDEX(Pagos_Odoo!$G:$G, MATCH(X393, Pagos_Odoo!$B:$B, 0)), "")) | AD393: 0 | AG393: =IF(AN393="","",AD393+AE393+AF393) | AH393: =IF(AN393="","",P393*(1-AG393)) | AI393: =IF(AN393="","",IF(Q393="Sin Factura",0,IFERROR(INDEX(Facturas_Odoo!$H:$H, MATCH(Q393, Facturas_Odoo!$B:$B, 0)), 0)*(1-AG393))) | AJ393: =IF(AN393="","",_xlfn.LET(idVenta, AN393&"", pagos, IFERROR(SUMIF(Aux_Datos!$B:$B, idVenta, Aux_Datos!$L:$L), 0), retenciones, IFERROR(SUMIF(Aux_Datos!$O:$O, idVenta, Aux_Datos!$S:$S), 0), pagos_manuales, IFERROR(SUMIF('Asignación Pagos'!$G:$G, idVenta, 'Asignación Pagos'!$F:$F), 0), pagos+retenciones+pagos_manuales)) | AK393: =IF(AN393="","",AH393-AJ393) | AL393: =IF(AN393="","",IF(Q393="Sin Factura","",AI393-AJ393)) | AM393: =IF(AN393="","",IF(Q393="Sin Factura",0,P393-IFERROR(INDEX(Facturas_Odoo!$H:$H, MATCH(Q393, Facturas_Odoo!$B:$B, 0)), 0))) | AN393: =IF(AND(A393="", J393=""), "", IF(A393<>"", VALUE(MID(A393,2,LEN(A393))), AN392)) | AO393: =IF(AN393="","",IF(AD393=0,"OK",_xlfn.LET(monedaPago, IF(AA393="","USD",AA393), limitePermitido, IFERROR(VLOOKUP(monedaPago, Configuración!$A$2:$B$3, 2, FALSE), 0.15), IF(AD393>limitePermitido, "ALERTA: EXCESO (" & TEXT(limitePermitido, "0%") & " máx)", "OK")))) | AP393: =IF(AN393="","",IF(AE393=0,"OK",_xlfn.LET(fechaPago, Z393, fechaFactura, R393, diasCredito, IF(E393="Pago inmediato", 0, IFERROR(VALUE(MID(E393, 1, SEARCH(" ", E393)-1)), 0)), tolerancia, Configuración!$E$2, limiteDias, diasCredito + tolerancia, IF(OR(fechaPago="", fechaFactura=""), "REVISAR: SIN FECHA", IF(fechaPago - fechaFactura > limiteDias, "ALERTA: PAGO FUERA DE PLAZO (" & (fechaPago - fechaFactura) & " días)", "OK"))))) | AQ393: =IF(AN393="","",IF(AND(N393>0, AG393>0), IF(Configuración!$K$2="NO", "ALERTA: DESCUENTO DOBLE NO PERMITIDO", "OK"), "OK")) | AR393: =IF(AN393="","",IF(OR(AO393<>"OK", AP393<>"OK", AQ393<>"OK"), "⚠️ REVISAR", "OK"))
A394: =IF('Ordenes_Odoo'!A394="","",'Ordenes_Odoo'!A394) | B394: =IF('Ordenes_Odoo'!B394="","",'Ordenes_Odoo'!B394) | C394: =IF('Ordenes_Odoo'!C394="","",'Ordenes_Odoo'!C394) | D394: =IF('Ordenes_Odoo'!D394="","",'Ordenes_Odoo'!D394) | E394: =IF('Ordenes_Odoo'!E394="","",'Ordenes_Odoo'!E394) | F394: =IF('Ordenes_Odoo'!F394="","",'Ordenes_Odoo'!F394) | G394: =IF('Ordenes_Odoo'!G394="","",'Ordenes_Odoo'!G394) | H394: =IF('Ordenes_Odoo'!H394="","",'Ordenes_Odoo'!H394) | ... P394: =IF('Ordenes_Odoo'!P394="","",'Ordenes_Odoo'!P394) | Q394: =IF(A394="","",IFERROR(INDEX(Facturas_Odoo!$B:$B, MATCH(A394, Facturas_Odoo!$D:$D, 0)), "Sin Factura")) | R394: =IF(Q394="Sin Factura","",IFERROR(INDEX(Facturas_Odoo!$A:$A, MATCH(Q394, Facturas_Odoo!$B:$B, 0)), "")) | S394: =IF(Q394="Sin Factura","",IFERROR(_xlfn.XLOOKUP(1, (Facturas_Odoo!$D:$D=A394) * (Facturas_Odoo!$K:$K=I394), Facturas_Odoo!$L:$L, ""), "")) | T394: =IF(Q394="Sin Factura",0,IFERROR(_xlfn.XLOOKUP(1, (Facturas_Odoo!$D:$D=A394) * (Facturas_Odoo!$K:$K=I394), Facturas_Odoo!$M:$M, 0), 0)) | U394: =IF(Q394="Sin Factura",0,IFERROR(_xlfn.XLOOKUP(1, (Facturas_Odoo!$D:$D=A394) * (Facturas_Odoo!$K:$K=I394), Facturas_Odoo!$N:$N, 0), 0)) | V394: =IF(Q394="Sin Factura",0,IFERROR(_xlfn.XLOOKUP(1, (Facturas_Odoo!$D:$D=A394) * (Facturas_Odoo!$K:$K=I394), Facturas_Odoo!$O:$O, 0), 0)) | W394: =IF(Q394="Sin Factura",0,IFERROR(_xlfn.XLOOKUP(1, (Facturas_Odoo!$D:$D=A394) * (Facturas_Odoo!$K:$K=I394), Facturas_Odoo!$Q:$Q, 0), 0)) | X394: =IF(OR(Q394="Sin Factura",Q394=""),"",IFERROR(INDEX(Pagos_Odoo!$B:$B, MATCH(Q394, Pagos_Odoo!$I:$I, 0)), "Sin Pago")) | Y394: =IF(X394="Sin Pago","",IFERROR(INDEX(Pagos_Odoo!$C:$C, MATCH(X394, Pagos_Odoo!$B:$B, 0)), "")) | Z394: =IF(X394="Sin Pago","",IFERROR(INDEX(Pagos_Odoo!$A:$A, MATCH(X394, Pagos_Odoo!$B:$B, 0)), "")) | AA394: =IF(X394="Sin Pago","",IFERROR(INDEX(Pagos_Odoo!$F:$F, MATCH(X394, Pagos_Odoo!$B:$B, 0)), "")) | AB394: =IF(X394="Sin Pago",0,IFERROR(INDEX(Pagos_Odoo!$E:$E, MATCH(X394, Pagos_Odoo!$B:$B, 0)), 0)) | AC394: =IF(X394="Sin Pago","",IFERROR(INDEX(Pagos_Odoo!$G:$G, MATCH(X394, Pagos_Odoo!$B:$B, 0)), "")) | AD394: 0 | AG394: =IF(AN394="","",AD394+AE394+AF394) | AH394: =IF(AN394="","",P394*(1-AG394)) | AI394: =IF(AN394="","",IF(Q394="Sin Factura",0,IFERROR(INDEX(Facturas_Odoo!$H:$H, MATCH(Q394, Facturas_Odoo!$B:$B, 0)), 0)*(1-AG394))) | AJ394: =IF(AN394="","",_xlfn.LET(idVenta, AN394&"", pagos, IFERROR(SUMIF(Aux_Datos!$B:$B, idVenta, Aux_Datos!$L:$L), 0), retenciones, IFERROR(SUMIF(Aux_Datos!$O:$O, idVenta, Aux_Datos!$S:$S), 0), pagos_manuales, IFERROR(SUMIF('Asignación Pagos'!$G:$G, idVenta, 'Asignación Pagos'!$F:$F), 0), pagos+retenciones+pagos_manuales)) | AK394: =IF(AN394="","",AH394-AJ394) | AL394: =IF(AN394="","",IF(Q394="Sin Factura","",AI394-AJ394)) | AM394: =IF(AN394="","",IF(Q394="Sin Factura",0,P394-IFERROR(INDEX(Facturas_Odoo!$H:$H, MATCH(Q394, Facturas_Odoo!$B:$B, 0)), 0))) | AN394: =IF(AND(A394="", J394=""), "", IF(A394<>"", VALUE(MID(A394,2,LEN(A394))), AN393)) | AO394: =IF(AN394="","",IF(AD394=0,"OK",_xlfn.LET(monedaPago, IF(AA394="","USD",AA394), limitePermitido, IFERROR(VLOOKUP(monedaPago, Configuración!$A$2:$B$3, 2, FALSE), 0.15), IF(AD394>limitePermitido, "ALERTA: EXCESO (" & TEXT(limitePermitido, "0%") & " máx)", "OK")))) | AP394: =IF(AN394="","",IF(AE394=0,"OK",_xlfn.LET(fechaPago, Z394, fechaFactura, R394, diasCredito, IF(E394="Pago inmediato", 0, IFERROR(VALUE(MID(E394, 1, SEARCH(" ", E394)-1)), 0)), tolerancia, Configuración!$E$2, limiteDias, diasCredito + tolerancia, IF(OR(fechaPago="", fechaFactura=""), "REVISAR: SIN FECHA", IF(fechaPago - fechaFactura > limiteDias, "ALERTA: PAGO FUERA DE PLAZO (" & (fechaPago - fechaFactura) & " días)", "OK"))))) | AQ394: =IF(AN394="","",IF(AND(N394>0, AG394>0), IF(Configuración!$K$2="NO", "ALERTA: DESCUENTO DOBLE NO PERMITIDO", "OK"), "OK")) | AR394: =IF(AN394="","",IF(OR(AO394<>"OK", AP394<>"OK", AQ394<>"OK"), "⚠️ REVISAR", "OK"))
A395: =IF('Ordenes_Odoo'!A395="","",'Ordenes_Odoo'!A395) | B395: =IF('Ordenes_Odoo'!B395="","",'Ordenes_Odoo'!B395) | C395: =IF('Ordenes_Odoo'!C395="","",'Ordenes_Odoo'!C395) | D395: =IF('Ordenes_Odoo'!D395="","",'Ordenes_Odoo'!D395) | E395: =IF('Ordenes_Odoo'!E395="","",'Ordenes_Odoo'!E395) | F395: =IF('Ordenes_Odoo'!F395="","",'Ordenes_Odoo'!F395) | G395: =IF('Ordenes_Odoo'!G395="","",'Ordenes_Odoo'!G395) | H395: =IF('Ordenes_Odoo'!H395="","",'Ordenes_Odoo'!H395) | ... P395: =IF('Ordenes_Odoo'!P395="","",'Ordenes_Odoo'!P395) | Q395: =IF(A395="","",IFERROR(INDEX(Facturas_Odoo!$B:$B, MATCH(A395, Facturas_Odoo!$D:$D, 0)), "Sin Factura")) | R395: =IF(Q395="Sin Factura","",IFERROR(INDEX(Facturas_Odoo!$A:$A, MATCH(Q395, Facturas_Odoo!$B:$B, 0)), "")) | S395: =IF(Q395="Sin Factura","",IFERROR(_xlfn.XLOOKUP(1, (Facturas_Odoo!$D:$D=A395) * (Facturas_Odoo!$K:$K=I395), Facturas_Odoo!$L:$L, ""), "")) | T395: =IF(Q395="Sin Factura",0,IFERROR(_xlfn.XLOOKUP(1, (Facturas_Odoo!$D:$D=A395) * (Facturas_Odoo!$K:$K=I395), Facturas_Odoo!$M:$M, 0), 0)) | U395: =IF(Q395="Sin Factura",0,IFERROR(_xlfn.XLOOKUP(1, (Facturas_Odoo!$D:$D=A395) * (Facturas_Odoo!$K:$K=I395), Facturas_Odoo!$N:$N, 0), 0)) | V395: =IF(Q395="Sin Factura",0,IFERROR(_xlfn.XLOOKUP(1, (Facturas_Odoo!$D:$D=A395) * (Facturas_Odoo!$K:$K=I395), Facturas_Odoo!$O:$O, 0), 0)) | W395: =IF(Q395="Sin Factura",0,IFERROR(_xlfn.XLOOKUP(1, (Facturas_Odoo!$D:$D=A395) * (Facturas_Odoo!$K:$K=I395), Facturas_Odoo!$Q:$Q, 0), 0)) | X395: =IF(OR(Q395="Sin Factura",Q395=""),"",IFERROR(INDEX(Pagos_Odoo!$B:$B, MATCH(Q395, Pagos_Odoo!$I:$I, 0)), "Sin Pago")) | Y395: =IF(X395="Sin Pago","",IFERROR(INDEX(Pagos_Odoo!$C:$C, MATCH(X395, Pagos_Odoo!$B:$B, 0)), "")) | Z395: =IF(X395="Sin Pago","",IFERROR(INDEX(Pagos_Odoo!$A:$A, MATCH(X395, Pagos_Odoo!$B:$B, 0)), "")) | AA395: =IF(X395="Sin Pago","",IFERROR(INDEX(Pagos_Odoo!$F:$F, MATCH(X395, Pagos_Odoo!$B:$B, 0)), "")) | AB395: =IF(X395="Sin Pago",0,IFERROR(INDEX(Pagos_Odoo!$E:$E, MATCH(X395, Pagos_Odoo!$B:$B, 0)), 0)) | AC395: =IF(X395="Sin Pago","",IFERROR(INDEX(Pagos_Odoo!$G:$G, MATCH(X395, Pagos_Odoo!$B:$B, 0)), "")) | AD395: 0 | AG395: =IF(AN395="","",AD395+AE395+AF395) | AH395: =IF(AN395="","",P395*(1-AG395)) | AI395: =IF(AN395="","",IF(Q395="Sin Factura",0,IFERROR(INDEX(Facturas_Odoo!$H:$H, MATCH(Q395, Facturas_Odoo!$B:$B, 0)), 0)*(1-AG395))) | AJ395: =IF(AN395="","",_xlfn.LET(idVenta, AN395&"", pagos, IFERROR(SUMIF(Aux_Datos!$B:$B, idVenta, Aux_Datos!$L:$L), 0), retenciones, IFERROR(SUMIF(Aux_Datos!$O:$O, idVenta, Aux_Datos!$S:$S), 0), pagos_manuales, IFERROR(SUMIF('Asignación Pagos'!$G:$G, idVenta, 'Asignación Pagos'!$F:$F), 0), pagos+retenciones+pagos_manuales)) | AK395: =IF(AN395="","",AH395-AJ395) | AL395: =IF(AN395="","",IF(Q395="Sin Factura","",AI395-AJ395)) | AM395: =IF(AN395="","",IF(Q395="Sin Factura",0,P395-IFERROR(INDEX(Facturas_Odoo!$H:$H, MATCH(Q395, Facturas_Odoo!$B:$B, 0)), 0))) | AN395: =IF(AND(A395="", J395=""), "", IF(A395<>"", VALUE(MID(A395,2,LEN(A395))), AN394)) | AO395: =IF(AN395="","",IF(AD395=0,"OK",_xlfn.LET(monedaPago, IF(AA395="","USD",AA395), limitePermitido, IFERROR(VLOOKUP(monedaPago, Configuración!$A$2:$B$3, 2, FALSE), 0.15), IF(AD395>limitePermitido, "ALERTA: EXCESO (" & TEXT(limitePermitido, "0%") & " máx)", "OK")))) | AP395: =IF(AN395="","",IF(AE395=0,"OK",_xlfn.LET(fechaPago, Z395, fechaFactura, R395, diasCredito, IF(E395="Pago inmediato", 0, IFERROR(VALUE(MID(E395, 1, SEARCH(" ", E395)-1)), 0)), tolerancia, Configuración!$E$2, limiteDias, diasCredito + tolerancia, IF(OR(fechaPago="", fechaFactura=""), "REVISAR: SIN FECHA", IF(fechaPago - fechaFactura > limiteDias, "ALERTA: PAGO FUERA DE PLAZO (" & (fechaPago - fechaFactura) & " días)", "OK"))))) | AQ395: =IF(AN395="","",IF(AND(N395>0, AG395>0), IF(Configuración!$K$2="NO", "ALERTA: DESCUENTO DOBLE NO PERMITIDO", "OK"), "OK")) | AR395: =IF(AN395="","",IF(OR(AO395<>"OK", AP395<>"OK", AQ395<>"OK"), "⚠️ REVISAR", "OK"))
A396: =IF('Ordenes_Odoo'!A396="","",'Ordenes_Odoo'!A396) | B396: =IF('Ordenes_Odoo'!B396="","",'Ordenes_Odoo'!B396) | C396: =IF('Ordenes_Odoo'!C396="","",'Ordenes_Odoo'!C396) | D396: =IF('Ordenes_Odoo'!D396="","",'Ordenes_Odoo'!D396) | E396: =IF('Ordenes_Odoo'!E396="","",'Ordenes_Odoo'!E396) | F396: =IF('Ordenes_Odoo'!F396="","",'Ordenes_Odoo'!F396) | G396: =IF('Ordenes_Odoo'!G396="","",'Ordenes_Odoo'!G396) | H396: =IF('Ordenes_Odoo'!H396="","",'Ordenes_Odoo'!H396) | ... P396: =IF('Ordenes_Odoo'!P396="","",'Ordenes_Odoo'!P396) | Q396: =IF(A396="","",IFERROR(INDEX(Facturas_Odoo!$B:$B, MATCH(A396, Facturas_Odoo!$D:$D, 0)), "Sin Factura")) | R396: =IF(Q396="Sin Factura","",IFERROR(INDEX(Facturas_Odoo!$A:$A, MATCH(Q396, Facturas_Odoo!$B:$B, 0)), "")) | S396: =IF(Q396="Sin Factura","",IFERROR(_xlfn.XLOOKUP(1, (Facturas_Odoo!$D:$D=A396) * (Facturas_Odoo!$K:$K=I396), Facturas_Odoo!$L:$L, ""), "")) | T396: =IF(Q396="Sin Factura",0,IFERROR(_xlfn.XLOOKUP(1, (Facturas_Odoo!$D:$D=A396) * (Facturas_Odoo!$K:$K=I396), Facturas_Odoo!$M:$M, 0), 0)) | U396: =IF(Q396="Sin Factura",0,IFERROR(_xlfn.XLOOKUP(1, (Facturas_Odoo!$D:$D=A396) * (Facturas_Odoo!$K:$K=I396), Facturas_Odoo!$N:$N, 0), 0)) | V396: =IF(Q396="Sin Factura",0,IFERROR(_xlfn.XLOOKUP(1, (Facturas_Odoo!$D:$D=A396) * (Facturas_Odoo!$K:$K=I396), Facturas_Odoo!$O:$O, 0), 0)) | W396: =IF(Q396="Sin Factura",0,IFERROR(_xlfn.XLOOKUP(1, (Facturas_Odoo!$D:$D=A396) * (Facturas_Odoo!$K:$K=I396), Facturas_Odoo!$Q:$Q, 0), 0)) | X396: =IF(OR(Q396="Sin Factura",Q396=""),"",IFERROR(INDEX(Pagos_Odoo!$B:$B, MATCH(Q396, Pagos_Odoo!$I:$I, 0)), "Sin Pago")) | Y396: =IF(X396="Sin Pago","",IFERROR(INDEX(Pagos_Odoo!$C:$C, MATCH(X396, Pagos_Odoo!$B:$B, 0)), "")) | Z396: =IF(X396="Sin Pago","",IFERROR(INDEX(Pagos_Odoo!$A:$A, MATCH(X396, Pagos_Odoo!$B:$B, 0)), "")) | AA396: =IF(X396="Sin Pago","",IFERROR(INDEX(Pagos_Odoo!$F:$F, MATCH(X396, Pagos_Odoo!$B:$B, 0)), "")) | AB396: =IF(X396="Sin Pago",0,IFERROR(INDEX(Pagos_Odoo!$E:$E, MATCH(X396, Pagos_Odoo!$B:$B, 0)), 0)) | AC396: =IF(X396="Sin Pago","",IFERROR(INDEX(Pagos_Odoo!$G:$G, MATCH(X396, Pagos_Odoo!$B:$B, 0)), "")) | AD396: 0 | AG396: =IF(AN396="","",AD396+AE396+AF396) | AH396: =IF(AN396="","",P396*(1-AG396)) | AI396: =IF(AN396="","",IF(Q396="Sin Factura",0,IFERROR(INDEX(Facturas_Odoo!$H:$H, MATCH(Q396, Facturas_Odoo!$B:$B, 0)), 0)*(1-AG396))) | AJ396: =IF(AN396="","",_xlfn.LET(idVenta, AN396&"", pagos, IFERROR(SUMIF(Aux_Datos!$B:$B, idVenta, Aux_Datos!$L:$L), 0), retenciones, IFERROR(SUMIF(Aux_Datos!$O:$O, idVenta, Aux_Datos!$S:$S), 0), pagos_manuales, IFERROR(SUMIF('Asignación Pagos'!$G:$G, idVenta, 'Asignación Pagos'!$F:$F), 0), pagos+retenciones+pagos_manuales)) | AK396: =IF(AN396="","",AH396-AJ396) | AL396: =IF(AN396="","",IF(Q396="Sin Factura","",AI396-AJ396)) | AM396: =IF(AN396="","",IF(Q396="Sin Factura",0,P396-IFERROR(INDEX(Facturas_Odoo!$H:$H, MATCH(Q396, Facturas_Odoo!$B:$B, 0)), 0))) | AN396: =IF(AND(A396="", J396=""), "", IF(A396<>"", VALUE(MID(A396,2,LEN(A396))), AN395)) | AO396: =IF(AN396="","",IF(AD396=0,"OK",_xlfn.LET(monedaPago, IF(AA396="","USD",AA396), limitePermitido, IFERROR(VLOOKUP(monedaPago, Configuración!$A$2:$B$3, 2, FALSE), 0.15), IF(AD396>limitePermitido, "ALERTA: EXCESO (" & TEXT(limitePermitido, "0%") & " máx)", "OK")))) | AP396: =IF(AN396="","",IF(AE396=0,"OK",_xlfn.LET(fechaPago, Z396, fechaFactura, R396, diasCredito, IF(E396="Pago inmediato", 0, IFERROR(VALUE(MID(E396, 1, SEARCH(" ", E396)-1)), 0)), tolerancia, Configuración!$E$2, limiteDias, diasCredito + tolerancia, IF(OR(fechaPago="", fechaFactura=""), "REVISAR: SIN FECHA", IF(fechaPago - fechaFactura > limiteDias, "ALERTA: PAGO FUERA DE PLAZO (" & (fechaPago - fechaFactura) & " días)", "OK"))))) | AQ396: =IF(AN396="","",IF(AND(N396>0, AG396>0), IF(Configuración!$K$2="NO", "ALERTA: DESCUENTO DOBLE NO PERMITIDO", "OK"), "OK")) | AR396: =IF(AN396="","",IF(OR(AO396<>"OK", AP396<>"OK", AQ396<>"OK"), "⚠️ REVISAR", "OK"))
A397: =IF('Ordenes_Odoo'!A397="","",'Ordenes_Odoo'!A397) | B397: =IF('Ordenes_Odoo'!B397="","",'Ordenes_Odoo'!B397) | C397: =IF('Ordenes_Odoo'!C397="","",'Ordenes_Odoo'!C397) | D397: =IF('Ordenes_Odoo'!D397="","",'Ordenes_Odoo'!D397) | E397: =IF('Ordenes_Odoo'!E397="","",'Ordenes_Odoo'!E397) | F397: =IF('Ordenes_Odoo'!F397="","",'Ordenes_Odoo'!F397) | G397: =IF('Ordenes_Odoo'!G397="","",'Ordenes_Odoo'!G397) | H397: =IF('Ordenes_Odoo'!H397="","",'Ordenes_Odoo'!H397) | ... P397: =IF('Ordenes_Odoo'!P397="","",'Ordenes_Odoo'!P397) | Q397: =IF(A397="","",IFERROR(INDEX(Facturas_Odoo!$B:$B, MATCH(A397, Facturas_Odoo!$D:$D, 0)), "Sin Factura")) | R397: =IF(Q397="Sin Factura","",IFERROR(INDEX(Facturas_Odoo!$A:$A, MATCH(Q397, Facturas_Odoo!$B:$B, 0)), "")) | S397: =IF(Q397="Sin Factura","",IFERROR(_xlfn.XLOOKUP(1, (Facturas_Odoo!$D:$D=A397) * (Facturas_Odoo!$K:$K=I397), Facturas_Odoo!$L:$L, ""), "")) | T397: =IF(Q397="Sin Factura",0,IFERROR(_xlfn.XLOOKUP(1, (Facturas_Odoo!$D:$D=A397) * (Facturas_Odoo!$K:$K=I397), Facturas_Odoo!$M:$M, 0), 0)) | U397: =IF(Q397="Sin Factura",0,IFERROR(_xlfn.XLOOKUP(1, (Facturas_Odoo!$D:$D=A397) * (Facturas_Odoo!$K:$K=I397), Facturas_Odoo!$N:$N, 0), 0)) | V397: =IF(Q397="Sin Factura",0,IFERROR(_xlfn.XLOOKUP(1, (Facturas_Odoo!$D:$D=A397) * (Facturas_Odoo!$K:$K=I397), Facturas_Odoo!$O:$O, 0), 0)) | W397: =IF(Q397="Sin Factura",0,IFERROR(_xlfn.XLOOKUP(1, (Facturas_Odoo!$D:$D=A397) * (Facturas_Odoo!$K:$K=I397), Facturas_Odoo!$Q:$Q, 0), 0)) | X397: =IF(OR(Q397="Sin Factura",Q397=""),"",IFERROR(INDEX(Pagos_Odoo!$B:$B, MATCH(Q397, Pagos_Odoo!$I:$I, 0)), "Sin Pago")) | Y397: =IF(X397="Sin Pago","",IFERROR(INDEX(Pagos_Odoo!$C:$C, MATCH(X397, Pagos_Odoo!$B:$B, 0)), "")) | Z397: =IF(X397="Sin Pago","",IFERROR(INDEX(Pagos_Odoo!$A:$A, MATCH(X397, Pagos_Odoo!$B:$B, 0)), "")) | AA397: =IF(X397="Sin Pago","",IFERROR(INDEX(Pagos_Odoo!$F:$F, MATCH(X397, Pagos_Odoo!$B:$B, 0)), "")) | AB397: =IF(X397="Sin Pago",0,IFERROR(INDEX(Pagos_Odoo!$E:$E, MATCH(X397, Pagos_Odoo!$B:$B, 0)), 0)) | AC397: =IF(X397="Sin Pago","",IFERROR(INDEX(Pagos_Odoo!$G:$G, MATCH(X397, Pagos_Odoo!$B:$B, 0)), "")) | AD397: 0 | AG397: =IF(AN397="","",AD397+AE397+AF397) | AH397: =IF(AN397="","",P397*(1-AG397)) | AI397: =IF(AN397="","",IF(Q397="Sin Factura",0,IFERROR(INDEX(Facturas_Odoo!$H:$H, MATCH(Q397, Facturas_Odoo!$B:$B, 0)), 0)*(1-AG397))) | AJ397: =IF(AN397="","",_xlfn.LET(idVenta, AN397&"", pagos, IFERROR(SUMIF(Aux_Datos!$B:$B, idVenta, Aux_Datos!$L:$L), 0), retenciones, IFERROR(SUMIF(Aux_Datos!$O:$O, idVenta, Aux_Datos!$S:$S), 0), pagos_manuales, IFERROR(SUMIF('Asignación Pagos'!$G:$G, idVenta, 'Asignación Pagos'!$F:$F), 0), pagos+retenciones+pagos_manuales)) | AK397: =IF(AN397="","",AH397-AJ397) | AL397: =IF(AN397="","",IF(Q397="Sin Factura","",AI397-AJ397)) | AM397: =IF(AN397="","",IF(Q397="Sin Factura",0,P397-IFERROR(INDEX(Facturas_Odoo!$H:$H, MATCH(Q397, Facturas_Odoo!$B:$B, 0)), 0))) | AN397: =IF(AND(A397="", J397=""), "", IF(A397<>"", VALUE(MID(A397,2,LEN(A397))), AN396)) | AO397: =IF(AN397="","",IF(AD397=0,"OK",_xlfn.LET(monedaPago, IF(AA397="","USD",AA397), limitePermitido, IFERROR(VLOOKUP(monedaPago, Configuración!$A$2:$B$3, 2, FALSE), 0.15), IF(AD397>limitePermitido, "ALERTA: EXCESO (" & TEXT(limitePermitido, "0%") & " máx)", "OK")))) | AP397: =IF(AN397="","",IF(AE397=0,"OK",_xlfn.LET(fechaPago, Z397, fechaFactura, R397, diasCredito, IF(E397="Pago inmediato", 0, IFERROR(VALUE(MID(E397, 1, SEARCH(" ", E397)-1)), 0)), tolerancia, Configuración!$E$2, limiteDias, diasCredito + tolerancia, IF(OR(fechaPago="", fechaFactura=""), "REVISAR: SIN FECHA", IF(fechaPago - fechaFactura > limiteDias, "ALERTA: PAGO FUERA DE PLAZO (" & (fechaPago - fechaFactura) & " días)", "OK"))))) | AQ397: =IF(AN397="","",IF(AND(N397>0, AG397>0), IF(Configuración!$K$2="NO", "ALERTA: DESCUENTO DOBLE NO PERMITIDO", "OK"), "OK")) | AR397: =IF(AN397="","",IF(OR(AO397<>"OK", AP397<>"OK", AQ397<>"OK"), "⚠️ REVISAR", "OK"))
A398: =IF('Ordenes_Odoo'!A398="","",'Ordenes_Odoo'!A398) | B398: =IF('Ordenes_Odoo'!B398="","",'Ordenes_Odoo'!B398) | C398: =IF('Ordenes_Odoo'!C398="","",'Ordenes_Odoo'!C398) | D398: =IF('Ordenes_Odoo'!D398="","",'Ordenes_Odoo'!D398) | E398: =IF('Ordenes_Odoo'!E398="","",'Ordenes_Odoo'!E398) | F398: =IF('Ordenes_Odoo'!F398="","",'Ordenes_Odoo'!F398) | G398: =IF('Ordenes_Odoo'!G398="","",'Ordenes_Odoo'!G398) | H398: =IF('Ordenes_Odoo'!H398="","",'Ordenes_Odoo'!H398) | ... P398: =IF('Ordenes_Odoo'!P398="","",'Ordenes_Odoo'!P398) | Q398: =IF(A398="","",IFERROR(INDEX(Facturas_Odoo!$B:$B, MATCH(A398, Facturas_Odoo!$D:$D, 0)), "Sin Factura")) | R398: =IF(Q398="Sin Factura","",IFERROR(INDEX(Facturas_Odoo!$A:$A, MATCH(Q398, Facturas_Odoo!$B:$B, 0)), "")) | S398: =IF(Q398="Sin Factura","",IFERROR(_xlfn.XLOOKUP(1, (Facturas_Odoo!$D:$D=A398) * (Facturas_Odoo!$K:$K=I398), Facturas_Odoo!$L:$L, ""), "")) | T398: =IF(Q398="Sin Factura",0,IFERROR(_xlfn.XLOOKUP(1, (Facturas_Odoo!$D:$D=A398) * (Facturas_Odoo!$K:$K=I398), Facturas_Odoo!$M:$M, 0), 0)) | U398: =IF(Q398="Sin Factura",0,IFERROR(_xlfn.XLOOKUP(1, (Facturas_Odoo!$D:$D=A398) * (Facturas_Odoo!$K:$K=I398), Facturas_Odoo!$N:$N, 0), 0)) | V398: =IF(Q398="Sin Factura",0,IFERROR(_xlfn.XLOOKUP(1, (Facturas_Odoo!$D:$D=A398) * (Facturas_Odoo!$K:$K=I398), Facturas_Odoo!$O:$O, 0), 0)) | W398: =IF(Q398="Sin Factura",0,IFERROR(_xlfn.XLOOKUP(1, (Facturas_Odoo!$D:$D=A398) * (Facturas_Odoo!$K:$K=I398), Facturas_Odoo!$Q:$Q, 0), 0)) | X398: =IF(OR(Q398="Sin Factura",Q398=""),"",IFERROR(INDEX(Pagos_Odoo!$B:$B, MATCH(Q398, Pagos_Odoo!$I:$I, 0)), "Sin Pago")) | Y398: =IF(X398="Sin Pago","",IFERROR(INDEX(Pagos_Odoo!$C:$C, MATCH(X398, Pagos_Odoo!$B:$B, 0)), "")) | Z398: =IF(X398="Sin Pago","",IFERROR(INDEX(Pagos_Odoo!$A:$A, MATCH(X398, Pagos_Odoo!$B:$B, 0)), "")) | AA398: =IF(X398="Sin Pago","",IFERROR(INDEX(Pagos_Odoo!$F:$F, MATCH(X398, Pagos_Odoo!$B:$B, 0)), "")) | AB398: =IF(X398="Sin Pago",0,IFERROR(INDEX(Pagos_Odoo!$E:$E, MATCH(X398, Pagos_Odoo!$B:$B, 0)), 0)) | AC398: =IF(X398="Sin Pago","",IFERROR(INDEX(Pagos_Odoo!$G:$G, MATCH(X398, Pagos_Odoo!$B:$B, 0)), "")) | AD398: 0 | AG398: =IF(AN398="","",AD398+AE398+AF398) | AH398: =IF(AN398="","",P398*(1-AG398)) | AI398: =IF(AN398="","",IF(Q398="Sin Factura",0,IFERROR(INDEX(Facturas_Odoo!$H:$H, MATCH(Q398, Facturas_Odoo!$B:$B, 0)), 0)*(1-AG398))) | AJ398: =IF(AN398="","",_xlfn.LET(idVenta, AN398&"", pagos, IFERROR(SUMIF(Aux_Datos!$B:$B, idVenta, Aux_Datos!$L:$L), 0), retenciones, IFERROR(SUMIF(Aux_Datos!$O:$O, idVenta, Aux_Datos!$S:$S), 0), pagos_manuales, IFERROR(SUMIF('Asignación Pagos'!$G:$G, idVenta, 'Asignación Pagos'!$F:$F), 0), pagos+retenciones+pagos_manuales)) | AK398: =IF(AN398="","",AH398-AJ398) | AL398: =IF(AN398="","",IF(Q398="Sin Factura","",AI398-AJ398)) | AM398: =IF(AN398="","",IF(Q398="Sin Factura",0,P398-IFERROR(INDEX(Facturas_Odoo!$H:$H, MATCH(Q398, Facturas_Odoo!$B:$B, 0)), 0))) | AN398: =IF(AND(A398="", J398=""), "", IF(A398<>"", VALUE(MID(A398,2,LEN(A398))), AN397)) | AO398: =IF(AN398="","",IF(AD398=0,"OK",_xlfn.LET(monedaPago, IF(AA398="","USD",AA398), limitePermitido, IFERROR(VLOOKUP(monedaPago, Configuración!$A$2:$B$3, 2, FALSE), 0.15), IF(AD398>limitePermitido, "ALERTA: EXCESO (" & TEXT(limitePermitido, "0%") & " máx)", "OK")))) | AP398: =IF(AN398="","",IF(AE398=0,"OK",_xlfn.LET(fechaPago, Z398, fechaFactura, R398, diasCredito, IF(E398="Pago inmediato", 0, IFERROR(VALUE(MID(E398, 1, SEARCH(" ", E398)-1)), 0)), tolerancia, Configuración!$E$2, limiteDias, diasCredito + tolerancia, IF(OR(fechaPago="", fechaFactura=""), "REVISAR: SIN FECHA", IF(fechaPago - fechaFactura > limiteDias, "ALERTA: PAGO FUERA DE PLAZO (" & (fechaPago - fechaFactura) & " días)", "OK"))))) | AQ398: =IF(AN398="","",IF(AND(N398>0, AG398>0), IF(Configuración!$K$2="NO", "ALERTA: DESCUENTO DOBLE NO PERMITIDO", "OK"), "OK")) | AR398: =IF(AN398="","",IF(OR(AO398<>"OK", AP398<>"OK", AQ398<>"OK"), "⚠️ REVISAR", "OK"))
A399: =IF('Ordenes_Odoo'!A399="","",'Ordenes_Odoo'!A399) | B399: =IF('Ordenes_Odoo'!B399="","",'Ordenes_Odoo'!B399) | C399: =IF('Ordenes_Odoo'!C399="","",'Ordenes_Odoo'!C399) | D399: =IF('Ordenes_Odoo'!D399="","",'Ordenes_Odoo'!D399) | E399: =IF('Ordenes_Odoo'!E399="","",'Ordenes_Odoo'!E399) | F399: =IF('Ordenes_Odoo'!F399="","",'Ordenes_Odoo'!F399) | G399: =IF('Ordenes_Odoo'!G399="","",'Ordenes_Odoo'!G399) | H399: =IF('Ordenes_Odoo'!H399="","",'Ordenes_Odoo'!H399) | ... P399: =IF('Ordenes_Odoo'!P399="","",'Ordenes_Odoo'!P399) | Q399: =IF(A399="","",IFERROR(INDEX(Facturas_Odoo!$B:$B, MATCH(A399, Facturas_Odoo!$D:$D, 0)), "Sin Factura")) | R399: =IF(Q399="Sin Factura","",IFERROR(INDEX(Facturas_Odoo!$A:$A, MATCH(Q399, Facturas_Odoo!$B:$B, 0)), "")) | S399: =IF(Q399="Sin Factura","",IFERROR(_xlfn.XLOOKUP(1, (Facturas_Odoo!$D:$D=A399) * (Facturas_Odoo!$K:$K=I399), Facturas_Odoo!$L:$L, ""), "")) | T399: =IF(Q399="Sin Factura",0,IFERROR(_xlfn.XLOOKUP(1, (Facturas_Odoo!$D:$D=A399) * (Facturas_Odoo!$K:$K=I399), Facturas_Odoo!$M:$M, 0), 0)) | U399: =IF(Q399="Sin Factura",0,IFERROR(_xlfn.XLOOKUP(1, (Facturas_Odoo!$D:$D=A399) * (Facturas_Odoo!$K:$K=I399), Facturas_Odoo!$N:$N, 0), 0)) | V399: =IF(Q399="Sin Factura",0,IFERROR(_xlfn.XLOOKUP(1, (Facturas_Odoo!$D:$D=A399) * (Facturas_Odoo!$K:$K=I399), Facturas_Odoo!$O:$O, 0), 0)) | W399: =IF(Q399="Sin Factura",0,IFERROR(_xlfn.XLOOKUP(1, (Facturas_Odoo!$D:$D=A399) * (Facturas_Odoo!$K:$K=I399), Facturas_Odoo!$Q:$Q, 0), 0)) | X399: =IF(OR(Q399="Sin Factura",Q399=""),"",IFERROR(INDEX(Pagos_Odoo!$B:$B, MATCH(Q399, Pagos_Odoo!$I:$I, 0)), "Sin Pago")) | Y399: =IF(X399="Sin Pago","",IFERROR(INDEX(Pagos_Odoo!$C:$C, MATCH(X399, Pagos_Odoo!$B:$B, 0)), "")) | Z399: =IF(X399="Sin Pago","",IFERROR(INDEX(Pagos_Odoo!$A:$A, MATCH(X399, Pagos_Odoo!$B:$B, 0)), "")) | AA399: =IF(X399="Sin Pago","",IFERROR(INDEX(Pagos_Odoo!$F:$F, MATCH(X399, Pagos_Odoo!$B:$B, 0)), "")) | AB399: =IF(X399="Sin Pago",0,IFERROR(INDEX(Pagos_Odoo!$E:$E, MATCH(X399, Pagos_Odoo!$B:$B, 0)), 0)) | AC399: =IF(X399="Sin Pago","",IFERROR(INDEX(Pagos_Odoo!$G:$G, MATCH(X399, Pagos_Odoo!$B:$B, 0)), "")) | AD399: 0 | AG399: =IF(AN399="","",AD399+AE399+AF399) | AH399: =IF(AN399="","",P399*(1-AG399)) | AI399: =IF(AN399="","",IF(Q399="Sin Factura",0,IFERROR(INDEX(Facturas_Odoo!$H:$H, MATCH(Q399, Facturas_Odoo!$B:$B, 0)), 0)*(1-AG399))) | AJ399: =IF(AN399="","",_xlfn.LET(idVenta, AN399&"", pagos, IFERROR(SUMIF(Aux_Datos!$B:$B, idVenta, Aux_Datos!$L:$L), 0), retenciones, IFERROR(SUMIF(Aux_Datos!$O:$O, idVenta, Aux_Datos!$S:$S), 0), pagos_manuales, IFERROR(SUMIF('Asignación Pagos'!$G:$G, idVenta, 'Asignación Pagos'!$F:$F), 0), pagos+retenciones+pagos_manuales)) | AK399: =IF(AN399="","",AH399-AJ399) | AL399: =IF(AN399="","",IF(Q399="Sin Factura","",AI399-AJ399)) | AM399: =IF(AN399="","",IF(Q399="Sin Factura",0,P399-IFERROR(INDEX(Facturas_Odoo!$H:$H, MATCH(Q399, Facturas_Odoo!$B:$B, 0)), 0))) | AN399: =IF(AND(A399="", J399=""), "", IF(A399<>"", VALUE(MID(A399,2,LEN(A399))), AN398)) | AO399: =IF(AN399="","",IF(AD399=0,"OK",_xlfn.LET(monedaPago, IF(AA399="","USD",AA399), limitePermitido, IFERROR(VLOOKUP(monedaPago, Configuración!$A$2:$B$3, 2, FALSE), 0.15), IF(AD399>limitePermitido, "ALERTA: EXCESO (" & TEXT(limitePermitido, "0%") & " máx)", "OK")))) | AP399: =IF(AN399="","",IF(AE399=0,"OK",_xlfn.LET(fechaPago, Z399, fechaFactura, R399, diasCredito, IF(E399="Pago inmediato", 0, IFERROR(VALUE(MID(E399, 1, SEARCH(" ", E399)-1)), 0)), tolerancia, Configuración!$E$2, limiteDias, diasCredito + tolerancia, IF(OR(fechaPago="", fechaFactura=""), "REVISAR: SIN FECHA", IF(fechaPago - fechaFactura > limiteDias, "ALERTA: PAGO FUERA DE PLAZO (" & (fechaPago - fechaFactura) & " días)", "OK"))))) | AQ399: =IF(AN399="","",IF(AND(N399>0, AG399>0), IF(Configuración!$K$2="NO", "ALERTA: DESCUENTO DOBLE NO PERMITIDO", "OK"), "OK")) | AR399: =IF(AN399="","",IF(OR(AO399<>"OK", AP399<>"OK", AQ399<>"OK"), "⚠️ REVISAR", "OK"))
A400: =IF('Ordenes_Odoo'!A400="","",'Ordenes_Odoo'!A400) | B400: =IF('Ordenes_Odoo'!B400="","",'Ordenes_Odoo'!B400) | C400: =IF('Ordenes_Odoo'!C400="","",'Ordenes_Odoo'!C400) | D400: =IF('Ordenes_Odoo'!D400="","",'Ordenes_Odoo'!D400) | E400: =IF('Ordenes_Odoo'!E400="","",'Ordenes_Odoo'!E400) | F400: =IF('Ordenes_Odoo'!F400="","",'Ordenes_Odoo'!F400) | G400: =IF('Ordenes_Odoo'!G400="","",'Ordenes_Odoo'!G400) | H400: =IF('Ordenes_Odoo'!H400="","",'Ordenes_Odoo'!H400) | ... P400: =IF('Ordenes_Odoo'!P400="","",'Ordenes_Odoo'!P400) | Q400: =IF(A400="","",IFERROR(INDEX(Facturas_Odoo!$B:$B, MATCH(A400, Facturas_Odoo!$D:$D, 0)), "Sin Factura")) | R400: =IF(Q400="Sin Factura","",IFERROR(INDEX(Facturas_Odoo!$A:$A, MATCH(Q400, Facturas_Odoo!$B:$B, 0)), "")) | S400: =IF(Q400="Sin Factura","",IFERROR(_xlfn.XLOOKUP(1, (Facturas_Odoo!$D:$D=A400) * (Facturas_Odoo!$K:$K=I400), Facturas_Odoo!$L:$L, ""), "")) | T400: =IF(Q400="Sin Factura",0,IFERROR(_xlfn.XLOOKUP(1, (Facturas_Odoo!$D:$D=A400) * (Facturas_Odoo!$K:$K=I400), Facturas_Odoo!$M:$M, 0), 0)) | U400: =IF(Q400="Sin Factura",0,IFERROR(_xlfn.XLOOKUP(1, (Facturas_Odoo!$D:$D=A400) * (Facturas_Odoo!$K:$K=I400), Facturas_Odoo!$N:$N, 0), 0)) | V400: =IF(Q400="Sin Factura",0,IFERROR(_xlfn.XLOOKUP(1, (Facturas_Odoo!$D:$D=A400) * (Facturas_Odoo!$K:$K=I400), Facturas_Odoo!$O:$O, 0), 0)) | W400: =IF(Q400="Sin Factura",0,IFERROR(_xlfn.XLOOKUP(1, (Facturas_Odoo!$D:$D=A400) * (Facturas_Odoo!$K:$K=I400), Facturas_Odoo!$Q:$Q, 0), 0)) | X400: =IF(OR(Q400="Sin Factura",Q400=""),"",IFERROR(INDEX(Pagos_Odoo!$B:$B, MATCH(Q400, Pagos_Odoo!$I:$I, 0)), "Sin Pago")) | Y400: =IF(X400="Sin Pago","",IFERROR(INDEX(Pagos_Odoo!$C:$C, MATCH(X400, Pagos_Odoo!$B:$B, 0)), "")) | Z400: =IF(X400="Sin Pago","",IFERROR(INDEX(Pagos_Odoo!$A:$A, MATCH(X400, Pagos_Odoo!$B:$B, 0)), "")) | AA400: =IF(X400="Sin Pago","",IFERROR(INDEX(Pagos_Odoo!$F:$F, MATCH(X400, Pagos_Odoo!$B:$B, 0)), "")) | AB400: =IF(X400="Sin Pago",0,IFERROR(INDEX(Pagos_Odoo!$E:$E, MATCH(X400, Pagos_Odoo!$B:$B, 0)), 0)) | AC400: =IF(X400="Sin Pago","",IFERROR(INDEX(Pagos_Odoo!$G:$G, MATCH(X400, Pagos_Odoo!$B:$B, 0)), "")) | AD400: 0 | AG400: =IF(AN400="","",AD400+AE400+AF400) | AH400: =IF(AN400="","",P400*(1-AG400)) | AI400: =IF(AN400="","",IF(Q400="Sin Factura",0,IFERROR(INDEX(Facturas_Odoo!$H:$H, MATCH(Q400, Facturas_Odoo!$B:$B, 0)), 0)*(1-AG400))) | AJ400: =IF(AN400="","",_xlfn.LET(idVenta, AN400&"", pagos, IFERROR(SUMIF(Aux_Datos!$B:$B, idVenta, Aux_Datos!$L:$L), 0), retenciones, IFERROR(SUMIF(Aux_Datos!$O:$O, idVenta, Aux_Datos!$S:$S), 0), pagos_manuales, IFERROR(SUMIF('Asignación Pagos'!$G:$G, idVenta, 'Asignación Pagos'!$F:$F), 0), pagos+retenciones+pagos_manuales)) | AK400: =IF(AN400="","",AH400-AJ400) | AL400: =IF(AN400="","",IF(Q400="Sin Factura","",AI400-AJ400)) | AM400: =IF(AN400="","",IF(Q400="Sin Factura",0,P400-IFERROR(INDEX(Facturas_Odoo!$H:$H, MATCH(Q400, Facturas_Odoo!$B:$B, 0)), 0))) | AN400: =IF(AND(A400="", J400=""), "", IF(A400<>"", VALUE(MID(A400,2,LEN(A400))), AN399)) | AO400: =IF(AN400="","",IF(AD400=0,"OK",_xlfn.LET(monedaPago, IF(AA400="","USD",AA400), limitePermitido, IFERROR(VLOOKUP(monedaPago, Configuración!$A$2:$B$3, 2, FALSE), 0.15), IF(AD400>limitePermitido, "ALERTA: EXCESO (" & TEXT(limitePermitido, "0%") & " máx)", "OK")))) | AP400: =IF(AN400="","",IF(AE400=0,"OK",_xlfn.LET(fechaPago, Z400, fechaFactura, R400, diasCredito, IF(E400="Pago inmediato", 0, IFERROR(VALUE(MID(E400, 1, SEARCH(" ", E400)-1)), 0)), tolerancia, Configuración!$E$2, limiteDias, diasCredito + tolerancia, IF(OR(fechaPago="", fechaFactura=""), "REVISAR: SIN FECHA", IF(fechaPago - fechaFactura > limiteDias, "ALERTA: PAGO FUERA DE PLAZO (" & (fechaPago - fechaFactura) & " días)", "OK"))))) | AQ400: =IF(AN400="","",IF(AND(N400>0, AG400>0), IF(Configuración!$K$2="NO", "ALERTA: DESCUENTO DOBLE NO PERMITIDO", "OK"), "OK")) | AR400: =IF(AN400="","",IF(OR(AO400<>"OK", AP400<>"OK", AQ400<>"OK"), "⚠️ REVISAR", "OK"))
A401: =IF('Ordenes_Odoo'!A401="","",'Ordenes_Odoo'!A401) | B401: =IF('Ordenes_Odoo'!B401="","",'Ordenes_Odoo'!B401) | C401: =IF('Ordenes_Odoo'!C401="","",'Ordenes_Odoo'!C401) | D401: =IF('Ordenes_Odoo'!D401="","",'Ordenes_Odoo'!D401) | E401: =IF('Ordenes_Odoo'!E401="","",'Ordenes_Odoo'!E401) | F401: =IF('Ordenes_Odoo'!F401="","",'Ordenes_Odoo'!F401) | G401: =IF('Ordenes_Odoo'!G401="","",'Ordenes_Odoo'!G401) | H401: =IF('Ordenes_Odoo'!H401="","",'Ordenes_Odoo'!H401) | ... P401: =IF('Ordenes_Odoo'!P401="","",'Ordenes_Odoo'!P401) | Q401: =IF(A401="","",IFERROR(INDEX(Facturas_Odoo!$B:$B, MATCH(A401, Facturas_Odoo!$D:$D, 0)), "Sin Factura")) | R401: =IF(Q401="Sin Factura","",IFERROR(INDEX(Facturas_Odoo!$A:$A, MATCH(Q401, Facturas_Odoo!$B:$B, 0)), "")) | S401: =IF(Q401="Sin Factura","",IFERROR(_xlfn.XLOOKUP(1, (Facturas_Odoo!$D:$D=A401) * (Facturas_Odoo!$K:$K=I401), Facturas_Odoo!$L:$L, ""), "")) | T401: =IF(Q401="Sin Factura",0,IFERROR(_xlfn.XLOOKUP(1, (Facturas_Odoo!$D:$D=A401) * (Facturas_Odoo!$K:$K=I401), Facturas_Odoo!$M:$M, 0), 0)) | U401: =IF(Q401="Sin Factura",0,IFERROR(_xlfn.XLOOKUP(1, (Facturas_Odoo!$D:$D=A401) * (Facturas_Odoo!$K:$K=I401), Facturas_Odoo!$N:$N, 0), 0)) | V401: =IF(Q401="Sin Factura",0,IFERROR(_xlfn.XLOOKUP(1, (Facturas_Odoo!$D:$D=A401) * (Facturas_Odoo!$K:$K=I401), Facturas_Odoo!$O:$O, 0), 0)) | W401: =IF(Q401="Sin Factura",0,IFERROR(_xlfn.XLOOKUP(1, (Facturas_Odoo!$D:$D=A401) * (Facturas_Odoo!$K:$K=I401), Facturas_Odoo!$Q:$Q, 0), 0)) | X401: =IF(OR(Q401="Sin Factura",Q401=""),"",IFERROR(INDEX(Pagos_Odoo!$B:$B, MATCH(Q401, Pagos_Odoo!$I:$I, 0)), "Sin Pago")) | Y401: =IF(X401="Sin Pago","",IFERROR(INDEX(Pagos_Odoo!$C:$C, MATCH(X401, Pagos_Odoo!$B:$B, 0)), "")) | Z401: =IF(X401="Sin Pago","",IFERROR(INDEX(Pagos_Odoo!$A:$A, MATCH(X401, Pagos_Odoo!$B:$B, 0)), "")) | AA401: =IF(X401="Sin Pago","",IFERROR(INDEX(Pagos_Odoo!$F:$F, MATCH(X401, Pagos_Odoo!$B:$B, 0)), "")) | AB401: =IF(X401="Sin Pago",0,IFERROR(INDEX(Pagos_Odoo!$E:$E, MATCH(X401, Pagos_Odoo!$B:$B, 0)), 0)) | AC401: =IF(X401="Sin Pago","",IFERROR(INDEX(Pagos_Odoo!$G:$G, MATCH(X401, Pagos_Odoo!$B:$B, 0)), "")) | AD401: 0 | AG401: =IF(AN401="","",AD401+AE401+AF401) | AH401: =IF(AN401="","",P401*(1-AG401)) | AI401: =IF(AN401="","",IF(Q401="Sin Factura",0,IFERROR(INDEX(Facturas_Odoo!$H:$H, MATCH(Q401, Facturas_Odoo!$B:$B, 0)), 0)*(1-AG401))) | AJ401: =IF(AN401="","",_xlfn.LET(idVenta, AN401&"", pagos, IFERROR(SUMIF(Aux_Datos!$B:$B, idVenta, Aux_Datos!$L:$L), 0), retenciones, IFERROR(SUMIF(Aux_Datos!$O:$O, idVenta, Aux_Datos!$S:$S), 0), pagos_manuales, IFERROR(SUMIF('Asignación Pagos'!$G:$G, idVenta, 'Asignación Pagos'!$F:$F), 0), pagos+retenciones+pagos_manuales)) | AK401: =IF(AN401="","",AH401-AJ401) | AL401: =IF(AN401="","",IF(Q401="Sin Factura","",AI401-AJ401)) | AM401: =IF(AN401="","",IF(Q401="Sin Factura",0,P401-IFERROR(INDEX(Facturas_Odoo!$H:$H, MATCH(Q401, Facturas_Odoo!$B:$B, 0)), 0))) | AN401: =IF(AND(A401="", J401=""), "", IF(A401<>"", VALUE(MID(A401,2,LEN(A401))), AN400)) | AO401: =IF(AN401="","",IF(AD401=0,"OK",_xlfn.LET(monedaPago, IF(AA401="","USD",AA401), limitePermitido, IFERROR(VLOOKUP(monedaPago, Configuración!$A$2:$B$3, 2, FALSE), 0.15), IF(AD401>limitePermitido, "ALERTA: EXCESO (" & TEXT(limitePermitido, "0%") & " máx)", "OK")))) | AP401: =IF(AN401="","",IF(AE401=0,"OK",_xlfn.LET(fechaPago, Z401, fechaFactura, R401, diasCredito, IF(E401="Pago inmediato", 0, IFERROR(VALUE(MID(E401, 1, SEARCH(" ", E401)-1)), 0)), tolerancia, Configuración!$E$2, limiteDias, diasCredito + tolerancia, IF(OR(fechaPago="", fechaFactura=""), "REVISAR: SIN FECHA", IF(fechaPago - fechaFactura > limiteDias, "ALERTA: PAGO FUERA DE PLAZO (" & (fechaPago - fechaFactura) & " días)", "OK"))))) | AQ401: =IF(AN401="","",IF(AND(N401>0, AG401>0), IF(Configuración!$K$2="NO", "ALERTA: DESCUENTO DOBLE NO PERMITIDO", "OK"), "OK")) | AR401: =IF(AN401="","",IF(OR(AO401<>"OK", AP401<>"OK", AQ401<>"OK"), "⚠️ REVISAR", "OK"))
A402: =IF('Ordenes_Odoo'!A402="","",'Ordenes_Odoo'!A402) | B402: =IF('Ordenes_Odoo'!B402="","",'Ordenes_Odoo'!B402) | C402: =IF('Ordenes_Odoo'!C402="","",'Ordenes_Odoo'!C402) | D402: =IF('Ordenes_Odoo'!D402="","",'Ordenes_Odoo'!D402) | E402: =IF('Ordenes_Odoo'!E402="","",'Ordenes_Odoo'!E402) | F402: =IF('Ordenes_Odoo'!F402="","",'Ordenes_Odoo'!F402) | G402: =IF('Ordenes_Odoo'!G402="","",'Ordenes_Odoo'!G402) | H402: =IF('Ordenes_Odoo'!H402="","",'Ordenes_Odoo'!H402) | ... P402: =IF('Ordenes_Odoo'!P402="","",'Ordenes_Odoo'!P402) | Q402: =IF(A402="","",IFERROR(INDEX(Facturas_Odoo!$B:$B, MATCH(A402, Facturas_Odoo!$D:$D, 0)), "Sin Factura")) | R402: =IF(Q402="Sin Factura","",IFERROR(INDEX(Facturas_Odoo!$A:$A, MATCH(Q402, Facturas_Odoo!$B:$B, 0)), "")) | S402: =IF(Q402="Sin Factura","",IFERROR(_xlfn.XLOOKUP(1, (Facturas_Odoo!$D:$D=A402) * (Facturas_Odoo!$K:$K=I402), Facturas_Odoo!$L:$L, ""), "")) | T402: =IF(Q402="Sin Factura",0,IFERROR(_xlfn.XLOOKUP(1, (Facturas_Odoo!$D:$D=A402) * (Facturas_Odoo!$K:$K=I402), Facturas_Odoo!$M:$M, 0), 0)) | U402: =IF(Q402="Sin Factura",0,IFERROR(_xlfn.XLOOKUP(1, (Facturas_Odoo!$D:$D=A402) * (Facturas_Odoo!$K:$K=I402), Facturas_Odoo!$N:$N, 0), 0)) | V402: =IF(Q402="Sin Factura",0,IFERROR(_xlfn.XLOOKUP(1, (Facturas_Odoo!$D:$D=A402) * (Facturas_Odoo!$K:$K=I402), Facturas_Odoo!$O:$O, 0), 0)) | W402: =IF(Q402="Sin Factura",0,IFERROR(_xlfn.XLOOKUP(1, (Facturas_Odoo!$D:$D=A402) * (Facturas_Odoo!$K:$K=I402), Facturas_Odoo!$Q:$Q, 0), 0)) | X402: =IF(OR(Q402="Sin Factura",Q402=""),"",IFERROR(INDEX(Pagos_Odoo!$B:$B, MATCH(Q402, Pagos_Odoo!$I:$I, 0)), "Sin Pago")) | Y402: =IF(X402="Sin Pago","",IFERROR(INDEX(Pagos_Odoo!$C:$C, MATCH(X402, Pagos_Odoo!$B:$B, 0)), "")) | Z402: =IF(X402="Sin Pago","",IFERROR(INDEX(Pagos_Odoo!$A:$A, MATCH(X402, Pagos_Odoo!$B:$B, 0)), "")) | AA402: =IF(X402="Sin Pago","",IFERROR(INDEX(Pagos_Odoo!$F:$F, MATCH(X402, Pagos_Odoo!$B:$B, 0)), "")) | AB402: =IF(X402="Sin Pago",0,IFERROR(INDEX(Pagos_Odoo!$E:$E, MATCH(X402, Pagos_Odoo!$B:$B, 0)), 0)) | AC402: =IF(X402="Sin Pago","",IFERROR(INDEX(Pagos_Odoo!$G:$G, MATCH(X402, Pagos_Odoo!$B:$B, 0)), "")) | AD402: 0 | AG402: =IF(AN402="","",AD402+AE402+AF402) | AH402: =IF(AN402="","",P402*(1-AG402)) | AI402: =IF(AN402="","",IF(Q402="Sin Factura",0,IFERROR(INDEX(Facturas_Odoo!$H:$H, MATCH(Q402, Facturas_Odoo!$B:$B, 0)), 0)*(1-AG402))) | AJ402: =IF(AN402="","",_xlfn.LET(idVenta, AN402&"", pagos, IFERROR(SUMIF(Aux_Datos!$B:$B, idVenta, Aux_Datos!$L:$L), 0), retenciones, IFERROR(SUMIF(Aux_Datos!$O:$O, idVenta, Aux_Datos!$S:$S), 0), pagos_manuales, IFERROR(SUMIF('Asignación Pagos'!$G:$G, idVenta, 'Asignación Pagos'!$F:$F), 0), pagos+retenciones+pagos_manuales)) | AK402: =IF(AN402="","",AH402-AJ402) | AL402: =IF(AN402="","",IF(Q402="Sin Factura","",AI402-AJ402)) | AM402: =IF(AN402="","",IF(Q402="Sin Factura",0,P402-IFERROR(INDEX(Facturas_Odoo!$H:$H, MATCH(Q402, Facturas_Odoo!$B:$B, 0)), 0))) | AN402: =IF(AND(A402="", J402=""), "", IF(A402<>"", VALUE(MID(A402,2,LEN(A402))), AN401)) | AO402: =IF(AN402="","",IF(AD402=0,"OK",_xlfn.LET(monedaPago, IF(AA402="","USD",AA402), limitePermitido, IFERROR(VLOOKUP(monedaPago, Configuración!$A$2:$B$3, 2, FALSE), 0.15), IF(AD402>limitePermitido, "ALERTA: EXCESO (" & TEXT(limitePermitido, "0%") & " máx)", "OK")))) | AP402: =IF(AN402="","",IF(AE402=0,"OK",_xlfn.LET(fechaPago, Z402, fechaFactura, R402, diasCredito, IF(E402="Pago inmediato", 0, IFERROR(VALUE(MID(E402, 1, SEARCH(" ", E402)-1)), 0)), tolerancia, Configuración!$E$2, limiteDias, diasCredito + tolerancia, IF(OR(fechaPago="", fechaFactura=""), "REVISAR: SIN FECHA", IF(fechaPago - fechaFactura > limiteDias, "ALERTA: PAGO FUERA DE PLAZO (" & (fechaPago - fechaFactura) & " días)", "OK"))))) | AQ402: =IF(AN402="","",IF(AND(N402>0, AG402>0), IF(Configuración!$K$2="NO", "ALERTA: DESCUENTO DOBLE NO PERMITIDO", "OK"), "OK")) | AR402: =IF(AN402="","",IF(OR(AO402<>"OK", AP402<>"OK", AQ402<>"OK"), "⚠️ REVISAR", "OK"))
... A882: =IF('Ordenes_Odoo'!A882="","",'Ordenes_Odoo'!A882) | B882: =IF('Ordenes_Odoo'!B882="","",'Ordenes_Odoo'!B882) | C882: =IF('Ordenes_Odoo'!C882="","",'Ordenes_Odoo'!C882) | D882: =IF('Ordenes_Odoo'!D882="","",'Ordenes_Odoo'!D882) | E882: =IF('Ordenes_Odoo'!E882="","",'Ordenes_Odoo'!E882) | F882: =IF('Ordenes_Odoo'!F882="","",'Ordenes_Odoo'!F882) | G882: =IF('Ordenes_Odoo'!G882="","",'Ordenes_Odoo'!G882) | H882: =IF('Ordenes_Odoo'!H882="","",'Ordenes_Odoo'!H882) | ... P882: =IF('Ordenes_Odoo'!P882="","",'Ordenes_Odoo'!P882) | Q882: =IF(A882="","",IFERROR(INDEX(Facturas_Odoo!$B:$B, MATCH(A882, Facturas_Odoo!$D:$D, 0)), "Sin Factura")) | R882: =IF(Q882="Sin Factura","",IFERROR(INDEX(Facturas_Odoo!$A:$A, MATCH(Q882, Facturas_Odoo!$B:$B, 0)), "")) | S882: =IF(Q882="Sin Factura","",IFERROR(_xlfn.XLOOKUP(1, (Facturas_Odoo!$D:$D=A882) * (Facturas_Odoo!$K:$K=I882), Facturas_Odoo!$L:$L, ""), "")) | T882: =IF(Q882="Sin Factura",0,IFERROR(_xlfn.XLOOKUP(1, (Facturas_Odoo!$D:$D=A882) * (Facturas_Odoo!$K:$K=I882), Facturas_Odoo!$M:$M, 0), 0)) | U882: =IF(Q882="Sin Factura",0,IFERROR(_xlfn.XLOOKUP(1, (Facturas_Odoo!$D:$D=A882) * (Facturas_Odoo!$K:$K=I882), Facturas_Odoo!$N:$N, 0), 0)) | V882: =IF(Q882="Sin Factura",0,IFERROR(_xlfn.XLOOKUP(1, (Facturas_Odoo!$D:$D=A882) * (Facturas_Odoo!$K:$K=I882), Facturas_Odoo!$O:$O, 0), 0)) | W882: =IF(Q882="Sin Factura",0,IFERROR(_xlfn.XLOOKUP(1, (Facturas_Odoo!$D:$D=A882) * (Facturas_Odoo!$K:$K=I882), Facturas_Odoo!$Q:$Q, 0), 0)) | X882: =IF(OR(Q882="Sin Factura",Q882=""),"",IFERROR(INDEX(Pagos_Odoo!$B:$B, MATCH(Q882, Pagos_Odoo!$I:$I, 0)), "Sin Pago")) | Y882: =IF(X882="Sin Pago","",IFERROR(INDEX(Pagos_Odoo!$C:$C, MATCH(X882, Pagos_Odoo!$B:$B, 0)), "")) | Z882: =IF(X882="Sin Pago","",IFERROR(INDEX(Pagos_Odoo!$A:$A, MATCH(X882, Pagos_Odoo!$B:$B, 0)), "")) | AA882: =IF(X882="Sin Pago","",IFERROR(INDEX(Pagos_Odoo!$F:$F, MATCH(X882, Pagos_Odoo!$B:$B, 0)), "")) | AB882: =IF(X882="Sin Pago",0,IFERROR(INDEX(Pagos_Odoo!$E:$E, MATCH(X882, Pagos_Odoo!$B:$B, 0)), 0)) | AC882: =IF(X882="Sin Pago","",IFERROR(INDEX(Pagos_Odoo!$G:$G, MATCH(X882, Pagos_Odoo!$B:$B, 0)), "")) | AD882: 0 | AG882: =IF(AN882="","",AD882+AE882+AF882) | AH882: =IF(AN882="","",P882*(1-AG882)) | AI882: =IF(AN882="","",IF(Q882="Sin Factura",0,IFERROR(INDEX(Facturas_Odoo!$H:$H, MATCH(Q882, Facturas_Odoo!$B:$B, 0)), 0)*(1-AG882))) | AJ882: =IF(AN882="","",_xlfn.LET(idVenta, AN882&"", pagos, IFERROR(SUMIF(Aux_Datos!$B:$B, idVenta, Aux_Datos!$L:$L), 0), retenciones, IFERROR(SUMIF(Aux_Datos!$O:$O, idVenta, Aux_Datos!$S:$S), 0), pagos_manuales, IFERROR(SUMIF('Asignación Pagos'!$G:$G, idVenta, 'Asignación Pagos'!$F:$F), 0), pagos+retenciones+pagos_manuales)) | AK882: =IF(AN882="","",AH882-AJ882) | AL882: =IF(AN882="","",IF(Q882="Sin Factura","",AI882-AJ882)) | AM882: =IF(AN882="","",IF(Q882="Sin Factura",0,P882-IFERROR(INDEX(Facturas_Odoo!$H:$H, MATCH(Q882, Facturas_Odoo!$B:$B, 0)), 0))) | AN882: =IF(AND(A882="", J882=""), "", IF(A882<>"", VALUE(MID(A882,2,LEN(A882))), AN881)) | AO882: =IF(AN882="","",IF(AD882=0,"OK",_xlfn.LET(monedaPago, IF(AA882="","USD",AA882), limitePermitido, IFERROR(VLOOKUP(monedaPago, Configuración!$A$2:$B$3, 2, FALSE), 0.15), IF(AD882>limitePermitido, "ALERTA: EXCESO (" & TEXT(limitePermitido, "0%") & " máx)", "OK")))) | AP882: =IF(AN882="","",IF(AE882=0,"OK",_xlfn.LET(fechaPago, Z882, fechaFactura, R882, diasCredito, IF(E882="Pago inmediato", 0, IFERROR(VALUE(MID(E882, 1, SEARCH(" ", E882)-1)), 0)), tolerancia, Configuración!$E$2, limiteDias, diasCredito + tolerancia, IF(OR(fechaPago="", fechaFactura=""), "REVISAR: SIN FECHA", IF(fechaPago - fechaFactura > limiteDias, "ALERTA: PAGO FUERA DE PLAZO (" & (fechaPago - fechaFactura) & " días)", "OK"))))) | AQ882: =IF(AN882="","",IF(AND(N882>0, AG882>0), IF(Configuración!$K$2="NO", "ALERTA: DESCUENTO DOBLE NO PERMITIDO", "OK"), "OK")) | AR882: =IF(AN882="","",IF(OR(AO882<>"OK", AP882<>"OK", AQ882<>"OK"), "⚠️ REVISAR", "OK"))
A883: =IF('Ordenes_Odoo'!A883="","",'Ordenes_Odoo'!A883) | B883: =IF('Ordenes_Odoo'!B883="","",'Ordenes_Odoo'!B883) | C883: =IF('Ordenes_Odoo'!C883="","",'Ordenes_Odoo'!C883) | D883: =IF('Ordenes_Odoo'!D883="","",'Ordenes_Odoo'!D883) | E883: =IF('Ordenes_Odoo'!E883="","",'Ordenes_Odoo'!E883) | F883: =IF('Ordenes_Odoo'!F883="","",'Ordenes_Odoo'!F883) | G883: =IF('Ordenes_Odoo'!G883="","",'Ordenes_Odoo'!G883) | H883: =IF('Ordenes_Odoo'!H883="","",'Ordenes_Odoo'!H883) | ... P883: =IF('Ordenes_Odoo'!P883="","",'Ordenes_Odoo'!P883) | Q883: =IF(A883="","",IFERROR(INDEX(Facturas_Odoo!$B:$B, MATCH(A883, Facturas_Odoo!$D:$D, 0)), "Sin Factura")) | R883: =IF(Q883="Sin Factura","",IFERROR(INDEX(Facturas_Odoo!$A:$A, MATCH(Q883, Facturas_Odoo!$B:$B, 0)), "")) | S883: =IF(Q883="Sin Factura","",IFERROR(_xlfn.XLOOKUP(1, (Facturas_Odoo!$D:$D=A883) * (Facturas_Odoo!$K:$K=I883), Facturas_Odoo!$L:$L, ""), "")) | T883: =IF(Q883="Sin Factura",0,IFERROR(_xlfn.XLOOKUP(1, (Facturas_Odoo!$D:$D=A883) * (Facturas_Odoo!$K:$K=I883), Facturas_Odoo!$M:$M, 0), 0)) | U883: =IF(Q883="Sin Factura",0,IFERROR(_xlfn.XLOOKUP(1, (Facturas_Odoo!$D:$D=A883) * (Facturas_Odoo!$K:$K=I883), Facturas_Odoo!$N:$N, 0), 0)) | V883: =IF(Q883="Sin Factura",0,IFERROR(_xlfn.XLOOKUP(1, (Facturas_Odoo!$D:$D=A883) * (Facturas_Odoo!$K:$K=I883), Facturas_Odoo!$O:$O, 0), 0)) | W883: =IF(Q883="Sin Factura",0,IFERROR(_xlfn.XLOOKUP(1, (Facturas_Odoo!$D:$D=A883) * (Facturas_Odoo!$K:$K=I883), Facturas_Odoo!$Q:$Q, 0), 0)) | X883: =IF(OR(Q883="Sin Factura",Q883=""),"",IFERROR(INDEX(Pagos_Odoo!$B:$B, MATCH(Q883, Pagos_Odoo!$I:$I, 0)), "Sin Pago")) | Y883: =IF(X883="Sin Pago","",IFERROR(INDEX(Pagos_Odoo!$C:$C, MATCH(X883, Pagos_Odoo!$B:$B, 0)), "")) | Z883: =IF(X883="Sin Pago","",IFERROR(INDEX(Pagos_Odoo!$A:$A, MATCH(X883, Pagos_Odoo!$B:$B, 0)), "")) | AA883: =IF(X883="Sin Pago","",IFERROR(INDEX(Pagos_Odoo!$F:$F, MATCH(X883, Pagos_Odoo!$B:$B, 0)), "")) | AB883: =IF(X883="Sin Pago",0,IFERROR(INDEX(Pagos_Odoo!$E:$E, MATCH(X883, Pagos_Odoo!$B:$B, 0)), 0)) | AC883: =IF(X883="Sin Pago","",IFERROR(INDEX(Pagos_Odoo!$G:$G, MATCH(X883, Pagos_Odoo!$B:$B, 0)), "")) | AD883: 0 | AE883: 0.06 | AG883: =IF(AN883="","",AD883+AE883+AF883) | AH883: =IF(AN883="","",P883*(1-AG883)) | AI883: =IF(AN883="","",IF(Q883="Sin Factura",0,IFERROR(INDEX(Facturas_Odoo!$H:$H, MATCH(Q883, Facturas_Odoo!$B:$B, 0)), 0)*(1-AG883))) | AJ883: =IF(AN883="","",_xlfn.LET(idVenta, AN883&"", pagos, IFERROR(SUMIF(Aux_Datos!$B:$B, idVenta, Aux_Datos!$L:$L), 0), retenciones, IFERROR(SUMIF(Aux_Datos!$O:$O, idVenta, Aux_Datos!$S:$S), 0), pagos_manuales, IFERROR(SUMIF('Asignación Pagos'!$G:$G, idVenta, 'Asignación Pagos'!$F:$F), 0), pagos+retenciones+pagos_manuales)) | AK883: =IF(AN883="","",AH883-AJ883) | AL883: =IF(AN883="","",IF(Q883="Sin Factura","",AI883-AJ883)) | AM883: =IF(AN883="","",IF(Q883="Sin Factura",0,P883-IFERROR(INDEX(Facturas_Odoo!$H:$H, MATCH(Q883, Facturas_Odoo!$B:$B, 0)), 0))) | AN883: =IF(AND(A883="", J883=""), "", IF(A883<>"", VALUE(MID(A883,2,LEN(A883))), AN882)) | AO883: =IF(AN883="","",IF(AD883=0,"OK",_xlfn.LET(monedaPago, IF(AA883="","USD",AA883), limitePermitido, IFERROR(VLOOKUP(monedaPago, Configuración!$A$2:$B$3, 2, FALSE), 0.15), IF(AD883>limitePermitido, "ALERTA: EXCESO (" & TEXT(limitePermitido, "0%") & " máx)", "OK")))) | AP883: =IF(AN883="","",IF(AE883=0,"OK",_xlfn.LET(fechaPago, Z883, fechaFactura, R883, diasCredito, IF(E883="Pago inmediato", 0, IFERROR(VALUE(MID(E883, 1, SEARCH(" ", E883)-1)), 0)), tolerancia, Configuración!$E$2, limiteDias, diasCredito + tolerancia, IF(OR(fechaPago="", fechaFactura=""), "REVISAR: SIN FECHA", IF(fechaPago - fechaFactura > limiteDias, "ALERTA: PAGO FUERA DE PLAZO (" & (fechaPago - fechaFactura) & " días)", "OK"))))) | AQ883: =IF(AN883="","",IF(AND(N883>0, AG883>0), IF(Configuración!$K$2="NO", "ALERTA: DESCUENTO DOBLE NO PERMITIDO", "OK"), "OK")) | AR883: =IF(AN883="","",IF(OR(AO883<>"OK", AP883<>"OK", AQ883<>"OK"), "⚠️ REVISAR", "OK"))
A884: =IF('Ordenes_Odoo'!A884="","",'Ordenes_Odoo'!A884) | B884: =IF('Ordenes_Odoo'!B884="","",'Ordenes_Odoo'!B884) | C884: =IF('Ordenes_Odoo'!C884="","",'Ordenes_Odoo'!C884) | D884: =IF('Ordenes_Odoo'!D884="","",'Ordenes_Odoo'!D884) | E884: =IF('Ordenes_Odoo'!E884="","",'Ordenes_Odoo'!E884) | F884: =IF('Ordenes_Odoo'!F884="","",'Ordenes_Odoo'!F884) | G884: =IF('Ordenes_Odoo'!G884="","",'Ordenes_Odoo'!G884) | H884: =IF('Ordenes_Odoo'!H884="","",'Ordenes_Odoo'!H884) | ... P884: =IF('Ordenes_Odoo'!P884="","",'Ordenes_Odoo'!P884) | Q884: =IF(A884="","",IFERROR(INDEX(Facturas_Odoo!$B:$B, MATCH(A884, Facturas_Odoo!$D:$D, 0)), "Sin Factura")) | R884: =IF(Q884="Sin Factura","",IFERROR(INDEX(Facturas_Odoo!$A:$A, MATCH(Q884, Facturas_Odoo!$B:$B, 0)), "")) | S884: =IF(Q884="Sin Factura","",IFERROR(_xlfn.XLOOKUP(1, (Facturas_Odoo!$D:$D=A884) * (Facturas_Odoo!$K:$K=I884), Facturas_Odoo!$L:$L, ""), "")) | T884: =IF(Q884="Sin Factura",0,IFERROR(_xlfn.XLOOKUP(1, (Facturas_Odoo!$D:$D=A884) * (Facturas_Odoo!$K:$K=I884), Facturas_Odoo!$M:$M, 0), 0)) | U884: =IF(Q884="Sin Factura",0,IFERROR(_xlfn.XLOOKUP(1, (Facturas_Odoo!$D:$D=A884) * (Facturas_Odoo!$K:$K=I884), Facturas_Odoo!$N:$N, 0), 0)) | V884: =IF(Q884="Sin Factura",0,IFERROR(_xlfn.XLOOKUP(1, (Facturas_Odoo!$D:$D=A884) * (Facturas_Odoo!$K:$K=I884), Facturas_Odoo!$O:$O, 0), 0)) | W884: =IF(Q884="Sin Factura",0,IFERROR(_xlfn.XLOOKUP(1, (Facturas_Odoo!$D:$D=A884) * (Facturas_Odoo!$K:$K=I884), Facturas_Odoo!$Q:$Q, 0), 0)) | X884: =IF(OR(Q884="Sin Factura",Q884=""),"",IFERROR(INDEX(Pagos_Odoo!$B:$B, MATCH(Q884, Pagos_Odoo!$I:$I, 0)), "Sin Pago")) | Y884: =IF(X884="Sin Pago","",IFERROR(INDEX(Pagos_Odoo!$C:$C, MATCH(X884, Pagos_Odoo!$B:$B, 0)), "")) | Z884: =IF(X884="Sin Pago","",IFERROR(INDEX(Pagos_Odoo!$A:$A, MATCH(X884, Pagos_Odoo!$B:$B, 0)), "")) | AA884: =IF(X884="Sin Pago","",IFERROR(INDEX(Pagos_Odoo!$F:$F, MATCH(X884, Pagos_Odoo!$B:$B, 0)), "")) | AB884: =IF(X884="Sin Pago",0,IFERROR(INDEX(Pagos_Odoo!$E:$E, MATCH(X884, Pagos_Odoo!$B:$B, 0)), 0)) | AC884: =IF(X884="Sin Pago","",IFERROR(INDEX(Pagos_Odoo!$G:$G, MATCH(X884, Pagos_Odoo!$B:$B, 0)), "")) | AD884: 0 | AG884: =IF(AN884="","",AD884+AE884+AF884) | AH884: =IF(AN884="","",P884*(1-AG884)) | AI884: =IF(AN884="","",IF(Q884="Sin Factura",0,IFERROR(INDEX(Facturas_Odoo!$H:$H, MATCH(Q884, Facturas_Odoo!$B:$B, 0)), 0)*(1-AG884))) | AJ884: =IF(AN884="","",_xlfn.LET(idVenta, AN884&"", pagos, IFERROR(SUMIF(Aux_Datos!$B:$B, idVenta, Aux_Datos!$L:$L), 0), retenciones, IFERROR(SUMIF(Aux_Datos!$O:$O, idVenta, Aux_Datos!$S:$S), 0), pagos_manuales, IFERROR(SUMIF('Asignación Pagos'!$G:$G, idVenta, 'Asignación Pagos'!$F:$F), 0), pagos+retenciones+pagos_manuales)) | AK884: =IF(AN884="","",AH884-AJ884) | AL884: =IF(AN884="","",IF(Q884="Sin Factura","",AI884-AJ884)) | AM884: =IF(AN884="","",IF(Q884="Sin Factura",0,P884-IFERROR(INDEX(Facturas_Odoo!$H:$H, MATCH(Q884, Facturas_Odoo!$B:$B, 0)), 0))) | AN884: =IF(AND(A884="", J884=""), "", IF(A884<>"", VALUE(MID(A884,2,LEN(A884))), AN883)) | AO884: =IF(AN884="","",IF(AD884=0,"OK",_xlfn.LET(monedaPago, IF(AA884="","USD",AA884), limitePermitido, IFERROR(VLOOKUP(monedaPago, Configuración!$A$2:$B$3, 2, FALSE), 0.15), IF(AD884>limitePermitido, "ALERTA: EXCESO (" & TEXT(limitePermitido, "0%") & " máx)", "OK")))) | AP884: =IF(AN884="","",IF(AE884=0,"OK",_xlfn.LET(fechaPago, Z884, fechaFactura, R884, diasCredito, IF(E884="Pago inmediato", 0, IFERROR(VALUE(MID(E884, 1, SEARCH(" ", E884)-1)), 0)), tolerancia, Configuración!$E$2, limiteDias, diasCredito + tolerancia, IF(OR(fechaPago="", fechaFactura=""), "REVISAR: SIN FECHA", IF(fechaPago - fechaFactura > limiteDias, "ALERTA: PAGO FUERA DE PLAZO (" & (fechaPago - fechaFactura) & " días)", "OK"))))) | AQ884: =IF(AN884="","",IF(AND(N884>0, AG884>0), IF(Configuración!$K$2="NO", "ALERTA: DESCUENTO DOBLE NO PERMITIDO", "OK"), "OK")) | AR884: =IF(AN884="","",IF(OR(AO884<>"OK", AP884<>"OK", AQ884<>"OK"), "⚠️ REVISAR", "OK"))
A885: =IF('Ordenes_Odoo'!A885="","",'Ordenes_Odoo'!A885) | B885: =IF('Ordenes_Odoo'!B885="","",'Ordenes_Odoo'!B885) | C885: =IF('Ordenes_Odoo'!C885="","",'Ordenes_Odoo'!C885) | D885: =IF('Ordenes_Odoo'!D885="","",'Ordenes_Odoo'!D885) | E885: =IF('Ordenes_Odoo'!E885="","",'Ordenes_Odoo'!E885) | F885: =IF('Ordenes_Odoo'!F885="","",'Ordenes_Odoo'!F885) | G885: =IF('Ordenes_Odoo'!G885="","",'Ordenes_Odoo'!G885) | H885: =IF('Ordenes_Odoo'!H885="","",'Ordenes_Odoo'!H885) | ... P885: =IF('Ordenes_Odoo'!P885="","",'Ordenes_Odoo'!P885) | Q885: =IF(A885="","",IFERROR(INDEX(Facturas_Odoo!$B:$B, MATCH(A885, Facturas_Odoo!$D:$D, 0)), "Sin Factura")) | R885: =IF(Q885="Sin Factura","",IFERROR(INDEX(Facturas_Odoo!$A:$A, MATCH(Q885, Facturas_Odoo!$B:$B, 0)), "")) | S885: =IF(Q885="Sin Factura","",IFERROR(_xlfn.XLOOKUP(1, (Facturas_Odoo!$D:$D=A885) * (Facturas_Odoo!$K:$K=I885), Facturas_Odoo!$L:$L, ""), "")) | T885: =IF(Q885="Sin Factura",0,IFERROR(_xlfn.XLOOKUP(1, (Facturas_Odoo!$D:$D=A885) * (Facturas_Odoo!$K:$K=I885), Facturas_Odoo!$M:$M, 0), 0)) | U885: =IF(Q885="Sin Factura",0,IFERROR(_xlfn.XLOOKUP(1, (Facturas_Odoo!$D:$D=A885) * (Facturas_Odoo!$K:$K=I885), Facturas_Odoo!$N:$N, 0), 0)) | V885: =IF(Q885="Sin Factura",0,IFERROR(_xlfn.XLOOKUP(1, (Facturas_Odoo!$D:$D=A885) * (Facturas_Odoo!$K:$K=I885), Facturas_Odoo!$O:$O, 0), 0)) | W885: =IF(Q885="Sin Factura",0,IFERROR(_xlfn.XLOOKUP(1, (Facturas_Odoo!$D:$D=A885) * (Facturas_Odoo!$K:$K=I885), Facturas_Odoo!$Q:$Q, 0), 0)) | X885: =IF(OR(Q885="Sin Factura",Q885=""),"",IFERROR(INDEX(Pagos_Odoo!$B:$B, MATCH(Q885, Pagos_Odoo!$I:$I, 0)), "Sin Pago")) | Y885: =IF(X885="Sin Pago","",IFERROR(INDEX(Pagos_Odoo!$C:$C, MATCH(X885, Pagos_Odoo!$B:$B, 0)), "")) | Z885: =IF(X885="Sin Pago","",IFERROR(INDEX(Pagos_Odoo!$A:$A, MATCH(X885, Pagos_Odoo!$B:$B, 0)), "")) | AA885: =IF(X885="Sin Pago","",IFERROR(INDEX(Pagos_Odoo!$F:$F, MATCH(X885, Pagos_Odoo!$B:$B, 0)), "")) | AB885: =IF(X885="Sin Pago",0,IFERROR(INDEX(Pagos_Odoo!$E:$E, MATCH(X885, Pagos_Odoo!$B:$B, 0)), 0)) | AC885: =IF(X885="Sin Pago","",IFERROR(INDEX(Pagos_Odoo!$G:$G, MATCH(X885, Pagos_Odoo!$B:$B, 0)), "")) | AD885: 0 | AG885: =IF(AN885="","",AD885+AE885+AF885) | AH885: =IF(AN885="","",P885*(1-AG885)) | AI885: =IF(AN885="","",IF(Q885="Sin Factura",0,IFERROR(INDEX(Facturas_Odoo!$H:$H, MATCH(Q885, Facturas_Odoo!$B:$B, 0)), 0)*(1-AG885))) | AJ885: =IF(AN885="","",_xlfn.LET(idVenta, AN885&"", pagos, IFERROR(SUMIF(Aux_Datos!$B:$B, idVenta, Aux_Datos!$L:$L), 0), retenciones, IFERROR(SUMIF(Aux_Datos!$O:$O, idVenta, Aux_Datos!$S:$S), 0), pagos_manuales, IFERROR(SUMIF('Asignación Pagos'!$G:$G, idVenta, 'Asignación Pagos'!$F:$F), 0), pagos+retenciones+pagos_manuales)) | AK885: =IF(AN885="","",AH885-AJ885) | AL885: =IF(AN885="","",IF(Q885="Sin Factura","",AI885-AJ885)) | AM885: =IF(AN885="","",IF(Q885="Sin Factura",0,P885-IFERROR(INDEX(Facturas_Odoo!$H:$H, MATCH(Q885, Facturas_Odoo!$B:$B, 0)), 0))) | AN885: =IF(AND(A885="", J885=""), "", IF(A885<>"", VALUE(MID(A885,2,LEN(A885))), AN884)) | AO885: =IF(AN885="","",IF(AD885=0,"OK",_xlfn.LET(monedaPago, IF(AA885="","USD",AA885), limitePermitido, IFERROR(VLOOKUP(monedaPago, Configuración!$A$2:$B$3, 2, FALSE), 0.15), IF(AD885>limitePermitido, "ALERTA: EXCESO (" & TEXT(limitePermitido, "0%") & " máx)", "OK")))) | AP885: =IF(AN885="","",IF(AE885=0,"OK",_xlfn.LET(fechaPago, Z885, fechaFactura, R885, diasCredito, IF(E885="Pago inmediato", 0, IFERROR(VALUE(MID(E885, 1, SEARCH(" ", E885)-1)), 0)), tolerancia, Configuración!$E$2, limiteDias, diasCredito + tolerancia, IF(OR(fechaPago="", fechaFactura=""), "REVISAR: SIN FECHA", IF(fechaPago - fechaFactura > limiteDias, "ALERTA: PAGO FUERA DE PLAZO (" & (fechaPago - fechaFactura) & " días)", "OK"))))) | AQ885: =IF(AN885="","",IF(AND(N885>0, AG885>0), IF(Configuración!$K$2="NO", "ALERTA: DESCUENTO DOBLE NO PERMITIDO", "OK"), "OK")) | AR885: =IF(AN885="","",IF(OR(AO885<>"OK", AP885<>"OK", AQ885<>"OK"), "⚠️ REVISAR", "OK"))
A886: =IF('Ordenes_Odoo'!A886="","",'Ordenes_Odoo'!A886) | B886: =IF('Ordenes_Odoo'!B886="","",'Ordenes_Odoo'!B886) | C886: =IF('Ordenes_Odoo'!C886="","",'Ordenes_Odoo'!C886) | D886: =IF('Ordenes_Odoo'!D886="","",'Ordenes_Odoo'!D886) | E886: =IF('Ordenes_Odoo'!E886="","",'Ordenes_Odoo'!E886) | F886: =IF('Ordenes_Odoo'!F886="","",'Ordenes_Odoo'!F886) | G886: =IF('Ordenes_Odoo'!G886="","",'Ordenes_Odoo'!G886) | H886: =IF('Ordenes_Odoo'!H886="","",'Ordenes_Odoo'!H886) | ... P886: =IF('Ordenes_Odoo'!P886="","",'Ordenes_Odoo'!P886) | Q886: =IF(A886="","",IFERROR(INDEX(Facturas_Odoo!$B:$B, MATCH(A886, Facturas_Odoo!$D:$D, 0)), "Sin Factura")) | R886: =IF(Q886="Sin Factura","",IFERROR(INDEX(Facturas_Odoo!$A:$A, MATCH(Q886, Facturas_Odoo!$B:$B, 0)), "")) | S886: =IF(Q886="Sin Factura","",IFERROR(_xlfn.XLOOKUP(1, (Facturas_Odoo!$D:$D=A886) * (Facturas_Odoo!$K:$K=I886), Facturas_Odoo!$L:$L, ""), "")) | T886: =IF(Q886="Sin Factura",0,IFERROR(_xlfn.XLOOKUP(1, (Facturas_Odoo!$D:$D=A886) * (Facturas_Odoo!$K:$K=I886), Facturas_Odoo!$M:$M, 0), 0)) | U886: =IF(Q886="Sin Factura",0,IFERROR(_xlfn.XLOOKUP(1, (Facturas_Odoo!$D:$D=A886) * (Facturas_Odoo!$K:$K=I886), Facturas_Odoo!$N:$N, 0), 0)) | V886: =IF(Q886="Sin Factura",0,IFERROR(_xlfn.XLOOKUP(1, (Facturas_Odoo!$D:$D=A886) * (Facturas_Odoo!$K:$K=I886), Facturas_Odoo!$O:$O, 0), 0)) | W886: =IF(Q886="Sin Factura",0,IFERROR(_xlfn.XLOOKUP(1, (Facturas_Odoo!$D:$D=A886) * (Facturas_Odoo!$K:$K=I886), Facturas_Odoo!$Q:$Q, 0), 0)) | X886: =IF(OR(Q886="Sin Factura",Q886=""),"",IFERROR(INDEX(Pagos_Odoo!$B:$B, MATCH(Q886, Pagos_Odoo!$I:$I, 0)), "Sin Pago")) | Y886: =IF(X886="Sin Pago","",IFERROR(INDEX(Pagos_Odoo!$C:$C, MATCH(X886, Pagos_Odoo!$B:$B, 0)), "")) | Z886: =IF(X886="Sin Pago","",IFERROR(INDEX(Pagos_Odoo!$A:$A, MATCH(X886, Pagos_Odoo!$B:$B, 0)), "")) | AA886: =IF(X886="Sin Pago","",IFERROR(INDEX(Pagos_Odoo!$F:$F, MATCH(X886, Pagos_Odoo!$B:$B, 0)), "")) | AB886: =IF(X886="Sin Pago",0,IFERROR(INDEX(Pagos_Odoo!$E:$E, MATCH(X886, Pagos_Odoo!$B:$B, 0)), 0)) | AC886: =IF(X886="Sin Pago","",IFERROR(INDEX(Pagos_Odoo!$G:$G, MATCH(X886, Pagos_Odoo!$B:$B, 0)), "")) | AD886: 0 | AG886: =IF(AN886="","",AD886+AE886+AF886) | AH886: =IF(AN886="","",P886*(1-AG886)) | AI886: =IF(AN886="","",IF(Q886="Sin Factura",0,IFERROR(INDEX(Facturas_Odoo!$H:$H, MATCH(Q886, Facturas_Odoo!$B:$B, 0)), 0)*(1-AG886))) | AJ886: =IF(AN886="","",_xlfn.LET(idVenta, AN886&"", pagos, IFERROR(SUMIF(Aux_Datos!$B:$B, idVenta, Aux_Datos!$L:$L), 0), retenciones, IFERROR(SUMIF(Aux_Datos!$O:$O, idVenta, Aux_Datos!$S:$S), 0), pagos_manuales, IFERROR(SUMIF('Asignación Pagos'!$G:$G, idVenta, 'Asignación Pagos'!$F:$F), 0), pagos+retenciones+pagos_manuales)) | AK886: =IF(AN886="","",AH886-AJ886) | AL886: =IF(AN886="","",IF(Q886="Sin Factura","",AI886-AJ886)) | AM886: =IF(AN886="","",IF(Q886="Sin Factura",0,P886-IFERROR(INDEX(Facturas_Odoo!$H:$H, MATCH(Q886, Facturas_Odoo!$B:$B, 0)), 0))) | AN886: =IF(AND(A886="", J886=""), "", IF(A886<>"", VALUE(MID(A886,2,LEN(A886))), AN885)) | AO886: =IF(AN886="","",IF(AD886=0,"OK",_xlfn.LET(monedaPago, IF(AA886="","USD",AA886), limitePermitido, IFERROR(VLOOKUP(monedaPago, Configuración!$A$2:$B$3, 2, FALSE), 0.15), IF(AD886>limitePermitido, "ALERTA: EXCESO (" & TEXT(limitePermitido, "0%") & " máx)", "OK")))) | AP886: =IF(AN886="","",IF(AE886=0,"OK",_xlfn.LET(fechaPago, Z886, fechaFactura, R886, diasCredito, IF(E886="Pago inmediato", 0, IFERROR(VALUE(MID(E886, 1, SEARCH(" ", E886)-1)), 0)), tolerancia, Configuración!$E$2, limiteDias, diasCredito + tolerancia, IF(OR(fechaPago="", fechaFactura=""), "REVISAR: SIN FECHA", IF(fechaPago - fechaFactura > limiteDias, "ALERTA: PAGO FUERA DE PLAZO (" & (fechaPago - fechaFactura) & " días)", "OK"))))) | AQ886: =IF(AN886="","",IF(AND(N886>0, AG886>0), IF(Configuración!$K$2="NO", "ALERTA: DESCUENTO DOBLE NO PERMITIDO", "OK"), "OK")) | AR886: =IF(AN886="","",IF(OR(AO886<>"OK", AP886<>"OK", AQ886<>"OK"), "⚠️ REVISAR", "OK"))
A887: =IF('Ordenes_Odoo'!A887="","",'Ordenes_Odoo'!A887) | B887: =IF('Ordenes_Odoo'!B887="","",'Ordenes_Odoo'!B887) | C887: =IF('Ordenes_Odoo'!C887="","",'Ordenes_Odoo'!C887) | D887: =IF('Ordenes_Odoo'!D887="","",'Ordenes_Odoo'!D887) | E887: =IF('Ordenes_Odoo'!E887="","",'Ordenes_Odoo'!E887) | F887: =IF('Ordenes_Odoo'!F887="","",'Ordenes_Odoo'!F887) | G887: =IF('Ordenes_Odoo'!G887="","",'Ordenes_Odoo'!G887) | H887: =IF('Ordenes_Odoo'!H887="","",'Ordenes_Odoo'!H887) | ... P887: =IF('Ordenes_Odoo'!P887="","",'Ordenes_Odoo'!P887) | Q887: =IF(A887="","",IFERROR(INDEX(Facturas_Odoo!$B:$B, MATCH(A887, Facturas_Odoo!$D:$D, 0)), "Sin Factura")) | R887: =IF(Q887="Sin Factura","",IFERROR(INDEX(Facturas_Odoo!$A:$A, MATCH(Q887, Facturas_Odoo!$B:$B, 0)), "")) | S887: =IF(Q887="Sin Factura","",IFERROR(_xlfn.XLOOKUP(1, (Facturas_Odoo!$D:$D=A887) * (Facturas_Odoo!$K:$K=I887), Facturas_Odoo!$L:$L, ""), "")) | T887: =IF(Q887="Sin Factura",0,IFERROR(_xlfn.XLOOKUP(1, (Facturas_Odoo!$D:$D=A887) * (Facturas_Odoo!$K:$K=I887), Facturas_Odoo!$M:$M, 0), 0)) | U887: =IF(Q887="Sin Factura",0,IFERROR(_xlfn.XLOOKUP(1, (Facturas_Odoo!$D:$D=A887) * (Facturas_Odoo!$K:$K=I887), Facturas_Odoo!$N:$N, 0), 0)) | V887: =IF(Q887="Sin Factura",0,IFERROR(_xlfn.XLOOKUP(1, (Facturas_Odoo!$D:$D=A887) * (Facturas_Odoo!$K:$K=I887), Facturas_Odoo!$O:$O, 0), 0)) | W887: =IF(Q887="Sin Factura",0,IFERROR(_xlfn.XLOOKUP(1, (Facturas_Odoo!$D:$D=A887) * (Facturas_Odoo!$K:$K=I887), Facturas_Odoo!$Q:$Q, 0), 0)) | X887: =IF(OR(Q887="Sin Factura",Q887=""),"",IFERROR(INDEX(Pagos_Odoo!$B:$B, MATCH(Q887, Pagos_Odoo!$I:$I, 0)), "Sin Pago")) | Y887: =IF(X887="Sin Pago","",IFERROR(INDEX(Pagos_Odoo!$C:$C, MATCH(X887, Pagos_Odoo!$B:$B, 0)), "")) | Z887: =IF(X887="Sin Pago","",IFERROR(INDEX(Pagos_Odoo!$A:$A, MATCH(X887, Pagos_Odoo!$B:$B, 0)), "")) | AA887: =IF(X887="Sin Pago","",IFERROR(INDEX(Pagos_Odoo!$F:$F, MATCH(X887, Pagos_Odoo!$B:$B, 0)), "")) | AB887: =IF(X887="Sin Pago",0,IFERROR(INDEX(Pagos_Odoo!$E:$E, MATCH(X887, Pagos_Odoo!$B:$B, 0)), 0)) | AC887: =IF(X887="Sin Pago","",IFERROR(INDEX(Pagos_Odoo!$G:$G, MATCH(X887, Pagos_Odoo!$B:$B, 0)), "")) | AD887: 0 | AE887: 0.02 | AG887: =IF(AN887="","",AD887+AE887+AF887) | AH887: =IF(AN887="","",P887*(1-AG887)) | AI887: =IF(AN887="","",IF(Q887="Sin Factura",0,IFERROR(INDEX(Facturas_Odoo!$H:$H, MATCH(Q887, Facturas_Odoo!$B:$B, 0)), 0)*(1-AG887))) | AJ887: =IF(AN887="","",_xlfn.LET(idVenta, AN887&"", pagos, IFERROR(SUMIF(Aux_Datos!$B:$B, idVenta, Aux_Datos!$L:$L), 0), retenciones, IFERROR(SUMIF(Aux_Datos!$O:$O, idVenta, Aux_Datos!$S:$S), 0), pagos_manuales, IFERROR(SUMIF('Asignación Pagos'!$G:$G, idVenta, 'Asignación Pagos'!$F:$F), 0), pagos+retenciones+pagos_manuales)) | AK887: =IF(AN887="","",AH887-AJ887) | AL887: =IF(AN887="","",IF(Q887="Sin Factura","",AI887-AJ887)) | AM887: =IF(AN887="","",IF(Q887="Sin Factura",0,P887-IFERROR(INDEX(Facturas_Odoo!$H:$H, MATCH(Q887, Facturas_Odoo!$B:$B, 0)), 0))) | AN887: =IF(AND(A887="", J887=""), "", IF(A887<>"", VALUE(MID(A887,2,LEN(A887))), AN886)) | AO887: =IF(AN887="","",IF(AD887=0,"OK",_xlfn.LET(monedaPago, IF(AA887="","USD",AA887), limitePermitido, IFERROR(VLOOKUP(monedaPago, Configuración!$A$2:$B$3, 2, FALSE), 0.15), IF(AD887>limitePermitido, "ALERTA: EXCESO (" & TEXT(limitePermitido, "0%") & " máx)", "OK")))) | AP887: =IF(AN887="","",IF(AE887=0,"OK",_xlfn.LET(fechaPago, Z887, fechaFactura, R887, diasCredito, IF(E887="Pago inmediato", 0, IFERROR(VALUE(MID(E887, 1, SEARCH(" ", E887)-1)), 0)), tolerancia, Configuración!$E$2, limiteDias, diasCredito + tolerancia, IF(OR(fechaPago="", fechaFactura=""), "REVISAR: SIN FECHA", IF(fechaPago - fechaFactura > limiteDias, "ALERTA: PAGO FUERA DE PLAZO (" & (fechaPago - fechaFactura) & " días)", "OK"))))) | AQ887: =IF(AN887="","",IF(AND(N887>0, AG887>0), IF(Configuración!$K$2="NO", "ALERTA: DESCUENTO DOBLE NO PERMITIDO", "OK"), "OK")) | AR887: =IF(AN887="","",IF(OR(AO887<>"OK", AP887<>"OK", AQ887<>"OK"), "⚠️ REVISAR", "OK"))
A888: =IF('Ordenes_Odoo'!A888="","",'Ordenes_Odoo'!A888) | B888: =IF('Ordenes_Odoo'!B888="","",'Ordenes_Odoo'!B888) | C888: =IF('Ordenes_Odoo'!C888="","",'Ordenes_Odoo'!C888) | D888: =IF('Ordenes_Odoo'!D888="","",'Ordenes_Odoo'!D888) | E888: =IF('Ordenes_Odoo'!E888="","",'Ordenes_Odoo'!E888) | F888: =IF('Ordenes_Odoo'!F888="","",'Ordenes_Odoo'!F888) | G888: =IF('Ordenes_Odoo'!G888="","",'Ordenes_Odoo'!G888) | H888: =IF('Ordenes_Odoo'!H888="","",'Ordenes_Odoo'!H888) | ... P888: =IF('Ordenes_Odoo'!P888="","",'Ordenes_Odoo'!P888) | Q888: =IF(A888="","",IFERROR(INDEX(Facturas_Odoo!$B:$B, MATCH(A888, Facturas_Odoo!$D:$D, 0)), "Sin Factura")) | R888: =IF(Q888="Sin Factura","",IFERROR(INDEX(Facturas_Odoo!$A:$A, MATCH(Q888, Facturas_Odoo!$B:$B, 0)), "")) | S888: =IF(Q888="Sin Factura","",IFERROR(_xlfn.XLOOKUP(1, (Facturas_Odoo!$D:$D=A888) * (Facturas_Odoo!$K:$K=I888), Facturas_Odoo!$L:$L, ""), "")) | T888: =IF(Q888="Sin Factura",0,IFERROR(_xlfn.XLOOKUP(1, (Facturas_Odoo!$D:$D=A888) * (Facturas_Odoo!$K:$K=I888), Facturas_Odoo!$M:$M, 0), 0)) | U888: =IF(Q888="Sin Factura",0,IFERROR(_xlfn.XLOOKUP(1, (Facturas_Odoo!$D:$D=A888) * (Facturas_Odoo!$K:$K=I888), Facturas_Odoo!$N:$N, 0), 0)) | V888: =IF(Q888="Sin Factura",0,IFERROR(_xlfn.XLOOKUP(1, (Facturas_Odoo!$D:$D=A888) * (Facturas_Odoo!$K:$K=I888), Facturas_Odoo!$O:$O, 0), 0)) | W888: =IF(Q888="Sin Factura",0,IFERROR(_xlfn.XLOOKUP(1, (Facturas_Odoo!$D:$D=A888) * (Facturas_Odoo!$K:$K=I888), Facturas_Odoo!$Q:$Q, 0), 0)) | X888: =IF(OR(Q888="Sin Factura",Q888=""),"",IFERROR(INDEX(Pagos_Odoo!$B:$B, MATCH(Q888, Pagos_Odoo!$I:$I, 0)), "Sin Pago")) | Y888: =IF(X888="Sin Pago","",IFERROR(INDEX(Pagos_Odoo!$C:$C, MATCH(X888, Pagos_Odoo!$B:$B, 0)), "")) | Z888: =IF(X888="Sin Pago","",IFERROR(INDEX(Pagos_Odoo!$A:$A, MATCH(X888, Pagos_Odoo!$B:$B, 0)), "")) | AA888: =IF(X888="Sin Pago","",IFERROR(INDEX(Pagos_Odoo!$F:$F, MATCH(X888, Pagos_Odoo!$B:$B, 0)), "")) | AB888: =IF(X888="Sin Pago",0,IFERROR(INDEX(Pagos_Odoo!$E:$E, MATCH(X888, Pagos_Odoo!$B:$B, 0)), 0)) | AC888: =IF(X888="Sin Pago","",IFERROR(INDEX(Pagos_Odoo!$G:$G, MATCH(X888, Pagos_Odoo!$B:$B, 0)), "")) | AD888: 0 | AG888: =IF(AN888="","",AD888+AE888+AF888) | AH888: =IF(AN888="","",P888*(1-AG888)) | AI888: =IF(AN888="","",IF(Q888="Sin Factura",0,IFERROR(INDEX(Facturas_Odoo!$H:$H, MATCH(Q888, Facturas_Odoo!$B:$B, 0)), 0)*(1-AG888))) | AJ888: =IF(AN888="","",_xlfn.LET(idVenta, AN888&"", pagos, IFERROR(SUMIF(Aux_Datos!$B:$B, idVenta, Aux_Datos!$L:$L), 0), retenciones, IFERROR(SUMIF(Aux_Datos!$O:$O, idVenta, Aux_Datos!$S:$S), 0), pagos_manuales, IFERROR(SUMIF('Asignación Pagos'!$G:$G, idVenta, 'Asignación Pagos'!$F:$F), 0), pagos+retenciones+pagos_manuales)) | AK888: =IF(AN888="","",AH888-AJ888) | AL888: =IF(AN888="","",IF(Q888="Sin Factura","",AI888-AJ888)) | AM888: =IF(AN888="","",IF(Q888="Sin Factura",0,P888-IFERROR(INDEX(Facturas_Odoo!$H:$H, MATCH(Q888, Facturas_Odoo!$B:$B, 0)), 0))) | AN888: =IF(AND(A888="", J888=""), "", IF(A888<>"", VALUE(MID(A888,2,LEN(A888))), AN887)) | AO888: =IF(AN888="","",IF(AD888=0,"OK",_xlfn.LET(monedaPago, IF(AA888="","USD",AA888), limitePermitido, IFERROR(VLOOKUP(monedaPago, Configuración!$A$2:$B$3, 2, FALSE), 0.15), IF(AD888>limitePermitido, "ALERTA: EXCESO (" & TEXT(limitePermitido, "0%") & " máx)", "OK")))) | AP888: =IF(AN888="","",IF(AE888=0,"OK",_xlfn.LET(fechaPago, Z888, fechaFactura, R888, diasCredito, IF(E888="Pago inmediato", 0, IFERROR(VALUE(MID(E888, 1, SEARCH(" ", E888)-1)), 0)), tolerancia, Configuración!$E$2, limiteDias, diasCredito + tolerancia, IF(OR(fechaPago="", fechaFactura=""), "REVISAR: SIN FECHA", IF(fechaPago - fechaFactura > limiteDias, "ALERTA: PAGO FUERA DE PLAZO (" & (fechaPago - fechaFactura) & " días)", "OK"))))) | AQ888: =IF(AN888="","",IF(AND(N888>0, AG888>0), IF(Configuración!$K$2="NO", "ALERTA: DESCUENTO DOBLE NO PERMITIDO", "OK"), "OK")) | AR888: =IF(AN888="","",IF(OR(AO888<>"OK", AP888<>"OK", AQ888<>"OK"), "⚠️ REVISAR", "OK"))
A889: =IF('Ordenes_Odoo'!A889="","",'Ordenes_Odoo'!A889) | B889: =IF('Ordenes_Odoo'!B889="","",'Ordenes_Odoo'!B889) | C889: =IF('Ordenes_Odoo'!C889="","",'Ordenes_Odoo'!C889) | D889: =IF('Ordenes_Odoo'!D889="","",'Ordenes_Odoo'!D889) | E889: =IF('Ordenes_Odoo'!E889="","",'Ordenes_Odoo'!E889) | F889: =IF('Ordenes_Odoo'!F889="","",'Ordenes_Odoo'!F889) | G889: =IF('Ordenes_Odoo'!G889="","",'Ordenes_Odoo'!G889) | H889: =IF('Ordenes_Odoo'!H889="","",'Ordenes_Odoo'!H889) | ... P889: =IF('Ordenes_Odoo'!P889="","",'Ordenes_Odoo'!P889) | Q889: =IF(A889="","",IFERROR(INDEX(Facturas_Odoo!$B:$B, MATCH(A889, Facturas_Odoo!$D:$D, 0)), "Sin Factura")) | R889: =IF(Q889="Sin Factura","",IFERROR(INDEX(Facturas_Odoo!$A:$A, MATCH(Q889, Facturas_Odoo!$B:$B, 0)), "")) | S889: =IF(Q889="Sin Factura","",IFERROR(_xlfn.XLOOKUP(1, (Facturas_Odoo!$D:$D=A889) * (Facturas_Odoo!$K:$K=I889), Facturas_Odoo!$L:$L, ""), "")) | T889: =IF(Q889="Sin Factura",0,IFERROR(_xlfn.XLOOKUP(1, (Facturas_Odoo!$D:$D=A889) * (Facturas_Odoo!$K:$K=I889), Facturas_Odoo!$M:$M, 0), 0)) | U889: =IF(Q889="Sin Factura",0,IFERROR(_xlfn.XLOOKUP(1, (Facturas_Odoo!$D:$D=A889) * (Facturas_Odoo!$K:$K=I889), Facturas_Odoo!$N:$N, 0), 0)) | V889: =IF(Q889="Sin Factura",0,IFERROR(_xlfn.XLOOKUP(1, (Facturas_Odoo!$D:$D=A889) * (Facturas_Odoo!$K:$K=I889), Facturas_Odoo!$O:$O, 0), 0)) | W889: =IF(Q889="Sin Factura",0,IFERROR(_xlfn.XLOOKUP(1, (Facturas_Odoo!$D:$D=A889) * (Facturas_Odoo!$K:$K=I889), Facturas_Odoo!$Q:$Q, 0), 0)) | X889: =IF(OR(Q889="Sin Factura",Q889=""),"",IFERROR(INDEX(Pagos_Odoo!$B:$B, MATCH(Q889, Pagos_Odoo!$I:$I, 0)), "Sin Pago")) | Y889: =IF(X889="Sin Pago","",IFERROR(INDEX(Pagos_Odoo!$C:$C, MATCH(X889, Pagos_Odoo!$B:$B, 0)), "")) | Z889: =IF(X889="Sin Pago","",IFERROR(INDEX(Pagos_Odoo!$A:$A, MATCH(X889, Pagos_Odoo!$B:$B, 0)), "")) | AA889: =IF(X889="Sin Pago","",IFERROR(INDEX(Pagos_Odoo!$F:$F, MATCH(X889, Pagos_Odoo!$B:$B, 0)), "")) | AB889: =IF(X889="Sin Pago",0,IFERROR(INDEX(Pagos_Odoo!$E:$E, MATCH(X889, Pagos_Odoo!$B:$B, 0)), 0)) | AC889: =IF(X889="Sin Pago","",IFERROR(INDEX(Pagos_Odoo!$G:$G, MATCH(X889, Pagos_Odoo!$B:$B, 0)), "")) | AD889: 0 | AG889: =IF(AN889="","",AD889+AE889+AF889) | AH889: =IF(AN889="","",P889*(1-AG889)) | AI889: =IF(AN889="","",IF(Q889="Sin Factura",0,IFERROR(INDEX(Facturas_Odoo!$H:$H, MATCH(Q889, Facturas_Odoo!$B:$B, 0)), 0)*(1-AG889))) | AJ889: =IF(AN889="","",_xlfn.LET(idVenta, AN889&"", pagos, IFERROR(SUMIF(Aux_Datos!$B:$B, idVenta, Aux_Datos!$L:$L), 0), retenciones, IFERROR(SUMIF(Aux_Datos!$O:$O, idVenta, Aux_Datos!$S:$S), 0), pagos_manuales, IFERROR(SUMIF('Asignación Pagos'!$G:$G, idVenta, 'Asignación Pagos'!$F:$F), 0), pagos+retenciones+pagos_manuales)) | AK889: =IF(AN889="","",AH889-AJ889) | AL889: =IF(AN889="","",IF(Q889="Sin Factura","",AI889-AJ889)) | AM889: =IF(AN889="","",IF(Q889="Sin Factura",0,P889-IFERROR(INDEX(Facturas_Odoo!$H:$H, MATCH(Q889, Facturas_Odoo!$B:$B, 0)), 0))) | AN889: =IF(AND(A889="", J889=""), "", IF(A889<>"", VALUE(MID(A889,2,LEN(A889))), AN888)) | AO889: =IF(AN889="","",IF(AD889=0,"OK",_xlfn.LET(monedaPago, IF(AA889="","USD",AA889), limitePermitido, IFERROR(VLOOKUP(monedaPago, Configuración!$A$2:$B$3, 2, FALSE), 0.15), IF(AD889>limitePermitido, "ALERTA: EXCESO (" & TEXT(limitePermitido, "0%") & " máx)", "OK")))) | AP889: =IF(AN889="","",IF(AE889=0,"OK",_xlfn.LET(fechaPago, Z889, fechaFactura, R889, diasCredito, IF(E889="Pago inmediato", 0, IFERROR(VALUE(MID(E889, 1, SEARCH(" ", E889)-1)), 0)), tolerancia, Configuración!$E$2, limiteDias, diasCredito + tolerancia, IF(OR(fechaPago="", fechaFactura=""), "REVISAR: SIN FECHA", IF(fechaPago - fechaFactura > limiteDias, "ALERTA: PAGO FUERA DE PLAZO (" & (fechaPago - fechaFactura) & " días)", "OK"))))) | AQ889: =IF(AN889="","",IF(AND(N889>0, AG889>0), IF(Configuración!$K$2="NO", "ALERTA: DESCUENTO DOBLE NO PERMITIDO", "OK"), "OK")) | AR889: =IF(AN889="","",IF(OR(AO889<>"OK", AP889<>"OK", AQ889<>"OK"), "⚠️ REVISAR", "OK"))
A890: =IF('Ordenes_Odoo'!A890="","",'Ordenes_Odoo'!A890) | B890: =IF('Ordenes_Odoo'!B890="","",'Ordenes_Odoo'!B890) | C890: =IF('Ordenes_Odoo'!C890="","",'Ordenes_Odoo'!C890) | D890: =IF('Ordenes_Odoo'!D890="","",'Ordenes_Odoo'!D890) | E890: =IF('Ordenes_Odoo'!E890="","",'Ordenes_Odoo'!E890) | F890: =IF('Ordenes_Odoo'!F890="","",'Ordenes_Odoo'!F890) | G890: =IF('Ordenes_Odoo'!G890="","",'Ordenes_Odoo'!G890) | H890: =IF('Ordenes_Odoo'!H890="","",'Ordenes_Odoo'!H890) | ... P890: =IF('Ordenes_Odoo'!P890="","",'Ordenes_Odoo'!P890) | Q890: =IF(A890="","",IFERROR(INDEX(Facturas_Odoo!$B:$B, MATCH(A890, Facturas_Odoo!$D:$D, 0)), "Sin Factura")) | R890: =IF(Q890="Sin Factura","",IFERROR(INDEX(Facturas_Odoo!$A:$A, MATCH(Q890, Facturas_Odoo!$B:$B, 0)), "")) | S890: =IF(Q890="Sin Factura","",IFERROR(_xlfn.XLOOKUP(1, (Facturas_Odoo!$D:$D=A890) * (Facturas_Odoo!$K:$K=I890), Facturas_Odoo!$L:$L, ""), "")) | T890: =IF(Q890="Sin Factura",0,IFERROR(_xlfn.XLOOKUP(1, (Facturas_Odoo!$D:$D=A890) * (Facturas_Odoo!$K:$K=I890), Facturas_Odoo!$M:$M, 0), 0)) | U890: =IF(Q890="Sin Factura",0,IFERROR(_xlfn.XLOOKUP(1, (Facturas_Odoo!$D:$D=A890) * (Facturas_Odoo!$K:$K=I890), Facturas_Odoo!$N:$N, 0), 0)) | V890: =IF(Q890="Sin Factura",0,IFERROR(_xlfn.XLOOKUP(1, (Facturas_Odoo!$D:$D=A890) * (Facturas_Odoo!$K:$K=I890), Facturas_Odoo!$O:$O, 0), 0)) | W890: =IF(Q890="Sin Factura",0,IFERROR(_xlfn.XLOOKUP(1, (Facturas_Odoo!$D:$D=A890) * (Facturas_Odoo!$K:$K=I890), Facturas_Odoo!$Q:$Q, 0), 0)) | X890: =IF(OR(Q890="Sin Factura",Q890=""),"",IFERROR(INDEX(Pagos_Odoo!$B:$B, MATCH(Q890, Pagos_Odoo!$I:$I, 0)), "Sin Pago")) | Y890: =IF(X890="Sin Pago","",IFERROR(INDEX(Pagos_Odoo!$C:$C, MATCH(X890, Pagos_Odoo!$B:$B, 0)), "")) | Z890: =IF(X890="Sin Pago","",IFERROR(INDEX(Pagos_Odoo!$A:$A, MATCH(X890, Pagos_Odoo!$B:$B, 0)), "")) | AA890: =IF(X890="Sin Pago","",IFERROR(INDEX(Pagos_Odoo!$F:$F, MATCH(X890, Pagos_Odoo!$B:$B, 0)), "")) | AB890: =IF(X890="Sin Pago",0,IFERROR(INDEX(Pagos_Odoo!$E:$E, MATCH(X890, Pagos_Odoo!$B:$B, 0)), 0)) | AC890: =IF(X890="Sin Pago","",IFERROR(INDEX(Pagos_Odoo!$G:$G, MATCH(X890, Pagos_Odoo!$B:$B, 0)), "")) | AD890: 0 | AG890: =IF(AN890="","",AD890+AE890+AF890) | AH890: =IF(AN890="","",P890*(1-AG890)) | AI890: =IF(AN890="","",IF(Q890="Sin Factura",0,IFERROR(INDEX(Facturas_Odoo!$H:$H, MATCH(Q890, Facturas_Odoo!$B:$B, 0)), 0)*(1-AG890))) | AJ890: =IF(AN890="","",_xlfn.LET(idVenta, AN890&"", pagos, IFERROR(SUMIF(Aux_Datos!$B:$B, idVenta, Aux_Datos!$L:$L), 0), retenciones, IFERROR(SUMIF(Aux_Datos!$O:$O, idVenta, Aux_Datos!$S:$S), 0), pagos_manuales, IFERROR(SUMIF('Asignación Pagos'!$G:$G, idVenta, 'Asignación Pagos'!$F:$F), 0), pagos+retenciones+pagos_manuales)) | AK890: =IF(AN890="","",AH890-AJ890) | AL890: =IF(AN890="","",IF(Q890="Sin Factura","",AI890-AJ890)) | AM890: =IF(AN890="","",IF(Q890="Sin Factura",0,P890-IFERROR(INDEX(Facturas_Odoo!$H:$H, MATCH(Q890, Facturas_Odoo!$B:$B, 0)), 0))) | AN890: =IF(AND(A890="", J890=""), "", IF(A890<>"", VALUE(MID(A890,2,LEN(A890))), AN889)) | AO890: =IF(AN890="","",IF(AD890=0,"OK",_xlfn.LET(monedaPago, IF(AA890="","USD",AA890), limitePermitido, IFERROR(VLOOKUP(monedaPago, Configuración!$A$2:$B$3, 2, FALSE), 0.15), IF(AD890>limitePermitido, "ALERTA: EXCESO (" & TEXT(limitePermitido, "0%") & " máx)", "OK")))) | AP890: =IF(AN890="","",IF(AE890=0,"OK",_xlfn.LET(fechaPago, Z890, fechaFactura, R890, diasCredito, IF(E890="Pago inmediato", 0, IFERROR(VALUE(MID(E890, 1, SEARCH(" ", E890)-1)), 0)), tolerancia, Configuración!$E$2, limiteDias, diasCredito + tolerancia, IF(OR(fechaPago="", fechaFactura=""), "REVISAR: SIN FECHA", IF(fechaPago - fechaFactura > limiteDias, "ALERTA: PAGO FUERA DE PLAZO (" & (fechaPago - fechaFactura) & " días)", "OK"))))) | AQ890: =IF(AN890="","",IF(AND(N890>0, AG890>0), IF(Configuración!$K$2="NO", "ALERTA: DESCUENTO DOBLE NO PERMITIDO", "OK"), "OK")) | AR890: =IF(AN890="","",IF(OR(AO890<>"OK", AP890<>"OK", AQ890<>"OK"), "⚠️ REVISAR", "OK"))
A891: =IF('Ordenes_Odoo'!A891="","",'Ordenes_Odoo'!A891) | B891: =IF('Ordenes_Odoo'!B891="","",'Ordenes_Odoo'!B891) | C891: =IF('Ordenes_Odoo'!C891="","",'Ordenes_Odoo'!C891) | D891: =IF('Ordenes_Odoo'!D891="","",'Ordenes_Odoo'!D891) | E891: =IF('Ordenes_Odoo'!E891="","",'Ordenes_Odoo'!E891) | F891: =IF('Ordenes_Odoo'!F891="","",'Ordenes_Odoo'!F891) | G891: =IF('Ordenes_Odoo'!G891="","",'Ordenes_Odoo'!G891) | H891: =IF('Ordenes_Odoo'!H891="","",'Ordenes_Odoo'!H891) | ... P891: =IF('Ordenes_Odoo'!P891="","",'Ordenes_Odoo'!P891) | Q891: =IF(A891="","",IFERROR(INDEX(Facturas_Odoo!$B:$B, MATCH(A891, Facturas_Odoo!$D:$D, 0)), "Sin Factura")) | R891: =IF(Q891="Sin Factura","",IFERROR(INDEX(Facturas_Odoo!$A:$A, MATCH(Q891, Facturas_Odoo!$B:$B, 0)), "")) | S891: =IF(Q891="Sin Factura","",IFERROR(_xlfn.XLOOKUP(1, (Facturas_Odoo!$D:$D=A891) * (Facturas_Odoo!$K:$K=I891), Facturas_Odoo!$L:$L, ""), "")) | T891: =IF(Q891="Sin Factura",0,IFERROR(_xlfn.XLOOKUP(1, (Facturas_Odoo!$D:$D=A891) * (Facturas_Odoo!$K:$K=I891), Facturas_Odoo!$M:$M, 0), 0)) | U891: =IF(Q891="Sin Factura",0,IFERROR(_xlfn.XLOOKUP(1, (Facturas_Odoo!$D:$D=A891) * (Facturas_Odoo!$K:$K=I891), Facturas_Odoo!$N:$N, 0), 0)) | V891: =IF(Q891="Sin Factura",0,IFERROR(_xlfn.XLOOKUP(1, (Facturas_Odoo!$D:$D=A891) * (Facturas_Odoo!$K:$K=I891), Facturas_Odoo!$O:$O, 0), 0)) | W891: =IF(Q891="Sin Factura",0,IFERROR(_xlfn.XLOOKUP(1, (Facturas_Odoo!$D:$D=A891) * (Facturas_Odoo!$K:$K=I891), Facturas_Odoo!$Q:$Q, 0), 0)) | X891: =IF(OR(Q891="Sin Factura",Q891=""),"",IFERROR(INDEX(Pagos_Odoo!$B:$B, MATCH(Q891, Pagos_Odoo!$I:$I, 0)), "Sin Pago")) | Y891: =IF(X891="Sin Pago","",IFERROR(INDEX(Pagos_Odoo!$C:$C, MATCH(X891, Pagos_Odoo!$B:$B, 0)), "")) | Z891: =IF(X891="Sin Pago","",IFERROR(INDEX(Pagos_Odoo!$A:$A, MATCH(X891, Pagos_Odoo!$B:$B, 0)), "")) | AA891: =IF(X891="Sin Pago","",IFERROR(INDEX(Pagos_Odoo!$F:$F, MATCH(X891, Pagos_Odoo!$B:$B, 0)), "")) | AB891: =IF(X891="Sin Pago",0,IFERROR(INDEX(Pagos_Odoo!$E:$E, MATCH(X891, Pagos_Odoo!$B:$B, 0)), 0)) | AC891: =IF(X891="Sin Pago","",IFERROR(INDEX(Pagos_Odoo!$G:$G, MATCH(X891, Pagos_Odoo!$B:$B, 0)), "")) | AD891: 0 | AG891: =IF(AN891="","",AD891+AE891+AF891) | AH891: =IF(AN891="","",P891*(1-AG891)) | AI891: =IF(AN891="","",IF(Q891="Sin Factura",0,IFERROR(INDEX(Facturas_Odoo!$H:$H, MATCH(Q891, Facturas_Odoo!$B:$B, 0)), 0)*(1-AG891))) | AJ891: =IF(AN891="","",_xlfn.LET(idVenta, AN891&"", pagos, IFERROR(SUMIF(Aux_Datos!$B:$B, idVenta, Aux_Datos!$L:$L), 0), retenciones, IFERROR(SUMIF(Aux_Datos!$O:$O, idVenta, Aux_Datos!$S:$S), 0), pagos_manuales, IFERROR(SUMIF('Asignación Pagos'!$G:$G, idVenta, 'Asignación Pagos'!$F:$F), 0), pagos+retenciones+pagos_manuales)) | AK891: =IF(AN891="","",AH891-AJ891) | AL891: =IF(AN891="","",IF(Q891="Sin Factura","",AI891-AJ891)) | AM891: =IF(AN891="","",IF(Q891="Sin Factura",0,P891-IFERROR(INDEX(Facturas_Odoo!$H:$H, MATCH(Q891, Facturas_Odoo!$B:$B, 0)), 0))) | AN891: =IF(AND(A891="", J891=""), "", IF(A891<>"", VALUE(MID(A891,2,LEN(A891))), AN890)) | AO891: =IF(AN891="","",IF(AD891=0,"OK",_xlfn.LET(monedaPago, IF(AA891="","USD",AA891), limitePermitido, IFERROR(VLOOKUP(monedaPago, Configuración!$A$2:$B$3, 2, FALSE), 0.15), IF(AD891>limitePermitido, "ALERTA: EXCESO (" & TEXT(limitePermitido, "0%") & " máx)", "OK")))) | AP891: =IF(AN891="","",IF(AE891=0,"OK",_xlfn.LET(fechaPago, Z891, fechaFactura, R891, diasCredito, IF(E891="Pago inmediato", 0, IFERROR(VALUE(MID(E891, 1, SEARCH(" ", E891)-1)), 0)), tolerancia, Configuración!$E$2, limiteDias, diasCredito + tolerancia, IF(OR(fechaPago="", fechaFactura=""), "REVISAR: SIN FECHA", IF(fechaPago - fechaFactura > limiteDias, "ALERTA: PAGO FUERA DE PLAZO (" & (fechaPago - fechaFactura) & " días)", "OK"))))) | AQ891: =IF(AN891="","",IF(AND(N891>0, AG891>0), IF(Configuración!$K$2="NO", "ALERTA: DESCUENTO DOBLE NO PERMITIDO", "OK"), "OK")) | AR891: =IF(AN891="","",IF(OR(AO891<>"OK", AP891<>"OK", AQ891<>"OK"), "⚠️ REVISAR", "OK"))
A892: =IF('Ordenes_Odoo'!A892="","",'Ordenes_Odoo'!A892) | B892: =IF('Ordenes_Odoo'!B892="","",'Ordenes_Odoo'!B892) | C892: =IF('Ordenes_Odoo'!C892="","",'Ordenes_Odoo'!C892) | D892: =IF('Ordenes_Odoo'!D892="","",'Ordenes_Odoo'!D892) | E892: =IF('Ordenes_Odoo'!E892="","",'Ordenes_Odoo'!E892) | F892: =IF('Ordenes_Odoo'!F892="","",'Ordenes_Odoo'!F892) | G892: =IF('Ordenes_Odoo'!G892="","",'Ordenes_Odoo'!G892) | H892: =IF('Ordenes_Odoo'!H892="","",'Ordenes_Odoo'!H892) | ... P892: =IF('Ordenes_Odoo'!P892="","",'Ordenes_Odoo'!P892) | Q892: =IF(A892="","",IFERROR(INDEX(Facturas_Odoo!$B:$B, MATCH(A892, Facturas_Odoo!$D:$D, 0)), "Sin Factura")) | R892: =IF(Q892="Sin Factura","",IFERROR(INDEX(Facturas_Odoo!$A:$A, MATCH(Q892, Facturas_Odoo!$B:$B, 0)), "")) | S892: =IF(Q892="Sin Factura","",IFERROR(_xlfn.XLOOKUP(1, (Facturas_Odoo!$D:$D=A892) * (Facturas_Odoo!$K:$K=I892), Facturas_Odoo!$L:$L, ""), "")) | T892: =IF(Q892="Sin Factura",0,IFERROR(_xlfn.XLOOKUP(1, (Facturas_Odoo!$D:$D=A892) * (Facturas_Odoo!$K:$K=I892), Facturas_Odoo!$M:$M, 0), 0)) | U892: =IF(Q892="Sin Factura",0,IFERROR(_xlfn.XLOOKUP(1, (Facturas_Odoo!$D:$D=A892) * (Facturas_Odoo!$K:$K=I892), Facturas_Odoo!$N:$N, 0), 0)) | V892: =IF(Q892="Sin Factura",0,IFERROR(_xlfn.XLOOKUP(1, (Facturas_Odoo!$D:$D=A892) * (Facturas_Odoo!$K:$K=I892), Facturas_Odoo!$O:$O, 0), 0)) | W892: =IF(Q892="Sin Factura",0,IFERROR(_xlfn.XLOOKUP(1, (Facturas_Odoo!$D:$D=A892) * (Facturas_Odoo!$K:$K=I892), Facturas_Odoo!$Q:$Q, 0), 0)) | X892: =IF(OR(Q892="Sin Factura",Q892=""),"",IFERROR(INDEX(Pagos_Odoo!$B:$B, MATCH(Q892, Pagos_Odoo!$I:$I, 0)), "Sin Pago")) | Y892: =IF(X892="Sin Pago","",IFERROR(INDEX(Pagos_Odoo!$C:$C, MATCH(X892, Pagos_Odoo!$B:$B, 0)), "")) | Z892: =IF(X892="Sin Pago","",IFERROR(INDEX(Pagos_Odoo!$A:$A, MATCH(X892, Pagos_Odoo!$B:$B, 0)), "")) | AA892: =IF(X892="Sin Pago","",IFERROR(INDEX(Pagos_Odoo!$F:$F, MATCH(X892, Pagos_Odoo!$B:$B, 0)), "")) | AB892: =IF(X892="Sin Pago",0,IFERROR(INDEX(Pagos_Odoo!$E:$E, MATCH(X892, Pagos_Odoo!$B:$B, 0)), 0)) | AC892: =IF(X892="Sin Pago","",IFERROR(INDEX(Pagos_Odoo!$G:$G, MATCH(X892, Pagos_Odoo!$B:$B, 0)), "")) | AD892: 0 | AG892: =IF(AN892="","",AD892+AE892+AF892) | AH892: =IF(AN892="","",P892*(1-AG892)) | AI892: =IF(AN892="","",IF(Q892="Sin Factura",0,IFERROR(INDEX(Facturas_Odoo!$H:$H, MATCH(Q892, Facturas_Odoo!$B:$B, 0)), 0)*(1-AG892))) | AJ892: =IF(AN892="","",_xlfn.LET(idVenta, AN892&"", pagos, IFERROR(SUMIF(Aux_Datos!$B:$B, idVenta, Aux_Datos!$L:$L), 0), retenciones, IFERROR(SUMIF(Aux_Datos!$O:$O, idVenta, Aux_Datos!$S:$S), 0), pagos_manuales, IFERROR(SUMIF('Asignación Pagos'!$G:$G, idVenta, 'Asignación Pagos'!$F:$F), 0), pagos+retenciones+pagos_manuales)) | AK892: =IF(AN892="","",AH892-AJ892) | AL892: =IF(AN892="","",IF(Q892="Sin Factura","",AI892-AJ892)) | AM892: =IF(AN892="","",IF(Q892="Sin Factura",0,P892-IFERROR(INDEX(Facturas_Odoo!$H:$H, MATCH(Q892, Facturas_Odoo!$B:$B, 0)), 0))) | AN892: =IF(AND(A892="", J892=""), "", IF(A892<>"", VALUE(MID(A892,2,LEN(A892))), AN891)) | AO892: =IF(AN892="","",IF(AD892=0,"OK",_xlfn.LET(monedaPago, IF(AA892="","USD",AA892), limitePermitido, IFERROR(VLOOKUP(monedaPago, Configuración!$A$2:$B$3, 2, FALSE), 0.15), IF(AD892>limitePermitido, "ALERTA: EXCESO (" & TEXT(limitePermitido, "0%") & " máx)", "OK")))) | AP892: =IF(AN892="","",IF(AE892=0,"OK",_xlfn.LET(fechaPago, Z892, fechaFactura, R892, diasCredito, IF(E892="Pago inmediato", 0, IFERROR(VALUE(MID(E892, 1, SEARCH(" ", E892)-1)), 0)), tolerancia, Configuración!$E$2, limiteDias, diasCredito + tolerancia, IF(OR(fechaPago="", fechaFactura=""), "REVISAR: SIN FECHA", IF(fechaPago - fechaFactura > limiteDias, "ALERTA: PAGO FUERA DE PLAZO (" & (fechaPago - fechaFactura) & " días)", "OK"))))) | AQ892: =IF(AN892="","",IF(AND(N892>0, AG892>0), IF(Configuración!$K$2="NO", "ALERTA: DESCUENTO DOBLE NO PERMITIDO", "OK"), "OK")) | AR892: =IF(AN892="","",IF(OR(AO892<>"OK", AP892<>"OK", AQ892<>"OK"), "⚠️ REVISAR", "OK"))
A893: =IF('Ordenes_Odoo'!A893="","",'Ordenes_Odoo'!A893) | B893: =IF('Ordenes_Odoo'!B893="","",'Ordenes_Odoo'!B893) | C893: =IF('Ordenes_Odoo'!C893="","",'Ordenes_Odoo'!C893) | D893: =IF('Ordenes_Odoo'!D893="","",'Ordenes_Odoo'!D893) | E893: =IF('Ordenes_Odoo'!E893="","",'Ordenes_Odoo'!E893) | F893: =IF('Ordenes_Odoo'!F893="","",'Ordenes_Odoo'!F893) | G893: =IF('Ordenes_Odoo'!G893="","",'Ordenes_Odoo'!G893) | H893: =IF('Ordenes_Odoo'!H893="","",'Ordenes_Odoo'!H893) | ... P893: =IF('Ordenes_Odoo'!P893="","",'Ordenes_Odoo'!P893) | Q893: =IF(A893="","",IFERROR(INDEX(Facturas_Odoo!$B:$B, MATCH(A893, Facturas_Odoo!$D:$D, 0)), "Sin Factura")) | R893: =IF(Q893="Sin Factura","",IFERROR(INDEX(Facturas_Odoo!$A:$A, MATCH(Q893, Facturas_Odoo!$B:$B, 0)), "")) | S893: =IF(Q893="Sin Factura","",IFERROR(_xlfn.XLOOKUP(1, (Facturas_Odoo!$D:$D=A893) * (Facturas_Odoo!$K:$K=I893), Facturas_Odoo!$L:$L, ""), "")) | T893: =IF(Q893="Sin Factura",0,IFERROR(_xlfn.XLOOKUP(1, (Facturas_Odoo!$D:$D=A893) * (Facturas_Odoo!$K:$K=I893), Facturas_Odoo!$M:$M, 0), 0)) | U893: =IF(Q893="Sin Factura",0,IFERROR(_xlfn.XLOOKUP(1, (Facturas_Odoo!$D:$D=A893) * (Facturas_Odoo!$K:$K=I893), Facturas_Odoo!$N:$N, 0), 0)) | V893: =IF(Q893="Sin Factura",0,IFERROR(_xlfn.XLOOKUP(1, (Facturas_Odoo!$D:$D=A893) * (Facturas_Odoo!$K:$K=I893), Facturas_Odoo!$O:$O, 0), 0)) | W893: =IF(Q893="Sin Factura",0,IFERROR(_xlfn.XLOOKUP(1, (Facturas_Odoo!$D:$D=A893) * (Facturas_Odoo!$K:$K=I893), Facturas_Odoo!$Q:$Q, 0), 0)) | X893: =IF(OR(Q893="Sin Factura",Q893=""),"",IFERROR(INDEX(Pagos_Odoo!$B:$B, MATCH(Q893, Pagos_Odoo!$I:$I, 0)), "Sin Pago")) | Y893: =IF(X893="Sin Pago","",IFERROR(INDEX(Pagos_Odoo!$C:$C, MATCH(X893, Pagos_Odoo!$B:$B, 0)), "")) | Z893: =IF(X893="Sin Pago","",IFERROR(INDEX(Pagos_Odoo!$A:$A, MATCH(X893, Pagos_Odoo!$B:$B, 0)), "")) | AA893: =IF(X893="Sin Pago","",IFERROR(INDEX(Pagos_Odoo!$F:$F, MATCH(X893, Pagos_Odoo!$B:$B, 0)), "")) | AB893: =IF(X893="Sin Pago",0,IFERROR(INDEX(Pagos_Odoo!$E:$E, MATCH(X893, Pagos_Odoo!$B:$B, 0)), 0)) | AC893: =IF(X893="Sin Pago","",IFERROR(INDEX(Pagos_Odoo!$G:$G, MATCH(X893, Pagos_Odoo!$B:$B, 0)), "")) | AD893: 0 | AG893: =IF(AN893="","",AD893+AE893+AF893) | AH893: =IF(AN893="","",P893*(1-AG893)) | AI893: =IF(AN893="","",IF(Q893="Sin Factura",0,IFERROR(INDEX(Facturas_Odoo!$H:$H, MATCH(Q893, Facturas_Odoo!$B:$B, 0)), 0)*(1-AG893))) | AJ893: =IF(AN893="","",_xlfn.LET(idVenta, AN893&"", pagos, IFERROR(SUMIF(Aux_Datos!$B:$B, idVenta, Aux_Datos!$L:$L), 0), retenciones, IFERROR(SUMIF(Aux_Datos!$O:$O, idVenta, Aux_Datos!$S:$S), 0), pagos_manuales, IFERROR(SUMIF('Asignación Pagos'!$G:$G, idVenta, 'Asignación Pagos'!$F:$F), 0), pagos+retenciones+pagos_manuales)) | AK893: =IF(AN893="","",AH893-AJ893) | AL893: =IF(AN893="","",IF(Q893="Sin Factura","",AI893-AJ893)) | AM893: =IF(AN893="","",IF(Q893="Sin Factura",0,P893-IFERROR(INDEX(Facturas_Odoo!$H:$H, MATCH(Q893, Facturas_Odoo!$B:$B, 0)), 0))) | AN893: =IF(AND(A893="", J893=""), "", IF(A893<>"", VALUE(MID(A893,2,LEN(A893))), AN892)) | AO893: =IF(AN893="","",IF(AD893=0,"OK",_xlfn.LET(monedaPago, IF(AA893="","USD",AA893), limitePermitido, IFERROR(VLOOKUP(monedaPago, Configuración!$A$2:$B$3, 2, FALSE), 0.15), IF(AD893>limitePermitido, "ALERTA: EXCESO (" & TEXT(limitePermitido, "0%") & " máx)", "OK")))) | AP893: =IF(AN893="","",IF(AE893=0,"OK",_xlfn.LET(fechaPago, Z893, fechaFactura, R893, diasCredito, IF(E893="Pago inmediato", 0, IFERROR(VALUE(MID(E893, 1, SEARCH(" ", E893)-1)), 0)), tolerancia, Configuración!$E$2, limiteDias, diasCredito + tolerancia, IF(OR(fechaPago="", fechaFactura=""), "REVISAR: SIN FECHA", IF(fechaPago - fechaFactura > limiteDias, "ALERTA: PAGO FUERA DE PLAZO (" & (fechaPago - fechaFactura) & " días)", "OK"))))) | AQ893: =IF(AN893="","",IF(AND(N893>0, AG893>0), IF(Configuración!$K$2="NO", "ALERTA: DESCUENTO DOBLE NO PERMITIDO", "OK"), "OK")) | AR893: =IF(AN893="","",IF(OR(AO893<>"OK", AP893<>"OK", AQ893<>"OK"), "⚠️ REVISAR", "OK"))
A894: =IF('Ordenes_Odoo'!A894="","",'Ordenes_Odoo'!A894) | B894: =IF('Ordenes_Odoo'!B894="","",'Ordenes_Odoo'!B894) | C894: =IF('Ordenes_Odoo'!C894="","",'Ordenes_Odoo'!C894) | D894: =IF('Ordenes_Odoo'!D894="","",'Ordenes_Odoo'!D894) | E894: =IF('Ordenes_Odoo'!E894="","",'Ordenes_Odoo'!E894) | F894: =IF('Ordenes_Odoo'!F894="","",'Ordenes_Odoo'!F894) | G894: =IF('Ordenes_Odoo'!G894="","",'Ordenes_Odoo'!G894) | H894: =IF('Ordenes_Odoo'!H894="","",'Ordenes_Odoo'!H894) | ... P894: =IF('Ordenes_Odoo'!P894="","",'Ordenes_Odoo'!P894) | Q894: =IF(A894="","",IFERROR(INDEX(Facturas_Odoo!$B:$B, MATCH(A894, Facturas_Odoo!$D:$D, 0)), "Sin Factura")) | R894: =IF(Q894="Sin Factura","",IFERROR(INDEX(Facturas_Odoo!$A:$A, MATCH(Q894, Facturas_Odoo!$B:$B, 0)), "")) | S894: =IF(Q894="Sin Factura","",IFERROR(_xlfn.XLOOKUP(1, (Facturas_Odoo!$D:$D=A894) * (Facturas_Odoo!$K:$K=I894), Facturas_Odoo!$L:$L, ""), "")) | T894: =IF(Q894="Sin Factura",0,IFERROR(_xlfn.XLOOKUP(1, (Facturas_Odoo!$D:$D=A894) * (Facturas_Odoo!$K:$K=I894), Facturas_Odoo!$M:$M, 0), 0)) | U894: =IF(Q894="Sin Factura",0,IFERROR(_xlfn.XLOOKUP(1, (Facturas_Odoo!$D:$D=A894) * (Facturas_Odoo!$K:$K=I894), Facturas_Odoo!$N:$N, 0), 0)) | V894: =IF(Q894="Sin Factura",0,IFERROR(_xlfn.XLOOKUP(1, (Facturas_Odoo!$D:$D=A894) * (Facturas_Odoo!$K:$K=I894), Facturas_Odoo!$O:$O, 0), 0)) | W894: =IF(Q894="Sin Factura",0,IFERROR(_xlfn.XLOOKUP(1, (Facturas_Odoo!$D:$D=A894) * (Facturas_Odoo!$K:$K=I894), Facturas_Odoo!$Q:$Q, 0), 0)) | X894: =IF(OR(Q894="Sin Factura",Q894=""),"",IFERROR(INDEX(Pagos_Odoo!$B:$B, MATCH(Q894, Pagos_Odoo!$I:$I, 0)), "Sin Pago")) | Y894: =IF(X894="Sin Pago","",IFERROR(INDEX(Pagos_Odoo!$C:$C, MATCH(X894, Pagos_Odoo!$B:$B, 0)), "")) | Z894: =IF(X894="Sin Pago","",IFERROR(INDEX(Pagos_Odoo!$A:$A, MATCH(X894, Pagos_Odoo!$B:$B, 0)), "")) | AA894: =IF(X894="Sin Pago","",IFERROR(INDEX(Pagos_Odoo!$F:$F, MATCH(X894, Pagos_Odoo!$B:$B, 0)), "")) | AB894: =IF(X894="Sin Pago",0,IFERROR(INDEX(Pagos_Odoo!$E:$E, MATCH(X894, Pagos_Odoo!$B:$B, 0)), 0)) | AC894: =IF(X894="Sin Pago","",IFERROR(INDEX(Pagos_Odoo!$G:$G, MATCH(X894, Pagos_Odoo!$B:$B, 0)), "")) | AD894: 0 | AG894: =IF(AN894="","",AD894+AE894+AF894) | AH894: =IF(AN894="","",P894*(1-AG894)) | AI894: =IF(AN894="","",IF(Q894="Sin Factura",0,IFERROR(INDEX(Facturas_Odoo!$H:$H, MATCH(Q894, Facturas_Odoo!$B:$B, 0)), 0)*(1-AG894))) | AJ894: =IF(AN894="","",_xlfn.LET(idVenta, AN894&"", pagos, IFERROR(SUMIF(Aux_Datos!$B:$B, idVenta, Aux_Datos!$L:$L), 0), retenciones, IFERROR(SUMIF(Aux_Datos!$O:$O, idVenta, Aux_Datos!$S:$S), 0), pagos_manuales, IFERROR(SUMIF('Asignación Pagos'!$G:$G, idVenta, 'Asignación Pagos'!$F:$F), 0), pagos+retenciones+pagos_manuales)) | AK894: =IF(AN894="","",AH894-AJ894) | AL894: =IF(AN894="","",IF(Q894="Sin Factura","",AI894-AJ894)) | AM894: =IF(AN894="","",IF(Q894="Sin Factura",0,P894-IFERROR(INDEX(Facturas_Odoo!$H:$H, MATCH(Q894, Facturas_Odoo!$B:$B, 0)), 0))) | AN894: =IF(AND(A894="", J894=""), "", IF(A894<>"", VALUE(MID(A894,2,LEN(A894))), AN893)) | AO894: =IF(AN894="","",IF(AD894=0,"OK",_xlfn.LET(monedaPago, IF(AA894="","USD",AA894), limitePermitido, IFERROR(VLOOKUP(monedaPago, Configuración!$A$2:$B$3, 2, FALSE), 0.15), IF(AD894>limitePermitido, "ALERTA: EXCESO (" & TEXT(limitePermitido, "0%") & " máx)", "OK")))) | AP894: =IF(AN894="","",IF(AE894=0,"OK",_xlfn.LET(fechaPago, Z894, fechaFactura, R894, diasCredito, IF(E894="Pago inmediato", 0, IFERROR(VALUE(MID(E894, 1, SEARCH(" ", E894)-1)), 0)), tolerancia, Configuración!$E$2, limiteDias, diasCredito + tolerancia, IF(OR(fechaPago="", fechaFactura=""), "REVISAR: SIN FECHA", IF(fechaPago - fechaFactura > limiteDias, "ALERTA: PAGO FUERA DE PLAZO (" & (fechaPago - fechaFactura) & " días)", "OK"))))) | AQ894: =IF(AN894="","",IF(AND(N894>0, AG894>0), IF(Configuración!$K$2="NO", "ALERTA: DESCUENTO DOBLE NO PERMITIDO", "OK"), "OK")) | AR894: =IF(AN894="","",IF(OR(AO894<>"OK", AP894<>"OK", AQ894<>"OK"), "⚠️ REVISAR", "OK"))
A895: =IF('Ordenes_Odoo'!A895="","",'Ordenes_Odoo'!A895) | B895: =IF('Ordenes_Odoo'!B895="","",'Ordenes_Odoo'!B895) | C895: =IF('Ordenes_Odoo'!C895="","",'Ordenes_Odoo'!C895) | D895: =IF('Ordenes_Odoo'!D895="","",'Ordenes_Odoo'!D895) | E895: =IF('Ordenes_Odoo'!E895="","",'Ordenes_Odoo'!E895) | F895: =IF('Ordenes_Odoo'!F895="","",'Ordenes_Odoo'!F895) | G895: =IF('Ordenes_Odoo'!G895="","",'Ordenes_Odoo'!G895) | H895: =IF('Ordenes_Odoo'!H895="","",'Ordenes_Odoo'!H895) | ... P895: =IF('Ordenes_Odoo'!P895="","",'Ordenes_Odoo'!P895) | Q895: =IF(A895="","",IFERROR(INDEX(Facturas_Odoo!$B:$B, MATCH(A895, Facturas_Odoo!$D:$D, 0)), "Sin Factura")) | R895: =IF(Q895="Sin Factura","",IFERROR(INDEX(Facturas_Odoo!$A:$A, MATCH(Q895, Facturas_Odoo!$B:$B, 0)), "")) | S895: =IF(Q895="Sin Factura","",IFERROR(_xlfn.XLOOKUP(1, (Facturas_Odoo!$D:$D=A895) * (Facturas_Odoo!$K:$K=I895), Facturas_Odoo!$L:$L, ""), "")) | T895: =IF(Q895="Sin Factura",0,IFERROR(_xlfn.XLOOKUP(1, (Facturas_Odoo!$D:$D=A895) * (Facturas_Odoo!$K:$K=I895), Facturas_Odoo!$M:$M, 0), 0)) | U895: =IF(Q895="Sin Factura",0,IFERROR(_xlfn.XLOOKUP(1, (Facturas_Odoo!$D:$D=A895) * (Facturas_Odoo!$K:$K=I895), Facturas_Odoo!$N:$N, 0), 0)) | V895: =IF(Q895="Sin Factura",0,IFERROR(_xlfn.XLOOKUP(1, (Facturas_Odoo!$D:$D=A895) * (Facturas_Odoo!$K:$K=I895), Facturas_Odoo!$O:$O, 0), 0)) | W895: =IF(Q895="Sin Factura",0,IFERROR(_xlfn.XLOOKUP(1, (Facturas_Odoo!$D:$D=A895) * (Facturas_Odoo!$K:$K=I895), Facturas_Odoo!$Q:$Q, 0), 0)) | X895: =IF(OR(Q895="Sin Factura",Q895=""),"",IFERROR(INDEX(Pagos_Odoo!$B:$B, MATCH(Q895, Pagos_Odoo!$I:$I, 0)), "Sin Pago")) | Y895: =IF(X895="Sin Pago","",IFERROR(INDEX(Pagos_Odoo!$C:$C, MATCH(X895, Pagos_Odoo!$B:$B, 0)), "")) | Z895: =IF(X895="Sin Pago","",IFERROR(INDEX(Pagos_Odoo!$A:$A, MATCH(X895, Pagos_Odoo!$B:$B, 0)), "")) | AA895: =IF(X895="Sin Pago","",IFERROR(INDEX(Pagos_Odoo!$F:$F, MATCH(X895, Pagos_Odoo!$B:$B, 0)), "")) | AB895: =IF(X895="Sin Pago",0,IFERROR(INDEX(Pagos_Odoo!$E:$E, MATCH(X895, Pagos_Odoo!$B:$B, 0)), 0)) | AC895: =IF(X895="Sin Pago","",IFERROR(INDEX(Pagos_Odoo!$G:$G, MATCH(X895, Pagos_Odoo!$B:$B, 0)), "")) | AD895: 0 | AG895: =IF(AN895="","",AD895+AE895+AF895) | AH895: =IF(AN895="","",P895*(1-AG895)) | AI895: =IF(AN895="","",IF(Q895="Sin Factura",0,IFERROR(INDEX(Facturas_Odoo!$H:$H, MATCH(Q895, Facturas_Odoo!$B:$B, 0)), 0)*(1-AG895))) | AJ895: =IF(AN895="","",_xlfn.LET(idVenta, AN895&"", pagos, IFERROR(SUMIF(Aux_Datos!$B:$B, idVenta, Aux_Datos!$L:$L), 0), retenciones, IFERROR(SUMIF(Aux_Datos!$O:$O, idVenta, Aux_Datos!$S:$S), 0), pagos_manuales, IFERROR(SUMIF('Asignación Pagos'!$G:$G, idVenta, 'Asignación Pagos'!$F:$F), 0), pagos+retenciones+pagos_manuales)) | AK895: =IF(AN895="","",AH895-AJ895) | AL895: =IF(AN895="","",IF(Q895="Sin Factura","",AI895-AJ895)) | AM895: =IF(AN895="","",IF(Q895="Sin Factura",0,P895-IFERROR(INDEX(Facturas_Odoo!$H:$H, MATCH(Q895, Facturas_Odoo!$B:$B, 0)), 0))) | AN895: =IF(AND(A895="", J895=""), "", IF(A895<>"", VALUE(MID(A895,2,LEN(A895))), AN894)) | AO895: =IF(AN895="","",IF(AD895=0,"OK",_xlfn.LET(monedaPago, IF(AA895="","USD",AA895), limitePermitido, IFERROR(VLOOKUP(monedaPago, Configuración!$A$2:$B$3, 2, FALSE), 0.15), IF(AD895>limitePermitido, "ALERTA: EXCESO (" & TEXT(limitePermitido, "0%") & " máx)", "OK")))) | AP895: =IF(AN895="","",IF(AE895=0,"OK",_xlfn.LET(fechaPago, Z895, fechaFactura, R895, diasCredito, IF(E895="Pago inmediato", 0, IFERROR(VALUE(MID(E895, 1, SEARCH(" ", E895)-1)), 0)), tolerancia, Configuración!$E$2, limiteDias, diasCredito + tolerancia, IF(OR(fechaPago="", fechaFactura=""), "REVISAR: SIN FECHA", IF(fechaPago - fechaFactura > limiteDias, "ALERTA: PAGO FUERA DE PLAZO (" & (fechaPago - fechaFactura) & " días)", "OK"))))) | AQ895: =IF(AN895="","",IF(AND(N895>0, AG895>0), IF(Configuración!$K$2="NO", "ALERTA: DESCUENTO DOBLE NO PERMITIDO", "OK"), "OK")) | AR895: =IF(AN895="","",IF(OR(AO895<>"OK", AP895<>"OK", AQ895<>"OK"), "⚠️ REVISAR", "OK"))
A896: =IF('Ordenes_Odoo'!A896="","",'Ordenes_Odoo'!A896) | B896: =IF('Ordenes_Odoo'!B896="","",'Ordenes_Odoo'!B896) | C896: =IF('Ordenes_Odoo'!C896="","",'Ordenes_Odoo'!C896) | D896: =IF('Ordenes_Odoo'!D896="","",'Ordenes_Odoo'!D896) | E896: =IF('Ordenes_Odoo'!E896="","",'Ordenes_Odoo'!E896) | F896: =IF('Ordenes_Odoo'!F896="","",'Ordenes_Odoo'!F896) | G896: =IF('Ordenes_Odoo'!G896="","",'Ordenes_Odoo'!G896) | H896: =IF('Ordenes_Odoo'!H896="","",'Ordenes_Odoo'!H896) | ... P896: =IF('Ordenes_Odoo'!P896="","",'Ordenes_Odoo'!P896) | Q896: =IF(A896="","",IFERROR(INDEX(Facturas_Odoo!$B:$B, MATCH(A896, Facturas_Odoo!$D:$D, 0)), "Sin Factura")) | R896: =IF(Q896="Sin Factura","",IFERROR(INDEX(Facturas_Odoo!$A:$A, MATCH(Q896, Facturas_Odoo!$B:$B, 0)), "")) | S896: =IF(Q896="Sin Factura","",IFERROR(_xlfn.XLOOKUP(1, (Facturas_Odoo!$D:$D=A896) * (Facturas_Odoo!$K:$K=I896), Facturas_Odoo!$L:$L, ""), "")) | T896: =IF(Q896="Sin Factura",0,IFERROR(_xlfn.XLOOKUP(1, (Facturas_Odoo!$D:$D=A896) * (Facturas_Odoo!$K:$K=I896), Facturas_Odoo!$M:$M, 0), 0)) | U896: =IF(Q896="Sin Factura",0,IFERROR(_xlfn.XLOOKUP(1, (Facturas_Odoo!$D:$D=A896) * (Facturas_Odoo!$K:$K=I896), Facturas_Odoo!$N:$N, 0), 0)) | V896: =IF(Q896="Sin Factura",0,IFERROR(_xlfn.XLOOKUP(1, (Facturas_Odoo!$D:$D=A896) * (Facturas_Odoo!$K:$K=I896), Facturas_Odoo!$O:$O, 0), 0)) | W896: =IF(Q896="Sin Factura",0,IFERROR(_xlfn.XLOOKUP(1, (Facturas_Odoo!$D:$D=A896) * (Facturas_Odoo!$K:$K=I896), Facturas_Odoo!$Q:$Q, 0), 0)) | X896: =IF(OR(Q896="Sin Factura",Q896=""),"",IFERROR(INDEX(Pagos_Odoo!$B:$B, MATCH(Q896, Pagos_Odoo!$I:$I, 0)), "Sin Pago")) | Y896: =IF(X896="Sin Pago","",IFERROR(INDEX(Pagos_Odoo!$C:$C, MATCH(X896, Pagos_Odoo!$B:$B, 0)), "")) | Z896: =IF(X896="Sin Pago","",IFERROR(INDEX(Pagos_Odoo!$A:$A, MATCH(X896, Pagos_Odoo!$B:$B, 0)), "")) | AA896: =IF(X896="Sin Pago","",IFERROR(INDEX(Pagos_Odoo!$F:$F, MATCH(X896, Pagos_Odoo!$B:$B, 0)), "")) | AB896: =IF(X896="Sin Pago",0,IFERROR(INDEX(Pagos_Odoo!$E:$E, MATCH(X896, Pagos_Odoo!$B:$B, 0)), 0)) | AC896: =IF(X896="Sin Pago","",IFERROR(INDEX(Pagos_Odoo!$G:$G, MATCH(X896, Pagos_Odoo!$B:$B, 0)), "")) | AD896: 0 | AG896: =IF(AN896="","",AD896+AE896+AF896) | AH896: =IF(AN896="","",P896*(1-AG896)) | AI896: =IF(AN896="","",IF(Q896="Sin Factura",0,IFERROR(INDEX(Facturas_Odoo!$H:$H, MATCH(Q896, Facturas_Odoo!$B:$B, 0)), 0)*(1-AG896))) | AJ896: =IF(AN896="","",_xlfn.LET(idVenta, AN896&"", pagos, IFERROR(SUMIF(Aux_Datos!$B:$B, idVenta, Aux_Datos!$L:$L), 0), retenciones, IFERROR(SUMIF(Aux_Datos!$O:$O, idVenta, Aux_Datos!$S:$S), 0), pagos_manuales, IFERROR(SUMIF('Asignación Pagos'!$G:$G, idVenta, 'Asignación Pagos'!$F:$F), 0), pagos+retenciones+pagos_manuales)) | AK896: =IF(AN896="","",AH896-AJ896) | AL896: =IF(AN896="","",IF(Q896="Sin Factura","",AI896-AJ896)) | AM896: =IF(AN896="","",IF(Q896="Sin Factura",0,P896-IFERROR(INDEX(Facturas_Odoo!$H:$H, MATCH(Q896, Facturas_Odoo!$B:$B, 0)), 0))) | AN896: =IF(AND(A896="", J896=""), "", IF(A896<>"", VALUE(MID(A896,2,LEN(A896))), AN895)) | AO896: =IF(AN896="","",IF(AD896=0,"OK",_xlfn.LET(monedaPago, IF(AA896="","USD",AA896), limitePermitido, IFERROR(VLOOKUP(monedaPago, Configuración!$A$2:$B$3, 2, FALSE), 0.15), IF(AD896>limitePermitido, "ALERTA: EXCESO (" & TEXT(limitePermitido, "0%") & " máx)", "OK")))) | AP896: =IF(AN896="","",IF(AE896=0,"OK",_xlfn.LET(fechaPago, Z896, fechaFactura, R896, diasCredito, IF(E896="Pago inmediato", 0, IFERROR(VALUE(MID(E896, 1, SEARCH(" ", E896)-1)), 0)), tolerancia, Configuración!$E$2, limiteDias, diasCredito + tolerancia, IF(OR(fechaPago="", fechaFactura=""), "REVISAR: SIN FECHA", IF(fechaPago - fechaFactura > limiteDias, "ALERTA: PAGO FUERA DE PLAZO (" & (fechaPago - fechaFactura) & " días)", "OK"))))) | AQ896: =IF(AN896="","",IF(AND(N896>0, AG896>0), IF(Configuración!$K$2="NO", "ALERTA: DESCUENTO DOBLE NO PERMITIDO", "OK"), "OK")) | AR896: =IF(AN896="","",IF(OR(AO896<>"OK", AP896<>"OK", AQ896<>"OK"), "⚠️ REVISAR", "OK"))
A897: =IF('Ordenes_Odoo'!A897="","",'Ordenes_Odoo'!A897) | B897: =IF('Ordenes_Odoo'!B897="","",'Ordenes_Odoo'!B897) | C897: =IF('Ordenes_Odoo'!C897="","",'Ordenes_Odoo'!C897) | D897: =IF('Ordenes_Odoo'!D897="","",'Ordenes_Odoo'!D897) | E897: =IF('Ordenes_Odoo'!E897="","",'Ordenes_Odoo'!E897) | F897: =IF('Ordenes_Odoo'!F897="","",'Ordenes_Odoo'!F897) | G897: =IF('Ordenes_Odoo'!G897="","",'Ordenes_Odoo'!G897) | H897: =IF('Ordenes_Odoo'!H897="","",'Ordenes_Odoo'!H897) | ... P897: =IF('Ordenes_Odoo'!P897="","",'Ordenes_Odoo'!P897) | Q897: =IF(A897="","",IFERROR(INDEX(Facturas_Odoo!$B:$B, MATCH(A897, Facturas_Odoo!$D:$D, 0)), "Sin Factura")) | R897: =IF(Q897="Sin Factura","",IFERROR(INDEX(Facturas_Odoo!$A:$A, MATCH(Q897, Facturas_Odoo!$B:$B, 0)), "")) | S897: =IF(Q897="Sin Factura","",IFERROR(_xlfn.XLOOKUP(1, (Facturas_Odoo!$D:$D=A897) * (Facturas_Odoo!$K:$K=I897), Facturas_Odoo!$L:$L, ""), "")) | T897: =IF(Q897="Sin Factura",0,IFERROR(_xlfn.XLOOKUP(1, (Facturas_Odoo!$D:$D=A897) * (Facturas_Odoo!$K:$K=I897), Facturas_Odoo!$M:$M, 0), 0)) | U897: =IF(Q897="Sin Factura",0,IFERROR(_xlfn.XLOOKUP(1, (Facturas_Odoo!$D:$D=A897) * (Facturas_Odoo!$K:$K=I897), Facturas_Odoo!$N:$N, 0), 0)) | V897: =IF(Q897="Sin Factura",0,IFERROR(_xlfn.XLOOKUP(1, (Facturas_Odoo!$D:$D=A897) * (Facturas_Odoo!$K:$K=I897), Facturas_Odoo!$O:$O, 0), 0)) | W897: =IF(Q897="Sin Factura",0,IFERROR(_xlfn.XLOOKUP(1, (Facturas_Odoo!$D:$D=A897) * (Facturas_Odoo!$K:$K=I897), Facturas_Odoo!$Q:$Q, 0), 0)) | X897: =IF(OR(Q897="Sin Factura",Q897=""),"",IFERROR(INDEX(Pagos_Odoo!$B:$B, MATCH(Q897, Pagos_Odoo!$I:$I, 0)), "Sin Pago")) | Y897: =IF(X897="Sin Pago","",IFERROR(INDEX(Pagos_Odoo!$C:$C, MATCH(X897, Pagos_Odoo!$B:$B, 0)), "")) | Z897: =IF(X897="Sin Pago","",IFERROR(INDEX(Pagos_Odoo!$A:$A, MATCH(X897, Pagos_Odoo!$B:$B, 0)), "")) | AA897: =IF(X897="Sin Pago","",IFERROR(INDEX(Pagos_Odoo!$F:$F, MATCH(X897, Pagos_Odoo!$B:$B, 0)), "")) | AB897: =IF(X897="Sin Pago",0,IFERROR(INDEX(Pagos_Odoo!$E:$E, MATCH(X897, Pagos_Odoo!$B:$B, 0)), 0)) | AC897: =IF(X897="Sin Pago","",IFERROR(INDEX(Pagos_Odoo!$G:$G, MATCH(X897, Pagos_Odoo!$B:$B, 0)), "")) | AD897: 0 | AG897: =IF(AN897="","",AD897+AE897+AF897) | AH897: =IF(AN897="","",P897*(1-AG897)) | AI897: =IF(AN897="","",IF(Q897="Sin Factura",0,IFERROR(INDEX(Facturas_Odoo!$H:$H, MATCH(Q897, Facturas_Odoo!$B:$B, 0)), 0)*(1-AG897))) | AJ897: =IF(AN897="","",_xlfn.LET(idVenta, AN897&"", pagos, IFERROR(SUMIF(Aux_Datos!$B:$B, idVenta, Aux_Datos!$L:$L), 0), retenciones, IFERROR(SUMIF(Aux_Datos!$O:$O, idVenta, Aux_Datos!$S:$S), 0), pagos_manuales, IFERROR(SUMIF('Asignación Pagos'!$G:$G, idVenta, 'Asignación Pagos'!$F:$F), 0), pagos+retenciones+pagos_manuales)) | AK897: =IF(AN897="","",AH897-AJ897) | AL897: =IF(AN897="","",IF(Q897="Sin Factura","",AI897-AJ897)) | AM897: =IF(AN897="","",IF(Q897="Sin Factura",0,P897-IFERROR(INDEX(Facturas_Odoo!$H:$H, MATCH(Q897, Facturas_Odoo!$B:$B, 0)), 0))) | AN897: =IF(AND(A897="", J897=""), "", IF(A897<>"", VALUE(MID(A897,2,LEN(A897))), AN896)) | AO897: =IF(AN897="","",IF(AD897=0,"OK",_xlfn.LET(monedaPago, IF(AA897="","USD",AA897), limitePermitido, IFERROR(VLOOKUP(monedaPago, Configuración!$A$2:$B$3, 2, FALSE), 0.15), IF(AD897>limitePermitido, "ALERTA: EXCESO (" & TEXT(limitePermitido, "0%") & " máx)", "OK")))) | AP897: =IF(AN897="","",IF(AE897=0,"OK",_xlfn.LET(fechaPago, Z897, fechaFactura, R897, diasCredito, IF(E897="Pago inmediato", 0, IFERROR(VALUE(MID(E897, 1, SEARCH(" ", E897)-1)), 0)), tolerancia, Configuración!$E$2, limiteDias, diasCredito + tolerancia, IF(OR(fechaPago="", fechaFactura=""), "REVISAR: SIN FECHA", IF(fechaPago - fechaFactura > limiteDias, "ALERTA: PAGO FUERA DE PLAZO (" & (fechaPago - fechaFactura) & " días)", "OK"))))) | AQ897: =IF(AN897="","",IF(AND(N897>0, AG897>0), IF(Configuración!$K$2="NO", "ALERTA: DESCUENTO DOBLE NO PERMITIDO", "OK"), "OK")) | AR897: =IF(AN897="","",IF(OR(AO897<>"OK", AP897<>"OK", AQ897<>"OK"), "⚠️ REVISAR", "OK"))
A898: =IF('Ordenes_Odoo'!A898="","",'Ordenes_Odoo'!A898) | B898: =IF('Ordenes_Odoo'!B898="","",'Ordenes_Odoo'!B898) | C898: =IF('Ordenes_Odoo'!C898="","",'Ordenes_Odoo'!C898) | D898: =IF('Ordenes_Odoo'!D898="","",'Ordenes_Odoo'!D898) | E898: =IF('Ordenes_Odoo'!E898="","",'Ordenes_Odoo'!E898) | F898: =IF('Ordenes_Odoo'!F898="","",'Ordenes_Odoo'!F898) | G898: =IF('Ordenes_Odoo'!G898="","",'Ordenes_Odoo'!G898) | H898: =IF('Ordenes_Odoo'!H898="","",'Ordenes_Odoo'!H898) | ... P898: =IF('Ordenes_Odoo'!P898="","",'Ordenes_Odoo'!P898) | Q898: =IF(A898="","",IFERROR(INDEX(Facturas_Odoo!$B:$B, MATCH(A898, Facturas_Odoo!$D:$D, 0)), "Sin Factura")) | R898: =IF(Q898="Sin Factura","",IFERROR(INDEX(Facturas_Odoo!$A:$A, MATCH(Q898, Facturas_Odoo!$B:$B, 0)), "")) | S898: =IF(Q898="Sin Factura","",IFERROR(_xlfn.XLOOKUP(1, (Facturas_Odoo!$D:$D=A898) * (Facturas_Odoo!$K:$K=I898), Facturas_Odoo!$L:$L, ""), "")) | T898: =IF(Q898="Sin Factura",0,IFERROR(_xlfn.XLOOKUP(1, (Facturas_Odoo!$D:$D=A898) * (Facturas_Odoo!$K:$K=I898), Facturas_Odoo!$M:$M, 0), 0)) | U898: =IF(Q898="Sin Factura",0,IFERROR(_xlfn.XLOOKUP(1, (Facturas_Odoo!$D:$D=A898) * (Facturas_Odoo!$K:$K=I898), Facturas_Odoo!$N:$N, 0), 0)) | V898: =IF(Q898="Sin Factura",0,IFERROR(_xlfn.XLOOKUP(1, (Facturas_Odoo!$D:$D=A898) * (Facturas_Odoo!$K:$K=I898), Facturas_Odoo!$O:$O, 0), 0)) | W898: =IF(Q898="Sin Factura",0,IFERROR(_xlfn.XLOOKUP(1, (Facturas_Odoo!$D:$D=A898) * (Facturas_Odoo!$K:$K=I898), Facturas_Odoo!$Q:$Q, 0), 0)) | X898: =IF(OR(Q898="Sin Factura",Q898=""),"",IFERROR(INDEX(Pagos_Odoo!$B:$B, MATCH(Q898, Pagos_Odoo!$I:$I, 0)), "Sin Pago")) | Y898: =IF(X898="Sin Pago","",IFERROR(INDEX(Pagos_Odoo!$C:$C, MATCH(X898, Pagos_Odoo!$B:$B, 0)), "")) | Z898: =IF(X898="Sin Pago","",IFERROR(INDEX(Pagos_Odoo!$A:$A, MATCH(X898, Pagos_Odoo!$B:$B, 0)), "")) | AA898: =IF(X898="Sin Pago","",IFERROR(INDEX(Pagos_Odoo!$F:$F, MATCH(X898, Pagos_Odoo!$B:$B, 0)), "")) | AB898: =IF(X898="Sin Pago",0,IFERROR(INDEX(Pagos_Odoo!$E:$E, MATCH(X898, Pagos_Odoo!$B:$B, 0)), 0)) | AC898: =IF(X898="Sin Pago","",IFERROR(INDEX(Pagos_Odoo!$G:$G, MATCH(X898, Pagos_Odoo!$B:$B, 0)), "")) | AD898: 0 | AG898: =IF(AN898="","",AD898+AE898+AF898) | AH898: =IF(AN898="","",P898*(1-AG898)) | AI898: =IF(AN898="","",IF(Q898="Sin Factura",0,IFERROR(INDEX(Facturas_Odoo!$H:$H, MATCH(Q898, Facturas_Odoo!$B:$B, 0)), 0)*(1-AG898))) | AJ898: =IF(AN898="","",_xlfn.LET(idVenta, AN898&"", pagos, IFERROR(SUMIF(Aux_Datos!$B:$B, idVenta, Aux_Datos!$L:$L), 0), retenciones, IFERROR(SUMIF(Aux_Datos!$O:$O, idVenta, Aux_Datos!$S:$S), 0), pagos_manuales, IFERROR(SUMIF('Asignación Pagos'!$G:$G, idVenta, 'Asignación Pagos'!$F:$F), 0), pagos+retenciones+pagos_manuales)) | AK898: =IF(AN898="","",AH898-AJ898) | AL898: =IF(AN898="","",IF(Q898="Sin Factura","",AI898-AJ898)) | AM898: =IF(AN898="","",IF(Q898="Sin Factura",0,P898-IFERROR(INDEX(Facturas_Odoo!$H:$H, MATCH(Q898, Facturas_Odoo!$B:$B, 0)), 0))) | AN898: =IF(AND(A898="", J898=""), "", IF(A898<>"", VALUE(MID(A898,2,LEN(A898))), AN897)) | AO898: =IF(AN898="","",IF(AD898=0,"OK",_xlfn.LET(monedaPago, IF(AA898="","USD",AA898), limitePermitido, IFERROR(VLOOKUP(monedaPago, Configuración!$A$2:$B$3, 2, FALSE), 0.15), IF(AD898>limitePermitido, "ALERTA: EXCESO (" & TEXT(limitePermitido, "0%") & " máx)", "OK")))) | AP898: =IF(AN898="","",IF(AE898=0,"OK",_xlfn.LET(fechaPago, Z898, fechaFactura, R898, diasCredito, IF(E898="Pago inmediato", 0, IFERROR(VALUE(MID(E898, 1, SEARCH(" ", E898)-1)), 0)), tolerancia, Configuración!$E$2, limiteDias, diasCredito + tolerancia, IF(OR(fechaPago="", fechaFactura=""), "REVISAR: SIN FECHA", IF(fechaPago - fechaFactura > limiteDias, "ALERTA: PAGO FUERA DE PLAZO (" & (fechaPago - fechaFactura) & " días)", "OK"))))) | AQ898: =IF(AN898="","",IF(AND(N898>0, AG898>0), IF(Configuración!$K$2="NO", "ALERTA: DESCUENTO DOBLE NO PERMITIDO", "OK"), "OK")) | AR898: =IF(AN898="","",IF(OR(AO898<>"OK", AP898<>"OK", AQ898<>"OK"), "⚠️ REVISAR", "OK"))
A899: =IF('Ordenes_Odoo'!A899="","",'Ordenes_Odoo'!A899) | B899: =IF('Ordenes_Odoo'!B899="","",'Ordenes_Odoo'!B899) | C899: =IF('Ordenes_Odoo'!C899="","",'Ordenes_Odoo'!C899) | D899: =IF('Ordenes_Odoo'!D899="","",'Ordenes_Odoo'!D899) | E899: =IF('Ordenes_Odoo'!E899="","",'Ordenes_Odoo'!E899) | F899: =IF('Ordenes_Odoo'!F899="","",'Ordenes_Odoo'!F899) | G899: =IF('Ordenes_Odoo'!G899="","",'Ordenes_Odoo'!G899) | H899: =IF('Ordenes_Odoo'!H899="","",'Ordenes_Odoo'!H899) | ... P899: =IF('Ordenes_Odoo'!P899="","",'Ordenes_Odoo'!P899) | Q899: =IF(A899="","",IFERROR(INDEX(Facturas_Odoo!$B:$B, MATCH(A899, Facturas_Odoo!$D:$D, 0)), "Sin Factura")) | R899: =IF(Q899="Sin Factura","",IFERROR(INDEX(Facturas_Odoo!$A:$A, MATCH(Q899, Facturas_Odoo!$B:$B, 0)), "")) | S899: =IF(Q899="Sin Factura","",IFERROR(_xlfn.XLOOKUP(1, (Facturas_Odoo!$D:$D=A899) * (Facturas_Odoo!$K:$K=I899), Facturas_Odoo!$L:$L, ""), "")) | T899: =IF(Q899="Sin Factura",0,IFERROR(_xlfn.XLOOKUP(1, (Facturas_Odoo!$D:$D=A899) * (Facturas_Odoo!$K:$K=I899), Facturas_Odoo!$M:$M, 0), 0)) | U899: =IF(Q899="Sin Factura",0,IFERROR(_xlfn.XLOOKUP(1, (Facturas_Odoo!$D:$D=A899) * (Facturas_Odoo!$K:$K=I899), Facturas_Odoo!$N:$N, 0), 0)) | V899: =IF(Q899="Sin Factura",0,IFERROR(_xlfn.XLOOKUP(1, (Facturas_Odoo!$D:$D=A899) * (Facturas_Odoo!$K:$K=I899), Facturas_Odoo!$O:$O, 0), 0)) | W899: =IF(Q899="Sin Factura",0,IFERROR(_xlfn.XLOOKUP(1, (Facturas_Odoo!$D:$D=A899) * (Facturas_Odoo!$K:$K=I899), Facturas_Odoo!$Q:$Q, 0), 0)) | X899: =IF(OR(Q899="Sin Factura",Q899=""),"",IFERROR(INDEX(Pagos_Odoo!$B:$B, MATCH(Q899, Pagos_Odoo!$I:$I, 0)), "Sin Pago")) | Y899: =IF(X899="Sin Pago","",IFERROR(INDEX(Pagos_Odoo!$C:$C, MATCH(X899, Pagos_Odoo!$B:$B, 0)), "")) | Z899: =IF(X899="Sin Pago","",IFERROR(INDEX(Pagos_Odoo!$A:$A, MATCH(X899, Pagos_Odoo!$B:$B, 0)), "")) | AA899: =IF(X899="Sin Pago","",IFERROR(INDEX(Pagos_Odoo!$F:$F, MATCH(X899, Pagos_Odoo!$B:$B, 0)), "")) | AB899: =IF(X899="Sin Pago",0,IFERROR(INDEX(Pagos_Odoo!$E:$E, MATCH(X899, Pagos_Odoo!$B:$B, 0)), 0)) | AC899: =IF(X899="Sin Pago","",IFERROR(INDEX(Pagos_Odoo!$G:$G, MATCH(X899, Pagos_Odoo!$B:$B, 0)), "")) | AD899: 0 | AG899: =IF(AN899="","",AD899+AE899+AF899) | AH899: =IF(AN899="","",P899*(1-AG899)) | AI899: =IF(AN899="","",IF(Q899="Sin Factura",0,IFERROR(INDEX(Facturas_Odoo!$H:$H, MATCH(Q899, Facturas_Odoo!$B:$B, 0)), 0)*(1-AG899))) | AJ899: =IF(AN899="","",_xlfn.LET(idVenta, AN899&"", pagos, IFERROR(SUMIF(Aux_Datos!$B:$B, idVenta, Aux_Datos!$L:$L), 0), retenciones, IFERROR(SUMIF(Aux_Datos!$O:$O, idVenta, Aux_Datos!$S:$S), 0), pagos_manuales, IFERROR(SUMIF('Asignación Pagos'!$G:$G, idVenta, 'Asignación Pagos'!$F:$F), 0), pagos+retenciones+pagos_manuales)) | AK899: =IF(AN899="","",AH899-AJ899) | AL899: =IF(AN899="","",IF(Q899="Sin Factura","",AI899-AJ899)) | AM899: =IF(AN899="","",IF(Q899="Sin Factura",0,P899-IFERROR(INDEX(Facturas_Odoo!$H:$H, MATCH(Q899, Facturas_Odoo!$B:$B, 0)), 0))) | AN899: =IF(AND(A899="", J899=""), "", IF(A899<>"", VALUE(MID(A899,2,LEN(A899))), AN898)) | AO899: =IF(AN899="","",IF(AD899=0,"OK",_xlfn.LET(monedaPago, IF(AA899="","USD",AA899), limitePermitido, IFERROR(VLOOKUP(monedaPago, Configuración!$A$2:$B$3, 2, FALSE), 0.15), IF(AD899>limitePermitido, "ALERTA: EXCESO (" & TEXT(limitePermitido, "0%") & " máx)", "OK")))) | AP899: =IF(AN899="","",IF(AE899=0,"OK",_xlfn.LET(fechaPago, Z899, fechaFactura, R899, diasCredito, IF(E899="Pago inmediato", 0, IFERROR(VALUE(MID(E899, 1, SEARCH(" ", E899)-1)), 0)), tolerancia, Configuración!$E$2, limiteDias, diasCredito + tolerancia, IF(OR(fechaPago="", fechaFactura=""), "REVISAR: SIN FECHA", IF(fechaPago - fechaFactura > limiteDias, "ALERTA: PAGO FUERA DE PLAZO (" & (fechaPago - fechaFactura) & " días)", "OK"))))) | AQ899: =IF(AN899="","",IF(AND(N899>0, AG899>0), IF(Configuración!$K$2="NO", "ALERTA: DESCUENTO DOBLE NO PERMITIDO", "OK"), "OK")) | AR899: =IF(AN899="","",IF(OR(AO899<>"OK", AP899<>"OK", AQ899<>"OK"), "⚠️ REVISAR", "OK"))
... A1153: =IF('Ordenes_Odoo'!A1153="","",'Ordenes_Odoo'!A1153) | B1153: =IF('Ordenes_Odoo'!B1153="","",'Ordenes_Odoo'!B1153) | C1153: =IF('Ordenes_Odoo'!C1153="","",'Ordenes_Odoo'!C1153) | D1153: =IF('Ordenes_Odoo'!D1153="","",'Ordenes_Odoo'!D1153) | E1153: =IF('Ordenes_Odoo'!E1153="","",'Ordenes_Odoo'!E1153) | F1153: =IF('Ordenes_Odoo'!F1153="","",'Ordenes_Odoo'!F1153) | G1153: =IF('Ordenes_Odoo'!G1153="","",'Ordenes_Odoo'!G1153) | H1153: =IF('Ordenes_Odoo'!H1153="","",'Ordenes_Odoo'!H1153) | ... P1153: =IF('Ordenes_Odoo'!P1153="","",'Ordenes_Odoo'!P1153) | Q1153: =IF(A1153="","",IFERROR(INDEX(Facturas_Odoo!$B:$B, MATCH(A1153, Facturas_Odoo!$D:$D, 0)), "Sin Factura")) | R1153: =IF(Q1153="Sin Factura","",IFERROR(INDEX(Facturas_Odoo!$A:$A, MATCH(Q1153, Facturas_Odoo!$B:$B, 0)), "")) | S1153: =IF(Q1153="Sin Factura","",IFERROR(_xlfn.XLOOKUP(1, (Facturas_Odoo!$D:$D=A1153) * (Facturas_Odoo!$K:$K=I1153), Facturas_Odoo!$L:$L, ""), "")) | T1153: =IF(Q1153="Sin Factura",0,IFERROR(_xlfn.XLOOKUP(1, (Facturas_Odoo!$D:$D=A1153) * (Facturas_Odoo!$K:$K=I1153), Facturas_Odoo!$M:$M, 0), 0)) | U1153: =IF(Q1153="Sin Factura",0,IFERROR(_xlfn.XLOOKUP(1, (Facturas_Odoo!$D:$D=A1153) * (Facturas_Odoo!$K:$K=I1153), Facturas_Odoo!$N:$N, 0), 0)) | V1153: =IF(Q1153="Sin Factura",0,IFERROR(_xlfn.XLOOKUP(1, (Facturas_Odoo!$D:$D=A1153) * (Facturas_Odoo!$K:$K=I1153), Facturas_Odoo!$O:$O, 0), 0)) | W1153: =IF(Q1153="Sin Factura",0,IFERROR(_xlfn.XLOOKUP(1, (Facturas_Odoo!$D:$D=A1153) * (Facturas_Odoo!$K:$K=I1153), Facturas_Odoo!$Q:$Q, 0), 0)) | X1153: =IF(OR(Q1153="Sin Factura",Q1153=""),"",IFERROR(INDEX(Pagos_Odoo!$B:$B, MATCH(Q1153, Pagos_Odoo!$I:$I, 0)), "Sin Pago")) | Y1153: =IF(X1153="Sin Pago","",IFERROR(INDEX(Pagos_Odoo!$C:$C, MATCH(X1153, Pagos_Odoo!$B:$B, 0)), "")) | Z1153: =IF(X1153="Sin Pago","",IFERROR(INDEX(Pagos_Odoo!$A:$A, MATCH(X1153, Pagos_Odoo!$B:$B, 0)), "")) | AA1153: =IF(X1153="Sin Pago","",IFERROR(INDEX(Pagos_Odoo!$F:$F, MATCH(X1153, Pagos_Odoo!$B:$B, 0)), "")) | AB1153: =IF(X1153="Sin Pago",0,IFERROR(INDEX(Pagos_Odoo!$E:$E, MATCH(X1153, Pagos_Odoo!$B:$B, 0)), 0)) | AC1153: =IF(X1153="Sin Pago","",IFERROR(INDEX(Pagos_Odoo!$G:$G, MATCH(X1153, Pagos_Odoo!$B:$B, 0)), "")) | AD1153: 0 | AG1153: =IF(AN1153="","",AD1153+AE1153+AF1153) | AH1153: =IF(AN1153="","",P1153*(1-AG1153)) | AI1153: =IF(AN1153="","",IF(Q1153="Sin Factura",0,IFERROR(INDEX(Facturas_Odoo!$H:$H, MATCH(Q1153, Facturas_Odoo!$B:$B, 0)), 0)*(1-AG1153))) | AJ1153: =IF(AN1153="","",_xlfn.LET(idVenta, AN1153&"", pagos, IFERROR(SUMIF(Aux_Datos!$B:$B, idVenta, Aux_Datos!$L:$L), 0), retenciones, IFERROR(SUMIF(Aux_Datos!$O:$O, idVenta, Aux_Datos!$S:$S), 0), pagos_manuales, IFERROR(SUMIF('Asignación Pagos'!$G:$G, idVenta, 'Asignación Pagos'!$F:$F), 0), pagos+retenciones+pagos_manuales)) | AK1153: =IF(AN1153="","",AH1153-AJ1153) | AL1153: =IF(AN1153="","",IF(Q1153="Sin Factura","",AI1153-AJ1153)) | AM1153: =IF(AN1153="","",IF(Q1153="Sin Factura",0,P1153-IFERROR(INDEX(Facturas_Odoo!$H:$H, MATCH(Q1153, Facturas_Odoo!$B:$B, 0)), 0))) | AN1153: =IF(AND(A1153="", J1153=""), "", IF(A1153<>"", VALUE(MID(A1153,2,LEN(A1153))), AN1152)) | AO1153: =IF(AN1153="","",IF(AD1153=0,"OK",_xlfn.LET(monedaPago, IF(AA1153="","USD",AA1153), limitePermitido, IFERROR(VLOOKUP(monedaPago, Configuración!$A$2:$B$3, 2, FALSE), 0.15), IF(AD1153>limitePermitido, "ALERTA: EXCESO (" & TEXT(limitePermitido, "0%") & " máx)", "OK")))) | AP1153: =IF(AN1153="","",IF(AE1153=0,"OK",_xlfn.LET(fechaPago, Z1153, fechaFactura, R1153, diasCredito, IF(E1153="Pago inmediato", 0, IFERROR(VALUE(MID(E1153, 1, SEARCH(" ", E1153)-1)), 0)), tolerancia, Configuración!$E$2, limiteDias, diasCredito + tolerancia, IF(OR(fechaPago="", fechaFactura=""), "REVISAR: SIN FECHA", IF(fechaPago - fechaFactura > limiteDias, "ALERTA: PAGO FUERA DE PLAZO (" & (fechaPago - fechaFactura) & " días)", "OK"))))) | AQ1153: =IF(AN1153="","",IF(AND(N1153>0, AG1153>0), IF(Configuración!$K$2="NO", "ALERTA: DESCUENTO DOBLE NO PERMITIDO", "OK"), "OK")) | AR1153: =IF(AN1153="","",IF(OR(AO1153<>"OK", AP1153<>"OK", AQ1153<>"OK"), "⚠️ REVISAR", "OK"))
A1154: =IF('Ordenes_Odoo'!A1154="","",'Ordenes_Odoo'!A1154) | B1154: =IF('Ordenes_Odoo'!B1154="","",'Ordenes_Odoo'!B1154) | C1154: =IF('Ordenes_Odoo'!C1154="","",'Ordenes_Odoo'!C1154) | D1154: =IF('Ordenes_Odoo'!D1154="","",'Ordenes_Odoo'!D1154) | E1154: =IF('Ordenes_Odoo'!E1154="","",'Ordenes_Odoo'!E1154) | F1154: =IF('Ordenes_Odoo'!F1154="","",'Ordenes_Odoo'!F1154) | G1154: =IF('Ordenes_Odoo'!G1154="","",'Ordenes_Odoo'!G1154) | H1154: =IF('Ordenes_Odoo'!H1154="","",'Ordenes_Odoo'!H1154) | ... P1154: =IF('Ordenes_Odoo'!P1154="","",'Ordenes_Odoo'!P1154) | Q1154: =IF(A1154="","",IFERROR(INDEX(Facturas_Odoo!$B:$B, MATCH(A1154, Facturas_Odoo!$D:$D, 0)), "Sin Factura")) | R1154: =IF(Q1154="Sin Factura","",IFERROR(INDEX(Facturas_Odoo!$A:$A, MATCH(Q1154, Facturas_Odoo!$B:$B, 0)), "")) | S1154: =IF(Q1154="Sin Factura","",IFERROR(_xlfn.XLOOKUP(1, (Facturas_Odoo!$D:$D=A1154) * (Facturas_Odoo!$K:$K=I1154), Facturas_Odoo!$L:$L, ""), "")) | T1154: =IF(Q1154="Sin Factura",0,IFERROR(_xlfn.XLOOKUP(1, (Facturas_Odoo!$D:$D=A1154) * (Facturas_Odoo!$K:$K=I1154), Facturas_Odoo!$M:$M, 0), 0)) | U1154: =IF(Q1154="Sin Factura",0,IFERROR(_xlfn.XLOOKUP(1, (Facturas_Odoo!$D:$D=A1154) * (Facturas_Odoo!$K:$K=I1154), Facturas_Odoo!$N:$N, 0), 0)) | V1154: =IF(Q1154="Sin Factura",0,IFERROR(_xlfn.XLOOKUP(1, (Facturas_Odoo!$D:$D=A1154) * (Facturas_Odoo!$K:$K=I1154), Facturas_Odoo!$O:$O, 0), 0)) | W1154: =IF(Q1154="Sin Factura",0,IFERROR(_xlfn.XLOOKUP(1, (Facturas_Odoo!$D:$D=A1154) * (Facturas_Odoo!$K:$K=I1154), Facturas_Odoo!$Q:$Q, 0), 0)) | X1154: =IF(OR(Q1154="Sin Factura",Q1154=""),"",IFERROR(INDEX(Pagos_Odoo!$B:$B, MATCH(Q1154, Pagos_Odoo!$I:$I, 0)), "Sin Pago")) | Y1154: =IF(X1154="Sin Pago","",IFERROR(INDEX(Pagos_Odoo!$C:$C, MATCH(X1154, Pagos_Odoo!$B:$B, 0)), "")) | Z1154: =IF(X1154="Sin Pago","",IFERROR(INDEX(Pagos_Odoo!$A:$A, MATCH(X1154, Pagos_Odoo!$B:$B, 0)), "")) | AA1154: =IF(X1154="Sin Pago","",IFERROR(INDEX(Pagos_Odoo!$F:$F, MATCH(X1154, Pagos_Odoo!$B:$B, 0)), "")) | AB1154: =IF(X1154="Sin Pago",0,IFERROR(INDEX(Pagos_Odoo!$E:$E, MATCH(X1154, Pagos_Odoo!$B:$B, 0)), 0)) | AC1154: =IF(X1154="Sin Pago","",IFERROR(INDEX(Pagos_Odoo!$G:$G, MATCH(X1154, Pagos_Odoo!$B:$B, 0)), "")) | AD1154: 0 | AE1154: 0.05 | AG1154: =IF(AN1154="","",AD1154+AE1154+AF1154) | AH1154: =IF(AN1154="","",P1154*(1-AG1154)) | AI1154: =IF(AN1154="","",IF(Q1154="Sin Factura",0,IFERROR(INDEX(Facturas_Odoo!$H:$H, MATCH(Q1154, Facturas_Odoo!$B:$B, 0)), 0)*(1-AG1154))) | AJ1154: =IF(AN1154="","",_xlfn.LET(idVenta, AN1154&"", pagos, IFERROR(SUMIF(Aux_Datos!$B:$B, idVenta, Aux_Datos!$L:$L), 0), retenciones, IFERROR(SUMIF(Aux_Datos!$O:$O, idVenta, Aux_Datos!$S:$S), 0), pagos_manuales, IFERROR(SUMIF('Asignación Pagos'!$G:$G, idVenta, 'Asignación Pagos'!$F:$F), 0), pagos+retenciones+pagos_manuales)) | AK1154: =IF(AN1154="","",AH1154-AJ1154) | AL1154: =IF(AN1154="","",IF(Q1154="Sin Factura","",AI1154-AJ1154)) | AM1154: =IF(AN1154="","",IF(Q1154="Sin Factura",0,P1154-IFERROR(INDEX(Facturas_Odoo!$H:$H, MATCH(Q1154, Facturas_Odoo!$B:$B, 0)), 0))) | AN1154: =IF(AND(A1154="", J1154=""), "", IF(A1154<>"", VALUE(MID(A1154,2,LEN(A1154))), AN1153)) | AO1154: =IF(AN1154="","",IF(AD1154=0,"OK",_xlfn.LET(monedaPago, IF(AA1154="","USD",AA1154), limitePermitido, IFERROR(VLOOKUP(monedaPago, Configuración!$A$2:$B$3, 2, FALSE), 0.15), IF(AD1154>limitePermitido, "ALERTA: EXCESO (" & TEXT(limitePermitido, "0%") & " máx)", "OK")))) | AP1154: =IF(AN1154="","",IF(AE1154=0,"OK",_xlfn.LET(fechaPago, Z1154, fechaFactura, R1154, diasCredito, IF(E1154="Pago inmediato", 0, IFERROR(VALUE(MID(E1154, 1, SEARCH(" ", E1154)-1)), 0)), tolerancia, Configuración!$E$2, limiteDias, diasCredito + tolerancia, IF(OR(fechaPago="", fechaFactura=""), "REVISAR: SIN FECHA", IF(fechaPago - fechaFactura > limiteDias, "ALERTA: PAGO FUERA DE PLAZO (" & (fechaPago - fechaFactura) & " días)", "OK"))))) | AQ1154: =IF(AN1154="","",IF(AND(N1154>0, AG1154>0), IF(Configuración!$K$2="NO", "ALERTA: DESCUENTO DOBLE NO PERMITIDO", "OK"), "OK")) | AR1154: =IF(AN1154="","",IF(OR(AO1154<>"OK", AP1154<>"OK", AQ1154<>"OK"), "⚠️ REVISAR", "OK"))
A1155: =IF('Ordenes_Odoo'!A1155="","",'Ordenes_Odoo'!A1155) | B1155: =IF('Ordenes_Odoo'!B1155="","",'Ordenes_Odoo'!B1155) | C1155: =IF('Ordenes_Odoo'!C1155="","",'Ordenes_Odoo'!C1155) | D1155: =IF('Ordenes_Odoo'!D1155="","",'Ordenes_Odoo'!D1155) | E1155: =IF('Ordenes_Odoo'!E1155="","",'Ordenes_Odoo'!E1155) | F1155: =IF('Ordenes_Odoo'!F1155="","",'Ordenes_Odoo'!F1155) | G1155: =IF('Ordenes_Odoo'!G1155="","",'Ordenes_Odoo'!G1155) | H1155: =IF('Ordenes_Odoo'!H1155="","",'Ordenes_Odoo'!H1155) | ... P1155: =IF('Ordenes_Odoo'!P1155="","",'Ordenes_Odoo'!P1155) | Q1155: =IF(A1155="","",IFERROR(INDEX(Facturas_Odoo!$B:$B, MATCH(A1155, Facturas_Odoo!$D:$D, 0)), "Sin Factura")) | R1155: =IF(Q1155="Sin Factura","",IFERROR(INDEX(Facturas_Odoo!$A:$A, MATCH(Q1155, Facturas_Odoo!$B:$B, 0)), "")) | S1155: =IF(Q1155="Sin Factura","",IFERROR(_xlfn.XLOOKUP(1, (Facturas_Odoo!$D:$D=A1155) * (Facturas_Odoo!$K:$K=I1155), Facturas_Odoo!$L:$L, ""), "")) | T1155: =IF(Q1155="Sin Factura",0,IFERROR(_xlfn.XLOOKUP(1, (Facturas_Odoo!$D:$D=A1155) * (Facturas_Odoo!$K:$K=I1155), Facturas_Odoo!$M:$M, 0), 0)) | U1155: =IF(Q1155="Sin Factura",0,IFERROR(_xlfn.XLOOKUP(1, (Facturas_Odoo!$D:$D=A1155) * (Facturas_Odoo!$K:$K=I1155), Facturas_Odoo!$N:$N, 0), 0)) | V1155: =IF(Q1155="Sin Factura",0,IFERROR(_xlfn.XLOOKUP(1, (Facturas_Odoo!$D:$D=A1155) * (Facturas_Odoo!$K:$K=I1155), Facturas_Odoo!$O:$O, 0), 0)) | W1155: =IF(Q1155="Sin Factura",0,IFERROR(_xlfn.XLOOKUP(1, (Facturas_Odoo!$D:$D=A1155) * (Facturas_Odoo!$K:$K=I1155), Facturas_Odoo!$Q:$Q, 0), 0)) | X1155: =IF(OR(Q1155="Sin Factura",Q1155=""),"",IFERROR(INDEX(Pagos_Odoo!$B:$B, MATCH(Q1155, Pagos_Odoo!$I:$I, 0)), "Sin Pago")) | Y1155: =IF(X1155="Sin Pago","",IFERROR(INDEX(Pagos_Odoo!$C:$C, MATCH(X1155, Pagos_Odoo!$B:$B, 0)), "")) | Z1155: =IF(X1155="Sin Pago","",IFERROR(INDEX(Pagos_Odoo!$A:$A, MATCH(X1155, Pagos_Odoo!$B:$B, 0)), "")) | AA1155: =IF(X1155="Sin Pago","",IFERROR(INDEX(Pagos_Odoo!$F:$F, MATCH(X1155, Pagos_Odoo!$B:$B, 0)), "")) | AB1155: =IF(X1155="Sin Pago",0,IFERROR(INDEX(Pagos_Odoo!$E:$E, MATCH(X1155, Pagos_Odoo!$B:$B, 0)), 0)) | AC1155: =IF(X1155="Sin Pago","",IFERROR(INDEX(Pagos_Odoo!$G:$G, MATCH(X1155, Pagos_Odoo!$B:$B, 0)), "")) | AD1155: 0 | AG1155: =IF(AN1155="","",AD1155+AE1155+AF1155) | AH1155: =IF(AN1155="","",P1155*(1-AG1155)) | AI1155: =IF(AN1155="","",IF(Q1155="Sin Factura",0,IFERROR(INDEX(Facturas_Odoo!$H:$H, MATCH(Q1155, Facturas_Odoo!$B:$B, 0)), 0)*(1-AG1155))) | AJ1155: =IF(AN1155="","",_xlfn.LET(idVenta, AN1155&"", pagos, IFERROR(SUMIF(Aux_Datos!$B:$B, idVenta, Aux_Datos!$L:$L), 0), retenciones, IFERROR(SUMIF(Aux_Datos!$O:$O, idVenta, Aux_Datos!$S:$S), 0), pagos_manuales, IFERROR(SUMIF('Asignación Pagos'!$G:$G, idVenta, 'Asignación Pagos'!$F:$F), 0), pagos+retenciones+pagos_manuales)) | AK1155: =IF(AN1155="","",AH1155-AJ1155) | AL1155: =IF(AN1155="","",IF(Q1155="Sin Factura","",AI1155-AJ1155)) | AM1155: =IF(AN1155="","",IF(Q1155="Sin Factura",0,P1155-IFERROR(INDEX(Facturas_Odoo!$H:$H, MATCH(Q1155, Facturas_Odoo!$B:$B, 0)), 0))) | AN1155: =IF(AND(A1155="", J1155=""), "", IF(A1155<>"", VALUE(MID(A1155,2,LEN(A1155))), AN1154)) | AO1155: =IF(AN1155="","",IF(AD1155=0,"OK",_xlfn.LET(monedaPago, IF(AA1155="","USD",AA1155), limitePermitido, IFERROR(VLOOKUP(monedaPago, Configuración!$A$2:$B$3, 2, FALSE), 0.15), IF(AD1155>limitePermitido, "ALERTA: EXCESO (" & TEXT(limitePermitido, "0%") & " máx)", "OK")))) | AP1155: =IF(AN1155="","",IF(AE1155=0,"OK",_xlfn.LET(fechaPago, Z1155, fechaFactura, R1155, diasCredito, IF(E1155="Pago inmediato", 0, IFERROR(VALUE(MID(E1155, 1, SEARCH(" ", E1155)-1)), 0)), tolerancia, Configuración!$E$2, limiteDias, diasCredito + tolerancia, IF(OR(fechaPago="", fechaFactura=""), "REVISAR: SIN FECHA", IF(fechaPago - fechaFactura > limiteDias, "ALERTA: PAGO FUERA DE PLAZO (" & (fechaPago - fechaFactura) & " días)", "OK"))))) | AQ1155: =IF(AN1155="","",IF(AND(N1155>0, AG1155>0), IF(Configuración!$K$2="NO", "ALERTA: DESCUENTO DOBLE NO PERMITIDO", "OK"), "OK")) | AR1155: =IF(AN1155="","",IF(OR(AO1155<>"OK", AP1155<>"OK", AQ1155<>"OK"), "⚠️ REVISAR", "OK"))
A1156: =IF('Ordenes_Odoo'!A1156="","",'Ordenes_Odoo'!A1156) | B1156: =IF('Ordenes_Odoo'!B1156="","",'Ordenes_Odoo'!B1156) | C1156: =IF('Ordenes_Odoo'!C1156="","",'Ordenes_Odoo'!C1156) | D1156: =IF('Ordenes_Odoo'!D1156="","",'Ordenes_Odoo'!D1156) | E1156: =IF('Ordenes_Odoo'!E1156="","",'Ordenes_Odoo'!E1156) | F1156: =IF('Ordenes_Odoo'!F1156="","",'Ordenes_Odoo'!F1156) | G1156: =IF('Ordenes_Odoo'!G1156="","",'Ordenes_Odoo'!G1156) | H1156: =IF('Ordenes_Odoo'!H1156="","",'Ordenes_Odoo'!H1156) | ... P1156: =IF('Ordenes_Odoo'!P1156="","",'Ordenes_Odoo'!P1156) | Q1156: =IF(A1156="","",IFERROR(INDEX(Facturas_Odoo!$B:$B, MATCH(A1156, Facturas_Odoo!$D:$D, 0)), "Sin Factura")) | R1156: =IF(Q1156="Sin Factura","",IFERROR(INDEX(Facturas_Odoo!$A:$A, MATCH(Q1156, Facturas_Odoo!$B:$B, 0)), "")) | S1156: =IF(Q1156="Sin Factura","",IFERROR(_xlfn.XLOOKUP(1, (Facturas_Odoo!$D:$D=A1156) * (Facturas_Odoo!$K:$K=I1156), Facturas_Odoo!$L:$L, ""), "")) | T1156: =IF(Q1156="Sin Factura",0,IFERROR(_xlfn.XLOOKUP(1, (Facturas_Odoo!$D:$D=A1156) * (Facturas_Odoo!$K:$K=I1156), Facturas_Odoo!$M:$M, 0), 0)) | U1156: =IF(Q1156="Sin Factura",0,IFERROR(_xlfn.XLOOKUP(1, (Facturas_Odoo!$D:$D=A1156) * (Facturas_Odoo!$K:$K=I1156), Facturas_Odoo!$N:$N, 0), 0)) | V1156: =IF(Q1156="Sin Factura",0,IFERROR(_xlfn.XLOOKUP(1, (Facturas_Odoo!$D:$D=A1156) * (Facturas_Odoo!$K:$K=I1156), Facturas_Odoo!$O:$O, 0), 0)) | W1156: =IF(Q1156="Sin Factura",0,IFERROR(_xlfn.XLOOKUP(1, (Facturas_Odoo!$D:$D=A1156) * (Facturas_Odoo!$K:$K=I1156), Facturas_Odoo!$Q:$Q, 0), 0)) | X1156: =IF(OR(Q1156="Sin Factura",Q1156=""),"",IFERROR(INDEX(Pagos_Odoo!$B:$B, MATCH(Q1156, Pagos_Odoo!$I:$I, 0)), "Sin Pago")) | Y1156: =IF(X1156="Sin Pago","",IFERROR(INDEX(Pagos_Odoo!$C:$C, MATCH(X1156, Pagos_Odoo!$B:$B, 0)), "")) | Z1156: =IF(X1156="Sin Pago","",IFERROR(INDEX(Pagos_Odoo!$A:$A, MATCH(X1156, Pagos_Odoo!$B:$B, 0)), "")) | AA1156: =IF(X1156="Sin Pago","",IFERROR(INDEX(Pagos_Odoo!$F:$F, MATCH(X1156, Pagos_Odoo!$B:$B, 0)), "")) | AB1156: =IF(X1156="Sin Pago",0,IFERROR(INDEX(Pagos_Odoo!$E:$E, MATCH(X1156, Pagos_Odoo!$B:$B, 0)), 0)) | AC1156: =IF(X1156="Sin Pago","",IFERROR(INDEX(Pagos_Odoo!$G:$G, MATCH(X1156, Pagos_Odoo!$B:$B, 0)), "")) | AD1156: 0 | AG1156: =IF(AN1156="","",AD1156+AE1156+AF1156) | AH1156: =IF(AN1156="","",P1156*(1-AG1156)) | AI1156: =IF(AN1156="","",IF(Q1156="Sin Factura",0,IFERROR(INDEX(Facturas_Odoo!$H:$H, MATCH(Q1156, Facturas_Odoo!$B:$B, 0)), 0)*(1-AG1156))) | AJ1156: =IF(AN1156="","",_xlfn.LET(idVenta, AN1156&"", pagos, IFERROR(SUMIF(Aux_Datos!$B:$B, idVenta, Aux_Datos!$L:$L), 0), retenciones, IFERROR(SUMIF(Aux_Datos!$O:$O, idVenta, Aux_Datos!$S:$S), 0), pagos_manuales, IFERROR(SUMIF('Asignación Pagos'!$G:$G, idVenta, 'Asignación Pagos'!$F:$F), 0), pagos+retenciones+pagos_manuales)) | AK1156: =IF(AN1156="","",AH1156-AJ1156) | AL1156: =IF(AN1156="","",IF(Q1156="Sin Factura","",AI1156-AJ1156)) | AM1156: =IF(AN1156="","",IF(Q1156="Sin Factura",0,P1156-IFERROR(INDEX(Facturas_Odoo!$H:$H, MATCH(Q1156, Facturas_Odoo!$B:$B, 0)), 0))) | AN1156: =IF(AND(A1156="", J1156=""), "", IF(A1156<>"", VALUE(MID(A1156,2,LEN(A1156))), AN1155)) | AO1156: =IF(AN1156="","",IF(AD1156=0,"OK",_xlfn.LET(monedaPago, IF(AA1156="","USD",AA1156), limitePermitido, IFERROR(VLOOKUP(monedaPago, Configuración!$A$2:$B$3, 2, FALSE), 0.15), IF(AD1156>limitePermitido, "ALERTA: EXCESO (" & TEXT(limitePermitido, "0%") & " máx)", "OK")))) | AP1156: =IF(AN1156="","",IF(AE1156=0,"OK",_xlfn.LET(fechaPago, Z1156, fechaFactura, R1156, diasCredito, IF(E1156="Pago inmediato", 0, IFERROR(VALUE(MID(E1156, 1, SEARCH(" ", E1156)-1)), 0)), tolerancia, Configuración!$E$2, limiteDias, diasCredito + tolerancia, IF(OR(fechaPago="", fechaFactura=""), "REVISAR: SIN FECHA", IF(fechaPago - fechaFactura > limiteDias, "ALERTA: PAGO FUERA DE PLAZO (" & (fechaPago - fechaFactura) & " días)", "OK"))))) | AQ1156: =IF(AN1156="","",IF(AND(N1156>0, AG1156>0), IF(Configuración!$K$2="NO", "ALERTA: DESCUENTO DOBLE NO PERMITIDO", "OK"), "OK")) | AR1156: =IF(AN1156="","",IF(OR(AO1156<>"OK", AP1156<>"OK", AQ1156<>"OK"), "⚠️ REVISAR", "OK"))
A1157: =IF('Ordenes_Odoo'!A1157="","",'Ordenes_Odoo'!A1157) | B1157: =IF('Ordenes_Odoo'!B1157="","",'Ordenes_Odoo'!B1157) | C1157: =IF('Ordenes_Odoo'!C1157="","",'Ordenes_Odoo'!C1157) | D1157: =IF('Ordenes_Odoo'!D1157="","",'Ordenes_Odoo'!D1157) | E1157: =IF('Ordenes_Odoo'!E1157="","",'Ordenes_Odoo'!E1157) | F1157: =IF('Ordenes_Odoo'!F1157="","",'Ordenes_Odoo'!F1157) | G1157: =IF('Ordenes_Odoo'!G1157="","",'Ordenes_Odoo'!G1157) | H1157: =IF('Ordenes_Odoo'!H1157="","",'Ordenes_Odoo'!H1157) | ... P1157: =IF('Ordenes_Odoo'!P1157="","",'Ordenes_Odoo'!P1157) | Q1157: =IF(A1157="","",IFERROR(INDEX(Facturas_Odoo!$B:$B, MATCH(A1157, Facturas_Odoo!$D:$D, 0)), "Sin Factura")) | R1157: =IF(Q1157="Sin Factura","",IFERROR(INDEX(Facturas_Odoo!$A:$A, MATCH(Q1157, Facturas_Odoo!$B:$B, 0)), "")) | S1157: =IF(Q1157="Sin Factura","",IFERROR(_xlfn.XLOOKUP(1, (Facturas_Odoo!$D:$D=A1157) * (Facturas_Odoo!$K:$K=I1157), Facturas_Odoo!$L:$L, ""), "")) | T1157: =IF(Q1157="Sin Factura",0,IFERROR(_xlfn.XLOOKUP(1, (Facturas_Odoo!$D:$D=A1157) * (Facturas_Odoo!$K:$K=I1157), Facturas_Odoo!$M:$M, 0), 0)) | U1157: =IF(Q1157="Sin Factura",0,IFERROR(_xlfn.XLOOKUP(1, (Facturas_Odoo!$D:$D=A1157) * (Facturas_Odoo!$K:$K=I1157), Facturas_Odoo!$N:$N, 0), 0)) | V1157: =IF(Q1157="Sin Factura",0,IFERROR(_xlfn.XLOOKUP(1, (Facturas_Odoo!$D:$D=A1157) * (Facturas_Odoo!$K:$K=I1157), Facturas_Odoo!$O:$O, 0), 0)) | W1157: =IF(Q1157="Sin Factura",0,IFERROR(_xlfn.XLOOKUP(1, (Facturas_Odoo!$D:$D=A1157) * (Facturas_Odoo!$K:$K=I1157), Facturas_Odoo!$Q:$Q, 0), 0)) | X1157: =IF(OR(Q1157="Sin Factura",Q1157=""),"",IFERROR(INDEX(Pagos_Odoo!$B:$B, MATCH(Q1157, Pagos_Odoo!$I:$I, 0)), "Sin Pago")) | Y1157: =IF(X1157="Sin Pago","",IFERROR(INDEX(Pagos_Odoo!$C:$C, MATCH(X1157, Pagos_Odoo!$B:$B, 0)), "")) | Z1157: =IF(X1157="Sin Pago","",IFERROR(INDEX(Pagos_Odoo!$A:$A, MATCH(X1157, Pagos_Odoo!$B:$B, 0)), "")) | AA1157: =IF(X1157="Sin Pago","",IFERROR(INDEX(Pagos_Odoo!$F:$F, MATCH(X1157, Pagos_Odoo!$B:$B, 0)), "")) | AB1157: =IF(X1157="Sin Pago",0,IFERROR(INDEX(Pagos_Odoo!$E:$E, MATCH(X1157, Pagos_Odoo!$B:$B, 0)), 0)) | AC1157: =IF(X1157="Sin Pago","",IFERROR(INDEX(Pagos_Odoo!$G:$G, MATCH(X1157, Pagos_Odoo!$B:$B, 0)), "")) | AD1157: 0 | AG1157: =IF(AN1157="","",AD1157+AE1157+AF1157) | AH1157: =IF(AN1157="","",P1157*(1-AG1157)) | AI1157: =IF(AN1157="","",IF(Q1157="Sin Factura",0,IFERROR(INDEX(Facturas_Odoo!$H:$H, MATCH(Q1157, Facturas_Odoo!$B:$B, 0)), 0)*(1-AG1157))) | AJ1157: =IF(AN1157="","",_xlfn.LET(idVenta, AN1157&"", pagos, IFERROR(SUMIF(Aux_Datos!$B:$B, idVenta, Aux_Datos!$L:$L), 0), retenciones, IFERROR(SUMIF(Aux_Datos!$O:$O, idVenta, Aux_Datos!$S:$S), 0), pagos_manuales, IFERROR(SUMIF('Asignación Pagos'!$G:$G, idVenta, 'Asignación Pagos'!$F:$F), 0), pagos+retenciones+pagos_manuales)) | AK1157: =IF(AN1157="","",AH1157-AJ1157) | AL1157: =IF(AN1157="","",IF(Q1157="Sin Factura","",AI1157-AJ1157)) | AM1157: =IF(AN1157="","",IF(Q1157="Sin Factura",0,P1157-IFERROR(INDEX(Facturas_Odoo!$H:$H, MATCH(Q1157, Facturas_Odoo!$B:$B, 0)), 0))) | AN1157: =IF(AND(A1157="", J1157=""), "", IF(A1157<>"", VALUE(MID(A1157,2,LEN(A1157))), AN1156)) | AO1157: =IF(AN1157="","",IF(AD1157=0,"OK",_xlfn.LET(monedaPago, IF(AA1157="","USD",AA1157), limitePermitido, IFERROR(VLOOKUP(monedaPago, Configuración!$A$2:$B$3, 2, FALSE), 0.15), IF(AD1157>limitePermitido, "ALERTA: EXCESO (" & TEXT(limitePermitido, "0%") & " máx)", "OK")))) | AP1157: =IF(AN1157="","",IF(AE1157=0,"OK",_xlfn.LET(fechaPago, Z1157, fechaFactura, R1157, diasCredito, IF(E1157="Pago inmediato", 0, IFERROR(VALUE(MID(E1157, 1, SEARCH(" ", E1157)-1)), 0)), tolerancia, Configuración!$E$2, limiteDias, diasCredito + tolerancia, IF(OR(fechaPago="", fechaFactura=""), "REVISAR: SIN FECHA", IF(fechaPago - fechaFactura > limiteDias, "ALERTA: PAGO FUERA DE PLAZO (" & (fechaPago - fechaFactura) & " días)", "OK"))))) | AQ1157: =IF(AN1157="","",IF(AND(N1157>0, AG1157>0), IF(Configuración!$K$2="NO", "ALERTA: DESCUENTO DOBLE NO PERMITIDO", "OK"), "OK")) | AR1157: =IF(AN1157="","",IF(OR(AO1157<>"OK", AP1157<>"OK", AQ1157<>"OK"), "⚠️ REVISAR", "OK"))
