Workbook
Name Limite_descuento: #REF!

Sheet Antiguedad

Sheet Cuentas x Cobrar

Sheet Cuentas x Cobrar x Mes

Sheet Cuentas x Dias Vencimiento

Sheet Cuentas x Vendedor

Sheet Resumen Ventas x Mes

Sheet Ventas
A1: Referencia de la orden | B1: Fecha de la orden | C1: Cliente | D1: Vendedor | E1: Total | F1: Terminos de pago | G1: Descuento x Diferencial % | H1: Dcto Pronto Pago % | I1: Numero de Orden | J1: Fecha | K1: Dias de credito | L1: Vencimiento | M1: Total C/Dcto | N1: Dias Vencido | O1: Estado Vencimiento | P1: Monto Pagado USD | Q1: Moneda de pago | R1: Saldo Orden | S1: Ultimo Pago | T1: Status de Pago | U1: Prioridad de Cobro | V1: Dias desde el ultimo Pago | W1: Validacion Descuento Diferencial | X1: Validacion Descuento Pronto Pago | Y1: Cobrado | Z1: Validación por Diferencial | AA1: Columna 27 | AB1: Columna 28 | AC1: Columna 29 | AD1: Columna 30 | AE1: Columna 31 | AF1: Columna 32
A2: S00004 | B2: 46090.24 | C2: GARAJE Y TALLERES FRIDELBA, C.A | D2: VILLABONA CORREA ALBA ESTEFANIA | E2: 232.98 | F2: Pago inmediato | G2: =IF($E2=0,0,IF(SUMIF(Aux_Datos!$B:$B,$I2,Aux_Datos!$K:$K)/$E2>=VLOOKUP(IF(COUNTIFS(Aux_Datos!$B:$B,$I2,Aux_Datos!$D:$D,"<>USD")=0,"USD","VES"),'Limites de Descuento'!$A$2:$D$4,4,FALSE),MAX(0,1-SUMIF(Aux_Datos!$B:$B,$I2,Aux_Datos!$K:$K)/$E2),0)) -> 0.24886256 | I2: =VALUE(MID(A2,2,LEN(A2))) -> 4 | J2: =INT(B2) -> 46090 | K2: =IF(F2="Pago inmediato", 0, IF(F2="", "", IFERROR(VALUE(MID(F2, 1, SEARCH(" ", F2)-1)), ""))) -> 0 | L2: =J2+K2+1 -> 46091 | M2: =E2-(E2*G2)-(E2*H2) -> 175 | N2: =IF(T2="PAGADA", 0, IF(L2 < TODAY(), TODAY() - L2, 0)) -> 0 | O2: =IF(T2="PAGADA", "PAGADA", IF(L2 < TODAY(), "VENCIDA", "EN TIEMPO")) -> PAGADA | P2: =LET( idVenta, I2&"", montoTotal, M2, pagos, IFERROR(SUMIF(Aux_Datos!$B:$B, idVenta, Aux_Datos!$K:$K), 0), retenciones, IFERROR(SUMIF(Aux_Datos!$N:$N, idVenta, Aux_Datos!$R:$R), 0), pagos + retenciones ) -> 175 | Q2: =IF(P2=0, "Sin Pago", LET( idVenta, I2&"", montoTotalPagado, P2, pagoUSD, IFERROR(SUMIFS(Aux_Datos!$C:$C, Aux_Datos!$B:$B, idVenta, Aux_Datos!$D:$D, "USD"), 0), pagoVES, IFERROR(SUMIFS(Aux_Datos!$C:$C, Aux_Datos!$B:$B, idVenta, Aux_Datos!$D:$D, "VES"), 0), IF(pagoUSD >= (montoTotalPagado * 0.84), "USD", IF(pagoVES >= (montoTotalPagado * 0.84), "VES", "MIXTO")) ) ) -> USD | R2: =M2-P2 -> 0 | S2: =IF(P2=0, "Sin Pago", IFERROR( MAXIFS(Aux_Datos!$A:$A, Aux_Datos!$B:$B, I2&""), IFERROR(MAXIFS(Aux_Datos!$A:$A, Aux_Datos!$B:$B, VALUE(I2)), "Revisar ID") ) ) -> 46100 | T2: =IF(R2<=0, "PAGADA", IF(P2>0, "PAGO PARCIAL", "PENDIENTE")) -> PAGADA | U2: =IF(AND(T2<>"PAGADA", L2<TODAY()), "CRÍTICO: VENCIDA", IF(T2="PAGADA", "SOLVENTE", "EN TIEMPO")) -> SOLVENTE | V2: =IF(T2="PAGADA", 0, IF(S2 < TODAY(), TODAY() - S2, 0)) -> 0 | W2: =IF(P2=0, "Sin Pago", LET( monedaPago, Q2, descuentoAplicado, G2, limitePermitido, IFERROR(VLOOKUP(monedaPago, 'Limites de Descuento'!$A$2:$B595, 2, FALSE), 0), IF(descuentoAplicado > limitePermitido, "ALERTA: EXCESO (" & TEXT(limitePermitido, "0%") & " máx)", "OK") ) ) -> OK | X2: =IF(OR(H2=0, S2="Sin Pago"), "", IF(AND(H2 > 0, S2 > (L2 + 2)), "⚠️ REVISAR DESCUENTO", "OK")) | Y2: {=IF(ISBLANK(I2:I595), , SUMIF(Aux_Datos!B:B, I2:I595, Aux_Datos!K:K))} -> 175 | Z2: {=IF(E2:E595="","",IF(E2:E595=0,"SIN TOTAL",IFNA(IF(P2:P595/E2:E595>=VLOOKUP(Q2:Q595,'Limites de Descuento'!$A$2:$D$4,4,FALSE),"CUMPLE","NO CUMPLE"),"SIN MONEDA VÁLIDA")))} -> CUMPLE
A3: S00007 | B3: 46079.461 | C3: EMPRENDIMIENTO IRMA RODRIGUEZ 6 | D3: CALDERON TERAN ARGIMIRO ANTONIO | E3: 246 | F3: Pago inmediato | G3: =IF($E3=0,0,IF(SUMIF(Aux_Datos!$B:$B,$I3,Aux_Datos!$K:$K)/$E3>=VLOOKUP(IF(COUNTIFS(Aux_Datos!$B:$B,$I3,Aux_Datos!$D:$D,"<>USD")=0,"USD","VES"),'Limites de Descuento'!$A$2:$D$4,4,FALSE),MAX(0,1-SUMIF(Aux_Datos!$B:$B,$I3,Aux_Datos!$K:$K)/$E3),0)) -> 0 | I3: =VALUE(MID(A3,2,LEN(A3))) -> 7 | J3: =INT(B3) -> 46079 | K3: =IF(F3="Pago inmediato", 0, IF(F3="", "", IFERROR(VALUE(MID(F3, 1, SEARCH(" ", F3)-1)), ""))) -> 0 | L3: =J3+K3+1 -> 46080 | M3: =E3-(E3*G3)-(E3*H3) -> 246 | N3: =IF(T3="PAGADA", 0, IF(L3 < TODAY(), TODAY() - L3, 0)) -> 0 | O3: =IF(T3="PAGADA", "PAGADA", IF(L3 < TODAY(), "VENCIDA", "EN TIEMPO")) -> PAGADA | P3: =LET( idVenta, I3&"", montoTotal, M3, pagos, IFERROR(SUMIF(Aux_Datos!$B:$B, idVenta, Aux_Datos!$K:$K), 0), retenciones, IFERROR(SUMIF(Aux_Datos!$N:$N, idVenta, Aux_Datos!$R:$R), 0), pagos + retenciones ) -> 246 | Q3: =IF(P3=0, "Sin Pago", LET( idVenta, I3&"", montoTotalPagado, P3, pagoUSD, IFERROR(SUMIFS(Aux_Datos!$C:$C, Aux_Datos!$B:$B, idVenta, Aux_Datos!$D:$D, "USD"), 0), pagoVES, IFERROR(SUMIFS(Aux_Datos!$C:$C, Aux_Datos!$B:$B, idVenta, Aux_Datos!$D:$D, "VES"), 0), IF(pagoUSD >= (montoTotalPagado * 0.84), "USD", IF(pagoVES >= (montoTotalPagado * 0.84), "VES", "MIXTO")) ) ) -> USD | R3: =M3-P3 -> 0 | S3: =IF(P3=0, "Sin Pago", IFERROR( MAXIFS(Aux_Datos!$A:$A, Aux_Datos!$B:$B, I3&""), IFERROR(MAXIFS(Aux_Datos!$A:$A, Aux_Datos!$B:$B, VALUE(I3)), "Revisar ID") ) ) -> 46084 | T3: =IF(R3<=0, "PAGADA", IF(P3>0, "PAGO PARCIAL", "PENDIENTE")) -> PAGADA | U3: =IF(AND(T3<>"PAGADA", L3<TODAY()), "CRÍTICO: VENCIDA", IF(T3="PAGADA", "SOLVENTE", "EN TIEMPO")) -> SOLVENTE | V3: =IF(T3="PAGADA", 0, IF(S3 < TODAY(), TODAY() - S3, 0)) -> 0 | W3: =IF(P3=0, "Sin Pago", LET( monedaPago, Q3, descuentoAplicado, G3, limitePermitido, IFERROR(VLOOKUP(monedaPago, 'Limites de Descuento'!$A$2:$B595, 2, FALSE), 0), IF(descuentoAplicado > limitePermitido, "ALERTA: EXCESO (" & TEXT(limitePermitido, "0%") & " máx)", "OK") ) ) -> OK | X3: =IF(OR(H3=0, S3="Sin Pago"), "", IF(AND(H3 > 0, S3 > (L3 + 2)), "⚠️ REVISAR DESCUENTO", "OK")) | Y3: 246 | Z3: CUMPLE
A4: S00008 | B4: 46079.503 | C4: ZIP MARKET, CA | D4: CALDERON TERAN ARGIMIRO ANTONIO | E4: 35.33 | F4: Pago inmediato | G4: =IF($E4=0,0,IF(SUMIF(Aux_Datos!$B:$B,$I4,Aux_Datos!$K:$K)/$E4>=VLOOKUP(IF(COUNTIFS(Aux_Datos!$B:$B,$I4,Aux_Datos!$D:$D,"<>USD")=0,"USD","VES"),'Limites de Descuento'!$A$2:$D$4,4,FALSE),MAX(0,1-SUMIF(Aux_Datos!$B:$B,$I4,Aux_Datos!$K:$K)/$E4),0)) -> 0 | I4: =VALUE(MID(A4,2,LEN(A4))) -> 8 | J4: =INT(B4) -> 46079 | K4: =IF(F4="Pago inmediato", 0, IF(F4="", "", IFERROR(VALUE(MID(F4, 1, SEARCH(" ", F4)-1)), ""))) -> 0 | L4: =J4+K4+1 -> 46080 | M4: =E4-(E4*G4)-(E4*H4) -> 35.33 | N4: =IF(T4="PAGADA", 0, IF(L4 < TODAY(), TODAY() - L4, 0)) -> 0 | O4: =IF(T4="PAGADA", "PAGADA", IF(L4 < TODAY(), "VENCIDA", "EN TIEMPO")) -> PAGADA | P4: =LET( idVenta, I4&"", montoTotal, M4, pagos, IFERROR(SUMIF(Aux_Datos!$B:$B, idVenta, Aux_Datos!$K:$K), 0), retenciones, IFERROR(SUMIF(Aux_Datos!$N:$N, idVenta, Aux_Datos!$R:$R), 0), pagos + retenciones ) -> 85.33 | Q4: =IF(P4=0, "Sin Pago", LET( idVenta, I4&"", montoTotalPagado, P4, pagoUSD, IFERROR(SUMIFS(Aux_Datos!$C:$C, Aux_Datos!$B:$B, idVenta, Aux_Datos!$D:$D, "USD"), 0), pagoVES, IFERROR(SUMIFS(Aux_Datos!$C:$C, Aux_Datos!$B:$B, idVenta, Aux_Datos!$D:$D, "VES"), 0), IF(pagoUSD >= (montoTotalPagado * 0.84), "USD", IF(pagoVES >= (montoTotalPagado * 0.84), "VES", "MIXTO")) ) ) -> USD | R4: =M4-P4 -> -50 | S4: =IF(P4=0, "Sin Pago", IFERROR( MAXIFS(Aux_Datos!$A:$A, Aux_Datos!$B:$B, I4&""), IFERROR(MAXIFS(Aux_Datos!$A:$A, Aux_Datos!$B:$B, VALUE(I4)), "Revisar ID") ) ) -> 46174 | T4: =IF(R4<=0, "PAGADA", IF(P4>0, "PAGO PARCIAL", "PENDIENTE")) -> PAGADA | U4: =IF(AND(T4<>"PAGADA", L4<TODAY()), "CRÍTICO: VENCIDA", IF(T4="PAGADA", "SOLVENTE", "EN TIEMPO")) -> SOLVENTE | V4: =IF(T4="PAGADA", 0, IF(S4 < TODAY(), TODAY() - S4, 0)) -> 0 | W4: =IF(P4=0, "Sin Pago", LET( monedaPago, Q4, descuentoAplicado, G4, limitePermitido, IFERROR(VLOOKUP(monedaPago, 'Limites de Descuento'!$A$2:$B595, 2, FALSE), 0), IF(descuentoAplicado > limitePermitido, "ALERTA: EXCESO (" & TEXT(limitePermitido, "0%") & " máx)", "OK") ) ) -> OK | X4: =IF(OR(H4=0, S4="Sin Pago"), "", IF(AND(H4 > 0, S4 > (L4 + 2)), "⚠️ REVISAR DESCUENTO", "OK")) | Y4: 85.33 | Z4: CUMPLE
A5: S00009 | B5: 46079.509 | C5: E&M CAR SHOP C.A | D5: CALDERON TERAN ARGIMIRO ANTONIO | E5: 335.98 | F5: Pago inmediato | G5: =IF($E5=0,0,IF(SUMIF(Aux_Datos!$B:$B,$I5,Aux_Datos!$K:$K)/$E5>=VLOOKUP(IF(COUNTIFS(Aux_Datos!$B:$B,$I5,Aux_Datos!$D:$D,"<>USD")=0,"USD","VES"),'Limites de Descuento'!$A$2:$D$4,4,FALSE),MAX(0,1-SUMIF(Aux_Datos!$B:$B,$I5,Aux_Datos!$K:$K)/$E5),0)) -> 0 | I5: =VALUE(MID(A5,2,LEN(A5))) -> 9 | J5: =INT(B5) -> 46079 | K5: =IF(F5="Pago inmediato", 0, IF(F5="", "", IFERROR(VALUE(MID(F5, 1, SEARCH(" ", F5)-1)), ""))) -> 0 | L5: =J5+K5+1 -> 46080 | M5: =E5-(E5*G5)-(E5*H5) -> 335.98 | N5: =IF(T5="PAGADA", 0, IF(L5 < TODAY(), TODAY() - L5, 0)) -> 0 | O5: =IF(T5="PAGADA", "PAGADA", IF(L5 < TODAY(), "VENCIDA", "EN TIEMPO")) -> PAGADA | P5: =LET( idVenta, I5&"", montoTotal, M5, pagos, IFERROR(SUMIF(Aux_Datos!$B:$B, idVenta, Aux_Datos!$K:$K), 0), retenciones, IFERROR(SUMIF(Aux_Datos!$N:$N, idVenta, Aux_Datos!$R:$R), 0), pagos + retenciones ) -> 396.47318 | Q5: =IF(P5=0, "Sin Pago", LET( idVenta, I5&"", montoTotalPagado, P5, pagoUSD, IFERROR(SUMIFS(Aux_Datos!$C:$C, Aux_Datos!$B:$B, idVenta, Aux_Datos!$D:$D, "USD"), 0), pagoVES, IFERROR(SUMIFS(Aux_Datos!$C:$C, Aux_Datos!$B:$B, idVenta, Aux_Datos!$D:$D, "VES"), 0), IF(pagoUSD >= (montoTotalPagado * 0.84), "USD", IF(pagoVES >= (montoTotalPagado * 0.84), "VES", "MIXTO")) ) ) -> VES | R5: =M5-P5 -> -60.493179 | S5: =IF(P5=0, "Sin Pago", IFERROR( MAXIFS(Aux_Datos!$A:$A, Aux_Datos!$B:$B, I5&""), IFERROR(MAXIFS(Aux_Datos!$A:$A, Aux_Datos!$B:$B, VALUE(I5)), "Revisar ID") ) ) -> 46083 | T5: =IF(R5<=0, "PAGADA", IF(P5>0, "PAGO PARCIAL", "PENDIENTE")) -> PAGADA | U5: =IF(AND(T5<>"PAGADA", L5<TODAY()), "CRÍTICO: VENCIDA", IF(T5="PAGADA", "SOLVENTE", "EN TIEMPO")) -> SOLVENTE | V5: =IF(T5="PAGADA", 0, IF(S5 < TODAY(), TODAY() - S5, 0)) -> 0 | W5: =IF(P5=0, "Sin Pago", LET( monedaPago, Q5, descuentoAplicado, G5, limitePermitido, IFERROR(VLOOKUP(monedaPago, 'Limites de Descuento'!$A$2:$B595, 2, FALSE), 0), IF(descuentoAplicado > limitePermitido, "ALERTA: EXCESO (" & TEXT(limitePermitido, "0%") & " máx)", "OK") ) ) -> OK | X5: =IF(OR(H5=0, S5="Sin Pago"), "", IF(AND(H5 > 0, S5 > (L5 + 2)), "⚠️ REVISAR DESCUENTO", "OK")) | Y5: 396.47318 | Z5: CUMPLE
A6: S00010 | B6: 46097.354 | C6: TERA INGENIERIA Y SERVICIOS INDUSTRIALES, C.A | D6: Marco Romero | E6: 27781.08 | F6: 21 días | G6: =IF($E6=0,0,IF(SUMIF(Aux_Datos!$B:$B,$I6,Aux_Datos!$K:$K)/$E6>=VLOOKUP(IF(COUNTIFS(Aux_Datos!$B:$B,$I6,Aux_Datos!$D:$D,"<>USD")=0,"USD","VES"),'Limites de Descuento'!$A$2:$D$4,4,FALSE),MAX(0,1-SUMIF(Aux_Datos!$B:$B,$I6,Aux_Datos!$K:$K)/$E6),0)) -> 0 | I6: =VALUE(MID(A6,2,LEN(A6))) -> 10 | J6: =INT(B6) -> 46097 | K6: =IF(F6="Pago inmediato", 0, IF(F6="", "", IFERROR(VALUE(MID(F6, 1, SEARCH(" ", F6)-1)), ""))) -> 21 | L6: =J6+K6+1 -> 46119 | M6: =E6-(E6*G6)-(E6*H6) -> 27781.08 | N6: =IF(T6="PAGADA", 0, IF(L6 < TODAY(), TODAY() - L6, 0)) -> 0 | O6: =IF(T6="PAGADA", "PAGADA", IF(L6 < TODAY(), "VENCIDA", "EN TIEMPO")) -> PAGADA | P6: =LET( idVenta, I6&"", montoTotal, M6, pagos, IFERROR(SUMIF(Aux_Datos!$B:$B, idVenta, Aux_Datos!$K:$K), 0), retenciones, IFERROR(SUMIF(Aux_Datos!$N:$N, idVenta, Aux_Datos!$R:$R), 0), pagos + retenciones ) -> 27781.08 | Q6: =IF(P6=0, "Sin Pago", LET( idVenta, I6&"", montoTotalPagado, P6, pagoUSD, IFERROR(SUMIFS(Aux_Datos!$C:$C, Aux_Datos!$B:$B, idVenta, Aux_Datos!$D:$D, "USD"), 0), pagoVES, IFERROR(SUMIFS(Aux_Datos!$C:$C, Aux_Datos!$B:$B, idVenta, Aux_Datos!$D:$D, "VES"), 0), IF(pagoUSD >= (montoTotalPagado * 0.84), "USD", IF(pagoVES >= (montoTotalPagado * 0.84), "VES", "MIXTO")) ) ) -> USD | R6: =M6-P6 -> 0 | S6: =IF(P6=0, "Sin Pago", IFERROR( MAXIFS(Aux_Datos!$A:$A, Aux_Datos!$B:$B, I6&""), IFERROR(MAXIFS(Aux_Datos!$A:$A, Aux_Datos!$B:$B, VALUE(I6)), "Revisar ID") ) ) -> 46181 | T6: =IF(R6<=0, "PAGADA", IF(P6>0, "PAGO PARCIAL", "PENDIENTE")) -> PAGADA | U6: =IF(AND(T6<>"PAGADA", L6<TODAY()), "CRÍTICO: VENCIDA", IF(T6="PAGADA", "SOLVENTE", "EN TIEMPO")) -> SOLVENTE | V6: =IF(T6="PAGADA", 0, IF(S6 < TODAY(), TODAY() - S6, 0)) -> 0 | W6: =IF(P6=0, "Sin Pago", LET( monedaPago, Q6, descuentoAplicado, G6, limitePermitido, IFERROR(VLOOKUP(monedaPago, 'Limites de Descuento'!$A$2:$B595, 2, FALSE), 0), IF(descuentoAplicado > limitePermitido, "ALERTA: EXCESO (" & TEXT(limitePermitido, "0%") & " máx)", "OK") ) ) -> OK | X6: =IF(OR(H6=0, S6="Sin Pago"), "", IF(AND(H6 > 0, S6 > (L6 + 2)), "⚠️ REVISAR DESCUENTO", "OK")) | Y6: 27781.08 | Z6: CUMPLE
A7: S00011 | B7: 46094.725 | C7: MOTO MARCE 21, CA | D7: CALDERON TERAN ARGIMIRO ANTONIO | E7: 63.77 | F7: Pago inmediato | G7: =IF($E7=0,0,IF(SUMIF(Aux_Datos!$B:$B,$I7,Aux_Datos!$K:$K)/$E7>=VLOOKUP(IF(COUNTIFS(Aux_Datos!$B:$B,$I7,Aux_Datos!$D:$D,"<>USD")=0,"USD","VES"),'Limites de Descuento'!$A$2:$D$4,4,FALSE),MAX(0,1-SUMIF(Aux_Datos!$B:$B,$I7,Aux_Datos!$K:$K)/$E7),0)) -> 0 | I7: =VALUE(MID(A7,2,LEN(A7))) -> 11 | J7: =INT(B7) -> 46094 | K7: =IF(F7="Pago inmediato", 0, IF(F7="", "", IFERROR(VALUE(MID(F7, 1, SEARCH(" ", F7)-1)), ""))) -> 0 | L7: =J7+K7+1 -> 46095 | M7: =E7-(E7*G7)-(E7*H7) -> 63.77 | N7: =IF(T7="PAGADA", 0, IF(L7 < TODAY(), TODAY() - L7, 0)) -> 0 | O7: =IF(T7="PAGADA", "PAGADA", IF(L7 < TODAY(), "VENCIDA", "EN TIEMPO")) -> PAGADA | P7: =LET( idVenta, I7&"", montoTotal, M7, pagos, IFERROR(SUMIF(Aux_Datos!$B:$B, idVenta, Aux_Datos!$K:$K), 0), retenciones, IFERROR(SUMIF(Aux_Datos!$N:$N, idVenta, Aux_Datos!$R:$R), 0), pagos + retenciones ) -> 74.960088 | Q7: =IF(P7=0, "Sin Pago", LET( idVenta, I7&"", montoTotalPagado, P7, pagoUSD, IFERROR(SUMIFS(Aux_Datos!$C:$C, Aux_Datos!$B:$B, idVenta, Aux_Datos!$D:$D, "USD"), 0), pagoVES, IFERROR(SUMIFS(Aux_Datos!$C:$C, Aux_Datos!$B:$B, idVenta, Aux_Datos!$D:$D, "VES"), 0), IF(pagoUSD >= (montoTotalPagado * 0.84), "USD", IF(pagoVES >= (montoTotalPagado * 0.84), "VES", "MIXTO")) ) ) -> VES | R7: =M7-P7 -> -11.190088 | S7: =IF(P7=0, "Sin Pago", IFERROR( MAXIFS(Aux_Datos!$A:$A, Aux_Datos!$B:$B, I7&""), IFERROR(MAXIFS(Aux_Datos!$A:$A, Aux_Datos!$B:$B, VALUE(I7)), "Revisar ID") ) ) -> 46171 | T7: =IF(R7<=0, "PAGADA", IF(P7>0, "PAGO PARCIAL", "PENDIENTE")) -> PAGADA | U7: =IF(AND(T7<>"PAGADA", L7<TODAY()), "CRÍTICO: VENCIDA", IF(T7="PAGADA", "SOLVENTE", "EN TIEMPO")) -> SOLVENTE | V7: =IF(T7="PAGADA", 0, IF(S7 < TODAY(), TODAY() - S7, 0)) -> 0 | W7: =IF(P7=0, "Sin Pago", LET( monedaPago, Q7, descuentoAplicado, G7, limitePermitido, IFERROR(VLOOKUP(monedaPago, 'Limites de Descuento'!$A$2:$B595, 2, FALSE), 0), IF(descuentoAplicado > limitePermitido, "ALERTA: EXCESO (" & TEXT(limitePermitido, "0%") & " máx)", "OK") ) ) -> OK | X7: =IF(OR(H7=0, S7="Sin Pago"), "", IF(AND(H7 > 0, S7 > (L7 + 2)), "⚠️ REVISAR DESCUENTO", "OK")) | Y7: 74.960088 | Z7: CUMPLE
A8: S00014 | B8: 46090.241 | C8: SPEED RACING, CA | D8: OCANTO ZABALA ROSALVY DEL CARMEN | E8: 82.24 | F8: 7 días | G8: =IF($E8=0,0,IF(SUMIF(Aux_Datos!$B:$B,$I8,Aux_Datos!$K:$K)/$E8>=VLOOKUP(IF(COUNTIFS(Aux_Datos!$B:$B,$I8,Aux_Datos!$D:$D,"<>USD")=0,"USD","VES"),'Limites de Descuento'!$A$2:$D$4,4,FALSE),MAX(0,1-SUMIF(Aux_Datos!$B:$B,$I8,Aux_Datos!$K:$K)/$E8),0)) -> 0 | I8: =VALUE(MID(A8,2,LEN(A8))) -> 14 | J8: =INT(B8) -> 46090 | K8: =IF(F8="Pago inmediato", 0, IF(F8="", "", IFERROR(VALUE(MID(F8, 1, SEARCH(" ", F8)-1)), ""))) -> 7 | L8: =J8+K8+1 -> 46098 | M8: =E8-(E8*G8)-(E8*H8) -> 82.24 | N8: =IF(T8="PAGADA", 0, IF(L8 < TODAY(), TODAY() - L8, 0)) -> 0 | O8: =IF(T8="PAGADA", "PAGADA", IF(L8 < TODAY(), "VENCIDA", "EN TIEMPO")) -> PAGADA | P8: =LET( idVenta, I8&"", montoTotal, M8, pagos, IFERROR(SUMIF(Aux_Datos!$B:$B, idVenta, Aux_Datos!$K:$K), 0), retenciones, IFERROR(SUMIF(Aux_Datos!$N:$N, idVenta, Aux_Datos!$R:$R), 0), pagos + retenciones ) -> 86.578275 | Q8: =IF(P8=0, "Sin Pago", LET( idVenta, I8&"", montoTotalPagado, P8, pagoUSD, IFERROR(SUMIFS(Aux_Datos!$C:$C, Aux_Datos!$B:$B, idVenta, Aux_Datos!$D:$D, "USD"), 0), pagoVES, IFERROR(SUMIFS(Aux_Datos!$C:$C, Aux_Datos!$B:$B, idVenta, Aux_Datos!$D:$D, "VES"), 0), IF(pagoUSD >= (montoTotalPagado * 0.84), "USD", IF(pagoVES >= (montoTotalPagado * 0.84), "VES", "MIXTO")) ) ) -> VES | R8: =M8-P8 -> -4.3382748 | S8: =IF(P8=0, "Sin Pago", IFERROR( MAXIFS(Aux_Datos!$A:$A, Aux_Datos!$B:$B, I8&""), IFERROR(MAXIFS(Aux_Datos!$A:$A, Aux_Datos!$B:$B, VALUE(I8)), "Revisar ID") ) ) -> 46156 | T8: =IF(R8<=0, "PAGADA", IF(P8>0, "PAGO PARCIAL", "PENDIENTE")) -> PAGADA | U8: =IF(AND(T8<>"PAGADA", L8<TODAY()), "CRÍTICO: VENCIDA", IF(T8="PAGADA", "SOLVENTE", "EN TIEMPO")) -> SOLVENTE | V8: =IF(T8="PAGADA", 0, IF(S8 < TODAY(), TODAY() - S8, 0)) -> 0 | W8: =IF(P8=0, "Sin Pago", LET( monedaPago, Q8, descuentoAplicado, G8, limitePermitido, IFERROR(VLOOKUP(monedaPago, 'Limites de Descuento'!$A$2:$B595, 2, FALSE), 0), IF(descuentoAplicado > limitePermitido, "ALERTA: EXCESO (" & TEXT(limitePermitido, "0%") & " máx)", "OK") ) ) -> OK | X8: =IF(OR(H8=0, S8="Sin Pago"), "", IF(AND(H8 > 0, S8 > (L8 + 2)), "⚠️ REVISAR DESCUENTO", "OK")) | Y8: 86.578275 | Z8: CUMPLE
A9: S00015 | B9: 46090.241 | C9: SERVICIOS Y MANTENIMIENTO SPACARS, C.A, Henry Blanco | D9: TORO ARDILES DAVID JOSE | E9: 954.79 | F9: 7 días | G9: =IF($E9=0,0,IF(SUMIF(Aux_Datos!$B:$B,$I9,Aux_Datos!$K:$K)/$E9>=VLOOKUP(IF(COUNTIFS(Aux_Datos!$B:$B,$I9,Aux_Datos!$D:$D,"<>USD")=0,"USD","VES"),'Limites de Descuento'!$A$2:$D$4,4,FALSE),MAX(0,1-SUMIF(Aux_Datos!$B:$B,$I9,Aux_Datos!$K:$K)/$E9),0)) -> 0 | I9: =VALUE(MID(A9,2,LEN(A9))) -> 15 | J9: =INT(B9) -> 46090 | K9: =IF(F9="Pago inmediato", 0, IF(F9="", "", IFERROR(VALUE(MID(F9, 1, SEARCH(" ", F9)-1)), ""))) -> 7 | L9: =J9+K9+1 -> 46098 | M9: =E9-(E9*G9)-(E9*H9) -> 954.79 | N9: =IF(T9="PAGADA", 0, IF(L9 < TODAY(), TODAY() - L9, 0)) -> 102 | O9: =IF(T9="PAGADA", "PAGADA", IF(L9 < TODAY(), "VENCIDA", "EN TIEMPO")) -> VENCIDA | P9: =LET( idVenta, I9&"", montoTotal, M9, pagos, IFERROR(SUMIF(Aux_Datos!$B:$B, idVenta, Aux_Datos!$K:$K), 0), retenciones, IFERROR(SUMIF(Aux_Datos!$N:$N, idVenta, Aux_Datos!$R:$R), 0), pagos + retenciones ) -> 713.0517 | Q9: =IF(P9=0, "Sin Pago", LET( idVenta, I9&"", montoTotalPagado, P9, pagoUSD, IFERROR(SUMIFS(Aux_Datos!$C:$C, Aux_Datos!$B:$B, idVenta, Aux_Datos!$D:$D, "USD"), 0), pagoVES, IFERROR(SUMIFS(Aux_Datos!$C:$C, Aux_Datos!$B:$B, idVenta, Aux_Datos!$D:$D, "VES"), 0), IF(pagoUSD >= (montoTotalPagado * 0.84), "USD", IF(pagoVES >= (montoTotalPagado * 0.84), "VES", "MIXTO")) ) ) -> VES | R9: =M9-P9 -> 241.7383 | S9: =IF(P9=0, "Sin Pago", IFERROR( MAXIFS(Aux_Datos!$A:$A, Aux_Datos!$B:$B, I9&""), IFERROR(MAXIFS(Aux_Datos!$A:$A, Aux_Datos!$B:$B, VALUE(I9)), "Revisar ID") ) ) -> 46129 | T9: =IF(R9<=0, "PAGADA", IF(P9>0, "PAGO PARCIAL", "PENDIENTE")) -> PAGO PARCIAL | U9: =IF(AND(T9<>"PAGADA", L9<TODAY()), "CRÍTICO: VENCIDA", IF(T9="PAGADA", "SOLVENTE", "EN TIEMPO")) -> CRÍTICO: VENCIDA | V9: =IF(T9="PAGADA", 0, IF(S9 < TODAY(), TODAY() - S9, 0)) -> 71 | W9: =IF(P9=0, "Sin Pago", LET( monedaPago, Q9, descuentoAplicado, G9, limitePermitido, IFERROR(VLOOKUP(monedaPago, 'Limites de Descuento'!$A$2:$B595, 2, FALSE), 0), IF(descuentoAplicado > limitePermitido, "ALERTA: EXCESO (" & TEXT(limitePermitido, "0%") & " máx)", "OK") ) ) -> OK | X9: =IF(OR(H9=0, S9="Sin Pago"), "", IF(AND(H9 > 0, S9 > (L9 + 2)), "⚠️ REVISAR DESCUENTO", "OK")) | Y9: 713.0517 | Z9: NO CUMPLE
A10: S00017 | B10: 46090.242 | C10: MOTO REPUESTOS LA FLECHA, C.A. | D10: TORO ARDILES DAVID JOSE | E10: 104.36 | F10: 7 días | G10: =IF($E10=0,0,IF(SUMIF(Aux_Datos!$B:$B,$I10,Aux_Datos!$K:$K)/$E10>=VLOOKUP(IF(COUNTIFS(Aux_Datos!$B:$B,$I10,Aux_Datos!$D:$D,"<>USD")=0,"USD","VES"),'Limites de Descuento'!$A$2:$D$4,4,FALSE),MAX(0,1-SUMIF(Aux_Datos!$B:$B,$I10,Aux_Datos!$K:$K)/$E10),0)) -> 0 | I10: =VALUE(MID(A10,2,LEN(A10))) -> 17 | J10: =INT(B10) -> 46090 | K10: =IF(F10="Pago inmediato", 0, IF(F10="", "", IFERROR(VALUE(MID(F10, 1, SEARCH(" ", F10)-1)), ""))) -> 7 | L10: =J10+K10+1 -> 46098 | M10: =E10-(E10*G10)-(E10*H10) -> 104.36 | N10: =IF(T10="PAGADA", 0, IF(L10 < TODAY(), TODAY() - L10, 0)) -> 0 | O10: =IF(T10="PAGADA", "PAGADA", IF(L10 < TODAY(), "VENCIDA", "EN TIEMPO")) -> PAGADA | P10: 1847 | Q10: =IF(P10=0, "Sin Pago", LET( idVenta, I10&"", montoTotalPagado, P10, pagoUSD, IFERROR(SUMIFS(Aux_Datos!$C:$C, Aux_Datos!$B:$B, idVenta, Aux_Datos!$D:$D, "USD"), 0), pagoVES, IFERROR(SUMIFS(Aux_Datos!$C:$C, Aux_Datos!$B:$B, idVenta, Aux_Datos!$D:$D, "VES"), 0), IF(pagoUSD >= (montoTotalPagado * 0.84), "USD", IF(pagoVES >= (montoTotalPagado * 0.84), "VES", "MIXTO")) ) ) -> VES | R10: 0 | S10: =IF(P10=0, "Sin Pago", IFERROR( MAXIFS(Aux_Datos!$A:$A, Aux_Datos!$B:$B, I10&""), IFERROR(MAXIFS(Aux_Datos!$A:$A, Aux_Datos!$B:$B, VALUE(I10)), "Revisar ID") ) ) -> 46133 | T10: =IF(R10<=0, "PAGADA", IF(P10>0, "PAGO PARCIAL", "PENDIENTE")) -> PAGADA | U10: =IF(AND(T10<>"PAGADA", L10<TODAY()), "CRÍTICO: VENCIDA", IF(T10="PAGADA", "SOLVENTE", "EN TIEMPO")) -> SOLVENTE | V10: =IF(T10="PAGADA", 0, IF(S10 < TODAY(), TODAY() - S10, 0)) -> 0 | W10: =IF(P10=0, "Sin Pago", LET( monedaPago, Q10, descuentoAplicado, G10, limitePermitido, IFERROR(VLOOKUP(monedaPago, 'Limites de Descuento'!$A$2:$B595, 2, FALSE), 0), IF(descuentoAplicado > limitePermitido, "ALERTA: EXCESO (" & TEXT(limitePermitido, "0%") & " máx)", "OK") ) ) -> OK | X10: =IF(OR(H10=0, S10="Sin Pago"), "", IF(AND(H10 > 0, S10 > (L10 + 2)), "⚠️ REVISAR DESCUENTO", "OK")) | Y10: 116.81781 | Z10: CUMPLE
A11: S00018 | B11: 46090.242 | C11: AUTO ACCESORIOS VZLA, C.A. | D11: VILLABONA CORREA ALBA ESTEFANIA | E11: 96 | F11: 7 días | G11: =IF($E11=0,0,IF(SUMIF(Aux_Datos!$B:$B,$I11,Aux_Datos!$K:$K)/$E11>=VLOOKUP(IF(COUNTIFS(Aux_Datos!$B:$B,$I11,Aux_Datos!$D:$D,"<>USD")=0,"USD","VES"),'Limites de Descuento'!$A$2:$D$4,4,FALSE),MAX(0,1-SUMIF(Aux_Datos!$B:$B,$I11,Aux_Datos!$K:$K)/$E11),0)) -> 0 | I11: =VALUE(MID(A11,2,LEN(A11))) -> 18 | J11: =INT(B11) -> 46090 | K11: =IF(F11="Pago inmediato", 0, IF(F11="", "", IFERROR(VALUE(MID(F11, 1, SEARCH(" ", F11)-1)), ""))) -> 7 | L11: =J11+K11+1 -> 46098 | M11: =E11-(E11*G11)-(E11*H11) -> 96 | N11: =IF(T11="PAGADA", 0, IF(L11 < TODAY(), TODAY() - L11, 0)) -> 0 | O11: =IF(T11="PAGADA", "PAGADA", IF(L11 < TODAY(), "VENCIDA", "EN TIEMPO")) -> PAGADA | P11: =LET( idVenta, I11&"", montoTotal, M11, pagos, IFERROR(SUMIF(Aux_Datos!$B:$B, idVenta, Aux_Datos!$K:$K), 0), retenciones, IFERROR(SUMIF(Aux_Datos!$N:$N, idVenta, Aux_Datos!$R:$R), 0), pagos + retenciones ) -> 96 | Q11: =IF(P11=0, "Sin Pago", LET( idVenta, I11&"", montoTotalPagado, P11, pagoUSD, IFERROR(SUMIFS(Aux_Datos!$C:$C, Aux_Datos!$B:$B, idVenta, Aux_Datos!$D:$D, "USD"), 0), pagoVES, IFERROR(SUMIFS(Aux_Datos!$C:$C, Aux_Datos!$B:$B, idVenta, Aux_Datos!$D:$D, "VES"), 0), IF(pagoUSD >= (montoTotalPagado * 0.84), "USD", IF(pagoVES >= (montoTotalPagado * 0.84), "VES", "MIXTO")) ) ) -> USD | R11: =M11-P11 -> 0 | S11: =IF(P11=0, "Sin Pago", IFERROR( MAXIFS(Aux_Datos!$A:$A, Aux_Datos!$B:$B, I11&""), IFERROR(MAXIFS(Aux_Datos!$A:$A, Aux_Datos!$B:$B, VALUE(I11)), "Revisar ID") ) ) -> 46126 | T11: =IF(R11<=0, "PAGADA", IF(P11>0, "PAGO PARCIAL", "PENDIENTE")) -> PAGADA | U11: =IF(AND(T11<>"PAGADA", L11<TODAY()), "CRÍTICO: VENCIDA", IF(T11="PAGADA", "SOLVENTE", "EN TIEMPO")) -> SOLVENTE | V11: =IF(T11="PAGADA", 0, IF(S11 < TODAY(), TODAY() - S11, 0)) -> 0 | W11: =IF(P11=0, "Sin Pago", LET( monedaPago, Q11, descuentoAplicado, G11, limitePermitido, IFERROR(VLOOKUP(monedaPago, 'Limites de Descuento'!$A$2:$B595, 2, FALSE), 0), IF(descuentoAplicado > limitePermitido, "ALERTA: EXCESO (" & TEXT(limitePermitido, "0%") & " máx)", "OK") ) ) -> OK | X11: =IF(OR(H11=0, S11="Sin Pago"), "", IF(AND(H11 > 0, S11 > (L11 + 2)), "⚠️ REVISAR DESCUENTO", "OK")) | Y11: 96 | Z11: CUMPLE
A12: S00019 | B12: 46084.647 | C12: Ruta 8 Autopartes,c.a. | D12: OCANTO ZABALA ROSALVY DEL CARMEN | E12: 78.25 | F12: 7 días | G12: =IF($E12=0,0,IF(SUMIF(Aux_Datos!$B:$B,$I12,Aux_Datos!$K:$K)/$E12>=VLOOKUP(IF(COUNTIFS(Aux_Datos!$B:$B,$I12,Aux_Datos!$D:$D,"<>USD")=0,"USD","VES"),'Limites de Descuento'!$A$2:$D$4,4,FALSE),MAX(0,1-SUMIF(Aux_Datos!$B:$B,$I12,Aux_Datos!$K:$K)/$E12),0)) -> 0 | I12: =VALUE(MID(A12,2,LEN(A12))) -> 19 | J12: =INT(B12) -> 46084 | K12: =IF(F12="Pago inmediato", 0, IF(F12="", "", IFERROR(VALUE(MID(F12, 1, SEARCH(" ", F12)-1)), ""))) -> 7 | L12: =J12+K12+1 -> 46092 | M12: =E12-(E12*G12)-(E12*H12) -> 78.25 | N12: =IF(T12="PAGADA", 0, IF(L12 < TODAY(), TODAY() - L12, 0)) -> 0 | O12: =IF(T12="PAGADA", "PAGADA", IF(L12 < TODAY(), "VENCIDA", "EN TIEMPO")) -> PAGADA | P12: =LET( idVenta, I12&"", montoTotal, M12, pagos, IFERROR(SUMIF(Aux_Datos!$B:$B, idVenta, Aux_Datos!$K:$K), 0), retenciones, IFERROR(SUMIF(Aux_Datos!$N:$N, idVenta, Aux_Datos!$R:$R), 0), pagos + retenciones ) -> 91.89855 | Q12: =IF(P12=0, "Sin Pago", LET( idVenta, I12&"", montoTotalPagado, P12, pagoUSD, IFERROR(SUMIFS(Aux_Datos!$C:$C, Aux_Datos!$B:$B, idVenta, Aux_Datos!$D:$D, "USD"), 0), pagoVES, IFERROR(SUMIFS(Aux_Datos!$C:$C, Aux_Datos!$B:$B, idVenta, Aux_Datos!$D:$D, "VES"), 0), IF(pagoUSD >= (montoTotalPagado * 0.84), "USD", IF(pagoVES >= (montoTotalPagado * 0.84), "VES", "MIXTO")) ) ) -> VES | R12: =M12-P12 -> -13.64855 | S12: =IF(P12=0, "Sin Pago", IFERROR( MAXIFS(Aux_Datos!$A:$A, Aux_Datos!$B:$B, I12&""), IFERROR(MAXIFS(Aux_Datos!$A:$A, Aux_Datos!$B:$B, VALUE(I12)), "Revisar ID") ) ) -> 46140 | T12: =IF(R12<=0, "PAGADA", IF(P12>0, "PAGO PARCIAL", "PENDIENTE")) -> PAGADA | U12: =IF(AND(T12<>"PAGADA", L12<TODAY()), "CRÍTICO: VENCIDA", IF(T12="PAGADA", "SOLVENTE", "EN TIEMPO")) -> SOLVENTE | V12: =IF(T12="PAGADA", 0, IF(S12 < TODAY(), TODAY() - S12, 0)) -> 0 | W12: =IF(P12=0, "Sin Pago", LET( monedaPago, Q12, descuentoAplicado, G12, limitePermitido, IFERROR(VLOOKUP(monedaPago, 'Limites de Descuento'!$A$2:$B595, 2, FALSE), 0), IF(descuentoAplicado > limitePermitido, "ALERTA: EXCESO (" & TEXT(limitePermitido, "0%") & " máx)", "OK") ) ) -> OK | X12: =IF(OR(H12=0, S12="Sin Pago"), "", IF(AND(H12 > 0, S12 > (L12 + 2)), "⚠️ REVISAR DESCUENTO", "OK")) | Y12: 91.89855 | Z12: CUMPLE
A13: S00020 | B13: 46090.242 | C13: EMPRENDIMIENTO TOMAS MARCANO 5 | D13: VILLABONA CORREA ALBA ESTEFANIA | E13: 472.53 | F13: 7 días | G13: =IF($E13=0,0,IF(SUMIF(Aux_Datos!$B:$B,$I13,Aux_Datos!$K:$K)/$E13>=VLOOKUP(IF(COUNTIFS(Aux_Datos!$B:$B,$I13,Aux_Datos!$D:$D,"<>USD")=0,"USD","VES"),'Limites de Descuento'!$A$2:$D$4,4,FALSE),MAX(0,1-SUMIF(Aux_Datos!$B:$B,$I13,Aux_Datos!$K:$K)/$E13),0)) -> 0 | I13: =VALUE(MID(A13,2,LEN(A13))) -> 20 | J13: =INT(B13) -> 46090 | K13: =IF(F13="Pago inmediato", 0, IF(F13="", "", IFERROR(VALUE(MID(F13, 1, SEARCH(" ", F13)-1)), ""))) -> 7 | L13: =J13+K13+1 -> 46098 | M13: =E13-(E13*G13)-(E13*H13) -> 472.53 | N13: =IF(T13="PAGADA", 0, IF(L13 < TODAY(), TODAY() - L13, 0)) -> 102 | O13: =IF(T13="PAGADA", "PAGADA", IF(L13 < TODAY(), "VENCIDA", "EN TIEMPO")) -> VENCIDA | P13: =LET( idVenta, I13&"", montoTotal, M13, pagos, IFERROR(SUMIF(Aux_Datos!$B:$B, idVenta, Aux_Datos!$K:$K), 0), retenciones, IFERROR(SUMIF(Aux_Datos!$N:$N, idVenta, Aux_Datos!$R:$R), 0), pagos + retenciones ) -> 166.24063 | Q13: =IF(P13=0, "Sin Pago", LET( idVenta, I13&"", montoTotalPagado, P13, pagoUSD, IFERROR(SUMIFS(Aux_Datos!$C:$C, Aux_Datos!$B:$B, idVenta, Aux_Datos!$D:$D, "USD"), 0), pagoVES, IFERROR(SUMIFS(Aux_Datos!$C:$C, Aux_Datos!$B:$B, idVenta, Aux_Datos!$D:$D, "VES"), 0), IF(pagoUSD >= (montoTotalPagado * 0.84), "USD", IF(pagoVES >= (montoTotalPagado * 0.84), "VES", "MIXTO")) ) ) -> VES | R13: =M13-P13 -> 306.28937 | S13: =IF(P13=0, "Sin Pago", IFERROR( MAXIFS(Aux_Datos!$A:$A, Aux_Datos!$B:$B, I13&""), IFERROR(MAXIFS(Aux_Datos!$A:$A, Aux_Datos!$B:$B, VALUE(I13)), "Revisar ID") ) ) -> 46177 | T13: =IF(R13<=0, "PAGADA", IF(P13>0, "PAGO PARCIAL", "PENDIENTE")) -> PAGO PARCIAL | U13: =IF(AND(T13<>"PAGADA", L13<TODAY()), "CRÍTICO: VENCIDA", IF(T13="PAGADA", "SOLVENTE", "EN TIEMPO")) -> CRÍTICO: VENCIDA | V13: =IF(T13="PAGADA", 0, IF(S13 < TODAY(), TODAY() - S13, 0)) -> 23 | W13: =IF(P13=0, "Sin Pago", LET( monedaPago, Q13, descuentoAplicado, G13, limitePermitido, IFERROR(VLOOKUP(monedaPago, 'Limites de Descuento'!$A$2:$B595, 2, FALSE), 0), IF(descuentoAplicado > limitePermitido, "ALERTA: EXCESO (" & TEXT(limitePermitido, "0%") & " máx)", "OK") ) ) -> OK | X13: =IF(OR(H13=0, S13="Sin Pago"), "", IF(AND(H13 > 0, S13 > (L13 + 2)), "⚠️ REVISAR DESCUENTO", "OK")) | Y13: 166.24063 | Z13: NO CUMPLE
A14: S00021 | B14: 46090.242 | C14: INVERSIONES SMALUM 21, C.A. | D14: VILLABONA CORREA ALBA ESTEFANIA | E14: 212.72 | F14: 7 días | G14: =IF($E14=0,0,IF(SUMIF(Aux_Datos!$B:$B,$I14,Aux_Datos!$K:$K)/$E14>=VLOOKUP(IF(COUNTIFS(Aux_Datos!$B:$B,$I14,Aux_Datos!$D:$D,"<>USD")=0,"USD","VES"),'Limites de Descuento'!$A$2:$D$4,4,FALSE),MAX(0,1-SUMIF(Aux_Datos!$B:$B,$I14,Aux_Datos!$K:$K)/$E14),0)) -> 0 | I14: =VALUE(MID(A14,2,LEN(A14))) -> 21 | J14: =INT(B14) -> 46090 | K14: =IF(F14="Pago inmediato", 0, IF(F14="", "", IFERROR(VALUE(MID(F14, 1, SEARCH(" ", F14)-1)), ""))) -> 7 | L14: =J14+K14+1 -> 46098 | M14: =E14-(E14*G14)-(E14*H14) -> 212.72 | N14: =IF(T14="PAGADA", 0, IF(L14 < TODAY(), TODAY() - L14, 0)) -> 0 | O14: =IF(T14="PAGADA", "PAGADA", IF(L14 < TODAY(), "VENCIDA", "EN TIEMPO")) -> PAGADA | P14: =LET( idVenta, I14&"", montoTotal, M14, pagos, IFERROR(SUMIF(Aux_Datos!$B:$B, idVenta, Aux_Datos!$K:$K), 0), retenciones, IFERROR(SUMIF(Aux_Datos!$N:$N, idVenta, Aux_Datos!$R:$R), 0), pagos + retenciones ) -> 238.6499 | Q14: =IF(P14=0, "Sin Pago", LET( idVenta, I14&"", montoTotalPagado, P14, pagoUSD, IFERROR(SUMIFS(Aux_Datos!$C:$C, Aux_Datos!$B:$B, idVenta, Aux_Datos!$D:$D, "USD"), 0), pagoVES, IFERROR(SUMIFS(Aux_Datos!$C:$C, Aux_Datos!$B:$B, idVenta, Aux_Datos!$D:$D, "VES"), 0), IF(pagoUSD >= (montoTotalPagado * 0.84), "USD", IF(pagoVES >= (montoTotalPagado * 0.84), "VES", "MIXTO")) ) ) -> VES | R14: =M14-P14 -> -25.929896 | S14: =IF(P14=0, "Sin Pago", IFERROR( MAXIFS(Aux_Datos!$A:$A, Aux_Datos!$B:$B, I14&""), IFERROR(MAXIFS(Aux_Datos!$A:$A, Aux_Datos!$B:$B, VALUE(I14)), "Revisar ID") ) ) -> 46153 | T14: =IF(R14<=0, "PAGADA", IF(P14>0, "PAGO PARCIAL", "PENDIENTE")) -> PAGADA | U14: =IF(AND(T14<>"PAGADA", L14<TODAY()), "CRÍTICO: VENCIDA", IF(T14="PAGADA", "SOLVENTE", "EN TIEMPO")) -> SOLVENTE | V14: =IF(T14="PAGADA", 0, IF(S14 < TODAY(), TODAY() - S14, 0)) -> 0 | W14: =IF(P14=0, "Sin Pago", LET( monedaPago, Q14, descuentoAplicado, G14, limitePermitido, IFERROR(VLOOKUP(monedaPago, 'Limites de Descuento'!$A$2:$B595, 2, FALSE), 0), IF(descuentoAplicado > limitePermitido, "ALERTA: EXCESO (" & TEXT(limitePermitido, "0%") & " máx)", "OK") ) ) -> OK | X14: =IF(OR(H14=0, S14="Sin Pago"), "", IF(AND(H14 > 0, S14 > (L14 + 2)), "⚠️ REVISAR DESCUENTO", "OK")) | Y14: 238.6499 | Z14: CUMPLE
A15: S00022 | B15: 46090.242 | C15: Autorepuestos las 24 horas | D15: MARTINEZ MONTES JEFFREY ENRIQUE | E15: 96 | F15: 7 días | G15: =IF($E15=0,0,IF(SUMIF(Aux_Datos!$B:$B,$I15,Aux_Datos!$K:$K)/$E15>=VLOOKUP(IF(COUNTIFS(Aux_Datos!$B:$B,$I15,Aux_Datos!$D:$D,"<>USD")=0,"USD","VES"),'Limites de Descuento'!$A$2:$D$4,4,FALSE),MAX(0,1-SUMIF(Aux_Datos!$B:$B,$I15,Aux_Datos!$K:$K)/$E15),0)) -> 0 | I15: =VALUE(MID(A15,2,LEN(A15))) -> 22 | J15: =INT(B15) -> 46090 | K15: =IF(F15="Pago inmediato", 0, IF(F15="", "", IFERROR(VALUE(MID(F15, 1, SEARCH(" ", F15)-1)), ""))) -> 7 | L15: =J15+K15+1 -> 46098 | M15: =E15-(E15*G15)-(E15*H15) -> 96 | N15: =IF(T15="PAGADA", 0, IF(L15 < TODAY(), TODAY() - L15, 0)) -> 0 | O15: =IF(T15="PAGADA", "PAGADA", IF(L15 < TODAY(), "VENCIDA", "EN TIEMPO")) -> PAGADA | P15: =LET( idVenta, I15&"", montoTotal, M15, pagos, IFERROR(SUMIF(Aux_Datos!$B:$B, idVenta, Aux_Datos!$K:$K), 0), retenciones, IFERROR(SUMIF(Aux_Datos!$N:$N, idVenta, Aux_Datos!$R:$R), 0), pagos + retenciones ) -> 96 | Q15: =IF(P15=0, "Sin Pago", LET( idVenta, I15&"", montoTotalPagado, P15, pagoUSD, IFERROR(SUMIFS(Aux_Datos!$C:$C, Aux_Datos!$B:$B, idVenta, Aux_Datos!$D:$D, "USD"), 0), pagoVES, IFERROR(SUMIFS(Aux_Datos!$C:$C, Aux_Datos!$B:$B, idVenta, Aux_Datos!$D:$D, "VES"), 0), IF(pagoUSD >= (montoTotalPagado * 0.84), "USD", IF(pagoVES >= (montoTotalPagado * 0.84), "VES", "MIXTO")) ) ) -> USD | R15: =M15-P15 -> 0 | S15: =IF(P15=0, "Sin Pago", IFERROR( MAXIFS(Aux_Datos!$A:$A, Aux_Datos!$B:$B, I15&""), IFERROR(MAXIFS(Aux_Datos!$A:$A, Aux_Datos!$B:$B, VALUE(I15)), "Revisar ID") ) ) -> 46111 | T15: =IF(R15<=0, "PAGADA", IF(P15>0, "PAGO PARCIAL", "PENDIENTE")) -> PAGADA | U15: =IF(AND(T15<>"PAGADA", L15<TODAY()), "CRÍTICO: VENCIDA", IF(T15="PAGADA", "SOLVENTE", "EN TIEMPO")) -> SOLVENTE | V15: =IF(T15="PAGADA", 0, IF(S15 < TODAY(), TODAY() - S15, 0)) -> 0 | W15: =IF(P15=0, "Sin Pago", LET( monedaPago, Q15, descuentoAplicado, G15, limitePermitido, IFERROR(VLOOKUP(monedaPago, 'Limites de Descuento'!$A$2:$B595, 2, FALSE), 0), IF(descuentoAplicado > limitePermitido, "ALERTA: EXCESO (" & TEXT(limitePermitido, "0%") & " máx)", "OK") ) ) -> OK | X15: =IF(OR(H15=0, S15="Sin Pago"), "", IF(AND(H15 > 0, S15 > (L15 + 2)), "⚠️ REVISAR DESCUENTO", "OK")) | Y15: 96 | Z15: CUMPLE
A16: S00023 | B16: 46090.243 | C16: Multiservicios Sanahuja 36 C.A | D16: GRIMAN DIAZ HECTOR EDUARDO | E16: 96 | F16: 15 días | G16: =IF($E16=0,0,IF(SUMIF(Aux_Datos!$B:$B,$I16,Aux_Datos!$K:$K)/$E16>=VLOOKUP(IF(COUNTIFS(Aux_Datos!$B:$B,$I16,Aux_Datos!$D:$D,"<>USD")=0,"USD","VES"),'Limites de Descuento'!$A$2:$D$4,4,FALSE),MAX(0,1-SUMIF(Aux_Datos!$B:$B,$I16,Aux_Datos!$K:$K)/$E16),0)) -> 0 | I16: =VALUE(MID(A16,2,LEN(A16))) -> 23 | J16: =INT(B16) -> 46090 | K16: =IF(F16="Pago inmediato", 0, IF(F16="", "", IFERROR(VALUE(MID(F16, 1, SEARCH(" ", F16)-1)), ""))) -> 15 | L16: =J16+K16+1 -> 46106 | M16: =E16-(E16*G16)-(E16*H16) -> 96 | N16: =IF(T16="PAGADA", 0, IF(L16 < TODAY(), TODAY() - L16, 0)) -> 0 | O16: =IF(T16="PAGADA", "PAGADA", IF(L16 < TODAY(), "VENCIDA", "EN TIEMPO")) -> PAGADA | P16: =LET( idVenta, I16&"", montoTotal, M16, pagos, IFERROR(SUMIF(Aux_Datos!$B:$B, idVenta, Aux_Datos!$K:$K), 0), retenciones, IFERROR(SUMIF(Aux_Datos!$N:$N, idVenta, Aux_Datos!$R:$R), 0), pagos + retenciones ) -> 96 | Q16: =IF(P16=0, "Sin Pago", LET( idVenta, I16&"", montoTotalPagado, P16, pagoUSD, IFERROR(SUMIFS(Aux_Datos!$C:$C, Aux_Datos!$B:$B, idVenta, Aux_Datos!$D:$D, "USD"), 0), pagoVES, IFERROR(SUMIFS(Aux_Datos!$C:$C, Aux_Datos!$B:$B, idVenta, Aux_Datos!$D:$D, "VES"), 0), IF(pagoUSD >= (montoTotalPagado * 0.84), "USD", IF(pagoVES >= (montoTotalPagado * 0.84), "VES", "MIXTO")) ) ) -> USD | R16: =M16-P16 -> 0 | S16: =IF(P16=0, "Sin Pago", IFERROR( MAXIFS(Aux_Datos!$A:$A, Aux_Datos!$B:$B, I16&""), IFERROR(MAXIFS(Aux_Datos!$A:$A, Aux_Datos!$B:$B, VALUE(I16)), "Revisar ID") ) ) -> 46098 | T16: =IF(R16<=0, "PAGADA", IF(P16>0, "PAGO PARCIAL", "PENDIENTE")) -> PAGADA | U16: =IF(AND(T16<>"PAGADA", L16<TODAY()), "CRÍTICO: VENCIDA", IF(T16="PAGADA", "SOLVENTE", "EN TIEMPO")) -> SOLVENTE | V16: =IF(T16="PAGADA", 0, IF(S16 < TODAY(), TODAY() - S16, 0)) -> 0 | W16: =IF(P16=0, "Sin Pago", LET( monedaPago, Q16, descuentoAplicado, G16, limitePermitido, IFERROR(VLOOKUP(monedaPago, 'Limites de Descuento'!$A$2:$B595, 2, FALSE), 0), IF(descuentoAplicado > limitePermitido, "ALERTA: EXCESO (" & TEXT(limitePermitido, "0%") & " máx)", "OK") ) ) -> OK | X16: =IF(OR(H16=0, S16="Sin Pago"), "", IF(AND(H16 > 0, S16 > (L16 + 2)), "⚠️ REVISAR DESCUENTO", "OK")) | Y16: 96 | Z16: CUMPLE
A17: S00024 | B17: 46090.243 | C17: Encamotors Catia C.A | D17: GRIMAN DIAZ HECTOR EDUARDO | E17: 90.44 | F17: 15 días | G17: =IF($E17=0,0,IF(SUMIF(Aux_Datos!$B:$B,$I17,Aux_Datos!$K:$K)/$E17>=VLOOKUP(IF(COUNTIFS(Aux_Datos!$B:$B,$I17,Aux_Datos!$D:$D,"<>USD")=0,"USD","VES"),'Limites de Descuento'!$A$2:$D$4,4,FALSE),MAX(0,1-SUMIF(Aux_Datos!$B:$B,$I17,Aux_Datos!$K:$K)/$E17),0)) -> 0 | I17: =VALUE(MID(A17,2,LEN(A17))) -> 24 | J17: =INT(B17) -> 46090 | K17: =IF(F17="Pago inmediato", 0, IF(F17="", "", IFERROR(VALUE(MID(F17, 1, SEARCH(" ", F17)-1)), ""))) -> 15 | L17: =J17+K17+1 -> 46106 | M17: =E17-(E17*G17)-(E17*H17) -> 90.44 | N17: =IF(T17="PAGADA", 0, IF(L17 < TODAY(), TODAY() - L17, 0)) -> 0 | O17: =IF(T17="PAGADA", "PAGADA", IF(L17 < TODAY(), "VENCIDA", "EN TIEMPO")) -> PAGADA | P17: =LET( idVenta, I17&"", montoTotal, M17, pagos, IFERROR(SUMIF(Aux_Datos!$B:$B, idVenta, Aux_Datos!$K:$K), 0), retenciones, IFERROR(SUMIF(Aux_Datos!$N:$N, idVenta, Aux_Datos!$R:$R), 0), pagos + retenciones ) -> 101.23959 | Q17: =IF(P17=0, "Sin Pago", LET( idVenta, I17&"", montoTotalPagado, P17, pagoUSD, IFERROR(SUMIFS(Aux_Datos!$C:$C, Aux_Datos!$B:$B, idVenta, Aux_Datos!$D:$D, "USD"), 0), pagoVES, IFERROR(SUMIFS(Aux_Datos!$C:$C, Aux_Datos!$B:$B, idVenta, Aux_Datos!$D:$D, "VES"), 0), IF(pagoUSD >= (montoTotalPagado * 0.84), "USD", IF(pagoVES >= (montoTotalPagado * 0.84), "VES", "MIXTO")) ) ) -> VES | R17: =M17-P17 -> -10.799592 | S17: =IF(P17=0, "Sin Pago", IFERROR( MAXIFS(Aux_Datos!$A:$A, Aux_Datos!$B:$B, I17&""), IFERROR(MAXIFS(Aux_Datos!$A:$A, Aux_Datos!$B:$B, VALUE(I17)), "Revisar ID") ) ) -> 46133 | T17: =IF(R17<=0, "PAGADA", IF(P17>0, "PAGO PARCIAL", "PENDIENTE")) -> PAGADA | U17: =IF(AND(T17<>"PAGADA", L17<TODAY()), "CRÍTICO: VENCIDA", IF(T17="PAGADA", "SOLVENTE", "EN TIEMPO")) -> SOLVENTE | V17: =IF(T17="PAGADA", 0, IF(S17 < TODAY(), TODAY() - S17, 0)) -> 0 | W17: =IF(P17=0, "Sin Pago", LET( monedaPago, Q17, descuentoAplicado, G17, limitePermitido, IFERROR(VLOOKUP(monedaPago, 'Limites de Descuento'!$A$2:$B595, 2, FALSE), 0), IF(descuentoAplicado > limitePermitido, "ALERTA: EXCESO (" & TEXT(limitePermitido, "0%") & " máx)", "OK") ) ) -> OK | X17: =IF(OR(H17=0, S17="Sin Pago"), "", IF(AND(H17 > 0, S17 > (L17 + 2)), "⚠️ REVISAR DESCUENTO", "OK")) | Y17: 101.23959 | Z17: CUMPLE
A18: S00026 | B18: 46090.243 | C18: Joel Duque | D18: CASERES GONZALEZ RONALD OSWALDO | E18: 72.48 | F18: 15 días | G18: =IF($E18=0,0,IF(SUMIF(Aux_Datos!$B:$B,$I18,Aux_Datos!$K:$K)/$E18>=VLOOKUP(IF(COUNTIFS(Aux_Datos!$B:$B,$I18,Aux_Datos!$D:$D,"<>USD")=0,"USD","VES"),'Limites de Descuento'!$A$2:$D$4,4,FALSE),MAX(0,1-SUMIF(Aux_Datos!$B:$B,$I18,Aux_Datos!$K:$K)/$E18),0)) -> 0 | I18: =VALUE(MID(A18,2,LEN(A18))) -> 26 | J18: =INT(B18) -> 46090 | K18: =IF(F18="Pago inmediato", 0, IF(F18="", "", IFERROR(VALUE(MID(F18, 1, SEARCH(" ", F18)-1)), ""))) -> 15 | L18: =J18+K18+1 -> 46106 | M18: =E18-(E18*G18)-(E18*H18) -> 72.48 | N18: =IF(T18="PAGADA", 0, IF(L18 < TODAY(), TODAY() - L18, 0)) -> 94 | O18: =IF(T18="PAGADA", "PAGADA", IF(L18 < TODAY(), "VENCIDA", "EN TIEMPO")) -> VENCIDA | P18: =LET( idVenta, I18&"", montoTotal, M18, pagos, IFERROR(SUMIF(Aux_Datos!$B:$B, idVenta, Aux_Datos!$K:$K), 0), retenciones, IFERROR(SUMIF(Aux_Datos!$N:$N, idVenta, Aux_Datos!$R:$R), 0), pagos + retenciones ) -> 30 | Q18: =IF(P18=0, "Sin Pago", LET( idVenta, I18&"", montoTotalPagado, P18, pagoUSD, IFERROR(SUMIFS(Aux_Datos!$C:$C, Aux_Datos!$B:$B, idVenta, Aux_Datos!$D:$D, "USD"), 0), pagoVES, IFERROR(SUMIFS(Aux_Datos!$C:$C, Aux_Datos!$B:$B, idVenta, Aux_Datos!$D:$D, "VES"), 0), IF(pagoUSD >= (montoTotalPagado * 0.84), "USD", IF(pagoVES >= (montoTotalPagado * 0.84), "VES", "MIXTO")) ) ) -> USD | R18: =M18-P18 -> 42.48 | S18: =IF(P18=0, "Sin Pago", IFERROR( MAXIFS(Aux_Datos!$A:$A, Aux_Datos!$B:$B, I18&""), IFERROR(MAXIFS(Aux_Datos!$A:$A, Aux_Datos!$B:$B, VALUE(I18)), "Revisar ID") ) ) -> 46175 | T18: =IF(R18<=0, "PAGADA", IF(P18>0, "PAGO PARCIAL", "PENDIENTE")) -> PAGO PARCIAL | U18: =IF(AND(T18<>"PAGADA", L18<TODAY()), "CRÍTICO: VENCIDA", IF(T18="PAGADA", "SOLVENTE", "EN TIEMPO")) -> CRÍTICO: VENCIDA | V18: =IF(T18="PAGADA", 0, IF(S18 < TODAY(), TODAY() - S18, 0)) -> 25 | W18: =IF(P18=0, "Sin Pago", LET( monedaPago, Q18, descuentoAplicado, G18, limitePermitido, IFERROR(VLOOKUP(monedaPago, 'Limites de Descuento'!$A$2:$B595, 2, FALSE), 0), IF(descuentoAplicado > limitePermitido, "ALERTA: EXCESO (" & TEXT(limitePermitido, "0%") & " máx)", "OK") ) ) -> OK | X18: =IF(OR(H18=0, S18="Sin Pago"), "", IF(AND(H18 > 0, S18 > (L18 + 2)), "⚠️ REVISAR DESCUENTO", "OK")) | Y18: 30 | Z18: NO CUMPLE
A19: S00027 | B19: 46090.244 | C19: Moises Alejandro Mares | D19: GRIMAN DIAZ HECTOR EDUARDO | E19: 510 | F19: 15 días | G19: =IF($E19=0,0,IF(SUMIF(Aux_Datos!$B:$B,$I19,Aux_Datos!$K:$K)/$E19>=VLOOKUP(IF(COUNTIFS(Aux_Datos!$B:$B,$I19,Aux_Datos!$D:$D,"<>USD")=0,"USD","VES"),'Limites de Descuento'!$A$2:$D$4,4,FALSE),MAX(0,1-SUMIF(Aux_Datos!$B:$B,$I19,Aux_Datos!$K:$K)/$E19),0)) -> 0 | I19: =VALUE(MID(A19,2,LEN(A19))) -> 27 | J19: =INT(B19) -> 46090 | K19: =IF(F19="Pago inmediato", 0, IF(F19="", "", IFERROR(VALUE(MID(F19, 1, SEARCH(" ", F19)-1)), ""))) -> 15 | L19: =J19+K19+1 -> 46106 | M19: =E19-(E19*G19)-(E19*H19) -> 510 | N19: =IF(T19="PAGADA", 0, IF(L19 < TODAY(), TODAY() - L19, 0)) -> 94 | O19: =IF(T19="PAGADA", "PAGADA", IF(L19 < TODAY(), "VENCIDA", "EN TIEMPO")) -> VENCIDA | P19: =LET( idVenta, I19&"", montoTotal, M19, pagos, IFERROR(SUMIF(Aux_Datos!$B:$B, idVenta, Aux_Datos!$K:$K), 0), retenciones, IFERROR(SUMIF(Aux_Datos!$N:$N, idVenta, Aux_Datos!$R:$R), 0), pagos + retenciones ) -> 150 | Q19: =IF(P19=0, "Sin Pago", LET( idVenta, I19&"", montoTotalPagado, P19, pagoUSD, IFERROR(SUMIFS(Aux_Datos!$C:$C, Aux_Datos!$B:$B, idVenta, Aux_Datos!$D:$D, "USD"), 0), pagoVES, IFERROR(SUMIFS(Aux_Datos!$C:$C, Aux_Datos!$B:$B, idVenta, Aux_Datos!$D:$D, "VES"), 0), IF(pagoUSD >= (montoTotalPagado * 0.84), "USD", IF(pagoVES >= (montoTotalPagado * 0.84), "VES", "MIXTO")) ) ) -> USD | R19: =M19-P19 -> 360 | S19: =IF(P19=0, "Sin Pago", IFERROR( MAXIFS(Aux_Datos!$A:$A, Aux_Datos!$B:$B, I19&""), IFERROR(MAXIFS(Aux_Datos!$A:$A, Aux_Datos!$B:$B, VALUE(I19)), "Revisar ID") ) ) -> 46192 | T19: =IF(R19<=0, "PAGADA", IF(P19>0, "PAGO PARCIAL", "PENDIENTE")) -> PAGO PARCIAL | U19: =IF(AND(T19<>"PAGADA", L19<TODAY()), "CRÍTICO: VENCIDA", IF(T19="PAGADA", "SOLVENTE", "EN TIEMPO")) -> CRÍTICO: VENCIDA | V19: =IF(T19="PAGADA", 0, IF(S19 < TODAY(), TODAY() - S19, 0)) -> 8 | W19: =IF(P19=0, "Sin Pago", LET( monedaPago, Q19, descuentoAplicado, G19, limitePermitido, IFERROR(VLOOKUP(monedaPago, 'Limites de Descuento'!$A$2:$B595, 2, FALSE), 0), IF(descuentoAplicado > limitePermitido, "ALERTA: EXCESO (" & TEXT(limitePermitido, "0%") & " máx)", "OK") ) ) -> OK | X19: =IF(OR(H19=0, S19="Sin Pago"), "", IF(AND(H19 > 0, S19 > (L19 + 2)), "⚠️ REVISAR DESCUENTO", "OK")) | Y19: 150 | Z19: NO CUMPLE
A20: S00028 | B20: 46085.588 | C20: Ricardo A. Fernandez. | D20: MARTINEZ MONTES JEFFREY ENRIQUE | E20: 69.28 | F20: 15 días | G20: =IF($E20=0,0,IF(SUMIF(Aux_Datos!$B:$B,$I20,Aux_Datos!$K:$K)/$E20>=VLOOKUP(IF(COUNTIFS(Aux_Datos!$B:$B,$I20,Aux_Datos!$D:$D,"<>USD")=0,"USD","VES"),'Limites de Descuento'!$A$2:$D$4,4,FALSE),MAX(0,1-SUMIF(Aux_Datos!$B:$B,$I20,Aux_Datos!$K:$K)/$E20),0)) -> 0.005312316 | I20: =VALUE(MID(A20,2,LEN(A20))) -> 28 | J20: =INT(B20) -> 46085 | K20: =IF(F20="Pago inmediato", 0, IF(F20="", "", IFERROR(VALUE(MID(F20, 1, SEARCH(" ", F20)-1)), ""))) -> 15 | L20: =J20+K20+1 -> 46101 | M20: =E20-(E20*G20)-(E20*H20) -> 68.911963 | N20: =IF(T20="PAGADA", 0, IF(L20 < TODAY(), TODAY() - L20, 0)) -> 0 | O20: =IF(T20="PAGADA", "PAGADA", IF(L20 < TODAY(), "VENCIDA", "EN TIEMPO")) -> PAGADA | P20: =LET( idVenta, I20&"", montoTotal, M20, pagos, IFERROR(SUMIF(Aux_Datos!$B:$B, idVenta, Aux_Datos!$K:$K), 0), retenciones, IFERROR(SUMIF(Aux_Datos!$N:$N, idVenta, Aux_Datos!$R:$R), 0), pagos + retenciones ) -> 68.911963 | Q20: =IF(P20=0, "Sin Pago", LET( idVenta, I20&"", montoTotalPagado, P20, pagoUSD, IFERROR(SUMIFS(Aux_Datos!$C:$C, Aux_Datos!$B:$B, idVenta, Aux_Datos!$D:$D, "USD"), 0), pagoVES, IFERROR(SUMIFS(Aux_Datos!$C:$C, Aux_Datos!$B:$B, idVenta, Aux_Datos!$D:$D, "VES"), 0), IF(pagoUSD >= (montoTotalPagado * 0.84), "USD", IF(pagoVES >= (montoTotalPagado * 0.84), "VES", "MIXTO")) ) ) -> VES | R20: =M20-P20 -> 0 | S20: =IF(P20=0, "Sin Pago", IFERROR( MAXIFS(Aux_Datos!$A:$A, Aux_Datos!$B:$B, I20&""), IFERROR(MAXIFS(Aux_Datos!$A:$A, Aux_Datos!$B:$B, VALUE(I20)), "Revisar ID") ) ) -> 46086 | T20: =IF(R20<=0, "PAGADA", IF(P20>0, "PAGO PARCIAL", "PENDIENTE")) -> PAGADA | U20: =IF(AND(T20<>"PAGADA", L20<TODAY()), "CRÍTICO: VENCIDA", IF(T20="PAGADA", "SOLVENTE", "EN TIEMPO")) -> SOLVENTE | V20: =IF(T20="PAGADA", 0, IF(S20 < TODAY(), TODAY() - S20, 0)) -> 0 | W20: =IF(P20=0, "Sin Pago", LET( monedaPago, Q20, descuentoAplicado, G20, limitePermitido, IFERROR(VLOOKUP(monedaPago, 'Limites de Descuento'!$A$2:$B595, 2, FALSE), 0), IF(descuentoAplicado > limitePermitido, "ALERTA: EXCESO (" & TEXT(limitePermitido, "0%") & " máx)", "OK") ) ) -> OK | X20: =IF(OR(H20=0, S20="Sin Pago"), "", IF(AND(H20 > 0, S20 > (L20 + 2)), "⚠️ REVISAR DESCUENTO", "OK")) | Y20: 68.911963 | Z20: CUMPLE
A21: S00029 | B21: 46090.243 | C21: AUTOREPUESTOS SION C.A. | D21: TORO ARDILES DAVID JOSE | E21: 261.98 | F21: 7 días | G21: =IF($E21=0,0,IF(SUMIF(Aux_Datos!$B:$B,$I21,Aux_Datos!$K:$K)/$E21>=VLOOKUP(IF(COUNTIFS(Aux_Datos!$B:$B,$I21,Aux_Datos!$D:$D,"<>USD")=0,"USD","VES"),'Limites de Descuento'!$A$2:$D$4,4,FALSE),MAX(0,1-SUMIF(Aux_Datos!$B:$B,$I21,Aux_Datos!$K:$K)/$E21),0)) -> 0.24421712 | I21: =VALUE(MID(A21,2,LEN(A21))) -> 29 | J21: =INT(B21) -> 46090 | K21: =IF(F21="Pago inmediato", 0, IF(F21="", "", IFERROR(VALUE(MID(F21, 1, SEARCH(" ", F21)-1)), ""))) -> 7 | L21: =J21+K21+1 -> 46098 | M21: =E21-(E21*G21)-(E21*H21) -> 198 | N21: =IF(T21="PAGADA", 0, IF(L21 < TODAY(), TODAY() - L21, 0)) -> 0 | O21: =IF(T21="PAGADA", "PAGADA", IF(L21 < TODAY(), "VENCIDA", "EN TIEMPO")) -> PAGADA | P21: =LET( idVenta, I21&"", montoTotal, M21, pagos, IFERROR(SUMIF(Aux_Datos!$B:$B, idVenta, Aux_Datos!$K:$K), 0), retenciones, IFERROR(SUMIF(Aux_Datos!$N:$N, idVenta, Aux_Datos!$R:$R), 0), pagos + retenciones ) -> 198 | Q21: =IF(P21=0, "Sin Pago", LET( idVenta, I21&"", montoTotalPagado, P21, pagoUSD, IFERROR(SUMIFS(Aux_Datos!$C:$C, Aux_Datos!$B:$B, idVenta, Aux_Datos!$D:$D, "USD"), 0), pagoVES, IFERROR(SUMIFS(Aux_Datos!$C:$C, Aux_Datos!$B:$B, idVenta, Aux_Datos!$D:$D, "VES"), 0), IF(pagoUSD >= (montoTotalPagado * 0.84), "USD", IF(pagoVES >= (montoTotalPagado * 0.84), "VES", "MIXTO")) ) ) -> USD | R21: =M21-P21 -> 0 | S21: =IF(P21=0, "Sin Pago", IFERROR( MAXIFS(Aux_Datos!$A:$A, Aux_Datos!$B:$B, I21&""), IFERROR(MAXIFS(Aux_Datos!$A:$A, Aux_Datos!$B:$B, VALUE(I21)), "Revisar ID") ) ) -> 46134 | T21: =IF(R21<=0, "PAGADA", IF(P21>0, "PAGO PARCIAL", "PENDIENTE")) -> PAGADA | U21: =IF(AND(T21<>"PAGADA", L21<TODAY()), "CRÍTICO: VENCIDA", IF(T21="PAGADA", "SOLVENTE", "EN TIEMPO")) -> SOLVENTE | V21: =IF(T21="PAGADA", 0, IF(S21 < TODAY(), TODAY() - S21, 0)) -> 0 | W21: =IF(P21=0, "Sin Pago", LET( monedaPago, Q21, descuentoAplicado, G21, limitePermitido, IFERROR(VLOOKUP(monedaPago, 'Limites de Descuento'!$A$2:$B595, 2, FALSE), 0), IF(descuentoAplicado > limitePermitido, "ALERTA: EXCESO (" & TEXT(limitePermitido, "0%") & " máx)", "OK") ) ) -> OK | X21: =IF(OR(H21=0, S21="Sin Pago"), "", IF(AND(H21 > 0, S21 > (L21 + 2)), "⚠️ REVISAR DESCUENTO", "OK")) | Y21: 198 | Z21: CUMPLE
A22: S00030 | B22: 46090.244 | C22: HIDRAULICAS CAICEDO C.A. | D22: VILLABONA CORREA ALBA ESTEFANIA | E22: 146.08 | F22: 7 días | G22: =IF($E22=0,0,IF(SUMIF(Aux_Datos!$B:$B,$I22,Aux_Datos!$K:$K)/$E22>=VLOOKUP(IF(COUNTIFS(Aux_Datos!$B:$B,$I22,Aux_Datos!$D:$D,"<>USD")=0,"USD","VES"),'Limites de Descuento'!$A$2:$D$4,4,FALSE),MAX(0,1-SUMIF(Aux_Datos!$B:$B,$I22,Aux_Datos!$K:$K)/$E22),0)) -> 0.00054764513 | I22: =VALUE(MID(A22,2,LEN(A22))) -> 30 | J22: =INT(B22) -> 46090 | K22: =IF(F22="Pago inmediato", 0, IF(F22="", "", IFERROR(VALUE(MID(F22, 1, SEARCH(" ", F22)-1)), ""))) -> 7 | L22: =J22+K22+1 -> 46098 | M22: =E22-(E22*G22)-(E22*H22) -> 146 | N22: =IF(T22="PAGADA", 0, IF(L22 < TODAY(), TODAY() - L22, 0)) -> 0 | O22: =IF(T22="PAGADA", "PAGADA", IF(L22 < TODAY(), "VENCIDA", "EN TIEMPO")) -> PAGADA | P22: =LET( idVenta, I22&"", montoTotal, M22, pagos, IFERROR(SUMIF(Aux_Datos!$B:$B, idVenta, Aux_Datos!$K:$K), 0), retenciones, IFERROR(SUMIF(Aux_Datos!$N:$N, idVenta, Aux_Datos!$R:$R), 0), pagos + retenciones ) -> 146 | Q22: =IF(P22=0, "Sin Pago", LET( idVenta, I22&"", montoTotalPagado, P22, pagoUSD, IFERROR(SUMIFS(Aux_Datos!$C:$C, Aux_Datos!$B:$B, idVenta, Aux_Datos!$D:$D, "USD"), 0), pagoVES, IFERROR(SUMIFS(Aux_Datos!$C:$C, Aux_Datos!$B:$B, idVenta, Aux_Datos!$D:$D, "VES"), 0), IF(pagoUSD >= (montoTotalPagado * 0.84), "USD", IF(pagoVES >= (montoTotalPagado * 0.84), "VES", "MIXTO")) ) ) -> USD | R22: =M22-P22 -> 0 | S22: =IF(P22=0, "Sin Pago", IFERROR( MAXIFS(Aux_Datos!$A:$A, Aux_Datos!$B:$B, I22&""), IFERROR(MAXIFS(Aux_Datos!$A:$A, Aux_Datos!$B:$B, VALUE(I22)), "Revisar ID") ) ) -> 46098 | T22: =IF(R22<=0, "PAGADA", IF(P22>0, "PAGO PARCIAL", "PENDIENTE")) -> PAGADA | U22: =IF(AND(T22<>"PAGADA", L22<TODAY()), "CRÍTICO: VENCIDA", IF(T22="PAGADA", "SOLVENTE", "EN TIEMPO")) -> SOLVENTE | V22: =IF(T22="PAGADA", 0, IF(S22 < TODAY(), TODAY() - S22, 0)) -> 0 | W22: =IF(P22=0, "Sin Pago", LET( monedaPago, Q22, descuentoAplicado, G22, limitePermitido, IFERROR(VLOOKUP(monedaPago, 'Limites de Descuento'!$A$2:$B595, 2, FALSE), 0), IF(descuentoAplicado > limitePermitido, "ALERTA: EXCESO (" & TEXT(limitePermitido, "0%") & " máx)", "OK") ) ) -> OK | X22: =IF(OR(H22=0, S22="Sin Pago"), "", IF(AND(H22 > 0, S22 > (L22 + 2)), "⚠️ REVISAR DESCUENTO", "OK")) | Y22: 146 | Z22: CUMPLE
A23: S00031 | B23: 46090.243 | C23: COMERCIAL REPUESTOS MUNDIALES RMS 2022 C.A. | D23: TORO ARDILES DAVID JOSE | E23: 289.16 | F23: 7 días | G23: =IF($E23=0,0,IF(SUMIF(Aux_Datos!$B:$B,$I23,Aux_Datos!$K:$K)/$E23>=VLOOKUP(IF(COUNTIFS(Aux_Datos!$B:$B,$I23,Aux_Datos!$D:$D,"<>USD")=0,"USD","VES"),'Limites de Descuento'!$A$2:$D$4,4,FALSE),MAX(0,1-SUMIF(Aux_Datos!$B:$B,$I23,Aux_Datos!$K:$K)/$E23),0)) -> 0 | I23: =VALUE(MID(A23,2,LEN(A23))) -> 31 | J23: =INT(B23) -> 46090 | K23: =IF(F23="Pago inmediato", 0, IF(F23="", "", IFERROR(VALUE(MID(F23, 1, SEARCH(" ", F23)-1)), ""))) -> 7 | L23: =J23+K23+1 -> 46098 | M23: =E23-(E23*G23)-(E23*H23) -> 289.16 | N23: =IF(T23="PAGADA", 0, IF(L23 < TODAY(), TODAY() - L23, 0)) -> 102 | O23: =IF(T23="PAGADA", "PAGADA", IF(L23 < TODAY(), "VENCIDA", "EN TIEMPO")) -> VENCIDA | P23: =LET( idVenta, I23&"", montoTotal, M23, pagos, IFERROR(SUMIF(Aux_Datos!$B:$B, idVenta, Aux_Datos!$K:$K), 0), retenciones, IFERROR(SUMIF(Aux_Datos!$N:$N, idVenta, Aux_Datos!$R:$R), 0), pagos + retenciones ) -> 50 | Q23: =IF(P23=0, "Sin Pago", LET( idVenta, I23&"", montoTotalPagado, P23, pagoUSD, IFERROR(SUMIFS(Aux_Datos!$C:$C, Aux_Datos!$B:$B, idVenta, Aux_Datos!$D:$D, "USD"), 0), pagoVES, IFERROR(SUMIFS(Aux_Datos!$C:$C, Aux_Datos!$B:$B, idVenta, Aux_Datos!$D:$D, "VES"), 0), IF(pagoUSD >= (montoTotalPagado * 0.84), "USD", IF(pagoVES >= (montoTotalPagado * 0.84), "VES", "MIXTO")) ) ) -> VES | R23: =M23-P23 -> 239.16 | S23: =IF(P23=0, "Sin Pago", IFERROR( MAXIFS(Aux_Datos!$A:$A, Aux_Datos!$B:$B, I23&""), IFERROR(MAXIFS(Aux_Datos!$A:$A, Aux_Datos!$B:$B, VALUE(I23)), "Revisar ID") ) ) -> 46183 | T23: =IF(R23<=0, "PAGADA", IF(P23>0, "PAGO PARCIAL", "PENDIENTE")) -> PAGO PARCIAL | U23: =IF(AND(T23<>"PAGADA", L23<TODAY()), "CRÍTICO: VENCIDA", IF(T23="PAGADA", "SOLVENTE", "EN TIEMPO")) -> CRÍTICO: VENCIDA | V23: =IF(T23="PAGADA", 0, IF(S23 < TODAY(), TODAY() - S23, 0)) -> 17 | W23: =IF(P23=0, "Sin Pago", LET( monedaPago, Q23, descuentoAplicado, G23, limitePermitido, IFERROR(VLOOKUP(monedaPago, 'Limites de Descuento'!$A$2:$B595, 2, FALSE), 0), IF(descuentoAplicado > limitePermitido, "ALERTA: EXCESO (" & TEXT(limitePermitido, "0%") & " máx)", "OK") ) ) -> OK | X23: =IF(OR(H23=0, S23="Sin Pago"), "", IF(AND(H23 > 0, S23 > (L23 + 2)), "⚠️ REVISAR DESCUENTO", "OK")) | Y23: 50 | Z23: NO CUMPLE
A24: S00032 | B24: 46090.243 | C24: Ferretería JJ Martins c.a | D24: TORO ARDILES DAVID JOSE | E24: 101 | F24: 7 días | G24: =IF($E24=0,0,IF(SUMIF(Aux_Datos!$B:$B,$I24,Aux_Datos!$K:$K)/$E24>=VLOOKUP(IF(COUNTIFS(Aux_Datos!$B:$B,$I24,Aux_Datos!$D:$D,"<>USD")=0,"USD","VES"),'Limites de Descuento'!$A$2:$D$4,4,FALSE),MAX(0,1-SUMIF(Aux_Datos!$B:$B,$I24,Aux_Datos!$K:$K)/$E24),0)) -> 0.14156227 | I24: =VALUE(MID(A24,2,LEN(A24))) -> 32 | J24: =INT(B24) -> 46090 | K24: =IF(F24="Pago inmediato", 0, IF(F24="", "", IFERROR(VALUE(MID(F24, 1, SEARCH(" ", F24)-1)), ""))) -> 7 | L24: =J24+K24+1 -> 46098 | M24: =E24-(E24*G24)-(E24*H24) -> 86.70221 | N24: =IF(T24="PAGADA", 0, IF(L24 < TODAY(), TODAY() - L24, 0)) -> 0 | O24: =IF(T24="PAGADA", "PAGADA", IF(L24 < TODAY(), "VENCIDA", "EN TIEMPO")) -> PAGADA | P24: =LET( idVenta, I24&"", montoTotal, M24, pagos, IFERROR(SUMIF(Aux_Datos!$B:$B, idVenta, Aux_Datos!$K:$K), 0), retenciones, IFERROR(SUMIF(Aux_Datos!$N:$N, idVenta, Aux_Datos!$R:$R), 0), pagos + retenciones ) -> 86.70221 | Q24: =IF(P24=0, "Sin Pago", LET( idVenta, I24&"", montoTotalPagado, P24, pagoUSD, IFERROR(SUMIFS(Aux_Datos!$C:$C, Aux_Datos!$B:$B, idVenta, Aux_Datos!$D:$D, "USD"), 0), pagoVES, IFERROR(SUMIFS(Aux_Datos!$C:$C, Aux_Datos!$B:$B, idVenta, Aux_Datos!$D:$D, "VES"), 0), IF(pagoUSD >= (montoTotalPagado * 0.84), "USD", IF(pagoVES >= (montoTotalPagado * 0.84), "VES", "MIXTO")) ) ) -> VES | R24: =M24-P24 -> 0 | S24: =IF(P24=0, "Sin Pago", IFERROR( MAXIFS(Aux_Datos!$A:$A, Aux_Datos!$B:$B, I24&""), IFERROR(MAXIFS(Aux_Datos!$A:$A, Aux_Datos!$B:$B, VALUE(I24)), "Revisar ID") ) ) -> 46086 | T24: =IF(R24<=0, "PAGADA", IF(P24>0, "PAGO PARCIAL", "PENDIENTE")) -> PAGADA | U24: =IF(AND(T24<>"PAGADA", L24<TODAY()), "CRÍTICO: VENCIDA", IF(T24="PAGADA", "SOLVENTE", "EN TIEMPO")) -> SOLVENTE | V24: =IF(T24="PAGADA", 0, IF(S24 < TODAY(), TODAY() - S24, 0)) -> 0 | W24: =IF(P24=0, "Sin Pago", LET( monedaPago, Q24, descuentoAplicado, G24, limitePermitido, IFERROR(VLOOKUP(monedaPago, 'Limites de Descuento'!$A$2:$B595, 2, FALSE), 0), IF(descuentoAplicado > limitePermitido, "ALERTA: EXCESO (" & TEXT(limitePermitido, "0%") & " máx)", "OK") ) ) -> OK | X24: =IF(OR(H24=0, S24="Sin Pago"), "", IF(AND(H24 > 0, S24 > (L24 + 2)), "⚠️ REVISAR DESCUENTO", "OK")) | Y24: 86.70221 | Z24: CUMPLE
A25: S00033 | B25: 46086.364 | C25: Angel ARMAS | D25: REVERON DE CONTRERAS MELANI AUSMAR | E25: 243.01 | F25: Pago inmediato | G25: =IF($E25=0,0,IF(SUMIF(Aux_Datos!$B:$B,$I25,Aux_Datos!$K:$K)/$E25>=VLOOKUP(IF(COUNTIFS(Aux_Datos!$B:$B,$I25,Aux_Datos!$D:$D,"<>USD")=0,"USD","VES"),'Limites de Descuento'!$A$2:$D$4,4,FALSE),MAX(0,1-SUMIF(Aux_Datos!$B:$B,$I25,Aux_Datos!$K:$K)/$E25),0)) -> 0.19756389 | I25: =VALUE(MID(A25,2,LEN(A25))) -> 33 | J25: =INT(B25) -> 46086 | K25: =IF(F25="Pago inmediato", 0, IF(F25="", "", IFERROR(VALUE(MID(F25, 1, SEARCH(" ", F25)-1)), ""))) -> 0 | L25: =J25+K25+1 -> 46087 | M25: =E25-(E25*G25)-(E25*H25) -> 195 | N25: =IF(T25="PAGADA", 0, IF(L25 < TODAY(), TODAY() - L25, 0)) -> 0 | O25: =IF(T25="PAGADA", "PAGADA", IF(L25 < TODAY(), "VENCIDA", "EN TIEMPO")) -> PAGADA | P25: =LET( idVenta, I25&"", montoTotal, M25, pagos, IFERROR(SUMIF(Aux_Datos!$B:$B, idVenta, Aux_Datos!$K:$K), 0), retenciones, IFERROR(SUMIF(Aux_Datos!$N:$N, idVenta, Aux_Datos!$R:$R), 0), pagos + retenciones ) -> 195 | Q25: =IF(P25=0, "Sin Pago", LET( idVenta, I25&"", montoTotalPagado, P25, pagoUSD, IFERROR(SUMIFS(Aux_Datos!$C:$C, Aux_Datos!$B:$B, idVenta, Aux_Datos!$D:$D, "USD"), 0), pagoVES, IFERROR(SUMIFS(Aux_Datos!$C:$C, Aux_Datos!$B:$B, idVenta, Aux_Datos!$D:$D, "VES"), 0), IF(pagoUSD >= (montoTotalPagado * 0.84), "USD", IF(pagoVES >= (montoTotalPagado * 0.84), "VES", "MIXTO")) ) ) -> USD | R25: =M25-P25 -> 0 | S25: =IF(P25=0, "Sin Pago", IFERROR( MAXIFS(Aux_Datos!$A:$A, Aux_Datos!$B:$B, I25&""), IFERROR(MAXIFS(Aux_Datos!$A:$A, Aux_Datos!$B:$B, VALUE(I25)), "Revisar ID") ) ) -> 46086 | T25: =IF(R25<=0, "PAGADA", IF(P25>0, "PAGO PARCIAL", "PENDIENTE")) -> PAGADA | U25: =IF(AND(T25<>"PAGADA", L25<TODAY()), "CRÍTICO: VENCIDA", IF(T25="PAGADA", "SOLVENTE", "EN TIEMPO")) -> SOLVENTE | V25: =IF(T25="PAGADA", 0, IF(S25 < TODAY(), TODAY() - S25, 0)) -> 0 | W25: =IF(P25=0, "Sin Pago", LET( monedaPago, Q25, descuentoAplicado, G25, limitePermitido, IFERROR(VLOOKUP(monedaPago, 'Limites de Descuento'!$A$2:$B595, 2, FALSE), 0), IF(descuentoAplicado > limitePermitido, "ALERTA: EXCESO (" & TEXT(limitePermitido, "0%") & " máx)", "OK") ) ) -> OK | X25: =IF(OR(H25=0, S25="Sin Pago"), "", IF(AND(H25 > 0, S25 > (L25 + 2)), "⚠️ REVISAR DESCUENTO", "OK")) | Y25: 195 | Z25: CUMPLE
A26: S00034 | B26: 46090.244 | C26: Miguel Antonio Chacon | D26: GRIMAN DIAZ HECTOR EDUARDO | E26: 185.04 | F26: 15 días | G26: =IF($E26=0,0,IF(SUMIF(Aux_Datos!$B:$B,$I26,Aux_Datos!$K:$K)/$E26>=VLOOKUP(IF(COUNTIFS(Aux_Datos!$B:$B,$I26,Aux_Datos!$D:$D,"<>USD")=0,"USD","VES"),'Limites de Descuento'!$A$2:$D$4,4,FALSE),MAX(0,1-SUMIF(Aux_Datos!$B:$B,$I26,Aux_Datos!$K:$K)/$E26),0)) -> 0 | I26: =VALUE(MID(A26,2,LEN(A26))) -> 34 | J26: =INT(B26) -> 46090 | K26: =IF(F26="Pago inmediato", 0, IF(F26="", "", IFERROR(VALUE(MID(F26, 1, SEARCH(" ", F26)-1)), ""))) -> 15 | L26: =J26+K26+1 -> 46106 | M26: =E26-(E26*G26)-(E26*H26) -> 185.04 | N26: =IF(T26="PAGADA", 0, IF(L26 < TODAY(), TODAY() - L26, 0)) -> 0 | O26: =IF(T26="PAGADA", "PAGADA", IF(L26 < TODAY(), "VENCIDA", "EN TIEMPO")) -> PAGADA | P26: =LET( idVenta, I26&"", montoTotal, M26, pagos, IFERROR(SUMIF(Aux_Datos!$B:$B, idVenta, Aux_Datos!$K:$K), 0), retenciones, IFERROR(SUMIF(Aux_Datos!$N:$N, idVenta, Aux_Datos!$R:$R), 0), pagos + retenciones ) -> 204.98768 | Q26: =IF(P26=0, "Sin Pago", LET( idVenta, I26&"", montoTotalPagado, P26, pagoUSD, IFERROR(SUMIFS(Aux_Datos!$C:$C, Aux_Datos!$B:$B, idVenta, Aux_Datos!$D:$D, "USD"), 0), pagoVES, IFERROR(SUMIFS(Aux_Datos!$C:$C, Aux_Datos!$B:$B, idVenta, Aux_Datos!$D:$D, "VES"), 0), IF(pagoUSD >= (montoTotalPagado * 0.84), "USD", IF(pagoVES >= (montoTotalPagado * 0.84), "VES", "MIXTO")) ) ) -> VES | R26: =M26-P26 -> -19.947685 | S26: =IF(P26=0, "Sin Pago", IFERROR( MAXIFS(Aux_Datos!$A:$A, Aux_Datos!$B:$B, I26&""), IFERROR(MAXIFS(Aux_Datos!$A:$A, Aux_Datos!$B:$B, VALUE(I26)), "Revisar ID") ) ) -> 46140 | T26: =IF(R26<=0, "PAGADA", IF(P26>0, "PAGO PARCIAL", "PENDIENTE")) -> PAGADA | U26: =IF(AND(T26<>"PAGADA", L26<TODAY()), "CRÍTICO: VENCIDA", IF(T26="PAGADA", "SOLVENTE", "EN TIEMPO")) -> SOLVENTE | V26: =IF(T26="PAGADA", 0, IF(S26 < TODAY(), TODAY() - S26, 0)) -> 0 | W26: =IF(P26=0, "Sin Pago", LET( monedaPago, Q26, descuentoAplicado, G26, limitePermitido, IFERROR(VLOOKUP(monedaPago, 'Limites de Descuento'!$A$2:$B595, 2, FALSE), 0), IF(descuentoAplicado > limitePermitido, "ALERTA: EXCESO (" & TEXT(limitePermitido, "0%") & " máx)", "OK") ) ) -> OK | X26: =IF(OR(H26=0, S26="Sin Pago"), "", IF(AND(H26 > 0, S26 > (L26 + 2)), "⚠️ REVISAR DESCUENTO", "OK")) | Y26: 204.98768 | Z26: CUMPLE
A27: S00036 | B27: 46090.244 | C27: inversiones El Gran Charles C.A | D27: GRIMAN DIAZ HECTOR EDUARDO | E27: 434.83 | F27: 15 días | G27: =IF($E27=0,0,IF(SUMIF(Aux_Datos!$B:$B,$I27,Aux_Datos!$K:$K)/$E27>=VLOOKUP(IF(COUNTIFS(Aux_Datos!$B:$B,$I27,Aux_Datos!$D:$D,"<>USD")=0,"USD","VES"),'Limites de Descuento'!$A$2:$D$4,4,FALSE),MAX(0,1-SUMIF(Aux_Datos!$B:$B,$I27,Aux_Datos!$K:$K)/$E27),0)) -> 0 | I27: =VALUE(MID(A27,2,LEN(A27))) -> 36 | J27: =INT(B27) -> 46090 | K27: =IF(F27="Pago inmediato", 0, IF(F27="", "", IFERROR(VALUE(MID(F27, 1, SEARCH(" ", F27)-1)), ""))) -> 15 | L27: =J27+K27+1 -> 46106 | M27: =E27-(E27*G27)-(E27*H27) -> 434.83 | N27: =IF(T27="PAGADA", 0, IF(L27 < TODAY(), TODAY() - L27, 0)) -> 94 | O27: =IF(T27="PAGADA", "PAGADA", IF(L27 < TODAY(), "VENCIDA", "EN TIEMPO")) -> VENCIDA | P27: =LET( idVenta, I27&"", montoTotal, M27, pagos, IFERROR(SUMIF(Aux_Datos!$B:$B, idVenta, Aux_Datos!$K:$K), 0), retenciones, IFERROR(SUMIF(Aux_Datos!$N:$N, idVenta, Aux_Datos!$R:$R), 0), pagos + retenciones ) -> 208.01027 | Q27: =IF(P27=0, "Sin Pago", LET( idVenta, I27&"", montoTotalPagado, P27, pagoUSD, IFERROR(SUMIFS(Aux_Datos!$C:$C, Aux_Datos!$B:$B, idVenta, Aux_Datos!$D:$D, "USD"), 0), pagoVES, IFERROR(SUMIFS(Aux_Datos!$C:$C, Aux_Datos!$B:$B, idVenta, Aux_Datos!$D:$D, "VES"), 0), IF(pagoUSD >= (montoTotalPagado * 0.84), "USD", IF(pagoVES >= (montoTotalPagado * 0.84), "VES", "MIXTO")) ) ) -> VES | R27: =M27-P27 -> 226.81973 | S27: =IF(P27=0, "Sin Pago", IFERROR( MAXIFS(Aux_Datos!$A:$A, Aux_Datos!$B:$B, I27&""), IFERROR(MAXIFS(Aux_Datos!$A:$A, Aux_Datos!$B:$B, VALUE(I27)), "Revisar ID") ) ) -> 46196 | T27: =IF(R27<=0, "PAGADA", IF(P27>0, "PAGO PARCIAL", "PENDIENTE")) -> PAGO PARCIAL | U27: =IF(AND(T27<>"PAGADA", L27<TODAY()), "CRÍTICO: VENCIDA", IF(T27="PAGADA", "SOLVENTE", "EN TIEMPO")) -> CRÍTICO: VENCIDA | V27: =IF(T27="PAGADA", 0, IF(S27 < TODAY(), TODAY() - S27, 0)) -> 4 | W27: =IF(P27=0, "Sin Pago", LET( monedaPago, Q27, descuentoAplicado, G27, limitePermitido, IFERROR(VLOOKUP(monedaPago, 'Limites de Descuento'!$A$2:$B595, 2, FALSE), 0), IF(descuentoAplicado > limitePermitido, "ALERTA: EXCESO (" & TEXT(limitePermitido, "0%") & " máx)", "OK") ) ) -> OK | X27: =IF(OR(H27=0, S27="Sin Pago"), "", IF(AND(H27 > 0, S27 > (L27 + 2)), "⚠️ REVISAR DESCUENTO", "OK")) | Y27: 208.01027 | Z27: NO CUMPLE
A28: S00037 | B28: 46090.255 | C28: Junior Marco Antonio Vivas Navas | D28: TORO ARDILES DAVID JOSE | E28: 75 | F28: 7 días | G28: =IF($E28=0,0,IF(SUMIF(Aux_Datos!$B:$B,$I28,Aux_Datos!$K:$K)/$E28>=VLOOKUP(IF(COUNTIFS(Aux_Datos!$B:$B,$I28,Aux_Datos!$D:$D,"<>USD")=0,"USD","VES"),'Limites de Descuento'!$A$2:$D$4,4,FALSE),MAX(0,1-SUMIF(Aux_Datos!$B:$B,$I28,Aux_Datos!$K:$K)/$E28),0)) -> 0.22666667 | I28: =VALUE(MID(A28,2,LEN(A28))) -> 37 | J28: =INT(B28) -> 46090 | K28: =IF(F28="Pago inmediato", 0, IF(F28="", "", IFERROR(VALUE(MID(F28, 1, SEARCH(" ", F28)-1)), ""))) -> 7 | L28: =J28+K28+1 -> 46098 | M28: =E28-(E28*G28)-(E28*H28) -> 58 | N28: =IF(T28="PAGADA", 0, IF(L28 < TODAY(), TODAY() - L28, 0)) -> 0 | O28: =IF(T28="PAGADA", "PAGADA", IF(L28 < TODAY(), "VENCIDA", "EN TIEMPO")) -> PAGADA | P28: =LET( idVenta, I28&"", montoTotal, M28, pagos, IFERROR(SUMIF(Aux_Datos!$B:$B, idVenta, Aux_Datos!$K:$K), 0), retenciones, IFERROR(SUMIF(Aux_Datos!$N:$N, idVenta, Aux_Datos!$R:$R), 0), pagos + retenciones ) -> 58 | Q28: =IF(P28=0, "Sin Pago", LET( idVenta, I28&"", montoTotalPagado, P28, pagoUSD, IFERROR(SUMIFS(Aux_Datos!$C:$C, Aux_Datos!$B:$B, idVenta, Aux_Datos!$D:$D, "USD"), 0), pagoVES, IFERROR(SUMIFS(Aux_Datos!$C:$C, Aux_Datos!$B:$B, idVenta, Aux_Datos!$D:$D, "VES"), 0), IF(pagoUSD >= (montoTotalPagado * 0.84), "USD", IF(pagoVES >= (montoTotalPagado * 0.84), "VES", "MIXTO")) ) ) -> USD | R28: =M28-P28 -> 0 | S28: =IF(P28=0, "Sin Pago", IFERROR( MAXIFS(Aux_Datos!$A:$A, Aux_Datos!$B:$B, I28&""), IFERROR(MAXIFS(Aux_Datos!$A:$A, Aux_Datos!$B:$B, VALUE(I28)), "Revisar ID") ) ) -> 46121 | T28: =IF(R28<=0, "PAGADA", IF(P28>0, "PAGO PARCIAL", "PENDIENTE")) -> PAGADA | U28: =IF(AND(T28<>"PAGADA", L28<TODAY()), "CRÍTICO: VENCIDA", IF(T28="PAGADA", "SOLVENTE", "EN TIEMPO")) -> SOLVENTE | V28: =IF(T28="PAGADA", 0, IF(S28 < TODAY(), TODAY() - S28, 0)) -> 0 | W28: =IF(P28=0, "Sin Pago", LET( monedaPago, Q28, descuentoAplicado, G28, limitePermitido, IFERROR(VLOOKUP(monedaPago, 'Limites de Descuento'!$A$2:$B595, 2, FALSE), 0), IF(descuentoAplicado > limitePermitido, "ALERTA: EXCESO (" & TEXT(limitePermitido, "0%") & " máx)", "OK") ) ) -> OK | X28: =IF(OR(H28=0, S28="Sin Pago"), "", IF(AND(H28 > 0, S28 > (L28 + 2)), "⚠️ REVISAR DESCUENTO", "OK")) | Y28: 58 | Z28: CUMPLE
A29: S00038 | B29: 46090.255 | C29: Auto repuestos Fontalvo | D29: MARTINEZ MONTES JEFFREY ENRIQUE | E29: 90.02 | F29: 15 días | G29: =IF($E29=0,0,IF(SUMIF(Aux_Datos!$B:$B,$I29,Aux_Datos!$K:$K)/$E29>=VLOOKUP(IF(COUNTIFS(Aux_Datos!$B:$B,$I29,Aux_Datos!$D:$D,"<>USD")=0,"USD","VES"),'Limites de Descuento'!$A$2:$D$4,4,FALSE),MAX(0,1-SUMIF(Aux_Datos!$B:$B,$I29,Aux_Datos!$K:$K)/$E29),0)) -> 0.20017774 | I29: =VALUE(MID(A29,2,LEN(A29))) -> 38 | J29: =INT(B29) -> 46090 | K29: =IF(F29="Pago inmediato", 0, IF(F29="", "", IFERROR(VALUE(MID(F29, 1, SEARCH(" ", F29)-1)), ""))) -> 15 | L29: =J29+K29+1 -> 46106 | M29: =E29-(E29*G29)-(E29*H29) -> 72 | N29: =IF(T29="PAGADA", 0, IF(L29 < TODAY(), TODAY() - L29, 0)) -> 0 | O29: =IF(T29="PAGADA", "PAGADA", IF(L29 < TODAY(), "VENCIDA", "EN TIEMPO")) -> PAGADA | P29: =LET( idVenta, I29&"", montoTotal, M29, pagos, IFERROR(SUMIF(Aux_Datos!$B:$B, idVenta, Aux_Datos!$K:$K), 0), retenciones, IFERROR(SUMIF(Aux_Datos!$N:$N, idVenta, Aux_Datos!$R:$R), 0), pagos + retenciones ) -> 72 | Q29: =IF(P29=0, "Sin Pago", LET( idVenta, I29&"", montoTotalPagado, P29, pagoUSD, IFERROR(SUMIFS(Aux_Datos!$C:$C, Aux_Datos!$B:$B, idVenta, Aux_Datos!$D:$D, "USD"), 0), pagoVES, IFERROR(SUMIFS(Aux_Datos!$C:$C, Aux_Datos!$B:$B, idVenta, Aux_Datos!$D:$D, "VES"), 0), IF(pagoUSD >= (montoTotalPagado * 0.84), "USD", IF(pagoVES >= (montoTotalPagado * 0.84), "VES", "MIXTO")) ) ) -> USD | R29: =M29-P29 -> 0 | S29: =IF(P29=0, "Sin Pago", IFERROR( MAXIFS(Aux_Datos!$A:$A, Aux_Datos!$B:$B, I29&""), IFERROR(MAXIFS(Aux_Datos!$A:$A, Aux_Datos!$B:$B, VALUE(I29)), "Revisar ID") ) ) -> 46129 | T29: =IF(R29<=0, "PAGADA", IF(P29>0, "PAGO PARCIAL", "PENDIENTE")) -> PAGADA | U29: =IF(AND(T29<>"PAGADA", L29<TODAY()), "CRÍTICO: VENCIDA", IF(T29="PAGADA", "SOLVENTE", "EN TIEMPO")) -> SOLVENTE | V29: =IF(T29="PAGADA", 0, IF(S29 < TODAY(), TODAY() - S29, 0)) -> 0 | W29: =IF(P29=0, "Sin Pago", LET( monedaPago, Q29, descuentoAplicado, G29, limitePermitido, IFERROR(VLOOKUP(monedaPago, 'Limites de Descuento'!$A$2:$B595, 2, FALSE), 0), IF(descuentoAplicado > limitePermitido, "ALERTA: EXCESO (" & TEXT(limitePermitido, "0%") & " máx)", "OK") ) ) -> OK | X29: =IF(OR(H29=0, S29="Sin Pago"), "", IF(AND(H29 > 0, S29 > (L29 + 2)), "⚠️ REVISAR DESCUENTO", "OK")) | Y29: 72 | Z29: CUMPLE
A30: S00039 | B30: 46090.255 | C30: Moto Bestia, C.A | D30: OCANTO ZABALA ROSALVY DEL CARMEN | E30: 28.88 | F30: 7 días | G30: =IF($E30=0,0,IF(SUMIF(Aux_Datos!$B:$B,$I30,Aux_Datos!$K:$K)/$E30>=VLOOKUP(IF(COUNTIFS(Aux_Datos!$B:$B,$I30,Aux_Datos!$D:$D,"<>USD")=0,"USD","VES"),'Limites de Descuento'!$A$2:$D$4,4,FALSE),MAX(0,1-SUMIF(Aux_Datos!$B:$B,$I30,Aux_Datos!$K:$K)/$E30),0)) -> 0 | I30: =VALUE(MID(A30,2,LEN(A30))) -> 39 | J30: =INT(B30) -> 46090 | K30: =IF(F30="Pago inmediato", 0, IF(F30="", "", IFERROR(VALUE(MID(F30, 1, SEARCH(" ", F30)-1)), ""))) -> 7 | L30: =J30+K30+1 -> 46098 | M30: =E30-(E30*G30)-(E30*H30) -> 28.88 | N30: =IF(T30="PAGADA", 0, IF(L30 < TODAY(), TODAY() - L30, 0)) -> 0 | O30: =IF(T30="PAGADA", "PAGADA", IF(L30 < TODAY(), "VENCIDA", "EN TIEMPO")) -> PAGADA | P30: =LET( idVenta, I30&"", montoTotal, M30, pagos, IFERROR(SUMIF(Aux_Datos!$B:$B, idVenta, Aux_Datos!$K:$K), 0), retenciones, IFERROR(SUMIF(Aux_Datos!$N:$N, idVenta, Aux_Datos!$R:$R), 0), pagos + retenciones ) -> 29.157303 | Q30: =IF(P30=0, "Sin Pago", LET( idVenta, I30&"", montoTotalPagado, P30, pagoUSD, IFERROR(SUMIFS(Aux_Datos!$C:$C, Aux_Datos!$B:$B, idVenta, Aux_Datos!$D:$D, "USD"), 0), pagoVES, IFERROR(SUMIFS(Aux_Datos!$C:$C, Aux_Datos!$B:$B, idVenta, Aux_Datos!$D:$D, "VES"), 0), IF(pagoUSD >= (montoTotalPagado * 0.84), "USD", IF(pagoVES >= (montoTotalPagado * 0.84), "VES", "MIXTO")) ) ) -> VES | R30: =M30-P30 -> -0.27730285 | S30: =IF(P30=0, "Sin Pago", IFERROR( MAXIFS(Aux_Datos!$A:$A, Aux_Datos!$B:$B, I30&""), IFERROR(MAXIFS(Aux_Datos!$A:$A, Aux_Datos!$B:$B, VALUE(I30)), "Revisar ID") ) ) -> 46156 | T30: =IF(R30<=0, "PAGADA", IF(P30>0, "PAGO PARCIAL", "PENDIENTE")) -> PAGADA | U30: =IF(AND(T30<>"PAGADA", L30<TODAY()), "CRÍTICO: VENCIDA", IF(T30="PAGADA", "SOLVENTE", "EN TIEMPO")) -> SOLVENTE | V30: =IF(T30="PAGADA", 0, IF(S30 < TODAY(), TODAY() - S30, 0)) -> 0 | W30: =IF(P30=0, "Sin Pago", LET( monedaPago, Q30, descuentoAplicado, G30, limitePermitido, IFERROR(VLOOKUP(monedaPago, 'Limites de Descuento'!$A$2:$B595, 2, FALSE), 0), IF(descuentoAplicado > limitePermitido, "ALERTA: EXCESO (" & TEXT(limitePermitido, "0%") & " máx)", "OK") ) ) -> OK | X30: =IF(OR(H30=0, S30="Sin Pago"), "", IF(AND(H30 > 0, S30 > (L30 + 2)), "⚠️ REVISAR DESCUENTO", "OK")) | Y30: 29.157303 | Z30: CUMPLE
A31: S00040 | B31: 46090.255 | C31: WILLY MOTOR CAR REPUESTOS Y SERVICIOS, C.A. | D31: VILLABONA CORREA ALBA ESTEFANIA | E31: 1080.62 | F31: 7 días | G31: =IF($E31=0,0,IF(SUMIF(Aux_Datos!$B:$B,$I31,Aux_Datos!$K:$K)/$E31>=VLOOKUP(IF(COUNTIFS(Aux_Datos!$B:$B,$I31,Aux_Datos!$D:$D,"<>USD")=0,"USD","VES"),'Limites de Descuento'!$A$2:$D$4,4,FALSE),MAX(0,1-SUMIF(Aux_Datos!$B:$B,$I31,Aux_Datos!$K:$K)/$E31),0)) -> 0 | I31: =VALUE(MID(A31,2,LEN(A31))) -> 40 | J31: =INT(B31) -> 46090 | K31: =IF(F31="Pago inmediato", 0, IF(F31="", "", IFERROR(VALUE(MID(F31, 1, SEARCH(" ", F31)-1)), ""))) -> 7 | L31: =J31+K31+1 -> 46098 | M31: =E31-(E31*G31)-(E31*H31) -> 1080.62 | N31: =IF(T31="PAGADA", 0, IF(L31 < TODAY(), TODAY() - L31, 0)) -> 102 | O31: =IF(T31="PAGADA", "PAGADA", IF(L31 < TODAY(), "VENCIDA", "EN TIEMPO")) -> VENCIDA | P31: =LET( idVenta, I31&"", montoTotal, M31, pagos, IFERROR(SUMIF(Aux_Datos!$B:$B, idVenta, Aux_Datos!$K:$K), 0), retenciones, IFERROR(SUMIF(Aux_Datos!$N:$N, idVenta, Aux_Datos!$R:$R), 0), pagos + retenciones ) -> 120 | Q31: =IF(P31=0, "Sin Pago", LET( idVenta, I31&"", montoTotalPagado, P31, pagoUSD, IFERROR(SUMIFS(Aux_Datos!$C:$C, Aux_Datos!$B:$B, idVenta, Aux_Datos!$D:$D, "USD"), 0), pagoVES, IFERROR(SUMIFS(Aux_Datos!$C:$C, Aux_Datos!$B:$B, idVenta, Aux_Datos!$D:$D, "VES"), 0), IF(pagoUSD >= (montoTotalPagado * 0.84), "USD", IF(pagoVES >= (montoTotalPagado * 0.84), "VES", "MIXTO")) ) ) -> USD | R31: =M31-P31 -> 960.62 | S31: =IF(P31=0, "Sin Pago", IFERROR( MAXIFS(Aux_Datos!$A:$A, Aux_Datos!$B:$B, I31&""), IFERROR(MAXIFS(Aux_Datos!$A:$A, Aux_Datos!$B:$B, VALUE(I31)), "Revisar ID") ) ) -> 46156 | T31: =IF(R31<=0, "PAGADA", IF(P31>0, "PAGO PARCIAL", "PENDIENTE")) -> PAGO PARCIAL | U31: =IF(AND(T31<>"PAGADA", L31<TODAY()), "CRÍTICO: VENCIDA", IF(T31="PAGADA", "SOLVENTE", "EN TIEMPO")) -> CRÍTICO: VENCIDA | V31: =IF(T31="PAGADA", 0, IF(S31 < TODAY(), TODAY() - S31, 0)) -> 44 | W31: =IF(P31=0, "Sin Pago", LET( monedaPago, Q31, descuentoAplicado, G31, limitePermitido, IFERROR(VLOOKUP(monedaPago, 'Limites de Descuento'!$A$2:$B595, 2, FALSE), 0), IF(descuentoAplicado > limitePermitido, "ALERTA: EXCESO (" & TEXT(limitePermitido, "0%") & " máx)", "OK") ) ) -> OK | X31: =IF(OR(H31=0, S31="Sin Pago"), "", IF(AND(H31 > 0, S31 > (L31 + 2)), "⚠️ REVISAR DESCUENTO", "OK")) | Y31: 120 | Z31: NO CUMPLE
A32: S00041 | B32: 46090.255 | C32: Inversiones Trip K, c.a. | D32: VILLABONA CORREA ALBA ESTEFANIA | E32: 160.98 | F32: Pago inmediato | G32: =IF($E32=0,0,IF(SUMIF(Aux_Datos!$B:$B,$I32,Aux_Datos!$K:$K)/$E32>=VLOOKUP(IF(COUNTIFS(Aux_Datos!$B:$B,$I32,Aux_Datos!$D:$D,"<>USD")=0,"USD","VES"),'Limites de Descuento'!$A$2:$D$4,4,FALSE),MAX(0,1-SUMIF(Aux_Datos!$B:$B,$I32,Aux_Datos!$K:$K)/$E32),0)) -> 0 | I32: =VALUE(MID(A32,2,LEN(A32))) -> 41 | J32: =INT(B32) -> 46090 | K32: =IF(F32="Pago inmediato", 0, IF(F32="", "", IFERROR(VALUE(MID(F32, 1, SEARCH(" ", F32)-1)), ""))) -> 0 | L32: =J32+K32+1 -> 46091 | M32: =E32-(E32*G32)-(E32*H32) -> 160.98 | N32: =IF(T32="PAGADA", 0, IF(L32 < TODAY(), TODAY() - L32, 0)) -> 0 | O32: =IF(T32="PAGADA", "PAGADA", IF(L32 < TODAY(), "VENCIDA", "EN TIEMPO")) -> PAGADA | P32: =LET( idVenta, I32&"", montoTotal, M32, pagos, IFERROR(SUMIF(Aux_Datos!$B:$B, idVenta, Aux_Datos!$K:$K), 0), retenciones, IFERROR(SUMIF(Aux_Datos!$N:$N, idVenta, Aux_Datos!$R:$R), 0), pagos + retenciones ) -> 161.0005 | Q32: =IF(P32=0, "Sin Pago", LET( idVenta, I32&"", montoTotalPagado, P32, pagoUSD, IFERROR(SUMIFS(Aux_Datos!$C:$C, Aux_Datos!$B:$B, idVenta, Aux_Datos!$D:$D, "USD"), 0), pagoVES, IFERROR(SUMIFS(Aux_Datos!$C:$C, Aux_Datos!$B:$B, idVenta, Aux_Datos!$D:$D, "VES"), 0), IF(pagoUSD >= (montoTotalPagado * 0.84), "USD", IF(pagoVES >= (montoTotalPagado * 0.84), "VES", "MIXTO")) ) ) -> USD | R32: =M32-P32 -> -0.020500043 | S32: =IF(P32=0, "Sin Pago", IFERROR( MAXIFS(Aux_Datos!$A:$A, Aux_Datos!$B:$B, I32&""), IFERROR(MAXIFS(Aux_Datos!$A:$A, Aux_Datos!$B:$B, VALUE(I32)), "Revisar ID") ) ) -> 46134 | T32: =IF(R32<=0, "PAGADA", IF(P32>0, "PAGO PARCIAL", "PENDIENTE")) -> PAGADA | U32: =IF(AND(T32<>"PAGADA", L32<TODAY()), "CRÍTICO: VENCIDA", IF(T32="PAGADA", "SOLVENTE", "EN TIEMPO")) -> SOLVENTE | V32: =IF(T32="PAGADA", 0, IF(S32 < TODAY(), TODAY() - S32, 0)) -> 0 | W32: =IF(P32=0, "Sin Pago", LET( monedaPago, Q32, descuentoAplicado, G32, limitePermitido, IFERROR(VLOOKUP(monedaPago, 'Limites de Descuento'!$A$2:$B595, 2, FALSE), 0), IF(descuentoAplicado > limitePermitido, "ALERTA: EXCESO (" & TEXT(limitePermitido, "0%") & " máx)", "OK") ) ) -> OK | X32: =IF(OR(H32=0, S32="Sin Pago"), "", IF(AND(H32 > 0, S32 > (L32 + 2)), "⚠️ REVISAR DESCUENTO", "OK")) | Y32: 161.0005 | Z32: CUMPLE
A33: S00042 | B33: 46087.586 | C33: ALIPLUS TRASPORTE Y EQUIPOS, CA | D33: Marco Romero | E33: 151.96 | F33: 7 días | G33: =IF($E33=0,0,IF(SUMIF(Aux_Datos!$B:$B,$I33,Aux_Datos!$K:$K)/$E33>=VLOOKUP(IF(COUNTIFS(Aux_Datos!$B:$B,$I33,Aux_Datos!$D:$D,"<>USD")=0,"USD","VES"),'Limites de Descuento'!$A$2:$D$4,4,FALSE),MAX(0,1-SUMIF(Aux_Datos!$B:$B,$I33,Aux_Datos!$K:$K)/$E33),0)) -> 0.13793104 | I33: =VALUE(MID(A33,2,LEN(A33))) -> 42 | J33: =INT(B33) -> 46087 | K33: =IF(F33="Pago inmediato", 0, IF(F33="", "", IFERROR(VALUE(MID(F33, 1, SEARCH(" ", F33)-1)), ""))) -> 7 | L33: =J33+K33+1 -> 46095 | M33: =E33-(E33*G33)-(E33*H33) -> 131 | N33: =IF(T33="PAGADA", 0, IF(L33 < TODAY(), TODAY() - L33, 0)) -> 0 | O33: =IF(T33="PAGADA", "PAGADA", IF(L33 < TODAY(), "VENCIDA", "EN TIEMPO")) -> PAGADA | P33: =LET( idVenta, I33&"", montoTotal, M33, pagos, IFERROR(SUMIF(Aux_Datos!$B:$B, idVenta, Aux_Datos!$K:$K), 0), retenciones, IFERROR(SUMIF(Aux_Datos!$N:$N, idVenta, Aux_Datos!$R:$R), 0), pagos + retenciones ) -> 151.96001 | Q33: =IF(P33=0, "Sin Pago", LET( idVenta, I33&"", montoTotalPagado, P33, pagoUSD, IFERROR(SUMIFS(Aux_Datos!$C:$C, Aux_Datos!$B:$B, idVenta, Aux_Datos!$D:$D, "USD"), 0), pagoVES, IFERROR(SUMIFS(Aux_Datos!$C:$C, Aux_Datos!$B:$B, idVenta, Aux_Datos!$D:$D, "VES"), 0), IF(pagoUSD >= (montoTotalPagado * 0.84), "USD", IF(pagoVES >= (montoTotalPagado * 0.84), "VES", "MIXTO")) ) ) -> VES | R33: =M33-P33 -> -20.960007 | S33: =IF(P33=0, "Sin Pago", IFERROR( MAXIFS(Aux_Datos!$A:$A, Aux_Datos!$B:$B, I33&""), IFERROR(MAXIFS(Aux_Datos!$A:$A, Aux_Datos!$B:$B, VALUE(I33)), "Revisar ID") ) ) -> 46087 | T33: =IF(R33<=0, "PAGADA", IF(P33>0, "PAGO PARCIAL", "PENDIENTE")) -> PAGADA | U33: =IF(AND(T33<>"PAGADA", L33<TODAY()), "CRÍTICO: VENCIDA", IF(T33="PAGADA", "SOLVENTE", "EN TIEMPO")) -> SOLVENTE | V33: =IF(T33="PAGADA", 0, IF(S33 < TODAY(), TODAY() - S33, 0)) -> 0 | W33: =IF(P33=0, "Sin Pago", LET( monedaPago, Q33, descuentoAplicado, G33, limitePermitido, IFERROR(VLOOKUP(monedaPago, 'Limites de Descuento'!$A$2:$B595, 2, FALSE), 0), IF(descuentoAplicado > limitePermitido, "ALERTA: EXCESO (" & TEXT(limitePermitido, "0%") & " máx)", "OK") ) ) -> OK | X33: =IF(OR(H33=0, S33="Sin Pago"), "", IF(AND(H33 > 0, S33 > (L33 + 2)), "⚠️ REVISAR DESCUENTO", "OK")) | Y33: 131 | Z33: CUMPLE
A34: S00043 | B34: 46087.679 | C34: Vianney García | D34: BETANCOURT ROBRIGUEZ LUIS ENRRIQUE | E34: 362.52 | F34: 15 días | G34: =IF($E34=0,0,IF(SUMIF(Aux_Datos!$B:$B,$I34,Aux_Datos!$K:$K)/$E34>=VLOOKUP(IF(COUNTIFS(Aux_Datos!$B:$B,$I34,Aux_Datos!$D:$D,"<>USD")=0,"USD","VES"),'Limites de Descuento'!$A$2:$D$4,4,FALSE),MAX(0,1-SUMIF(Aux_Datos!$B:$B,$I34,Aux_Datos!$K:$K)/$E34),0)) -> 0 | I34: =VALUE(MID(A34,2,LEN(A34))) -> 43 | J34: =INT(B34) -> 46087 | K34: =IF(F34="Pago inmediato", 0, IF(F34="", "", IFERROR(VALUE(MID(F34, 1, SEARCH(" ", F34)-1)), ""))) -> 15 | L34: =J34+K34+1 -> 46103 | M34: =E34-(E34*G34)-(E34*H34) -> 362.52 | N34: =IF(T34="PAGADA", 0, IF(L34 < TODAY(), TODAY() - L34, 0)) -> 0 | O34: =IF(T34="PAGADA", "PAGADA", IF(L34 < TODAY(), "VENCIDA", "EN TIEMPO")) -> PAGADA | P34: =LET( idVenta, I34&"", montoTotal, M34, pagos, IFERROR(SUMIF(Aux_Datos!$B:$B, idVenta, Aux_Datos!$K:$K), 0), retenciones, IFERROR(SUMIF(Aux_Datos!$N:$N, idVenta, Aux_Datos!$R:$R), 0), pagos + retenciones ) -> 426.5075 | Q34: =IF(P34=0, "Sin Pago", LET( idVenta, I34&"", montoTotalPagado, P34, pagoUSD, IFERROR(SUMIFS(Aux_Datos!$C:$C, Aux_Datos!$B:$B, idVenta, Aux_Datos!$D:$D, "USD"), 0), pagoVES, IFERROR(SUMIFS(Aux_Datos!$C:$C, Aux_Datos!$B:$B, idVenta, Aux_Datos!$D:$D, "VES"), 0), IF(pagoUSD >= (montoTotalPagado * 0.84), "USD", IF(pagoVES >= (montoTotalPagado * 0.84), "VES", "MIXTO")) ) ) -> VES | R34: =M34-P34 -> -63.9875 | S34: =IF(P34=0, "Sin Pago", IFERROR( MAXIFS(Aux_Datos!$A:$A, Aux_Datos!$B:$B, I34&""), IFERROR(MAXIFS(Aux_Datos!$A:$A, Aux_Datos!$B:$B, VALUE(I34)), "Revisar ID") ) ) -> 46150 | T34: =IF(R34<=0, "PAGADA", IF(P34>0, "PAGO PARCIAL", "PENDIENTE")) -> PAGADA | U34: =IF(AND(T34<>"PAGADA", L34<TODAY()), "CRÍTICO: VENCIDA", IF(T34="PAGADA", "SOLVENTE", "EN TIEMPO")) -> SOLVENTE | V34: =IF(T34="PAGADA", 0, IF(S34 < TODAY(), TODAY() - S34, 0)) -> 0 | W34: =IF(P34=0, "Sin Pago", LET( monedaPago, Q34, descuentoAplicado, G34, limitePermitido, IFERROR(VLOOKUP(monedaPago, 'Limites de Descuento'!$A$2:$B595, 2, FALSE), 0), IF(descuentoAplicado > limitePermitido, "ALERTA: EXCESO (" & TEXT(limitePermitido, "0%") & " máx)", "OK") ) ) -> OK | X34: =IF(OR(H34=0, S34="Sin Pago"), "", IF(AND(H34 > 0, S34 > (L34 + 2)), "⚠️ REVISAR DESCUENTO", "OK")) | Y34: 426.5075 | Z34: CUMPLE
A35: S00044 | B35: 46087.683 | C35: Comercializadora Garabote | D35: PEREZ DIAZ ANGEL DE DIOS | E35: 2421.89 | F35: 45 días | G35: =IF($E35=0,0,IF(SUMIF(Aux_Datos!$B:$B,$I35,Aux_Datos!$K:$K)/$E35>=VLOOKUP(IF(COUNTIFS(Aux_Datos!$B:$B,$I35,Aux_Datos!$D:$D,"<>USD")=0,"USD","VES"),'Limites de Descuento'!$A$2:$D$4,4,FALSE),MAX(0,1-SUMIF(Aux_Datos!$B:$B,$I35,Aux_Datos!$K:$K)/$E35),0)) -> 0.11350226 | I35: =VALUE(MID(A35,2,LEN(A35))) -> 44 | J35: =INT(B35) -> 46087 | K35: =IF(F35="Pago inmediato", 0, IF(F35="", "", IFERROR(VALUE(MID(F35, 1, SEARCH(" ", F35)-1)), ""))) -> 45 | L35: =J35+K35+1 -> 46133 | M35: =E35-(E35*G35)-(E35*H35) -> 2147 | N35: =IF(T35="PAGADA", 0, IF(L35 < TODAY(), TODAY() - L35, 0)) -> 0 | O35: =IF(T35="PAGADA", "PAGADA", IF(L35 < TODAY(), "VENCIDA", "EN TIEMPO")) -> PAGADA | P35: =LET( idVenta, I35&"", montoTotal, M35, pagos, IFERROR(SUMIF(Aux_Datos!$B:$B, idVenta, Aux_Datos!$K:$K), 0), retenciones, IFERROR(SUMIF(Aux_Datos!$N:$N, idVenta, Aux_Datos!$R:$R), 0), pagos + retenciones ) -> 2147 | Q35: =IF(P35=0, "Sin Pago", LET( idVenta, I35&"", montoTotalPagado, P35, pagoUSD, IFERROR(SUMIFS(Aux_Datos!$C:$C, Aux_Datos!$B:$B, idVenta, Aux_Datos!$D:$D, "USD"), 0), pagoVES, IFERROR(SUMIFS(Aux_Datos!$C:$C, Aux_Datos!$B:$B, idVenta, Aux_Datos!$D:$D, "VES"), 0), IF(pagoUSD >= (montoTotalPagado * 0.84), "USD", IF(pagoVES >= (montoTotalPagado * 0.84), "VES", "MIXTO")) ) ) -> USD | R35: =M35-P35 -> 0 | S35: =IF(P35=0, "Sin Pago", IFERROR( MAXIFS(Aux_Datos!$A:$A, Aux_Datos!$B:$B, I35&""), IFERROR(MAXIFS(Aux_Datos!$A:$A, Aux_Datos!$B:$B, VALUE(I35)), "Revisar ID") ) ) -> 46196 | T35: =IF(R35<=0, "PAGADA", IF(P35>0, "PAGO PARCIAL", "PENDIENTE")) -> PAGADA | U35: =IF(AND(T35<>"PAGADA", L35<TODAY()), "CRÍTICO: VENCIDA", IF(T35="PAGADA", "SOLVENTE", "EN TIEMPO")) -> SOLVENTE | V35: =IF(T35="PAGADA", 0, IF(S35 < TODAY(), TODAY() - S35, 0)) -> 0 | W35: =IF(P35=0, "Sin Pago", LET( monedaPago, Q35, descuentoAplicado, G35, limitePermitido, IFERROR(VLOOKUP(monedaPago, 'Limites de Descuento'!$A$2:$B595, 2, FALSE), 0), IF(descuentoAplicado > limitePermitido, "ALERTA: EXCESO (" & TEXT(limitePermitido, "0%") & " máx)", "OK") ) ) -> OK | X35: =IF(OR(H35=0, S35="Sin Pago"), "", IF(AND(H35 > 0, S35 > (L35 + 2)), "⚠️ REVISAR DESCUENTO", "OK")) | Y35: 2147 | Z35: CUMPLE
A36: S00045 | B36: 46090.24 | C36: INVERSIONES IRETE SUKA, C.A | D36: VILLABONA CORREA ALBA ESTEFANIA | E36: 55.34 | F36: 7 días | G36: =IF($E36=0,0,IF(SUMIF(Aux_Datos!$B:$B,$I36,Aux_Datos!$K:$K)/$E36>=VLOOKUP(IF(COUNTIFS(Aux_Datos!$B:$B,$I36,Aux_Datos!$D:$D,"<>USD")=0,"USD","VES"),'Limites de Descuento'!$A$2:$D$4,4,FALSE),MAX(0,1-SUMIF(Aux_Datos!$B:$B,$I36,Aux_Datos!$K:$K)/$E36),0)) -> 0 | I36: =VALUE(MID(A36,2,LEN(A36))) -> 45 | J36: =INT(B36) -> 46090 | K36: =IF(F36="Pago inmediato", 0, IF(F36="", "", IFERROR(VALUE(MID(F36, 1, SEARCH(" ", F36)-1)), ""))) -> 7 | L36: =J36+K36+1 -> 46098 | M36: =E36-(E36*G36)-(E36*H36) -> 55.34 | N36: =IF(T36="PAGADA", 0, IF(L36 < TODAY(), TODAY() - L36, 0)) -> 102 | O36: =IF(T36="PAGADA", "PAGADA", IF(L36 < TODAY(), "VENCIDA", "EN TIEMPO")) -> VENCIDA | P36: =LET( idVenta, I36&"", montoTotal, M36, pagos, IFERROR(SUMIF(Aux_Datos!$B:$B, idVenta, Aux_Datos!$K:$K), 0), retenciones, IFERROR(SUMIF(Aux_Datos!$N:$N, idVenta, Aux_Datos!$R:$R), 0), pagos + retenciones ) -> 0 | Q36: =IF(P36=0, "Sin Pago", LET( idVenta, I36&"", montoTotalPagado, P36, pagoUSD, IFERROR(SUMIFS(Aux_Datos!$C:$C, Aux_Datos!$B:$B, idVenta, Aux_Datos!$D:$D, "USD"), 0), pagoVES, IFERROR(SUMIFS(Aux_Datos!$C:$C, Aux_Datos!$B:$B, idVenta, Aux_Datos!$D:$D, "VES"), 0), IF(pagoUSD >= (montoTotalPagado * 0.84), "USD", IF(pagoVES >= (montoTotalPagado * 0.84), "VES", "MIXTO")) ) ) -> Sin Pago | R36: =M36-P36 -> 55.34 | S36: =IF(P36=0, "Sin Pago", IFERROR( MAXIFS(Aux_Datos!$A:$A, Aux_Datos!$B:$B, I36&""), IFERROR(MAXIFS(Aux_Datos!$A:$A, Aux_Datos!$B:$B, VALUE(I36)), "Revisar ID") ) ) -> Sin Pago | T36: =IF(R36<=0, "PAGADA", IF(P36>0, "PAGO PARCIAL", "PENDIENTE")) -> PENDIENTE | U36: =IF(AND(T36<>"PAGADA", L36<TODAY()), "CRÍTICO: VENCIDA", IF(T36="PAGADA", "SOLVENTE", "EN TIEMPO")) -> CRÍTICO: VENCIDA | V36: =IF(T36="PAGADA", 0, IF(S36 < TODAY(), TODAY() - S36, 0)) -> 0 | W36: =IF(P36=0, "Sin Pago", LET( monedaPago, Q36, descuentoAplicado, G36, limitePermitido, IFERROR(VLOOKUP(monedaPago, 'Limites de Descuento'!$A$2:$B595, 2, FALSE), 0), IF(descuentoAplicado > limitePermitido, "ALERTA: EXCESO (" & TEXT(limitePermitido, "0%") & " máx)", "OK") ) ) -> Sin Pago | X36: =IF(OR(H36=0, S36="Sin Pago"), "", IF(AND(H36 > 0, S36 > (L36 + 2)), "⚠️ REVISAR DESCUENTO", "OK")) | Y36: 0 | Z36: SIN MONEDA VÁLIDA
A37: S00046 | B37: 46091.442 | C37: EMPRENDIMIENTO IRMA RODRIGUEZ 6 | D37: TORO ARDILES DAVID JOSE | E37: 129.99 | F37: Pago inmediato | G37: =IF($E37=0,0,IF(SUMIF(Aux_Datos!$B:$B,$I37,Aux_Datos!$K:$K)/$E37>=VLOOKUP(IF(COUNTIFS(Aux_Datos!$B:$B,$I37,Aux_Datos!$D:$D,"<>USD")=0,"USD","VES"),'Limites de Descuento'!$A$2:$D$4,4,FALSE),MAX(0,1-SUMIF(Aux_Datos!$B:$B,$I37,Aux_Datos!$K:$K)/$E37),0)) -> 7.6928995e-05 | I37: =VALUE(MID(A37,2,LEN(A37))) -> 46 | J37: =INT(B37) -> 46091 | K37: =IF(F37="Pago inmediato", 0, IF(F37="", "", IFERROR(VALUE(MID(F37, 1, SEARCH(" ", F37)-1)), ""))) -> 0 | L37: =J37+K37+1 -> 46092 | M37: =E37-(E37*G37)-(E37*H37) -> 129.98 | N37: =IF(T37="PAGADA", 0, IF(L37 < TODAY(), TODAY() - L37, 0)) -> 0 | O37: =IF(T37="PAGADA", "PAGADA", IF(L37 < TODAY(), "VENCIDA", "EN TIEMPO")) -> PAGADA | P37: =LET( idVenta, I37&"", montoTotal, M37, pagos, IFERROR(SUMIF(Aux_Datos!$B:$B, idVenta, Aux_Datos!$K:$K), 0), retenciones, IFERROR(SUMIF(Aux_Datos!$N:$N, idVenta, Aux_Datos!$R:$R), 0), pagos + retenciones ) -> 129.98 | Q37: =IF(P37=0, "Sin Pago", LET( idVenta, I37&"", montoTotalPagado, P37, pagoUSD, IFERROR(SUMIFS(Aux_Datos!$C:$C, Aux_Datos!$B:$B, idVenta, Aux_Datos!$D:$D, "USD"), 0), pagoVES, IFERROR(SUMIFS(Aux_Datos!$C:$C, Aux_Datos!$B:$B, idVenta, Aux_Datos!$D:$D, "VES"), 0), IF(pagoUSD >= (montoTotalPagado * 0.84), "USD", IF(pagoVES >= (montoTotalPagado * 0.84), "VES", "MIXTO")) ) ) -> USD | R37: =M37-P37 -> 0 | S37: =IF(P37=0, "Sin Pago", IFERROR( MAXIFS(Aux_Datos!$A:$A, Aux_Datos!$B:$B, I37&""), IFERROR(MAXIFS(Aux_Datos!$A:$A, Aux_Datos!$B:$B, VALUE(I37)), "Revisar ID") ) ) -> 46094 | T37: =IF(R37<=0, "PAGADA", IF(P37>0, "PAGO PARCIAL", "PENDIENTE")) -> PAGADA | U37: =IF(AND(T37<>"PAGADA", L37<TODAY()), "CRÍTICO: VENCIDA", IF(T37="PAGADA", "SOLVENTE", "EN TIEMPO")) -> SOLVENTE | V37: =IF(T37="PAGADA", 0, IF(S37 < TODAY(), TODAY() - S37, 0)) -> 0 | W37: =IF(P37=0, "Sin Pago", LET( monedaPago, Q37, descuentoAplicado, G37, limitePermitido, IFERROR(VLOOKUP(monedaPago, 'Limites de Descuento'!$A$2:$B595, 2, FALSE), 0), IF(descuentoAplicado > limitePermitido, "ALERTA: EXCESO (" & TEXT(limitePermitido, "0%") & " máx)", "OK") ) ) -> OK | X37: =IF(OR(H37=0, S37="Sin Pago"), "", IF(AND(H37 > 0, S37 > (L37 + 2)), "⚠️ REVISAR DESCUENTO", "OK")) | Y37: 129.98 | Z37: CUMPLE
A38: S00047 | B38: 46090.551 | C38: Rawy Xavier Melendez Caripa | D38: CASERES GONZALEZ RONALD OSWALDO | E38: 1893.12 | F38: 7 días | G38: =IF($E38=0,0,IF(SUMIF(Aux_Datos!$B:$B,$I38,Aux_Datos!$K:$K)/$E38>=VLOOKUP(IF(COUNTIFS(Aux_Datos!$B:$B,$I38,Aux_Datos!$D:$D,"<>USD")=0,"USD","VES"),'Limites de Descuento'!$A$2:$D$4,4,FALSE),MAX(0,1-SUMIF(Aux_Datos!$B:$B,$I38,Aux_Datos!$K:$K)/$E38),0)) -> 0 | H38: 0.0509 | I38: =VALUE(MID(A38,2,LEN(A38))) -> 47 | J38: =INT(B38) -> 46090 | K38: =IF(F38="Pago inmediato", 0, IF(F38="", "", IFERROR(VALUE(MID(F38, 1, SEARCH(" ", F38)-1)), ""))) -> 7 | L38: =J38+K38+1 -> 46098 | M38: =E38-(E38*G38)-(E38*H38) -> 1796.7602 | N38: =IF(T38="PAGADA", 0, IF(L38 < TODAY(), TODAY() - L38, 0)) -> 0 | O38: =IF(T38="PAGADA", "PAGADA", IF(L38 < TODAY(), "VENCIDA", "EN TIEMPO")) -> PAGADA | P38: =LET( idVenta, I38&"", montoTotal, M38, pagos, IFERROR(SUMIF(Aux_Datos!$B:$B, idVenta, Aux_Datos!$K:$K), 0), retenciones, IFERROR(SUMIF(Aux_Datos!$N:$N, idVenta, Aux_Datos!$R:$R), 0), pagos + retenciones ) -> 1893.12 | Q38: =IF(P38=0, "Sin Pago", LET( idVenta, I38&"", montoTotalPagado, P38, pagoUSD, IFERROR(SUMIFS(Aux_Datos!$C:$C, Aux_Datos!$B:$B, idVenta, Aux_Datos!$D:$D, "USD"), 0), pagoVES, IFERROR(SUMIFS(Aux_Datos!$C:$C, Aux_Datos!$B:$B, idVenta, Aux_Datos!$D:$D, "VES"), 0), IF(pagoUSD >= (montoTotalPagado * 0.84), "USD", IF(pagoVES >= (montoTotalPagado * 0.84), "VES", "MIXTO")) ) ) -> VES | R38: =M38-P38 -> -96.359819 | S38: =IF(P38=0, "Sin Pago", IFERROR( MAXIFS(Aux_Datos!$A:$A, Aux_Datos!$B:$B, I38&""), IFERROR(MAXIFS(Aux_Datos!$A:$A, Aux_Datos!$B:$B, VALUE(I38)), "Revisar ID") ) ) -> 46090 | T38: =IF(R38<=0, "PAGADA", IF(P38>0, "PAGO PARCIAL", "PENDIENTE")) -> PAGADA | U38: =IF(AND(T38<>"PAGADA", L38<TODAY()), "CRÍTICO: VENCIDA", IF(T38="PAGADA", "SOLVENTE", "EN TIEMPO")) -> SOLVENTE | V38: =IF(T38="PAGADA", 0, IF(S38 < TODAY(), TODAY() - S38, 0)) -> 0 | W38: =IF(P38=0, "Sin Pago", LET( monedaPago, Q38, descuentoAplicado, G38, limitePermitido, IFERROR(VLOOKUP(monedaPago, 'Limites de Descuento'!$A$2:$B595, 2, FALSE), 0), IF(descuentoAplicado > limitePermitido, "ALERTA: EXCESO (" & TEXT(limitePermitido, "0%") & " máx)", "OK") ) ) -> OK | X38: =IF(OR(H38=0, S38="Sin Pago"), "", IF(AND(H38 > 0, S38 > (L38 + 2)), "⚠️ REVISAR DESCUENTO", "OK")) -> OK | Y38: 1893.12 | Z38: CUMPLE
A39: S00048 | B39: 46090.656 | C39: Autoelectronica Oranel, C.A. | D39: OCANTO ZABALA ROSALVY DEL CARMEN | E39: 53.79 | F39: 7 días | G39: =IF($E39=0,0,IF(SUMIF(Aux_Datos!$B:$B,$I39,Aux_Datos!$K:$K)/$E39>=VLOOKUP(IF(COUNTIFS(Aux_Datos!$B:$B,$I39,Aux_Datos!$D:$D,"<>USD")=0,"USD","VES"),'Limites de Descuento'!$A$2:$D$4,4,FALSE),MAX(0,1-SUMIF(Aux_Datos!$B:$B,$I39,Aux_Datos!$K:$K)/$E39),0)) -> 0 | I39: =VALUE(MID(A39,2,LEN(A39))) -> 48 | J39: =INT(B39) -> 46090 | K39: =IF(F39="Pago inmediato", 0, IF(F39="", "", IFERROR(VALUE(MID(F39, 1, SEARCH(" ", F39)-1)), ""))) -> 7 | L39: =J39+K39+1 -> 46098 | M39: =E39-(E39*G39)-(E39*H39) -> 53.79 | N39: =IF(T39="PAGADA", 0, IF(L39 < TODAY(), TODAY() - L39, 0)) -> 0 | O39: =IF(T39="PAGADA", "PAGADA", IF(L39 < TODAY(), "VENCIDA", "EN TIEMPO")) -> PAGADA | P39: =LET( idVenta, I39&"", montoTotal, M39, pagos, IFERROR(SUMIF(Aux_Datos!$B:$B, idVenta, Aux_Datos!$K:$K), 0), retenciones, IFERROR(SUMIF(Aux_Datos!$N:$N, idVenta, Aux_Datos!$R:$R), 0), pagos + retenciones ) -> 61.941265 | Q39: =IF(P39=0, "Sin Pago", LET( idVenta, I39&"", montoTotalPagado, P39, pagoUSD, IFERROR(SUMIFS(Aux_Datos!$C:$C, Aux_Datos!$B:$B, idVenta, Aux_Datos!$D:$D, "USD"), 0), pagoVES, IFERROR(SUMIFS(Aux_Datos!$C:$C, Aux_Datos!$B:$B, idVenta, Aux_Datos!$D:$D, "VES"), 0), IF(pagoUSD >= (montoTotalPagado * 0.84), "USD", IF(pagoVES >= (montoTotalPagado * 0.84), "VES", "MIXTO")) ) ) -> VES | R39: =M39-P39 -> -8.1512645 | S39: =IF(P39=0, "Sin Pago", IFERROR( MAXIFS(Aux_Datos!$A:$A, Aux_Datos!$B:$B, I39&""), IFERROR(MAXIFS(Aux_Datos!$A:$A, Aux_Datos!$B:$B, VALUE(I39)), "Revisar ID") ) ) -> 46104 | T39: =IF(R39<=0, "PAGADA", IF(P39>0, "PAGO PARCIAL", "PENDIENTE")) -> PAGADA | U39: =IF(AND(T39<>"PAGADA", L39<TODAY()), "CRÍTICO: VENCIDA", IF(T39="PAGADA", "SOLVENTE", "EN TIEMPO")) -> SOLVENTE | V39: =IF(T39="PAGADA", 0, IF(S39 < TODAY(), TODAY() - S39, 0)) -> 0 | W39: =IF(P39=0, "Sin Pago", LET( monedaPago, Q39, descuentoAplicado, G39, limitePermitido, IFERROR(VLOOKUP(monedaPago, 'Limites de Descuento'!$A$2:$B595, 2, FALSE), 0), IF(descuentoAplicado > limitePermitido, "ALERTA: EXCESO (" & TEXT(limitePermitido, "0%") & " máx)", "OK") ) ) -> OK | X39: =IF(OR(H39=0, S39="Sin Pago"), "", IF(AND(H39 > 0, S39 > (L39 + 2)), "⚠️ REVISAR DESCUENTO", "OK")) | Y39: 61.941265 | Z39: CUMPLE
A40: S00049 | B40: 46091.46 | C40: Marlene Herrera | D40: PEREZ DIAZ ANGEL DE DIOS | E40: 1033.52 | F40: 15 días | G40: =IF($E40=0,0,IF(SUMIF(Aux_Datos!$B:$B,$I40,Aux_Datos!$K:$K)/$E40>=VLOOKUP(IF(COUNTIFS(Aux_Datos!$B:$B,$I40,Aux_Datos!$D:$D,"<>USD")=0,"USD","VES"),'Limites de Descuento'!$A$2:$D$4,4,FALSE),MAX(0,1-SUMIF(Aux_Datos!$B:$B,$I40,Aux_Datos!$K:$K)/$E40),0)) -> 0 | I40: =VALUE(MID(A40,2,LEN(A40))) -> 49 | J40: =INT(B40) -> 46091 | K40: =IF(F40="Pago inmediato", 0, IF(F40="", "", IFERROR(VALUE(MID(F40, 1, SEARCH(" ", F40)-1)), ""))) -> 15 | L40: =J40+K40+1 -> 46107 | M40: =E40-(E40*G40)-(E40*H40) -> 1033.52 | N40: =IF(T40="PAGADA", 0, IF(L40 < TODAY(), TODAY() - L40, 0)) -> 93 | O40: =IF(T40="PAGADA", "PAGADA", IF(L40 < TODAY(), "VENCIDA", "EN TIEMPO")) -> VENCIDA | P40: =LET( idVenta, I40&"", montoTotal, M40, pagos, IFERROR(SUMIF(Aux_Datos!$B:$B, idVenta, Aux_Datos!$K:$K), 0), retenciones, IFERROR(SUMIF(Aux_Datos!$N:$N, idVenta, Aux_Datos!$R:$R), 0), pagos + retenciones ) -> 430 | Q40: =IF(P40=0, "Sin Pago", LET( idVenta, I40&"", montoTotalPagado, P40, pagoUSD, IFERROR(SUMIFS(Aux_Datos!$C:$C, Aux_Datos!$B:$B, idVenta, Aux_Datos!$D:$D, "USD"), 0), pagoVES, IFERROR(SUMIFS(Aux_Datos!$C:$C, Aux_Datos!$B:$B, idVenta, Aux_Datos!$D:$D, "VES"), 0), IF(pagoUSD >= (montoTotalPagado * 0.84), "USD", IF(pagoVES >= (montoTotalPagado * 0.84), "VES", "MIXTO")) ) ) -> USD | R40: =M40-P40 -> 603.52 | S40: =IF(P40=0, "Sin Pago", IFERROR( MAXIFS(Aux_Datos!$A:$A, Aux_Datos!$B:$B, I40&""), IFERROR(MAXIFS(Aux_Datos!$A:$A, Aux_Datos!$B:$B, VALUE(I40)), "Revisar ID") ) ) -> 46196 | T40: =IF(R40<=0, "PAGADA", IF(P40>0, "PAGO PARCIAL", "PENDIENTE")) -> PAGO PARCIAL | U40: =IF(AND(T40<>"PAGADA", L40<TODAY()), "CRÍTICO: VENCIDA", IF(T40="PAGADA", "SOLVENTE", "EN TIEMPO")) -> CRÍTICO: VENCIDA | V40: =IF(T40="PAGADA", 0, IF(S40 < TODAY(), TODAY() - S40, 0)) -> 4 | W40: =IF(P40=0, "Sin Pago", LET( monedaPago, Q40, descuentoAplicado, G40, limitePermitido, IFERROR(VLOOKUP(monedaPago, 'Limites de Descuento'!$A$2:$B595, 2, FALSE), 0), IF(descuentoAplicado > limitePermitido, "ALERTA: EXCESO (" & TEXT(limitePermitido, "0%") & " máx)", "OK") ) ) -> OK | X40: =IF(OR(H40=0, S40="Sin Pago"), "", IF(AND(H40 > 0, S40 > (L40 + 2)), "⚠️ REVISAR DESCUENTO", "OK")) | Y40: 430 | Z40: NO CUMPLE
A41: S00050 | B41: 46090.674 | C41: FREDI MARQUEZ | D41: PEREZ DIAZ ANGEL DE DIOS | E41: 64.99 | F41: 15 días | G41: =IF($E41=0,0,IF(SUMIF(Aux_Datos!$B:$B,$I41,Aux_Datos!$K:$K)/$E41>=VLOOKUP(IF(COUNTIFS(Aux_Datos!$B:$B,$I41,Aux_Datos!$D:$D,"<>USD")=0,"USD","VES"),'Limites de Descuento'!$A$2:$D$4,4,FALSE),MAX(0,1-SUMIF(Aux_Datos!$B:$B,$I41,Aux_Datos!$K:$K)/$E41),0)) -> 0 | I41: =VALUE(MID(A41,2,LEN(A41))) -> 50 | J41: =INT(B41) -> 46090 | K41: =IF(F41="Pago inmediato", 0, IF(F41="", "", IFERROR(VALUE(MID(F41, 1, SEARCH(" ", F41)-1)), ""))) -> 15 | L41: =J41+K41+1 -> 46106 | M41: =E41-(E41*G41)-(E41*H41) -> 64.99 | N41: =IF(T41="PAGADA", 0, IF(L41 < TODAY(), TODAY() - L41, 0)) -> 0 | O41: =IF(T41="PAGADA", "PAGADA", IF(L41 < TODAY(), "VENCIDA", "EN TIEMPO")) -> PAGADA | P41: =LET( idVenta, I41&"", montoTotal, M41, pagos, IFERROR(SUMIF(Aux_Datos!$B:$B, idVenta, Aux_Datos!$K:$K), 0), retenciones, IFERROR(SUMIF(Aux_Datos!$N:$N, idVenta, Aux_Datos!$R:$R), 0), pagos + retenciones ) -> 65 | Q41: =IF(P41=0, "Sin Pago", LET( idVenta, I41&"", montoTotalPagado, P41, pagoUSD, IFERROR(SUMIFS(Aux_Datos!$C:$C, Aux_Datos!$B:$B, idVenta, Aux_Datos!$D:$D, "USD"), 0), pagoVES, IFERROR(SUMIFS(Aux_Datos!$C:$C, Aux_Datos!$B:$B, idVenta, Aux_Datos!$D:$D, "VES"), 0), IF(pagoUSD >= (montoTotalPagado * 0.84), "USD", IF(pagoVES >= (montoTotalPagado * 0.84), "VES", "MIXTO")) ) ) -> USD | R41: =M41-P41 -> -0.01 | S41: =IF(P41=0, "Sin Pago", IFERROR( MAXIFS(Aux_Datos!$A:$A, Aux_Datos!$B:$B, I41&""), IFERROR(MAXIFS(Aux_Datos!$A:$A, Aux_Datos!$B:$B, VALUE(I41)), "Revisar ID") ) ) -> 46090 | T41: =IF(R41<=0, "PAGADA", IF(P41>0, "PAGO PARCIAL", "PENDIENTE")) -> PAGADA | U41: =IF(AND(T41<>"PAGADA", L41<TODAY()), "CRÍTICO: VENCIDA", IF(T41="PAGADA", "SOLVENTE", "EN TIEMPO")) -> SOLVENTE | V41: =IF(T41="PAGADA", 0, IF(S41 < TODAY(), TODAY() - S41, 0)) -> 0 | W41: =IF(P41=0, "Sin Pago", LET( monedaPago, Q41, descuentoAplicado, G41, limitePermitido, IFERROR(VLOOKUP(monedaPago, 'Limites de Descuento'!$A$2:$B595, 2, FALSE), 0), IF(descuentoAplicado > limitePermitido, "ALERTA: EXCESO (" & TEXT(limitePermitido, "0%") & " máx)", "OK") ) ) -> OK | X41: =IF(OR(H41=0, S41="Sin Pago"), "", IF(AND(H41 > 0, S41 > (L41 + 2)), "⚠️ REVISAR DESCUENTO", "OK")) | Y41: 65 | Z41: CUMPLE
A42: S00051 | B42: 46091.46 | C42: Auto Repuestos Acal C.A | D42: QUEVEDO BASTIDAS NEYKEL DAVID | E42: 120.02 | F42: 15 días | G42: =IF($E42=0,0,IF(SUMIF(Aux_Datos!$B:$B,$I42,Aux_Datos!$K:$K)/$E42>=VLOOKUP(IF(COUNTIFS(Aux_Datos!$B:$B,$I42,Aux_Datos!$D:$D,"<>USD")=0,"USD","VES"),'Limites de Descuento'!$A$2:$D$4,4,FALSE),MAX(0,1-SUMIF(Aux_Datos!$B:$B,$I42,Aux_Datos!$K:$K)/$E42),0)) -> 0.0044992501 | I42: =VALUE(MID(A42,2,LEN(A42))) -> 51 | J42: =INT(B42) -> 46091 | K42: =IF(F42="Pago inmediato", 0, IF(F42="", "", IFERROR(VALUE(MID(F42, 1, SEARCH(" ", F42)-1)), ""))) -> 15 | L42: =J42+K42+1 -> 46107 | M42: =E42-(E42*G42)-(E42*H42) -> 119.48 | N42: =IF(T42="PAGADA", 0, IF(L42 < TODAY(), TODAY() - L42, 0)) -> 0 | O42: =IF(T42="PAGADA", "PAGADA", IF(L42 < TODAY(), "VENCIDA", "EN TIEMPO")) -> PAGADA | P42: =LET( idVenta, I42&"", montoTotal, M42, pagos, IFERROR(SUMIF(Aux_Datos!$B:$B, idVenta, Aux_Datos!$K:$K), 0), retenciones, IFERROR(SUMIF(Aux_Datos!$N:$N, idVenta, Aux_Datos!$R:$R), 0), pagos + retenciones ) -> 119.48 | Q42: =IF(P42=0, "Sin Pago", LET( idVenta, I42&"", montoTotalPagado, P42, pagoUSD, IFERROR(SUMIFS(Aux_Datos!$C:$C, Aux_Datos!$B:$B, idVenta, Aux_Datos!$D:$D, "USD"), 0), pagoVES, IFERROR(SUMIFS(Aux_Datos!$C:$C, Aux_Datos!$B:$B, idVenta, Aux_Datos!$D:$D, "VES"), 0), IF(pagoUSD >= (montoTotalPagado * 0.84), "USD", IF(pagoVES >= (montoTotalPagado * 0.84), "VES", "MIXTO")) ) ) -> USD | R42: =M42-P42 -> 0 | S42: =IF(P42=0, "Sin Pago", IFERROR( MAXIFS(Aux_Datos!$A:$A, Aux_Datos!$B:$B, I42&""), IFERROR(MAXIFS(Aux_Datos!$A:$A, Aux_Datos!$B:$B, VALUE(I42)), "Revisar ID") ) ) -> 46108 | T42: =IF(R42<=0, "PAGADA", IF(P42>0, "PAGO PARCIAL", "PENDIENTE")) -> PAGADA | U42: =IF(AND(T42<>"PAGADA", L42<TODAY()), "CRÍTICO: VENCIDA", IF(T42="PAGADA", "SOLVENTE", "EN TIEMPO")) -> SOLVENTE | V42: =IF(T42="PAGADA", 0, IF(S42 < TODAY(), TODAY() - S42, 0)) -> 0 | W42: =IF(P42=0, "Sin Pago", LET( monedaPago, Q42, descuentoAplicado, G42, limitePermitido, IFERROR(VLOOKUP(monedaPago, 'Limites de Descuento'!$A$2:$B595, 2, FALSE), 0), IF(descuentoAplicado > limitePermitido, "ALERTA: EXCESO (" & TEXT(limitePermitido, "0%") & " máx)", "OK") ) ) -> OK | X42: =IF(OR(H42=0, S42="Sin Pago"), "", IF(AND(H42 > 0, S42 > (L42 + 2)), "⚠️ REVISAR DESCUENTO", "OK")) | Y42: 119.48 | Z42: CUMPLE
A43: S00052 | B43: 46091.328 | C43: FREDI MARQUEZ | D43: PEREZ DIAZ ANGEL DE DIOS | E43: 259.99 | F43: 15 días | G43: =IF($E43=0,0,IF(SUMIF(Aux_Datos!$B:$B,$I43,Aux_Datos!$K:$K)/$E43>=VLOOKUP(IF(COUNTIFS(Aux_Datos!$B:$B,$I43,Aux_Datos!$D:$D,"<>USD")=0,"USD","VES"),'Limites de Descuento'!$A$2:$D$4,4,FALSE),MAX(0,1-SUMIF(Aux_Datos!$B:$B,$I43,Aux_Datos!$K:$K)/$E43),0)) -> 0 | I43: =VALUE(MID(A43,2,LEN(A43))) -> 52 | J43: =INT(B43) -> 46091 | K43: =IF(F43="Pago inmediato", 0, IF(F43="", "", IFERROR(VALUE(MID(F43, 1, SEARCH(" ", F43)-1)), ""))) -> 15 | L43: =J43+K43+1 -> 46107 | M43: =E43-(E43*G43)-(E43*H43) -> 259.99 | N43: =IF(T43="PAGADA", 0, IF(L43 < TODAY(), TODAY() - L43, 0)) -> 0 | O43: =IF(T43="PAGADA", "PAGADA", IF(L43 < TODAY(), "VENCIDA", "EN TIEMPO")) -> PAGADA | P43: =LET( idVenta, I43&"", montoTotal, M43, pagos, IFERROR(SUMIF(Aux_Datos!$B:$B, idVenta, Aux_Datos!$K:$K), 0), retenciones, IFERROR(SUMIF(Aux_Datos!$N:$N, idVenta, Aux_Datos!$R:$R), 0), pagos + retenciones ) -> 260 | Q43: =IF(P43=0, "Sin Pago", LET( idVenta, I43&"", montoTotalPagado, P43, pagoUSD, IFERROR(SUMIFS(Aux_Datos!$C:$C, Aux_Datos!$B:$B, idVenta, Aux_Datos!$D:$D, "USD"), 0), pagoVES, IFERROR(SUMIFS(Aux_Datos!$C:$C, Aux_Datos!$B:$B, idVenta, Aux_Datos!$D:$D, "VES"), 0), IF(pagoUSD >= (montoTotalPagado * 0.84), "USD", IF(pagoVES >= (montoTotalPagado * 0.84), "VES", "MIXTO")) ) ) -> USD | R43: =M43-P43 -> -0.01 | S43: =IF(P43=0, "Sin Pago", IFERROR( MAXIFS(Aux_Datos!$A:$A, Aux_Datos!$B:$B, I43&""), IFERROR(MAXIFS(Aux_Datos!$A:$A, Aux_Datos!$B:$B, VALUE(I43)), "Revisar ID") ) ) -> 46083 | T43: =IF(R43<=0, "PAGADA", IF(P43>0, "PAGO PARCIAL", "PENDIENTE")) -> PAGADA | U43: =IF(AND(T43<>"PAGADA", L43<TODAY()), "CRÍTICO: VENCIDA", IF(T43="PAGADA", "SOLVENTE", "EN TIEMPO")) -> SOLVENTE | V43: =IF(T43="PAGADA", 0, IF(S43 < TODAY(), TODAY() - S43, 0)) -> 0 | W43: =IF(P43=0, "Sin Pago", LET( monedaPago, Q43, descuentoAplicado, G43, limitePermitido, IFERROR(VLOOKUP(monedaPago, 'Limites de Descuento'!$A$2:$B595, 2, FALSE), 0), IF(descuentoAplicado > limitePermitido, "ALERTA: EXCESO (" & TEXT(limitePermitido, "0%") & " máx)", "OK") ) ) -> OK | X43: =IF(OR(H43=0, S43="Sin Pago"), "", IF(AND(H43 > 0, S43 > (L43 + 2)), "⚠️ REVISAR DESCUENTO", "OK")) | Y43: 260 | Z43: CUMPLE
A44: S00053 | B44: 46091.46 | C44: INVERSIONES MI LINDA YEMAIRE 2019, C.A | D44: VILLABONA CORREA ALBA ESTEFANIA | E44: 792.33 | F44: 7 días | G44: =IF($E44=0,0,IF(SUMIF(Aux_Datos!$B:$B,$I44,Aux_Datos!$K:$K)/$E44>=VLOOKUP(IF(COUNTIFS(Aux_Datos!$B:$B,$I44,Aux_Datos!$D:$D,"<>USD")=0,"USD","VES"),'Limites de Descuento'!$A$2:$D$4,4,FALSE),MAX(0,1-SUMIF(Aux_Datos!$B:$B,$I44,Aux_Datos!$K:$K)/$E44),0)) -> 0 | I44: =VALUE(MID(A44,2,LEN(A44))) -> 53 | J44: =INT(B44) -> 46091 | K44: =IF(F44="Pago inmediato", 0, IF(F44="", "", IFERROR(VALUE(MID(F44, 1, SEARCH(" ", F44)-1)), ""))) -> 7 | L44: =J44+K44+1 -> 46099 | M44: =E44-(E44*G44)-(E44*H44) -> 792.33 | N44: =IF(T44="PAGADA", 0, IF(L44 < TODAY(), TODAY() - L44, 0)) -> 0 | O44: =IF(T44="PAGADA", "PAGADA", IF(L44 < TODAY(), "VENCIDA", "EN TIEMPO")) -> PAGADA | P44: =LET( idVenta, I44&"", montoTotal, M44, pagos, IFERROR(SUMIF(Aux_Datos!$B:$B, idVenta, Aux_Datos!$K:$K), 0), retenciones, IFERROR(SUMIF(Aux_Datos!$N:$N, idVenta, Aux_Datos!$R:$R), 0), pagos + retenciones ) -> 930.70202 | Q44: =IF(P44=0, "Sin Pago", LET( idVenta, I44&"", montoTotalPagado, P44, pagoUSD, IFERROR(SUMIFS(Aux_Datos!$C:$C, Aux_Datos!$B:$B, idVenta, Aux_Datos!$D:$D, "USD"), 0), pagoVES, IFERROR(SUMIFS(Aux_Datos!$C:$C, Aux_Datos!$B:$B, idVenta, Aux_Datos!$D:$D, "VES"), 0), IF(pagoUSD >= (montoTotalPagado * 0.84), "USD", IF(pagoVES >= (montoTotalPagado * 0.84), "VES", "MIXTO")) ) ) -> VES | R44: =M44-P44 -> -138.37202 | S44: =IF(P44=0, "Sin Pago", IFERROR( MAXIFS(Aux_Datos!$A:$A, Aux_Datos!$B:$B, I44&""), IFERROR(MAXIFS(Aux_Datos!$A:$A, Aux_Datos!$B:$B, VALUE(I44)), "Revisar ID") ) ) -> 46174 | T44: =IF(R44<=0, "PAGADA", IF(P44>0, "PAGO PARCIAL", "PENDIENTE")) -> PAGADA | U44: =IF(AND(T44<>"PAGADA", L44<TODAY()), "CRÍTICO: VENCIDA", IF(T44="PAGADA", "SOLVENTE", "EN TIEMPO")) -> SOLVENTE | V44: =IF(T44="PAGADA", 0, IF(S44 < TODAY(), TODAY() - S44, 0)) -> 0 | W44: =IF(P44=0, "Sin Pago", LET( monedaPago, Q44, descuentoAplicado, G44, limitePermitido, IFERROR(VLOOKUP(monedaPago, 'Limites de Descuento'!$A$2:$B595, 2, FALSE), 0), IF(descuentoAplicado > limitePermitido, "ALERTA: EXCESO (" & TEXT(limitePermitido, "0%") & " máx)", "OK") ) ) -> OK | X44: =IF(OR(H44=0, S44="Sin Pago"), "", IF(AND(H44 > 0, S44 > (L44 + 2)), "⚠️ REVISAR DESCUENTO", "OK")) | Y44: 930.70202 | Z44: CUMPLE
A45: S00054 | B45: 46092.374 | C45: Corporación Lubricantes 7ma Av.C.A | D45: GRIMAN DIAZ HECTOR EDUARDO | E45: 582.77 | F45: 15 días | G45: =IF($E45=0,0,IF(SUMIF(Aux_Datos!$B:$B,$I45,Aux_Datos!$K:$K)/$E45>=VLOOKUP(IF(COUNTIFS(Aux_Datos!$B:$B,$I45,Aux_Datos!$D:$D,"<>USD")=0,"USD","VES"),'Limites de Descuento'!$A$2:$D$4,4,FALSE),MAX(0,1-SUMIF(Aux_Datos!$B:$B,$I45,Aux_Datos!$K:$K)/$E45),0)) -> 0 | I45: =VALUE(MID(A45,2,LEN(A45))) -> 54 | J45: =INT(B45) -> 46092 | K45: =IF(F45="Pago inmediato", 0, IF(F45="", "", IFERROR(VALUE(MID(F45, 1, SEARCH(" ", F45)-1)), ""))) -> 15 | L45: =J45+K45+1 -> 46108 | M45: =E45-(E45*G45)-(E45*H45) -> 582.77 | N45: =IF(T45="PAGADA", 0, IF(L45 < TODAY(), TODAY() - L45, 0)) -> 92 | O45: =IF(T45="PAGADA", "PAGADA", IF(L45 < TODAY(), "VENCIDA", "EN TIEMPO")) -> VENCIDA | P45: =LET( idVenta, I45&"", montoTotal, M45, pagos, IFERROR(SUMIF(Aux_Datos!$B:$B, idVenta, Aux_Datos!$K:$K), 0), retenciones, IFERROR(SUMIF(Aux_Datos!$N:$N, idVenta, Aux_Datos!$R:$R), 0), pagos + retenciones ) -> 218.00235 | Q45: =IF(P45=0, "Sin Pago", LET( idVenta, I45&"", montoTotalPagado, P45, pagoUSD, IFERROR(SUMIFS(Aux_Datos!$C:$C, Aux_Datos!$B:$B, idVenta, Aux_Datos!$D:$D, "USD"), 0), pagoVES, IFERROR(SUMIFS(Aux_Datos!$C:$C, Aux_Datos!$B:$B, idVenta, Aux_Datos!$D:$D, "VES"), 0), IF(pagoUSD >= (montoTotalPagado * 0.84), "USD", IF(pagoVES >= (montoTotalPagado * 0.84), "VES", "MIXTO")) ) ) -> VES | R45: =M45-P45 -> 364.76765 | S45: =IF(P45=0, "Sin Pago", IFERROR( MAXIFS(Aux_Datos!$A:$A, Aux_Datos!$B:$B, I45&""), IFERROR(MAXIFS(Aux_Datos!$A:$A, Aux_Datos!$B:$B, VALUE(I45)), "Revisar ID") ) ) -> 46175 | T45: =IF(R45<=0, "PAGADA", IF(P45>0, "PAGO PARCIAL", "PENDIENTE")) -> PAGO PARCIAL | U45: =IF(AND(T45<>"PAGADA", L45<TODAY()), "CRÍTICO: VENCIDA", IF(T45="PAGADA", "SOLVENTE", "EN TIEMPO")) -> CRÍTICO: VENCIDA | V45: =IF(T45="PAGADA", 0, IF(S45 < TODAY(), TODAY() - S45, 0)) -> 25 | W45: =IF(P45=0, "Sin Pago", LET( monedaPago, Q45, descuentoAplicado, G45, limitePermitido, IFERROR(VLOOKUP(monedaPago, 'Limites de Descuento'!$A$2:$B595, 2, FALSE), 0), IF(descuentoAplicado > limitePermitido, "ALERTA: EXCESO (" & TEXT(limitePermitido, "0%") & " máx)", "OK") ) ) -> OK | X45: =IF(OR(H45=0, S45="Sin Pago"), "", IF(AND(H45 > 0, S45 > (L45 + 2)), "⚠️ REVISAR DESCUENTO", "OK")) | Y45: 218.00235 | Z45: NO CUMPLE
A46: S00055 | B46: 46091.484 | C46: Barrios Rodríguez Marlon Enrique | D46: TORO ARDILES DAVID JOSE | E46: 72 | F46: 7 días | G46: =IF($E46=0,0,IF(SUMIF(Aux_Datos!$B:$B,$I46,Aux_Datos!$K:$K)/$E46>=VLOOKUP(IF(COUNTIFS(Aux_Datos!$B:$B,$I46,Aux_Datos!$D:$D,"<>USD")=0,"USD","VES"),'Limites de Descuento'!$A$2:$D$4,4,FALSE),MAX(0,1-SUMIF(Aux_Datos!$B:$B,$I46,Aux_Datos!$K:$K)/$E46),0)) -> 0 | I46: =VALUE(MID(A46,2,LEN(A46))) -> 55 | J46: =INT(B46) -> 46091 | K46: =IF(F46="Pago inmediato", 0, IF(F46="", "", IFERROR(VALUE(MID(F46, 1, SEARCH(" ", F46)-1)), ""))) -> 7 | L46: =J46+K46+1 -> 46099 | M46: =E46-(E46*G46)-(E46*H46) -> 72 | N46: =IF(T46="PAGADA", 0, IF(L46 < TODAY(), TODAY() - L46, 0)) -> 0 | O46: =IF(T46="PAGADA", "PAGADA", IF(L46 < TODAY(), "VENCIDA", "EN TIEMPO")) -> PAGADA | P46: =LET( idVenta, I46&"", montoTotal, M46, pagos, IFERROR(SUMIF(Aux_Datos!$B:$B, idVenta, Aux_Datos!$K:$K), 0), retenciones, IFERROR(SUMIF(Aux_Datos!$N:$N, idVenta, Aux_Datos!$R:$R), 0), pagos + retenciones ) -> 72 | Q46: =IF(P46=0, "Sin Pago", LET( idVenta, I46&"", montoTotalPagado, P46, pagoUSD, IFERROR(SUMIFS(Aux_Datos!$C:$C, Aux_Datos!$B:$B, idVenta, Aux_Datos!$D:$D, "USD"), 0), pagoVES, IFERROR(SUMIFS(Aux_Datos!$C:$C, Aux_Datos!$B:$B, idVenta, Aux_Datos!$D:$D, "VES"), 0), IF(pagoUSD >= (montoTotalPagado * 0.84), "USD", IF(pagoVES >= (montoTotalPagado * 0.84), "VES", "MIXTO")) ) ) -> USD | R46: =M46-P46 -> 0 | S46: =IF(P46=0, "Sin Pago", IFERROR( MAXIFS(Aux_Datos!$A:$A, Aux_Datos!$B:$B, I46&""), IFERROR(MAXIFS(Aux_Datos!$A:$A, Aux_Datos!$B:$B, VALUE(I46)), "Revisar ID") ) ) -> 46132 | T46: =IF(R46<=0, "PAGADA", IF(P46>0, "PAGO PARCIAL", "PENDIENTE")) -> PAGADA | U46: =IF(AND(T46<>"PAGADA", L46<TODAY()), "CRÍTICO: VENCIDA", IF(T46="PAGADA", "SOLVENTE", "EN TIEMPO")) -> SOLVENTE | V46: =IF(T46="PAGADA", 0, IF(S46 < TODAY(), TODAY() - S46, 0)) -> 0 | W46: =IF(P46=0, "Sin Pago", LET( monedaPago, Q46, descuentoAplicado, G46, limitePermitido, IFERROR(VLOOKUP(monedaPago, 'Limites de Descuento'!$A$2:$B595, 2, FALSE), 0), IF(descuentoAplicado > limitePermitido, "ALERTA: EXCESO (" & TEXT(limitePermitido, "0%") & " máx)", "OK") ) ) -> OK | X46: =IF(OR(H46=0, S46="Sin Pago"), "", IF(AND(H46 > 0, S46 > (L46 + 2)), "⚠️ REVISAR DESCUENTO", "OK")) | Y46: 72 | Z46: CUMPLE
A47: S00056 | B47: 46091.665 | C47: Motolavado Yahir | D47: GRIMAN DIAZ HECTOR EDUARDO | E47: 133.99 | F47: 15 días | G47: =IF($E47=0,0,IF(SUMIF(Aux_Datos!$B:$B,$I47,Aux_Datos!$K:$K)/$E47>=VLOOKUP(IF(COUNTIFS(Aux_Datos!$B:$B,$I47,Aux_Datos!$D:$D,"<>USD")=0,"USD","VES"),'Limites de Descuento'!$A$2:$D$4,4,FALSE),MAX(0,1-SUMIF(Aux_Datos!$B:$B,$I47,Aux_Datos!$K:$K)/$E47),0)) -> 0 | I47: =VALUE(MID(A47,2,LEN(A47))) -> 56 | J47: =INT(B47) -> 46091 | K47: =IF(F47="Pago inmediato", 0, IF(F47="", "", IFERROR(VALUE(MID(F47, 1, SEARCH(" ", F47)-1)), ""))) -> 15 | L47: =J47+K47+1 -> 46107 | M47: =E47-(E47*G47)-(E47*H47) -> 133.99 | N47: =IF(T47="PAGADA", 0, IF(L47 < TODAY(), TODAY() - L47, 0)) -> 0 | O47: =IF(T47="PAGADA", "PAGADA", IF(L47 < TODAY(), "VENCIDA", "EN TIEMPO")) -> PAGADA | P47: =LET( idVenta, I47&"", montoTotal, M47, pagos, IFERROR(SUMIF(Aux_Datos!$B:$B, idVenta, Aux_Datos!$K:$K), 0), retenciones, IFERROR(SUMIF(Aux_Datos!$N:$N, idVenta, Aux_Datos!$R:$R), 0), pagos + retenciones ) -> 134 | Q47: =IF(P47=0, "Sin Pago", LET( idVenta, I47&"", montoTotalPagado, P47, pagoUSD, IFERROR(SUMIFS(Aux_Datos!$C:$C, Aux_Datos!$B:$B, idVenta, Aux_Datos!$D:$D, "USD"), 0), pagoVES, IFERROR(SUMIFS(Aux_Datos!$C:$C, Aux_Datos!$B:$B, idVenta, Aux_Datos!$D:$D, "VES"), 0), IF(pagoUSD >= (montoTotalPagado * 0.84), "USD", IF(pagoVES >= (montoTotalPagado * 0.84), "VES", "MIXTO")) ) ) -> USD | R47: =M47-P47 -> -0.01 | S47: =IF(P47=0, "Sin Pago", IFERROR( MAXIFS(Aux_Datos!$A:$A, Aux_Datos!$B:$B, I47&""), IFERROR(MAXIFS(Aux_Datos!$A:$A, Aux_Datos!$B:$B, VALUE(I47)), "Revisar ID") ) ) -> 46122 | T47: =IF(R47<=0, "PAGADA", IF(P47>0, "PAGO PARCIAL", "PENDIENTE")) -> PAGADA | U47: =IF(AND(T47<>"PAGADA", L47<TODAY()), "CRÍTICO: VENCIDA", IF(T47="PAGADA", "SOLVENTE", "EN TIEMPO")) -> SOLVENTE | V47: =IF(T47="PAGADA", 0, IF(S47 < TODAY(), TODAY() - S47, 0)) -> 0 | W47: =IF(P47=0, "Sin Pago", LET( monedaPago, Q47, descuentoAplicado, G47, limitePermitido, IFERROR(VLOOKUP(monedaPago, 'Limites de Descuento'!$A$2:$B595, 2, FALSE), 0), IF(descuentoAplicado > limitePermitido, "ALERTA: EXCESO (" & TEXT(limitePermitido, "0%") & " máx)", "OK") ) ) -> OK | X47: =IF(OR(H47=0, S47="Sin Pago"), "", IF(AND(H47 > 0, S47 > (L47 + 2)), "⚠️ REVISAR DESCUENTO", "OK")) | Y47: 134 | Z47: CUMPLE
A48: S00057 | B48: 46091.696 | C48: Comercial Rio Paraguas C.A | D48: QUEVEDO BASTIDAS NEYKEL DAVID | E48: 84.29 | F48: 15 días | G48: =IF($E48=0,0,IF(SUMIF(Aux_Datos!$B:$B,$I48,Aux_Datos!$K:$K)/$E48>=VLOOKUP(IF(COUNTIFS(Aux_Datos!$B:$B,$I48,Aux_Datos!$D:$D,"<>USD")=0,"USD","VES"),'Limites de Descuento'!$A$2:$D$4,4,FALSE),MAX(0,1-SUMIF(Aux_Datos!$B:$B,$I48,Aux_Datos!$K:$K)/$E48),0)) -> 8.5091199e-07 | I48: =VALUE(MID(A48,2,LEN(A48))) -> 57 | J48: =INT(B48) -> 46091 | K48: =IF(F48="Pago inmediato", 0, IF(F48="", "", IFERROR(VALUE(MID(F48, 1, SEARCH(" ", F48)-1)), ""))) -> 15 | L48: =J48+K48+1 -> 46107 | M48: =E48-(E48*G48)-(E48*H48) -> 84.289928 | N48: =IF(T48="PAGADA", 0, IF(L48 < TODAY(), TODAY() - L48, 0)) -> 0 | O48: =IF(T48="PAGADA", "PAGADA", IF(L48 < TODAY(), "VENCIDA", "EN TIEMPO")) -> PAGADA | P48: =LET( idVenta, I48&"", montoTotal, M48, pagos, IFERROR(SUMIF(Aux_Datos!$B:$B, idVenta, Aux_Datos!$K:$K), 0), retenciones, IFERROR(SUMIF(Aux_Datos!$N:$N, idVenta, Aux_Datos!$R:$R), 0), pagos + retenciones ) -> 84.289928 | Q48: =IF(P48=0, "Sin Pago", LET( idVenta, I48&"", montoTotalPagado, P48, pagoUSD, IFERROR(SUMIFS(Aux_Datos!$C:$C, Aux_Datos!$B:$B, idVenta, Aux_Datos!$D:$D, "USD"), 0), pagoVES, IFERROR(SUMIFS(Aux_Datos!$C:$C, Aux_Datos!$B:$B, idVenta, Aux_Datos!$D:$D, "VES"), 0), IF(pagoUSD >= (montoTotalPagado * 0.84), "USD", IF(pagoVES >= (montoTotalPagado * 0.84), "VES", "MIXTO")) ) ) -> VES | R48: =M48-P48 -> 0 | S48: =IF(P48=0, "Sin Pago", IFERROR( MAXIFS(Aux_Datos!$A:$A, Aux_Datos!$B:$B, I48&""), IFERROR(MAXIFS(Aux_Datos!$A:$A, Aux_Datos!$B:$B, VALUE(I48)), "Revisar ID") ) ) -> 46108 | T48: =IF(R48<=0, "PAGADA", IF(P48>0, "PAGO PARCIAL", "PENDIENTE")) -> PAGADA | U48: =IF(AND(T48<>"PAGADA", L48<TODAY()), "CRÍTICO: VENCIDA", IF(T48="PAGADA", "SOLVENTE", "EN TIEMPO")) -> SOLVENTE | V48: =IF(T48="PAGADA", 0, IF(S48 < TODAY(), TODAY() - S48, 0)) -> 0 | W48: =IF(P48=0, "Sin Pago", LET( monedaPago, Q48, descuentoAplicado, G48, limitePermitido, IFERROR(VLOOKUP(monedaPago, 'Limites de Descuento'!$A$2:$B595, 2, FALSE), 0), IF(descuentoAplicado > limitePermitido, "ALERTA: EXCESO (" & TEXT(limitePermitido, "0%") & " máx)", "OK") ) ) -> OK | X48: =IF(OR(H48=0, S48="Sin Pago"), "", IF(AND(H48 > 0, S48 > (L48 + 2)), "⚠️ REVISAR DESCUENTO", "OK")) | Y48: 84.289928 | Z48: CUMPLE
A49: S00058 | B49: 46091.695 | C49: Repuestos y Accesorios chaustre 2024 | D49: MARTINEZ MONTES JEFFREY ENRIQUE | E49: 241.81 | F49: 15 días | G49: =IF($E49=0,0,IF(SUMIF(Aux_Datos!$B:$B,$I49,Aux_Datos!$K:$K)/$E49>=VLOOKUP(IF(COUNTIFS(Aux_Datos!$B:$B,$I49,Aux_Datos!$D:$D,"<>USD")=0,"USD","VES"),'Limites de Descuento'!$A$2:$D$4,4,FALSE),MAX(0,1-SUMIF(Aux_Datos!$B:$B,$I49,Aux_Datos!$K:$K)/$E49),0)) -> 0 | I49: =VALUE(MID(A49,2,LEN(A49))) -> 58 | J49: =INT(B49) -> 46091 | K49: =IF(F49="Pago inmediato", 0, IF(F49="", "", IFERROR(VALUE(MID(F49, 1, SEARCH(" ", F49)-1)), ""))) -> 15 | L49: =J49+K49+1 -> 46107 | M49: =E49-(E49*G49)-(E49*H49) -> 241.81 | N49: =IF(T49="PAGADA", 0, IF(L49 < TODAY(), TODAY() - L49, 0)) -> 93 | O49: =IF(T49="PAGADA", "PAGADA", IF(L49 < TODAY(), "VENCIDA", "EN TIEMPO")) -> VENCIDA | P49: =LET( idVenta, I49&"", montoTotal, M49, pagos, IFERROR(SUMIF(Aux_Datos!$B:$B, idVenta, Aux_Datos!$K:$K), 0), retenciones, IFERROR(SUMIF(Aux_Datos!$N:$N, idVenta, Aux_Datos!$R:$R), 0), pagos + retenciones ) -> 0 | Q49: =IF(P49=0, "Sin Pago", LET( idVenta, I49&"", montoTotalPagado, P49, pagoUSD, IFERROR(SUMIFS(Aux_Datos!$C:$C, Aux_Datos!$B:$B, idVenta, Aux_Datos!$D:$D, "USD"), 0), pagoVES, IFERROR(SUMIFS(Aux_Datos!$C:$C, Aux_Datos!$B:$B, idVenta, Aux_Datos!$D:$D, "VES"), 0), IF(pagoUSD >= (montoTotalPagado * 0.84), "USD", IF(pagoVES >= (montoTotalPagado * 0.84), "VES", "MIXTO")) ) ) -> Sin Pago | R49: =M49-P49 -> 241.81 | S49: =IF(P49=0, "Sin Pago", IFERROR( MAXIFS(Aux_Datos!$A:$A, Aux_Datos!$B:$B, I49&""), IFERROR(MAXIFS(Aux_Datos!$A:$A, Aux_Datos!$B:$B, VALUE(I49)), "Revisar ID") ) ) -> Sin Pago | T49: =IF(R49<=0, "PAGADA", IF(P49>0, "PAGO PARCIAL", "PENDIENTE")) -> PENDIENTE | U49: =IF(AND(T49<>"PAGADA", L49<TODAY()), "CRÍTICO: VENCIDA", IF(T49="PAGADA", "SOLVENTE", "EN TIEMPO")) -> CRÍTICO: VENCIDA | V49: =IF(T49="PAGADA", 0, IF(S49 < TODAY(), TODAY() - S49, 0)) -> 0 | W49: =IF(P49=0, "Sin Pago", LET( monedaPago, Q49, descuentoAplicado, G49, limitePermitido, IFERROR(VLOOKUP(monedaPago, 'Limites de Descuento'!$A$2:$B595, 2, FALSE), 0), IF(descuentoAplicado > limitePermitido, "ALERTA: EXCESO (" & TEXT(limitePermitido, "0%") & " máx)", "OK") ) ) -> Sin Pago | X49: =IF(OR(H49=0, S49="Sin Pago"), "", IF(AND(H49 > 0, S49 > (L49 + 2)), "⚠️ REVISAR DESCUENTO", "OK")) | Y49: 0 | Z49: SIN MONEDA VÁLIDA
A50: S00059 | B50: 46091.696 | C50: Rhino Toyo Parts, C.A. | D50: OCANTO ZABALA ROSALVY DEL CARMEN | E50: 2036.91 | F50: 21 días | G50: =IF($E50=0,0,IF(SUMIF(Aux_Datos!$B:$B,$I50,Aux_Datos!$K:$K)/$E50>=VLOOKUP(IF(COUNTIFS(Aux_Datos!$B:$B,$I50,Aux_Datos!$D:$D,"<>USD")=0,"USD","VES"),'Limites de Descuento'!$A$2:$D$4,4,FALSE),MAX(0,1-SUMIF(Aux_Datos!$B:$B,$I50,Aux_Datos!$K:$K)/$E50),0)) -> 0 | I50: =VALUE(MID(A50,2,LEN(A50))) -> 59 | J50: =INT(B50) -> 46091 | K50: =IF(F50="Pago inmediato", 0, IF(F50="", "", IFERROR(VALUE(MID(F50, 1, SEARCH(" ", F50)-1)), ""))) -> 21 | L50: =J50+K50+1 -> 46113 | M50: =E50-(E50*G50)-(E50*H50) -> 2036.91 | N50: =IF(T50="PAGADA", 0, IF(L50 < TODAY(), TODAY() - L50, 0)) -> 87 | O50: =IF(T50="PAGADA", "PAGADA", IF(L50 < TODAY(), "VENCIDA", "EN TIEMPO")) -> VENCIDA | P50: =LET( idVenta, I50&"", montoTotal, M50, pagos, IFERROR(SUMIF(Aux_Datos!$B:$B, idVenta, Aux_Datos!$K:$K), 0), retenciones, IFERROR(SUMIF(Aux_Datos!$N:$N, idVenta, Aux_Datos!$R:$R), 0), pagos + retenciones ) -> 200 | Q50: =IF(P50=0, "Sin Pago", LET( idVenta, I50&"", montoTotalPagado, P50, pagoUSD, IFERROR(SUMIFS(Aux_Datos!$C:$C, Aux_Datos!$B:$B, idVenta, Aux_Datos!$D:$D, "USD"), 0), pagoVES, IFERROR(SUMIFS(Aux_Datos!$C:$C, Aux_Datos!$B:$B, idVenta, Aux_Datos!$D:$D, "VES"), 0), IF(pagoUSD >= (montoTotalPagado * 0.84), "USD", IF(pagoVES >= (montoTotalPagado * 0.84), "VES", "MIXTO")) ) ) -> USD | R50: =M50-P50 -> 1836.91 | S50: =IF(P50=0, "Sin Pago", IFERROR( MAXIFS(Aux_Datos!$A:$A, Aux_Datos!$B:$B, I50&""), IFERROR(MAXIFS(Aux_Datos!$A:$A, Aux_Datos!$B:$B, VALUE(I50)), "Revisar ID") ) ) -> 46182 | T50: =IF(R50<=0, "PAGADA", IF(P50>0, "PAGO PARCIAL", "PENDIENTE")) -> PAGO PARCIAL | U50: =IF(AND(T50<>"PAGADA", L50<TODAY()), "CRÍTICO: VENCIDA", IF(T50="PAGADA", "SOLVENTE", "EN TIEMPO")) -> CRÍTICO: VENCIDA | V50: =IF(T50="PAGADA", 0, IF(S50 < TODAY(), TODAY() - S50, 0)) -> 18 | W50: =IF(P50=0, "Sin Pago", LET( monedaPago, Q50, descuentoAplicado, G50, limitePermitido, IFERROR(VLOOKUP(monedaPago, 'Limites de Descuento'!$A$2:$B595, 2, FALSE), 0), IF(descuentoAplicado > limitePermitido, "ALERTA: EXCESO (" & TEXT(limitePermitido, "0%") & " máx)", "OK") ) ) -> OK | X50: =IF(OR(H50=0, S50="Sin Pago"), "", IF(AND(H50 > 0, S50 > (L50 + 2)), "⚠️ REVISAR DESCUENTO", "OK")) | Y50: 200 | Z50: NO CUMPLE
A51: S00060 | B51: 46091.695 | C51: INVERSIONES R&C 1817, c.a. | D51: VILLABONA CORREA ALBA ESTEFANIA | E51: 209.87 | F51: 7 días | G51: =IF($E51=0,0,IF(SUMIF(Aux_Datos!$B:$B,$I51,Aux_Datos!$K:$K)/$E51>=VLOOKUP(IF(COUNTIFS(Aux_Datos!$B:$B,$I51,Aux_Datos!$D:$D,"<>USD")=0,"USD","VES"),'Limites de Descuento'!$A$2:$D$4,4,FALSE),MAX(0,1-SUMIF(Aux_Datos!$B:$B,$I51,Aux_Datos!$K:$K)/$E51),0)) -> 0.094677658 | I51: =VALUE(MID(A51,2,LEN(A51))) -> 60 | J51: =INT(B51) -> 46091 | K51: =IF(F51="Pago inmediato", 0, IF(F51="", "", IFERROR(VALUE(MID(F51, 1, SEARCH(" ", F51)-1)), ""))) -> 7 | L51: =J51+K51+1 -> 46099 | M51: =E51-(E51*G51)-(E51*H51) -> 190 | N51: =IF(T51="PAGADA", 0, IF(L51 < TODAY(), TODAY() - L51, 0)) -> 0 | O51: =IF(T51="PAGADA", "PAGADA", IF(L51 < TODAY(), "VENCIDA", "EN TIEMPO")) -> PAGADA | P51: =LET( idVenta, I51&"", montoTotal, M51, pagos, IFERROR(SUMIF(Aux_Datos!$B:$B, idVenta, Aux_Datos!$K:$K), 0), retenciones, IFERROR(SUMIF(Aux_Datos!$N:$N, idVenta, Aux_Datos!$R:$R), 0), pagos + retenciones ) -> 190 | Q51: =IF(P51=0, "Sin Pago", LET( idVenta, I51&"", montoTotalPagado, P51, pagoUSD, IFERROR(SUMIFS(Aux_Datos!$C:$C, Aux_Datos!$B:$B, idVenta, Aux_Datos!$D:$D, "USD"), 0), pagoVES, IFERROR(SUMIFS(Aux_Datos!$C:$C, Aux_Datos!$B:$B, idVenta, Aux_Datos!$D:$D, "VES"), 0), IF(pagoUSD >= (montoTotalPagado * 0.84), "USD", IF(pagoVES >= (montoTotalPagado * 0.84), "VES", "MIXTO")) ) ) -> USD | R51: =M51-P51 -> 0 | S51: =IF(P51=0, "Sin Pago", IFERROR( MAXIFS(Aux_Datos!$A:$A, Aux_Datos!$B:$B, I51&""), IFERROR(MAXIFS(Aux_Datos!$A:$A, Aux_Datos!$B:$B, VALUE(I51)), "Revisar ID") ) ) -> 46147 | T51: =IF(R51<=0, "PAGADA", IF(P51>0, "PAGO PARCIAL", "PENDIENTE")) -> PAGADA | U51: =IF(AND(T51<>"PAGADA", L51<TODAY()), "CRÍTICO: VENCIDA", IF(T51="PAGADA", "SOLVENTE", "EN TIEMPO")) -> SOLVENTE | V51: =IF(T51="PAGADA", 0, IF(S51 < TODAY(), TODAY() - S51, 0)) -> 0 | W51: =IF(P51=0, "Sin Pago", LET( monedaPago, Q51, descuentoAplicado, G51, limitePermitido, IFERROR(VLOOKUP(monedaPago, 'Limites de Descuento'!$A$2:$B595, 2, FALSE), 0), IF(descuentoAplicado > limitePermitido, "ALERTA: EXCESO (" & TEXT(limitePermitido, "0%") & " máx)", "OK") ) ) -> OK | X51: =IF(OR(H51=0, S51="Sin Pago"), "", IF(AND(H51 > 0, S51 > (L51 + 2)), "⚠️ REVISAR DESCUENTO", "OK")) | Y51: 190 | Z51: CUMPLE
A52: S00061 | B52: 46092.7 | C52: SJMG 2012 C.A | D52: GRIMAN DIAZ HECTOR EDUARDO | E52: 10739.61 | F52: 45 días | G52: =IF($E52=0,0,IF(SUMIF(Aux_Datos!$B:$B,$I52,Aux_Datos!$K:$K)/$E52>=VLOOKUP(IF(COUNTIFS(Aux_Datos!$B:$B,$I52,Aux_Datos!$D:$D,"<>USD")=0,"USD","VES"),'Limites de Descuento'!$A$2:$D$4,4,FALSE),MAX(0,1-SUMIF(Aux_Datos!$B:$B,$I52,Aux_Datos!$K:$K)/$E52),0)) -> 0 | I52: =VALUE(MID(A52,2,LEN(A52))) -> 61 | J52: =INT(B52) -> 46092 | K52: =IF(F52="Pago inmediato", 0, IF(F52="", "", IFERROR(VALUE(MID(F52, 1, SEARCH(" ", F52)-1)), ""))) -> 45 | L52: =J52+K52+1 -> 46138 | M52: =E52-(E52*G52)-(E52*H52) -> 10739.61 | N52: =IF(T52="PAGADA", 0, IF(L52 < TODAY(), TODAY() - L52, 0)) -> 62 | O52: =IF(T52="PAGADA", "PAGADA", IF(L52 < TODAY(), "VENCIDA", "EN TIEMPO")) -> VENCIDA | P52: =LET( idVenta, I52&"", montoTotal, M52, pagos, IFERROR(SUMIF(Aux_Datos!$B:$B, idVenta, Aux_Datos!$K:$K), 0), retenciones, IFERROR(SUMIF(Aux_Datos!$N:$N, idVenta, Aux_Datos!$R:$R), 0), pagos + retenciones ) -> 3498 | Q52: =IF(P52=0, "Sin Pago", LET( idVenta, I52&"", montoTotalPagado, P52, pagoUSD, IFERROR(SUMIFS(Aux_Datos!$C:$C, Aux_Datos!$B:$B, idVenta, Aux_Datos!$D:$D, "USD"), 0), pagoVES, IFERROR(SUMIFS(Aux_Datos!$C:$C, Aux_Datos!$B:$B, idVenta, Aux_Datos!$D:$D, "VES"), 0), IF(pagoUSD >= (montoTotalPagado * 0.84), "USD", IF(pagoVES >= (montoTotalPagado * 0.84), "VES", "MIXTO")) ) ) -> USD | R52: =M52-P52 -> 7241.61 | S52: =IF(P52=0, "Sin Pago", IFERROR( MAXIFS(Aux_Datos!$A:$A, Aux_Datos!$B:$B, I52&""), IFERROR(MAXIFS(Aux_Datos!$A:$A, Aux_Datos!$B:$B, VALUE(I52)), "Revisar ID") ) ) -> 46189 | T52: =IF(R52<=0, "PAGADA", IF(P52>0, "PAGO PARCIAL", "PENDIENTE")) -> PAGO PARCIAL | U52: =IF(AND(T52<>"PAGADA", L52<TODAY()), "CRÍTICO: VENCIDA", IF(T52="PAGADA", "SOLVENTE", "EN TIEMPO")) -> CRÍTICO: VENCIDA | V52: =IF(T52="PAGADA", 0, IF(S52 < TODAY(), TODAY() - S52, 0)) -> 11 | W52: =IF(P52=0, "Sin Pago", LET( monedaPago, Q52, descuentoAplicado, G52, limitePermitido, IFERROR(VLOOKUP(monedaPago, 'Limites de Descuento'!$A$2:$B595, 2, FALSE), 0), IF(descuentoAplicado > limitePermitido, "ALERTA: EXCESO (" & TEXT(limitePermitido, "0%") & " máx)", "OK") ) ) -> OK | X52: =IF(OR(H52=0, S52="Sin Pago"), "", IF(AND(H52 > 0, S52 > (L52 + 2)), "⚠️ REVISAR DESCUENTO", "OK")) | Y52: 3498 | Z52: NO CUMPLE
A53: S00062 | B53: 46092.667 | C53: SJMG 2012 C.A | D53: GRIMAN DIAZ HECTOR EDUARDO | E53: 3393.87 | F53: 45 días | G53: =IF($E53=0,0,IF(SUMIF(Aux_Datos!$B:$B,$I53,Aux_Datos!$K:$K)/$E53>=VLOOKUP(IF(COUNTIFS(Aux_Datos!$B:$B,$I53,Aux_Datos!$D:$D,"<>USD")=0,"USD","VES"),'Limites de Descuento'!$A$2:$D$4,4,FALSE),MAX(0,1-SUMIF(Aux_Datos!$B:$B,$I53,Aux_Datos!$K:$K)/$E53),0)) -> 0.26573499 | I53: =VALUE(MID(A53,2,LEN(A53))) -> 62 | J53: =INT(B53) -> 46092 | K53: =IF(F53="Pago inmediato", 0, IF(F53="", "", IFERROR(VALUE(MID(F53, 1, SEARCH(" ", F53)-1)), ""))) -> 45 | L53: =J53+K53+1 -> 46138 | M53: =E53-(E53*G53)-(E53*H53) -> 2492 | N53: =IF(T53="PAGADA", 0, IF(L53 < TODAY(), TODAY() - L53, 0)) -> 0 | O53: =IF(T53="PAGADA", "PAGADA", IF(L53 < TODAY(), "VENCIDA", "EN TIEMPO")) -> PAGADA | P53: =LET( idVenta, I53&"", montoTotal, M53, pagos, IFERROR(SUMIF(Aux_Datos!$B:$B, idVenta, Aux_Datos!$K:$K), 0), retenciones, IFERROR(SUMIF(Aux_Datos!$N:$N, idVenta, Aux_Datos!$R:$R), 0), pagos + retenciones ) -> 2492 | Q53: =IF(P53=0, "Sin Pago", LET( idVenta, I53&"", montoTotalPagado, P53, pagoUSD, IFERROR(SUMIFS(Aux_Datos!$C:$C, Aux_Datos!$B:$B, idVenta, Aux_Datos!$D:$D, "USD"), 0), pagoVES, IFERROR(SUMIFS(Aux_Datos!$C:$C, Aux_Datos!$B:$B, idVenta, Aux_Datos!$D:$D, "VES"), 0), IF(pagoUSD >= (montoTotalPagado * 0.84), "USD", IF(pagoVES >= (montoTotalPagado * 0.84), "VES", "MIXTO")) ) ) -> USD | R53: =M53-P53 -> 0 | S53: =IF(P53=0, "Sin Pago", IFERROR( MAXIFS(Aux_Datos!$A:$A, Aux_Datos!$B:$B, I53&""), IFERROR(MAXIFS(Aux_Datos!$A:$A, Aux_Datos!$B:$B, VALUE(I53)), "Revisar ID") ) ) -> 46146 | T53: =IF(R53<=0, "PAGADA", IF(P53>0, "PAGO PARCIAL", "PENDIENTE")) -> PAGADA | U53: =IF(AND(T53<>"PAGADA", L53<TODAY()), "CRÍTICO: VENCIDA", IF(T53="PAGADA", "SOLVENTE", "EN TIEMPO")) -> SOLVENTE | V53: =IF(T53="PAGADA", 0, IF(S53 < TODAY(), TODAY() - S53, 0)) -> 0 | W53: =IF(P53=0, "Sin Pago", LET( monedaPago, Q53, descuentoAplicado, G53, limitePermitido, IFERROR(VLOOKUP(monedaPago, 'Limites de Descuento'!$A$2:$B595, 2, FALSE), 0), IF(descuentoAplicado > limitePermitido, "ALERTA: EXCESO (" & TEXT(limitePermitido, "0%") & " máx)", "OK") ) ) -> OK | X53: =IF(OR(H53=0, S53="Sin Pago"), "", IF(AND(H53 > 0, S53 > (L53 + 2)), "⚠️ REVISAR DESCUENTO", "OK")) | Y53: 2492 | Z53: CUMPLE
A54: S00063 | B54: 46092.373 | C54: TorniRepuesto BA 2015, C.A | D54: QUEVEDO BASTIDAS NEYKEL DAVID | E54: 72 | F54: 15 días | G54: =IF($E54=0,0,IF(SUMIF(Aux_Datos!$B:$B,$I54,Aux_Datos!$K:$K)/$E54>=VLOOKUP(IF(COUNTIFS(Aux_Datos!$B:$B,$I54,Aux_Datos!$D:$D,"<>USD")=0,"USD","VES"),'Limites de Descuento'!$A$2:$D$4,4,FALSE),MAX(0,1-SUMIF(Aux_Datos!$B:$B,$I54,Aux_Datos!$K:$K)/$E54),0)) -> 0 | I54: =VALUE(MID(A54,2,LEN(A54))) -> 63 | J54: =INT(B54) -> 46092 | K54: =IF(F54="Pago inmediato", 0, IF(F54="", "", IFERROR(VALUE(MID(F54, 1, SEARCH(" ", F54)-1)), ""))) -> 15 | L54: =J54+K54+1 -> 46108 | M54: =E54-(E54*G54)-(E54*H54) -> 72 | N54: =IF(T54="PAGADA", 0, IF(L54 < TODAY(), TODAY() - L54, 0)) -> 0 | O54: =IF(T54="PAGADA", "PAGADA", IF(L54 < TODAY(), "VENCIDA", "EN TIEMPO")) -> PAGADA | P54: =LET( idVenta, I54&"", montoTotal, M54, pagos, IFERROR(SUMIF(Aux_Datos!$B:$B, idVenta, Aux_Datos!$K:$K), 0), retenciones, IFERROR(SUMIF(Aux_Datos!$N:$N, idVenta, Aux_Datos!$R:$R), 0), pagos + retenciones ) -> 72.000746 | Q54: =IF(P54=0, "Sin Pago", LET( idVenta, I54&"", montoTotalPagado, P54, pagoUSD, IFERROR(SUMIFS(Aux_Datos!$C:$C, Aux_Datos!$B:$B, idVenta, Aux_Datos!$D:$D, "USD"), 0), pagoVES, IFERROR(SUMIFS(Aux_Datos!$C:$C, Aux_Datos!$B:$B, idVenta, Aux_Datos!$D:$D, "VES"), 0), IF(pagoUSD >= (montoTotalPagado * 0.84), "USD", IF(pagoVES >= (montoTotalPagado * 0.84), "VES", "MIXTO")) ) ) -> VES | R54: =M54-P54 -> -0.00074587599 | S54: =IF(P54=0, "Sin Pago", IFERROR( MAXIFS(Aux_Datos!$A:$A, Aux_Datos!$B:$B, I54&""), IFERROR(MAXIFS(Aux_Datos!$A:$A, Aux_Datos!$B:$B, VALUE(I54)), "Revisar ID") ) ) -> 46122 | T54: =IF(R54<=0, "PAGADA", IF(P54>0, "PAGO PARCIAL", "PENDIENTE")) -> PAGADA | U54: =IF(AND(T54<>"PAGADA", L54<TODAY()), "CRÍTICO: VENCIDA", IF(T54="PAGADA", "SOLVENTE", "EN TIEMPO")) -> SOLVENTE | V54: =IF(T54="PAGADA", 0, IF(S54 < TODAY(), TODAY() - S54, 0)) -> 0 | W54: =IF(P54=0, "Sin Pago", LET( monedaPago, Q54, descuentoAplicado, G54, limitePermitido, IFERROR(VLOOKUP(monedaPago, 'Limites de Descuento'!$A$2:$B595, 2, FALSE), 0), IF(descuentoAplicado > limitePermitido, "ALERTA: EXCESO (" & TEXT(limitePermitido, "0%") & " máx)", "OK") ) ) -> OK | X54: =IF(OR(H54=0, S54="Sin Pago"), "", IF(AND(H54 > 0, S54 > (L54 + 2)), "⚠️ REVISAR DESCUENTO", "OK")) | Y54: 72.000746 | Z54: CUMPLE
A55: S00064 | B55: 46092.351 | C55: VAL VAL 16 C.A | D55: QUEVEDO BASTIDAS NEYKEL DAVID | E55: 170.36 | F55: 15 días | G55: =IF($E55=0,0,IF(SUMIF(Aux_Datos!$B:$B,$I55,Aux_Datos!$K:$K)/$E55>=VLOOKUP(IF(COUNTIFS(Aux_Datos!$B:$B,$I55,Aux_Datos!$D:$D,"<>USD")=0,"USD","VES"),'Limites de Descuento'!$A$2:$D$4,4,FALSE),MAX(0,1-SUMIF(Aux_Datos!$B:$B,$I55,Aux_Datos!$K:$K)/$E55),0)) -> 0.013147169 | H55: 0.08 | I55: =VALUE(MID(A55,2,LEN(A55))) -> 64 | J55: =INT(B55) -> 46092 | K55: =IF(F55="Pago inmediato", 0, IF(F55="", "", IFERROR(VALUE(MID(F55, 1, SEARCH(" ", F55)-1)), ""))) -> 15 | L55: =J55+K55+1 -> 46108 | M55: =E55-(E55*G55)-(E55*H55) -> 154.49145 | N55: =IF(T55="PAGADA", 0, IF(L55 < TODAY(), TODAY() - L55, 0)) -> 0 | O55: =IF(T55="PAGADA", "PAGADA", IF(L55 < TODAY(), "VENCIDA", "EN TIEMPO")) -> PAGADA | P55: =LET( idVenta, I55&"", montoTotal, M55, pagos, IFERROR(SUMIF(Aux_Datos!$B:$B, idVenta, Aux_Datos!$K:$K), 0), retenciones, IFERROR(SUMIF(Aux_Datos!$N:$N, idVenta, Aux_Datos!$R:$R), 0), pagos + retenciones ) -> 168.12025 | Q55: =IF(P55=0, "Sin Pago", LET( idVenta, I55&"", montoTotalPagado, P55, pagoUSD, IFERROR(SUMIFS(Aux_Datos!$C:$C, Aux_Datos!$B:$B, idVenta, Aux_Datos!$D:$D, "USD"), 0), pagoVES, IFERROR(SUMIFS(Aux_Datos!$C:$C, Aux_Datos!$B:$B, idVenta, Aux_Datos!$D:$D, "VES"), 0), IF(pagoUSD >= (montoTotalPagado * 0.84), "USD", IF(pagoVES >= (montoTotalPagado * 0.84), "VES", "MIXTO")) ) ) -> VES | R55: =M55-P55 -> -13.6288 | S55: =IF(P55=0, "Sin Pago", IFERROR( MAXIFS(Aux_Datos!$A:$A, Aux_Datos!$B:$B, I55&""), IFERROR(MAXIFS(Aux_Datos!$A:$A, Aux_Datos!$B:$B, VALUE(I55)), "Revisar ID") ) ) -> 46127 | T55: =IF(R55<=0, "PAGADA", IF(P55>0, "PAGO PARCIAL", "PENDIENTE")) -> PAGADA | U55: =IF(AND(T55<>"PAGADA", L55<TODAY()), "CRÍTICO: VENCIDA", IF(T55="PAGADA", "SOLVENTE", "EN TIEMPO")) -> SOLVENTE | V55: =IF(T55="PAGADA", 0, IF(S55 < TODAY(), TODAY() - S55, 0)) -> 0 | W55: =IF(P55=0, "Sin Pago", LET( monedaPago, Q55, descuentoAplicado, G55, limitePermitido, IFERROR(VLOOKUP(monedaPago, 'Limites de Descuento'!$A$2:$B595, 2, FALSE), 0), IF(descuentoAplicado > limitePermitido, "ALERTA: EXCESO (" & TEXT(limitePermitido, "0%") & " máx)", "OK") ) ) -> OK | X55: =IF(OR(H55=0, S55="Sin Pago"), "", IF(AND(H55 > 0, S55 > (L55 + 2)), "⚠️ REVISAR DESCUENTO", "OK")) -> ⚠️ REVISAR DESCUENTO | Y55: 168.12025 | Z55: CUMPLE
A56: S00065 | B56: 46092.37 | C56: Auto Servicios HN 6972, C.A | D56: QUEVEDO BASTIDAS NEYKEL DAVID | E56: 375.35 | F56: 15 días | G56: =IF($E56=0,0,IF(SUMIF(Aux_Datos!$B:$B,$I56,Aux_Datos!$K:$K)/$E56>=VLOOKUP(IF(COUNTIFS(Aux_Datos!$B:$B,$I56,Aux_Datos!$D:$D,"<>USD")=0,"USD","VES"),'Limites de Descuento'!$A$2:$D$4,4,FALSE),MAX(0,1-SUMIF(Aux_Datos!$B:$B,$I56,Aux_Datos!$K:$K)/$E56),0)) -> 0 | I56: =VALUE(MID(A56,2,LEN(A56))) -> 65 | J56: =INT(B56) -> 46092 | K56: =IF(F56="Pago inmediato", 0, IF(F56="", "", IFERROR(VALUE(MID(F56, 1, SEARCH(" ", F56)-1)), ""))) -> 15 | L56: =J56+K56+1 -> 46108 | M56: =E56-(E56*G56)-(E56*H56) -> 375.35 | N56: =IF(T56="PAGADA", 0, IF(L56 < TODAY(), TODAY() - L56, 0)) -> 0 | O56: =IF(T56="PAGADA", "PAGADA", IF(L56 < TODAY(), "VENCIDA", "EN TIEMPO")) -> PAGADA | P56: =LET( idVenta, I56&"", montoTotal, M56, pagos, IFERROR(SUMIF(Aux_Datos!$B:$B, idVenta, Aux_Datos!$K:$K), 0), retenciones, IFERROR(SUMIF(Aux_Datos!$N:$N, idVenta, Aux_Datos!$R:$R), 0), pagos + retenciones ) -> 699.86265 | Q56: =IF(P56=0, "Sin Pago", LET( idVenta, I56&"", montoTotalPagado, P56, pagoUSD, IFERROR(SUMIFS(Aux_Datos!$C:$C, Aux_Datos!$B:$B, idVenta, Aux_Datos!$D:$D, "USD"), 0), pagoVES, IFERROR(SUMIFS(Aux_Datos!$C:$C, Aux_Datos!$B:$B, idVenta, Aux_Datos!$D:$D, "VES"), 0), IF(pagoUSD >= (montoTotalPagado * 0.84), "USD", IF(pagoVES >= (montoTotalPagado * 0.84), "VES", "MIXTO")) ) ) -> VES | R56: =M56-P56 -> -324.51265 | S56: =IF(P56=0, "Sin Pago", IFERROR( MAXIFS(Aux_Datos!$A:$A, Aux_Datos!$B:$B, I56&""), IFERROR(MAXIFS(Aux_Datos!$A:$A, Aux_Datos!$B:$B, VALUE(I56)), "Revisar ID") ) ) -> 46146 | T56: =IF(R56<=0, "PAGADA", IF(P56>0, "PAGO PARCIAL", "PENDIENTE")) -> PAGADA | U56: =IF(AND(T56<>"PAGADA", L56<TODAY()), "CRÍTICO: VENCIDA", IF(T56="PAGADA", "SOLVENTE", "EN TIEMPO")) -> SOLVENTE | V56: =IF(T56="PAGADA", 0, IF(S56 < TODAY(), TODAY() - S56, 0)) -> 0 | W56: =IF(P56=0, "Sin Pago", LET( monedaPago, Q56, descuentoAplicado, G56, limitePermitido, IFERROR(VLOOKUP(monedaPago, 'Limites de Descuento'!$A$2:$B595, 2, FALSE), 0), IF(descuentoAplicado > limitePermitido, "ALERTA: EXCESO (" & TEXT(limitePermitido, "0%") & " máx)", "OK") ) ) -> OK | X56: =IF(OR(H56=0, S56="Sin Pago"), "", IF(AND(H56 > 0, S56 > (L56 + 2)), "⚠️ REVISAR DESCUENTO", "OK")) | Y56: 699.86265 | Z56: CUMPLE
A57: S00066 | B57: 46092.666 | C57: EMPRENDIMIENTO IRMA RODRIGUEZ 6 | D57: TORO ARDILES DAVID JOSE | E57: 132.47 | F57: Pago inmediato | G57: =IF($E57=0,0,IF(SUMIF(Aux_Datos!$B:$B,$I57,Aux_Datos!$K:$K)/$E57>=VLOOKUP(IF(COUNTIFS(Aux_Datos!$B:$B,$I57,Aux_Datos!$D:$D,"<>USD")=0,"USD","VES"),'Limites de Descuento'!$A$2:$D$4,4,FALSE),MAX(0,1-SUMIF(Aux_Datos!$B:$B,$I57,Aux_Datos!$K:$K)/$E57),0)) -> 0 | I57: =VALUE(MID(A57,2,LEN(A57))) -> 66 | J57: =INT(B57) -> 46092 | K57: =IF(F57="Pago inmediato", 0, IF(F57="", "", IFERROR(VALUE(MID(F57, 1, SEARCH(" ", F57)-1)), ""))) -> 0 | L57: =J57+K57+1 -> 46093 | M57: =E57-(E57*G57)-(E57*H57) -> 132.47 | N57: =IF(T57="PAGADA", 0, IF(L57 < TODAY(), TODAY() - L57, 0)) -> 0 | O57: =IF(T57="PAGADA", "PAGADA", IF(L57 < TODAY(), "VENCIDA", "EN TIEMPO")) -> PAGADA | P57: =LET( idVenta, I57&"", montoTotal, M57, pagos, IFERROR(SUMIF(Aux_Datos!$B:$B, idVenta, Aux_Datos!$K:$K), 0), retenciones, IFERROR(SUMIF(Aux_Datos!$N:$N, idVenta, Aux_Datos!$R:$R), 0), pagos + retenciones ) -> 132.48 | Q57: =IF(P57=0, "Sin Pago", LET( idVenta, I57&"", montoTotalPagado, P57, pagoUSD, IFERROR(SUMIFS(Aux_Datos!$C:$C, Aux_Datos!$B:$B, idVenta, Aux_Datos!$D:$D, "USD"), 0), pagoVES, IFERROR(SUMIFS(Aux_Datos!$C:$C, Aux_Datos!$B:$B, idVenta, Aux_Datos!$D:$D, "VES"), 0), IF(pagoUSD >= (montoTotalPagado * 0.84), "USD", IF(pagoVES >= (montoTotalPagado * 0.84), "VES", "MIXTO")) ) ) -> USD | R57: =M57-P57 -> -0.01 | S57: =IF(P57=0, "Sin Pago", IFERROR( MAXIFS(Aux_Datos!$A:$A, Aux_Datos!$B:$B, I57&""), IFERROR(MAXIFS(Aux_Datos!$A:$A, Aux_Datos!$B:$B, VALUE(I57)), "Revisar ID") ) ) -> 46094 | T57: =IF(R57<=0, "PAGADA", IF(P57>0, "PAGO PARCIAL", "PENDIENTE")) -> PAGADA | U57: =IF(AND(T57<>"PAGADA", L57<TODAY()), "CRÍTICO: VENCIDA", IF(T57="PAGADA", "SOLVENTE", "EN TIEMPO")) -> SOLVENTE | V57: =IF(T57="PAGADA", 0, IF(S57 < TODAY(), TODAY() - S57, 0)) -> 0 | W57: =IF(P57=0, "Sin Pago", LET( monedaPago, Q57, descuentoAplicado, G57, limitePermitido, IFERROR(VLOOKUP(monedaPago, 'Limites de Descuento'!$A$2:$B595, 2, FALSE), 0), IF(descuentoAplicado > limitePermitido, "ALERTA: EXCESO (" & TEXT(limitePermitido, "0%") & " máx)", "OK") ) ) -> OK | X57: =IF(OR(H57=0, S57="Sin Pago"), "", IF(AND(H57 > 0, S57 > (L57 + 2)), "⚠️ REVISAR DESCUENTO", "OK")) | Y57: 132.48 | Z57: CUMPLE
A58: S00067 | B58: 46092.495 | C58: Jesus luciani Russiani. | D58: CASERES GONZALEZ RONALD OSWALDO | E58: 160.5 | F58: 7 días | G58: =IF($E58=0,0,IF(SUMIF(Aux_Datos!$B:$B,$I58,Aux_Datos!$K:$K)/$E58>=VLOOKUP(IF(COUNTIFS(Aux_Datos!$B:$B,$I58,Aux_Datos!$D:$D,"<>USD")=0,"USD","VES"),'Limites de Descuento'!$A$2:$D$4,4,FALSE),MAX(0,1-SUMIF(Aux_Datos!$B:$B,$I58,Aux_Datos!$K:$K)/$E58),0)) -> 0.0031266394 | I58: =VALUE(MID(A58,2,LEN(A58))) -> 67 | J58: =INT(B58) -> 46092 | K58: =IF(F58="Pago inmediato", 0, IF(F58="", "", IFERROR(VALUE(MID(F58, 1, SEARCH(" ", F58)-1)), ""))) -> 7 | L58: =J58+K58+1 -> 46100 | M58: =E58-(E58*G58)-(E58*H58) -> 159.99817 | N58: =IF(T58="PAGADA", 0, IF(L58 < TODAY(), TODAY() - L58, 0)) -> 0 | O58: =IF(T58="PAGADA", "PAGADA", IF(L58 < TODAY(), "VENCIDA", "EN TIEMPO")) -> PAGADA | P58: =LET( idVenta, I58&"", montoTotal, M58, pagos, IFERROR(SUMIF(Aux_Datos!$B:$B, idVenta, Aux_Datos!$K:$K), 0), retenciones, IFERROR(SUMIF(Aux_Datos!$N:$N, idVenta, Aux_Datos!$R:$R), 0), pagos + retenciones ) -> 159.99817 | Q58: =IF(P58=0, "Sin Pago", LET( idVenta, I58&"", montoTotalPagado, P58, pagoUSD, IFERROR(SUMIFS(Aux_Datos!$C:$C, Aux_Datos!$B:$B, idVenta, Aux_Datos!$D:$D, "USD"), 0), pagoVES, IFERROR(SUMIFS(Aux_Datos!$C:$C, Aux_Datos!$B:$B, idVenta, Aux_Datos!$D:$D, "VES"), 0), IF(pagoUSD >= (montoTotalPagado * 0.84), "USD", IF(pagoVES >= (montoTotalPagado * 0.84), "VES", "MIXTO")) ) ) -> VES | R58: =M58-P58 -> 0 | S58: =IF(P58=0, "Sin Pago", IFERROR( MAXIFS(Aux_Datos!$A:$A, Aux_Datos!$B:$B, I58&""), IFERROR(MAXIFS(Aux_Datos!$A:$A, Aux_Datos!$B:$B, VALUE(I58)), "Revisar ID") ) ) -> 46092 | T58: =IF(R58<=0, "PAGADA", IF(P58>0, "PAGO PARCIAL", "PENDIENTE")) -> PAGADA | U58: =IF(AND(T58<>"PAGADA", L58<TODAY()), "CRÍTICO: VENCIDA", IF(T58="PAGADA", "SOLVENTE", "EN TIEMPO")) -> SOLVENTE | V58: =IF(T58="PAGADA", 0, IF(S58 < TODAY(), TODAY() - S58, 0)) -> 0 | W58: =IF(P58=0, "Sin Pago", LET( monedaPago, Q58, descuentoAplicado, G58, limitePermitido, IFERROR(VLOOKUP(monedaPago, 'Limites de Descuento'!$A$2:$B595, 2, FALSE), 0), IF(descuentoAplicado > limitePermitido, "ALERTA: EXCESO (" & TEXT(limitePermitido, "0%") & " máx)", "OK") ) ) -> OK | X58: =IF(OR(H58=0, S58="Sin Pago"), "", IF(AND(H58 > 0, S58 > (L58 + 2)), "⚠️ REVISAR DESCUENTO", "OK")) | Y58: 159.99817 | Z58: CUMPLE
A59: S00069 | B59: 46092.664 | C59: Katiuska Alejandra Curvelo | D59: GRIMAN DIAZ HECTOR EDUARDO | E59: 560.84 | F59: 15 días | G59: =IF($E59=0,0,IF(SUMIF(Aux_Datos!$B:$B,$I59,Aux_Datos!$K:$K)/$E59>=VLOOKUP(IF(COUNTIFS(Aux_Datos!$B:$B,$I59,Aux_Datos!$D:$D,"<>USD")=0,"USD","VES"),'Limites de Descuento'!$A$2:$D$4,4,FALSE),MAX(0,1-SUMIF(Aux_Datos!$B:$B,$I59,Aux_Datos!$K:$K)/$E59),0)) -> 0 | I59: =VALUE(MID(A59,2,LEN(A59))) -> 69 | J59: =INT(B59) -> 46092 | K59: =IF(F59="Pago inmediato", 0, IF(F59="", "", IFERROR(VALUE(MID(F59, 1, SEARCH(" ", F59)-1)), ""))) -> 15 | L59: =J59+K59+1 -> 46108 | M59: =E59-(E59*G59)-(E59*H59) -> 560.84 | N59: =IF(T59="PAGADA", 0, IF(L59 < TODAY(), TODAY() - L59, 0)) -> 92 | O59: =IF(T59="PAGADA", "PAGADA", IF(L59 < TODAY(), "VENCIDA", "EN TIEMPO")) -> VENCIDA | P59: =LET( idVenta, I59&"", montoTotal, M59, pagos, IFERROR(SUMIF(Aux_Datos!$B:$B, idVenta, Aux_Datos!$K:$K), 0), retenciones, IFERROR(SUMIF(Aux_Datos!$N:$N, idVenta, Aux_Datos!$R:$R), 0), pagos + retenciones ) -> 104 | Q59: =IF(P59=0, "Sin Pago", LET( idVenta, I59&"", montoTotalPagado, P59, pagoUSD, IFERROR(SUMIFS(Aux_Datos!$C:$C, Aux_Datos!$B:$B, idVenta, Aux_Datos!$D:$D, "USD"), 0), pagoVES, IFERROR(SUMIFS(Aux_Datos!$C:$C, Aux_Datos!$B:$B, idVenta, Aux_Datos!$D:$D, "VES"), 0), IF(pagoUSD >= (montoTotalPagado * 0.84), "USD", IF(pagoVES >= (montoTotalPagado * 0.84), "VES", "MIXTO")) ) ) -> USD | R59: =M59-P59 -> 456.84 | S59: =IF(P59=0, "Sin Pago", IFERROR( MAXIFS(Aux_Datos!$A:$A, Aux_Datos!$B:$B, I59&""), IFERROR(MAXIFS(Aux_Datos!$A:$A, Aux_Datos!$B:$B, VALUE(I59)), "Revisar ID") ) ) -> 46163 | T59: =IF(R59<=0, "PAGADA", IF(P59>0, "PAGO PARCIAL", "PENDIENTE")) -> PAGO PARCIAL | U59: =IF(AND(T59<>"PAGADA", L59<TODAY()), "CRÍTICO: VENCIDA", IF(T59="PAGADA", "SOLVENTE", "EN TIEMPO")) -> CRÍTICO: VENCIDA | V59: =IF(T59="PAGADA", 0, IF(S59 < TODAY(), TODAY() - S59, 0)) -> 37 | W59: =IF(P59=0, "Sin Pago", LET( monedaPago, Q59, descuentoAplicado, G59, limitePermitido, IFERROR(VLOOKUP(monedaPago, 'Limites de Descuento'!$A$2:$B595, 2, FALSE), 0), IF(descuentoAplicado > limitePermitido, "ALERTA: EXCESO (" & TEXT(limitePermitido, "0%") & " máx)", "OK") ) ) -> OK | X59: =IF(OR(H59=0, S59="Sin Pago"), "", IF(AND(H59 > 0, S59 > (L59 + 2)), "⚠️ REVISAR DESCUENTO", "OK")) | Y59: 104 | Z59: NO CUMPLE
A60: S00072 | B60: 46092.7 | C60: DISTRIBUIDORA PINOS 181297 C.A | D60: QUEVEDO BASTIDAS NEYKEL DAVID | E60: 78.62 | F60: 15 días | G60: =IF($E60=0,0,IF(SUMIF(Aux_Datos!$B:$B,$I60,Aux_Datos!$K:$K)/$E60>=VLOOKUP(IF(COUNTIFS(Aux_Datos!$B:$B,$I60,Aux_Datos!$D:$D,"<>USD")=0,"USD","VES"),'Limites de Descuento'!$A$2:$D$4,4,FALSE),MAX(0,1-SUMIF(Aux_Datos!$B:$B,$I60,Aux_Datos!$K:$K)/$E60),0)) -> 0 | I60: =VALUE(MID(A60,2,LEN(A60))) -> 72 | J60: =INT(B60) -> 46092 | K60: =IF(F60="Pago inmediato", 0, IF(F60="", "", IFERROR(VALUE(MID(F60, 1, SEARCH(" ", F60)-1)), ""))) -> 15 | L60: =J60+K60+1 -> 46108 | M60: =E60-(E60*G60)-(E60*H60) -> 78.62 | N60: =IF(T60="PAGADA", 0, IF(L60 < TODAY(), TODAY() - L60, 0)) -> 0 | O60: =IF(T60="PAGADA", "PAGADA", IF(L60 < TODAY(), "VENCIDA", "EN TIEMPO")) -> PAGADA | P60: =LET( idVenta, I60&"", montoTotal, M60, pagos, IFERROR(SUMIF(Aux_Datos!$B:$B, idVenta, Aux_Datos!$K:$K), 0), retenciones, IFERROR(SUMIF(Aux_Datos!$N:$N, idVenta, Aux_Datos!$R:$R), 0), pagos + retenciones ) -> 78.620195 | Q60: =IF(P60=0, "Sin Pago", LET( idVenta, I60&"", montoTotalPagado, P60, pagoUSD, IFERROR(SUMIFS(Aux_Datos!$C:$C, Aux_Datos!$B:$B, idVenta, Aux_Datos!$D:$D, "USD"), 0), pagoVES, IFERROR(SUMIFS(Aux_Datos!$C:$C, Aux_Datos!$B:$B, idVenta, Aux_Datos!$D:$D, "VES"), 0), IF(pagoUSD >= (montoTotalPagado * 0.84), "USD", IF(pagoVES >= (montoTotalPagado * 0.84), "VES", "MIXTO")) ) ) -> VES | R60: =M60-P60 -> -0.00019474738 | S60: =IF(P60=0, "Sin Pago", IFERROR( MAXIFS(Aux_Datos!$A:$A, Aux_Datos!$B:$B, I60&""), IFERROR(MAXIFS(Aux_Datos!$A:$A, Aux_Datos!$B:$B, VALUE(I60)), "Revisar ID") ) ) -> 46125 | T60: =IF(R60<=0, "PAGADA", IF(P60>0, "PAGO PARCIAL", "PENDIENTE")) -> PAGADA | U60: =IF(AND(T60<>"PAGADA", L60<TODAY()), "CRÍTICO: VENCIDA", IF(T60="PAGADA", "SOLVENTE", "EN TIEMPO")) -> SOLVENTE | V60: =IF(T60="PAGADA", 0, IF(S60 < TODAY(), TODAY() - S60, 0)) -> 0 | W60: =IF(P60=0, "Sin Pago", LET( monedaPago, Q60, descuentoAplicado, G60, limitePermitido, IFERROR(VLOOKUP(monedaPago, 'Limites de Descuento'!$A$2:$B595, 2, FALSE), 0), IF(descuentoAplicado > limitePermitido, "ALERTA: EXCESO (" & TEXT(limitePermitido, "0%") & " máx)", "OK") ) ) -> OK | X60: =IF(OR(H60=0, S60="Sin Pago"), "", IF(AND(H60 > 0, S60 > (L60 + 2)), "⚠️ REVISAR DESCUENTO", "OK")) | Y60: 78.620195 | Z60: CUMPLE
A61: S00073 | B61: 46093.374 | C61: Remodelaciones Ivanro, C.A | D61: QUEVEDO BASTIDAS NEYKEL DAVID | E61: 415.08 | F61: 15 días | G61: =IF($E61=0,0,IF(SUMIF(Aux_Datos!$B:$B,$I61,Aux_Datos!$K:$K)/$E61>=VLOOKUP(IF(COUNTIFS(Aux_Datos!$B:$B,$I61,Aux_Datos!$D:$D,"<>USD")=0,"USD","VES"),'Limites de Descuento'!$A$2:$D$4,4,FALSE),MAX(0,1-SUMIF(Aux_Datos!$B:$B,$I61,Aux_Datos!$K:$K)/$E61),0)) -> 0 | I61: =VALUE(MID(A61,2,LEN(A61))) -> 73 | J61: =INT(B61) -> 46093 | K61: =IF(F61="Pago inmediato", 0, IF(F61="", "", IFERROR(VALUE(MID(F61, 1, SEARCH(" ", F61)-1)), ""))) -> 15 | L61: =J61+K61+1 -> 46109 | M61: =E61-(E61*G61)-(E61*H61) -> 415.08 | N61: =IF(T61="PAGADA", 0, IF(L61 < TODAY(), TODAY() - L61, 0)) -> 91 | O61: =IF(T61="PAGADA", "PAGADA", IF(L61 < TODAY(), "VENCIDA", "EN TIEMPO")) -> VENCIDA | P61: =LET( idVenta, I61&"", montoTotal, M61, pagos, IFERROR(SUMIF(Aux_Datos!$B:$B, idVenta, Aux_Datos!$K:$K), 0), retenciones, IFERROR(SUMIF(Aux_Datos!$N:$N, idVenta, Aux_Datos!$R:$R), 0), pagos + retenciones ) -> 0 | Q61: =IF(P61=0, "Sin Pago", LET( idVenta, I61&"", montoTotalPagado, P61, pagoUSD, IFERROR(SUMIFS(Aux_Datos!$C:$C, Aux_Datos!$B:$B, idVenta, Aux_Datos!$D:$D, "USD"), 0), pagoVES, IFERROR(SUMIFS(Aux_Datos!$C:$C, Aux_Datos!$B:$B, idVenta, Aux_Datos!$D:$D, "VES"), 0), IF(pagoUSD >= (montoTotalPagado * 0.84), "USD", IF(pagoVES >= (montoTotalPagado * 0.84), "VES", "MIXTO")) ) ) -> Sin Pago | R61: =M61-P61 -> 415.08 | S61: =IF(P61=0, "Sin Pago", IFERROR( MAXIFS(Aux_Datos!$A:$A, Aux_Datos!$B:$B, I61&""), IFERROR(MAXIFS(Aux_Datos!$A:$A, Aux_Datos!$B:$B, VALUE(I61)), "Revisar ID") ) ) -> Sin Pago | T61: =IF(R61<=0, "PAGADA", IF(P61>0, "PAGO PARCIAL", "PENDIENTE")) -> PENDIENTE | U61: =IF(AND(T61<>"PAGADA", L61<TODAY()), "CRÍTICO: VENCIDA", IF(T61="PAGADA", "SOLVENTE", "EN TIEMPO")) -> CRÍTICO: VENCIDA | V61: =IF(T61="PAGADA", 0, IF(S61 < TODAY(), TODAY() - S61, 0)) -> 0 | W61: =IF(P61=0, "Sin Pago", LET( monedaPago, Q61, descuentoAplicado, G61, limitePermitido, IFERROR(VLOOKUP(monedaPago, 'Limites de Descuento'!$A$2:$B595, 2, FALSE), 0), IF(descuentoAplicado > limitePermitido, "ALERTA: EXCESO (" & TEXT(limitePermitido, "0%") & " máx)", "OK") ) ) -> Sin Pago | X61: =IF(OR(H61=0, S61="Sin Pago"), "", IF(AND(H61 > 0, S61 > (L61 + 2)), "⚠️ REVISAR DESCUENTO", "OK")) | Y61: 0 | Z61: SIN MONEDA VÁLIDA
A62: S00074 | B62: 46093.373 | C62: Servicios Nicolazzo 97, C.A | D62: QUEVEDO BASTIDAS NEYKEL DAVID | E62: 183.49 | F62: 15 días | G62: =IF($E62=0,0,IF(SUMIF(Aux_Datos!$B:$B,$I62,Aux_Datos!$K:$K)/$E62>=VLOOKUP(IF(COUNTIFS(Aux_Datos!$B:$B,$I62,Aux_Datos!$D:$D,"<>USD")=0,"USD","VES"),'Limites de Descuento'!$A$2:$D$4,4,FALSE),MAX(0,1-SUMIF(Aux_Datos!$B:$B,$I62,Aux_Datos!$K:$K)/$E62),0)) -> 0.090674856 | I62: =VALUE(MID(A62,2,LEN(A62))) -> 74 | J62: =INT(B62) -> 46093 | K62: =IF(F62="Pago inmediato", 0, IF(F62="", "", IFERROR(VALUE(MID(F62, 1, SEARCH(" ", F62)-1)), ""))) -> 15 | L62: =J62+K62+1 -> 46109 | M62: =E62-(E62*G62)-(E62*H62) -> 166.85207 | N62: =IF(T62="PAGADA", 0, IF(L62 < TODAY(), TODAY() - L62, 0)) -> 0 | O62: =IF(T62="PAGADA", "PAGADA", IF(L62 < TODAY(), "VENCIDA", "EN TIEMPO")) -> PAGADA | P62: =LET( idVenta, I62&"", montoTotal, M62, pagos, IFERROR(SUMIF(Aux_Datos!$B:$B, idVenta, Aux_Datos!$K:$K), 0), retenciones, IFERROR(SUMIF(Aux_Datos!$N:$N, idVenta, Aux_Datos!$R:$R), 0), pagos + retenciones ) -> 166.85207 | Q62: =IF(P62=0, "Sin Pago", LET( idVenta, I62&"", montoTotalPagado, P62, pagoUSD, IFERROR(SUMIFS(Aux_Datos!$C:$C, Aux_Datos!$B:$B, idVenta, Aux_Datos!$D:$D, "USD"), 0), pagoVES, IFERROR(SUMIFS(Aux_Datos!$C:$C, Aux_Datos!$B:$B, idVenta, Aux_Datos!$D:$D, "VES"), 0), IF(pagoUSD >= (montoTotalPagado * 0.84), "USD", IF(pagoVES >= (montoTotalPagado * 0.84), "VES", "MIXTO")) ) ) -> VES | R62: =M62-P62 -> 0 | S62: =IF(P62=0, "Sin Pago", IFERROR( MAXIFS(Aux_Datos!$A:$A, Aux_Datos!$B:$B, I62&""), IFERROR(MAXIFS(Aux_Datos!$A:$A, Aux_Datos!$B:$B, VALUE(I62)), "Revisar ID") ) ) -> 46169 | T62: =IF(R62<=0, "PAGADA", IF(P62>0, "PAGO PARCIAL", "PENDIENTE")) -> PAGADA | U62: =IF(AND(T62<>"PAGADA", L62<TODAY()), "CRÍTICO: VENCIDA", IF(T62="PAGADA", "SOLVENTE", "EN TIEMPO")) -> SOLVENTE | V62: =IF(T62="PAGADA", 0, IF(S62 < TODAY(), TODAY() - S62, 0)) -> 0 | W62: =IF(P62=0, "Sin Pago", LET( monedaPago, Q62, descuentoAplicado, G62, limitePermitido, IFERROR(VLOOKUP(monedaPago, 'Limites de Descuento'!$A$2:$B595, 2, FALSE), 0), IF(descuentoAplicado > limitePermitido, "ALERTA: EXCESO (" & TEXT(limitePermitido, "0%") & " máx)", "OK") ) ) -> OK | X62: =IF(OR(H62=0, S62="Sin Pago"), "", IF(AND(H62 > 0, S62 > (L62 + 2)), "⚠️ REVISAR DESCUENTO", "OK")) | Y62: 166.85207 | Z62: CUMPLE
A63: S00077 | B63: 46093.412 | C63: Ruben Dario Fernandez | D63: CASERES GONZALEZ RONALD OSWALDO | E63: 35.99 | F63: 15 días | G63: =IF($E63=0,0,IF(SUMIF(Aux_Datos!$B:$B,$I63,Aux_Datos!$K:$K)/$E63>=VLOOKUP(IF(COUNTIFS(Aux_Datos!$B:$B,$I63,Aux_Datos!$D:$D,"<>USD")=0,"USD","VES"),'Limites de Descuento'!$A$2:$D$4,4,FALSE),MAX(0,1-SUMIF(Aux_Datos!$B:$B,$I63,Aux_Datos!$K:$K)/$E63),0)) -> 0 | I63: =VALUE(MID(A63,2,LEN(A63))) -> 77 | J63: =INT(B63) -> 46093 | K63: =IF(F63="Pago inmediato", 0, IF(F63="", "", IFERROR(VALUE(MID(F63, 1, SEARCH(" ", F63)-1)), ""))) -> 15 | L63: =J63+K63+1 -> 46109 | M63: =E63-(E63*G63)-(E63*H63) -> 35.99 | N63: =IF(T63="PAGADA", 0, IF(L63 < TODAY(), TODAY() - L63, 0)) -> 0 | O63: =IF(T63="PAGADA", "PAGADA", IF(L63 < TODAY(), "VENCIDA", "EN TIEMPO")) -> PAGADA | P63: =LET( idVenta, I63&"", montoTotal, M63, pagos, IFERROR(SUMIF(Aux_Datos!$B:$B, idVenta, Aux_Datos!$K:$K), 0), retenciones, IFERROR(SUMIF(Aux_Datos!$N:$N, idVenta, Aux_Datos!$R:$R), 0), pagos + retenciones ) -> 36 | Q63: =IF(P63=0, "Sin Pago", LET( idVenta, I63&"", montoTotalPagado, P63, pagoUSD, IFERROR(SUMIFS(Aux_Datos!$C:$C, Aux_Datos!$B:$B, idVenta, Aux_Datos!$D:$D, "USD"), 0), pagoVES, IFERROR(SUMIFS(Aux_Datos!$C:$C, Aux_Datos!$B:$B, idVenta, Aux_Datos!$D:$D, "VES"), 0), IF(pagoUSD >= (montoTotalPagado * 0.84), "USD", IF(pagoVES >= (montoTotalPagado * 0.84), "VES", "MIXTO")) ) ) -> USD | R63: =M63-P63 -> -0.01 | S63: =IF(P63=0, "Sin Pago", IFERROR( MAXIFS(Aux_Datos!$A:$A, Aux_Datos!$B:$B, I63&""), IFERROR(MAXIFS(Aux_Datos!$A:$A, Aux_Datos!$B:$B, VALUE(I63)), "Revisar ID") ) ) -> 46093 | T63: =IF(R63<=0, "PAGADA", IF(P63>0, "PAGO PARCIAL", "PENDIENTE")) -> PAGADA | U63: =IF(AND(T63<>"PAGADA", L63<TODAY()), "CRÍTICO: VENCIDA", IF(T63="PAGADA", "SOLVENTE", "EN TIEMPO")) -> SOLVENTE | V63: =IF(T63="PAGADA", 0, IF(S63 < TODAY(), TODAY() - S63, 0)) -> 0 | W63: =IF(P63=0, "Sin Pago", LET( monedaPago, Q63, descuentoAplicado, G63, limitePermitido, IFERROR(VLOOKUP(monedaPago, 'Limites de Descuento'!$A$2:$B595, 2, FALSE), 0), IF(descuentoAplicado > limitePermitido, "ALERTA: EXCESO (" & TEXT(limitePermitido, "0%") & " máx)", "OK") ) ) -> OK | X63: =IF(OR(H63=0, S63="Sin Pago"), "", IF(AND(H63 > 0, S63 > (L63 + 2)), "⚠️ REVISAR DESCUENTO", "OK")) | Y63: 36 | Z63: CUMPLE
A64: S00078 | B64: 46093.523 | C64: MULTISERVICIOS RECAM13, C.A. | D64: TORO ARDILES DAVID JOSE | E64: 300.86 | F64: Pago inmediato | G64: =IF($E64=0,0,IF(SUMIF(Aux_Datos!$B:$B,$I64,Aux_Datos!$K:$K)/$E64>=VLOOKUP(IF(COUNTIFS(Aux_Datos!$B:$B,$I64,Aux_Datos!$D:$D,"<>USD")=0,"USD","VES"),'Limites de Descuento'!$A$2:$D$4,4,FALSE),MAX(0,1-SUMIF(Aux_Datos!$B:$B,$I64,Aux_Datos!$K:$K)/$E64),0)) -> 0 | I64: =VALUE(MID(A64,2,LEN(A64))) -> 78 | J64: =INT(B64) -> 46093 | K64: =IF(F64="Pago inmediato", 0, IF(F64="", "", IFERROR(VALUE(MID(F64, 1, SEARCH(" ", F64)-1)), ""))) -> 0 | L64: =J64+K64+1 -> 46094 | M64: =E64-(E64*G64)-(E64*H64) -> 300.86 | N64: =IF(T64="PAGADA", 0, IF(L64 < TODAY(), TODAY() - L64, 0)) -> 106 | O64: =IF(T64="PAGADA", "PAGADA", IF(L64 < TODAY(), "VENCIDA", "EN TIEMPO")) -> VENCIDA | P64: =LET( idVenta, I64&"", montoTotal, M64, pagos, IFERROR(SUMIF(Aux_Datos!$B:$B, idVenta, Aux_Datos!$K:$K), 0), retenciones, IFERROR(SUMIF(Aux_Datos!$N:$N, idVenta, Aux_Datos!$R:$R), 0), pagos + retenciones ) -> 179.66749 | Q64: =IF(P64=0, "Sin Pago", LET( idVenta, I64&"", montoTotalPagado, P64, pagoUSD, IFERROR(SUMIFS(Aux_Datos!$C:$C, Aux_Datos!$B:$B, idVenta, Aux_Datos!$D:$D, "USD"), 0), pagoVES, IFERROR(SUMIFS(Aux_Datos!$C:$C, Aux_Datos!$B:$B, idVenta, Aux_Datos!$D:$D, "VES"), 0), IF(pagoUSD >= (montoTotalPagado * 0.84), "USD", IF(pagoVES >= (montoTotalPagado * 0.84), "VES", "MIXTO")) ) ) -> VES | R64: =M64-P64 -> 121.19251 | S64: =IF(P64=0, "Sin Pago", IFERROR( MAXIFS(Aux_Datos!$A:$A, Aux_Datos!$B:$B, I64&""), IFERROR(MAXIFS(Aux_Datos!$A:$A, Aux_Datos!$B:$B, VALUE(I64)), "Revisar ID") ) ) -> 46196 | T64: =IF(R64<=0, "PAGADA", IF(P64>0, "PAGO PARCIAL", "PENDIENTE")) -> PAGO PARCIAL | U64: =IF(AND(T64<>"PAGADA", L64<TODAY()), "CRÍTICO: VENCIDA", IF(T64="PAGADA", "SOLVENTE", "EN TIEMPO")) -> CRÍTICO: VENCIDA | V64: =IF(T64="PAGADA", 0, IF(S64 < TODAY(), TODAY() - S64, 0)) -> 4 | W64: =IF(P64=0, "Sin Pago", LET( monedaPago, Q64, descuentoAplicado, G64, limitePermitido, IFERROR(VLOOKUP(monedaPago, 'Limites de Descuento'!$A$2:$B595, 2, FALSE), 0), IF(descuentoAplicado > limitePermitido, "ALERTA: EXCESO (" & TEXT(limitePermitido, "0%") & " máx)", "OK") ) ) -> OK | X64: =IF(OR(H64=0, S64="Sin Pago"), "", IF(AND(H64 > 0, S64 > (L64 + 2)), "⚠️ REVISAR DESCUENTO", "OK")) | Y64: 179.66749 | Z64: NO CUMPLE
A65: S00079 | B65: 46093.642 | C65: E&M CAR SHOP C.A | D65: BETANCOURT ROBRIGUEZ LUIS ENRRIQUE | E65: 533.34 | F65: 15 días | G65: =IF($E65=0,0,IF(SUMIF(Aux_Datos!$B:$B,$I65,Aux_Datos!$K:$K)/$E65>=VLOOKUP(IF(COUNTIFS(Aux_Datos!$B:$B,$I65,Aux_Datos!$D:$D,"<>USD")=0,"USD","VES"),'Limites de Descuento'!$A$2:$D$4,4,FALSE),MAX(0,1-SUMIF(Aux_Datos!$B:$B,$I65,Aux_Datos!$K:$K)/$E65),0)) -> 0.13838151 | I65: =VALUE(MID(A65,2,LEN(A65))) -> 79 | J65: =INT(B65) -> 46093 | K65: =IF(F65="Pago inmediato", 0, IF(F65="", "", IFERROR(VALUE(MID(F65, 1, SEARCH(" ", F65)-1)), ""))) -> 15 | L65: =J65+K65+1 -> 46109 | M65: =E65-(E65*G65)-(E65*H65) -> 459.5356 | N65: =IF(T65="PAGADA", 0, IF(L65 < TODAY(), TODAY() - L65, 0)) -> 0 | O65: =IF(T65="PAGADA", "PAGADA", IF(L65 < TODAY(), "VENCIDA", "EN TIEMPO")) -> PAGADA | P65: =LET( idVenta, I65&"", montoTotal, M65, pagos, IFERROR(SUMIF(Aux_Datos!$B:$B, idVenta, Aux_Datos!$K:$K), 0), retenciones, IFERROR(SUMIF(Aux_Datos!$N:$N, idVenta, Aux_Datos!$R:$R), 0), pagos + retenciones ) -> 459.5356 | Q65: =IF(P65=0, "Sin Pago", LET( idVenta, I65&"", montoTotalPagado, P65, pagoUSD, IFERROR(SUMIFS(Aux_Datos!$C:$C, Aux_Datos!$B:$B, idVenta, Aux_Datos!$D:$D, "USD"), 0), pagoVES, IFERROR(SUMIFS(Aux_Datos!$C:$C, Aux_Datos!$B:$B, idVenta, Aux_Datos!$D:$D, "VES"), 0), IF(pagoUSD >= (montoTotalPagado * 0.84), "USD", IF(pagoVES >= (montoTotalPagado * 0.84), "VES", "MIXTO")) ) ) -> VES | R65: =M65-P65 -> 0 | S65: =IF(P65=0, "Sin Pago", IFERROR( MAXIFS(Aux_Datos!$A:$A, Aux_Datos!$B:$B, I65&""), IFERROR(MAXIFS(Aux_Datos!$A:$A, Aux_Datos!$B:$B, VALUE(I65)), "Revisar ID") ) ) -> 46140 | T65: =IF(R65<=0, "PAGADA", IF(P65>0, "PAGO PARCIAL", "PENDIENTE")) -> PAGADA | U65: =IF(AND(T65<>"PAGADA", L65<TODAY()), "CRÍTICO: VENCIDA", IF(T65="PAGADA", "SOLVENTE", "EN TIEMPO")) -> SOLVENTE | V65: =IF(T65="PAGADA", 0, IF(S65 < TODAY(), TODAY() - S65, 0)) -> 0 | W65: =IF(P65=0, "Sin Pago", LET( monedaPago, Q65, descuentoAplicado, G65, limitePermitido, IFERROR(VLOOKUP(monedaPago, 'Limites de Descuento'!$A$2:$B595, 2, FALSE), 0), IF(descuentoAplicado > limitePermitido, "ALERTA: EXCESO (" & TEXT(limitePermitido, "0%") & " máx)", "OK") ) ) -> OK | X65: =IF(OR(H65=0, S65="Sin Pago"), "", IF(AND(H65 > 0, S65 > (L65 + 2)), "⚠️ REVISAR DESCUENTO", "OK")) | Y65: 459.5356 | Z65: CUMPLE
A66: S00081 | B66: 46093.713 | C66: Coffee Party, C.A. | D66: OCANTO ZABALA ROSALVY DEL CARMEN | E66: 71.99 | F66: 7 días | G66: =IF($E66=0,0,IF(SUMIF(Aux_Datos!$B:$B,$I66,Aux_Datos!$K:$K)/$E66>=VLOOKUP(IF(COUNTIFS(Aux_Datos!$B:$B,$I66,Aux_Datos!$D:$D,"<>USD")=0,"USD","VES"),'Limites de Descuento'!$A$2:$D$4,4,FALSE),MAX(0,1-SUMIF(Aux_Datos!$B:$B,$I66,Aux_Datos!$K:$K)/$E66),0)) -> 0 | I66: =VALUE(MID(A66,2,LEN(A66))) -> 81 | J66: =INT(B66) -> 46093 | K66: =IF(F66="Pago inmediato", 0, IF(F66="", "", IFERROR(VALUE(MID(F66, 1, SEARCH(" ", F66)-1)), ""))) -> 7 | L66: =J66+K66+1 -> 46101 | M66: =E66-(E66*G66)-(E66*H66) -> 71.99 | N66: =IF(T66="PAGADA", 0, IF(L66 < TODAY(), TODAY() - L66, 0)) -> 0 | O66: =IF(T66="PAGADA", "PAGADA", IF(L66 < TODAY(), "VENCIDA", "EN TIEMPO")) -> PAGADA | P66: =LET( idVenta, I66&"", montoTotal, M66, pagos, IFERROR(SUMIF(Aux_Datos!$B:$B, idVenta, Aux_Datos!$K:$K), 0), retenciones, IFERROR(SUMIF(Aux_Datos!$N:$N, idVenta, Aux_Datos!$R:$R), 0), pagos + retenciones ) -> 72 | Q66: =IF(P66=0, "Sin Pago", LET( idVenta, I66&"", montoTotalPagado, P66, pagoUSD, IFERROR(SUMIFS(Aux_Datos!$C:$C, Aux_Datos!$B:$B, idVenta, Aux_Datos!$D:$D, "USD"), 0), pagoVES, IFERROR(SUMIFS(Aux_Datos!$C:$C, Aux_Datos!$B:$B, idVenta, Aux_Datos!$D:$D, "VES"), 0), IF(pagoUSD >= (montoTotalPagado * 0.84), "USD", IF(pagoVES >= (montoTotalPagado * 0.84), "VES", "MIXTO")) ) ) -> USD | R66: =M66-P66 -> -0.01 | S66: =IF(P66=0, "Sin Pago", IFERROR( MAXIFS(Aux_Datos!$A:$A, Aux_Datos!$B:$B, I66&""), IFERROR(MAXIFS(Aux_Datos!$A:$A, Aux_Datos!$B:$B, VALUE(I66)), "Revisar ID") ) ) -> 46107 | T66: =IF(R66<=0, "PAGADA", IF(P66>0, "PAGO PARCIAL", "PENDIENTE")) -> PAGADA | U66: =IF(AND(T66<>"PAGADA", L66<TODAY()), "CRÍTICO: VENCIDA", IF(T66="PAGADA", "SOLVENTE", "EN TIEMPO")) -> SOLVENTE | V66: =IF(T66="PAGADA", 0, IF(S66 < TODAY(), TODAY() - S66, 0)) -> 0 | W66: =IF(P66=0, "Sin Pago", LET( monedaPago, Q66, descuentoAplicado, G66, limitePermitido, IFERROR(VLOOKUP(monedaPago, 'Limites de Descuento'!$A$2:$B595, 2, FALSE), 0), IF(descuentoAplicado > limitePermitido, "ALERTA: EXCESO (" & TEXT(limitePermitido, "0%") & " máx)", "OK") ) ) -> OK | X66: =IF(OR(H66=0, S66="Sin Pago"), "", IF(AND(H66 > 0, S66 > (L66 + 2)), "⚠️ REVISAR DESCUENTO", "OK")) | Y66: 72 | Z66: CUMPLE
A67: S00082 | B67: 46093.662 | C67: Pedro Castro | D67: BETANCOURT ROBRIGUEZ LUIS ENRRIQUE | E67: 1633.07 | F67: 15 días | G67: =IF($E67=0,0,IF(SUMIF(Aux_Datos!$B:$B,$I67,Aux_Datos!$K:$K)/$E67>=VLOOKUP(IF(COUNTIFS(Aux_Datos!$B:$B,$I67,Aux_Datos!$D:$D,"<>USD")=0,"USD","VES"),'Limites de Descuento'!$A$2:$D$4,4,FALSE),MAX(0,1-SUMIF(Aux_Datos!$B:$B,$I67,Aux_Datos!$K:$K)/$E67),0)) -> 0.23457047 | I67: =VALUE(MID(A67,2,LEN(A67))) -> 82 | J67: =INT(B67) -> 46093 | K67: =IF(F67="Pago inmediato", 0, IF(F67="", "", IFERROR(VALUE(MID(F67, 1, SEARCH(" ", F67)-1)), ""))) -> 15 | L67: =J67+K67+1 -> 46109 | M67: =E67-(E67*G67)-(E67*H67) -> 1250 | N67: =IF(T67="PAGADA", 0, IF(L67 < TODAY(), TODAY() - L67, 0)) -> 0 | O67: =IF(T67="PAGADA", "PAGADA", IF(L67 < TODAY(), "VENCIDA", "EN TIEMPO")) -> PAGADA | P67: =LET( idVenta, I67&"", montoTotal, M67, pagos, IFERROR(SUMIF(Aux_Datos!$B:$B, idVenta, Aux_Datos!$K:$K), 0), retenciones, IFERROR(SUMIF(Aux_Datos!$N:$N, idVenta, Aux_Datos!$R:$R), 0), pagos + retenciones ) -> 1250 | Q67: =IF(P67=0, "Sin Pago", LET( idVenta, I67&"", montoTotalPagado, P67, pagoUSD, IFERROR(SUMIFS(Aux_Datos!$C:$C, Aux_Datos!$B:$B, idVenta, Aux_Datos!$D:$D, "USD"), 0), pagoVES, IFERROR(SUMIFS(Aux_Datos!$C:$C, Aux_Datos!$B:$B, idVenta, Aux_Datos!$D:$D, "VES"), 0), IF(pagoUSD >= (montoTotalPagado * 0.84), "USD", IF(pagoVES >= (montoTotalPagado * 0.84), "VES", "MIXTO")) ) ) -> USD | R67: =M67-P67 -> 0 | S67: =IF(P67=0, "Sin Pago", IFERROR( MAXIFS(Aux_Datos!$A:$A, Aux_Datos!$B:$B, I67&""), IFERROR(MAXIFS(Aux_Datos!$A:$A, Aux_Datos!$B:$B, VALUE(I67)), "Revisar ID") ) ) -> 46160 | T67: =IF(R67<=0, "PAGADA", IF(P67>0, "PAGO PARCIAL", "PENDIENTE")) -> PAGADA | U67: =IF(AND(T67<>"PAGADA", L67<TODAY()), "CRÍTICO: VENCIDA", IF(T67="PAGADA", "SOLVENTE", "EN TIEMPO")) -> SOLVENTE | V67: =IF(T67="PAGADA", 0, IF(S67 < TODAY(), TODAY() - S67, 0)) -> 0 | W67: =IF(P67=0, "Sin Pago", LET( monedaPago, Q67, descuentoAplicado, G67, limitePermitido, IFERROR(VLOOKUP(monedaPago, 'Limites de Descuento'!$A$2:$B595, 2, FALSE), 0), IF(descuentoAplicado > limitePermitido, "ALERTA: EXCESO (" & TEXT(limitePermitido, "0%") & " máx)", "OK") ) ) -> OK | X67: =IF(OR(H67=0, S67="Sin Pago"), "", IF(AND(H67 > 0, S67 > (L67 + 2)), "⚠️ REVISAR DESCUENTO", "OK")) | Y67: 1250 | Z67: CUMPLE
A68: S00083 | B68: 46093.73 | C68: Inversiones Famasa, C.A | D68: MARTINEZ MONTES JEFFREY ENRIQUE | E68: 970.07 | F68: 15 días | G68: =IF($E68=0,0,IF(SUMIF(Aux_Datos!$B:$B,$I68,Aux_Datos!$K:$K)/$E68>=VLOOKUP(IF(COUNTIFS(Aux_Datos!$B:$B,$I68,Aux_Datos!$D:$D,"<>USD")=0,"USD","VES"),'Limites de Descuento'!$A$2:$D$4,4,FALSE),MAX(0,1-SUMIF(Aux_Datos!$B:$B,$I68,Aux_Datos!$K:$K)/$E68),0)) -> 0 | I68: =VALUE(MID(A68,2,LEN(A68))) -> 83 | J68: =INT(B68) -> 46093 | K68: =IF(F68="Pago inmediato", 0, IF(F68="", "", IFERROR(VALUE(MID(F68, 1, SEARCH(" ", F68)-1)), ""))) -> 15 | L68: =J68+K68+1 -> 46109 | M68: =E68-(E68*G68)-(E68*H68) -> 970.07 | N68: =IF(T68="PAGADA", 0, IF(L68 < TODAY(), TODAY() - L68, 0)) -> 91 | O68: =IF(T68="PAGADA", "PAGADA", IF(L68 < TODAY(), "VENCIDA", "EN TIEMPO")) -> VENCIDA | P68: =LET( idVenta, I68&"", montoTotal, M68, pagos, IFERROR(SUMIF(Aux_Datos!$B:$B, idVenta, Aux_Datos!$K:$K), 0), retenciones, IFERROR(SUMIF(Aux_Datos!$N:$N, idVenta, Aux_Datos!$R:$R), 0), pagos + retenciones ) -> 470.45946 | Q68: =IF(P68=0, "Sin Pago", LET( idVenta, I68&"", montoTotalPagado, P68, pagoUSD, IFERROR(SUMIFS(Aux_Datos!$C:$C, Aux_Datos!$B:$B, idVenta, Aux_Datos!$D:$D, "USD"), 0), pagoVES, IFERROR(SUMIFS(Aux_Datos!$C:$C, Aux_Datos!$B:$B, idVenta, Aux_Datos!$D:$D, "VES"), 0), IF(pagoUSD >= (montoTotalPagado * 0.84), "USD", IF(pagoVES >= (montoTotalPagado * 0.84), "VES", "MIXTO")) ) ) -> VES | R68: =M68-P68 -> 499.61054 | S68: =IF(P68=0, "Sin Pago", IFERROR( MAXIFS(Aux_Datos!$A:$A, Aux_Datos!$B:$B, I68&""), IFERROR(MAXIFS(Aux_Datos!$A:$A, Aux_Datos!$B:$B, VALUE(I68)), "Revisar ID") ) ) -> 46175 | T68: =IF(R68<=0, "PAGADA", IF(P68>0, "PAGO PARCIAL", "PENDIENTE")) -> PAGO PARCIAL | U68: =IF(AND(T68<>"PAGADA", L68<TODAY()), "CRÍTICO: VENCIDA", IF(T68="PAGADA", "SOLVENTE", "EN TIEMPO")) -> CRÍTICO: VENCIDA | V68: =IF(T68="PAGADA", 0, IF(S68 < TODAY(), TODAY() - S68, 0)) -> 25 | W68: =IF(P68=0, "Sin Pago", LET( monedaPago, Q68, descuentoAplicado, G68, limitePermitido, IFERROR(VLOOKUP(monedaPago, 'Limites de Descuento'!$A$2:$B595, 2, FALSE), 0), IF(descuentoAplicado > limitePermitido, "ALERTA: EXCESO (" & TEXT(limitePermitido, "0%") & " máx)", "OK") ) ) -> OK | X68: =IF(OR(H68=0, S68="Sin Pago"), "", IF(AND(H68 > 0, S68 > (L68 + 2)), "⚠️ REVISAR DESCUENTO", "OK")) | Y68: 470.45946 | Z68: NO CUMPLE
A69: S00084 | B69: 46093.745 | C69: Inversiones maxgad & ef | D69: PEREZ DIAZ ANGEL DE DIOS | E69: 67.37 | F69: 7 días | G69: =IF($E69=0,0,IF(SUMIF(Aux_Datos!$B:$B,$I69,Aux_Datos!$K:$K)/$E69>=VLOOKUP(IF(COUNTIFS(Aux_Datos!$B:$B,$I69,Aux_Datos!$D:$D,"<>USD")=0,"USD","VES"),'Limites de Descuento'!$A$2:$D$4,4,FALSE),MAX(0,1-SUMIF(Aux_Datos!$B:$B,$I69,Aux_Datos!$K:$K)/$E69),0)) -> 0 | I69: =VALUE(MID(A69,2,LEN(A69))) -> 84 | J69: =INT(B69) -> 46093 | K69: =IF(F69="Pago inmediato", 0, IF(F69="", "", IFERROR(VALUE(MID(F69, 1, SEARCH(" ", F69)-1)), ""))) -> 7 | L69: =J69+K69+1 -> 46101 | M69: =E69-(E69*G69)-(E69*H69) -> 67.37 | N69: =IF(T69="PAGADA", 0, IF(L69 < TODAY(), TODAY() - L69, 0)) -> 99 | O69: =IF(T69="PAGADA", "PAGADA", IF(L69 < TODAY(), "VENCIDA", "EN TIEMPO")) -> VENCIDA | P69: =LET( idVenta, I69&"", montoTotal, M69, pagos, IFERROR(SUMIF(Aux_Datos!$B:$B, idVenta, Aux_Datos!$K:$K), 0), retenciones, IFERROR(SUMIF(Aux_Datos!$N:$N, idVenta, Aux_Datos!$R:$R), 0), pagos + retenciones ) -> 49.482848 | Q69: =IF(P69=0, "Sin Pago", LET( idVenta, I69&"", montoTotalPagado, P69, pagoUSD, IFERROR(SUMIFS(Aux_Datos!$C:$C, Aux_Datos!$B:$B, idVenta, Aux_Datos!$D:$D, "USD"), 0), pagoVES, IFERROR(SUMIFS(Aux_Datos!$C:$C, Aux_Datos!$B:$B, idVenta, Aux_Datos!$D:$D, "VES"), 0), IF(pagoUSD >= (montoTotalPagado * 0.84), "USD", IF(pagoVES >= (montoTotalPagado * 0.84), "VES", "MIXTO")) ) ) -> VES | R69: =M69-P69 -> 17.887152 | S69: =IF(P69=0, "Sin Pago", IFERROR( MAXIFS(Aux_Datos!$A:$A, Aux_Datos!$B:$B, I69&""), IFERROR(MAXIFS(Aux_Datos!$A:$A, Aux_Datos!$B:$B, VALUE(I69)), "Revisar ID") ) ) -> 46125 | T69: =IF(R69<=0, "PAGADA", IF(P69>0, "PAGO PARCIAL", "PENDIENTE")) -> PAGO PARCIAL | U69: =IF(AND(T69<>"PAGADA", L69<TODAY()), "CRÍTICO: VENCIDA", IF(T69="PAGADA", "SOLVENTE", "EN TIEMPO")) -> CRÍTICO: VENCIDA | V69: =IF(T69="PAGADA", 0, IF(S69 < TODAY(), TODAY() - S69, 0)) -> 75 | W69: =IF(P69=0, "Sin Pago", LET( monedaPago, Q69, descuentoAplicado, G69, limitePermitido, IFERROR(VLOOKUP(monedaPago, 'Limites de Descuento'!$A$2:$B595, 2, FALSE), 0), IF(descuentoAplicado > limitePermitido, "ALERTA: EXCESO (" & TEXT(limitePermitido, "0%") & " máx)", "OK") ) ) -> OK | X69: =IF(OR(H69=0, S69="Sin Pago"), "", IF(AND(H69 > 0, S69 > (L69 + 2)), "⚠️ REVISAR DESCUENTO", "OK")) | Y69: 49.482848 | Z69: NO CUMPLE
A70: S00086 | B70: 46093.745 | C70: Wuilliams bastidas | D70: PEREZ DIAZ ANGEL DE DIOS | E70: 173.65 | F70: 15 días | G70: =IF($E70=0,0,IF(SUMIF(Aux_Datos!$B:$B,$I70,Aux_Datos!$K:$K)/$E70>=VLOOKUP(IF(COUNTIFS(Aux_Datos!$B:$B,$I70,Aux_Datos!$D:$D,"<>USD")=0,"USD","VES"),'Limites de Descuento'!$A$2:$D$4,4,FALSE),MAX(0,1-SUMIF(Aux_Datos!$B:$B,$I70,Aux_Datos!$K:$K)/$E70),0)) -> 0 | I70: =VALUE(MID(A70,2,LEN(A70))) -> 86 | J70: =INT(B70) -> 46093 | K70: =IF(F70="Pago inmediato", 0, IF(F70="", "", IFERROR(VALUE(MID(F70, 1, SEARCH(" ", F70)-1)), ""))) -> 15 | L70: =J70+K70+1 -> 46109 | M70: =E70-(E70*G70)-(E70*H70) -> 173.65 | N70: =IF(T70="PAGADA", 0, IF(L70 < TODAY(), TODAY() - L70, 0)) -> 0 | O70: =IF(T70="PAGADA", "PAGADA", IF(L70 < TODAY(), "VENCIDA", "EN TIEMPO")) -> PAGADA | P70: =LET( idVenta, I70&"", montoTotal, M70, pagos, IFERROR(SUMIF(Aux_Datos!$B:$B, idVenta, Aux_Datos!$K:$K), 0), retenciones, IFERROR(SUMIF(Aux_Datos!$N:$N, idVenta, Aux_Datos!$R:$R), 0), pagos + retenciones ) -> 226.93084 | Q70: =IF(P70=0, "Sin Pago", LET( idVenta, I70&"", montoTotalPagado, P70, pagoUSD, IFERROR(SUMIFS(Aux_Datos!$C:$C, Aux_Datos!$B:$B, idVenta, Aux_Datos!$D:$D, "USD"), 0), pagoVES, IFERROR(SUMIFS(Aux_Datos!$C:$C, Aux_Datos!$B:$B, idVenta, Aux_Datos!$D:$D, "VES"), 0), IF(pagoUSD >= (montoTotalPagado * 0.84), "USD", IF(pagoVES >= (montoTotalPagado * 0.84), "VES", "MIXTO")) ) ) -> VES | R70: =M70-P70 -> -53.280844 | S70: =IF(P70=0, "Sin Pago", IFERROR( MAXIFS(Aux_Datos!$A:$A, Aux_Datos!$B:$B, I70&""), IFERROR(MAXIFS(Aux_Datos!$A:$A, Aux_Datos!$B:$B, VALUE(I70)), "Revisar ID") ) ) -> 46146 | T70: =IF(R70<=0, "PAGADA", IF(P70>0, "PAGO PARCIAL", "PENDIENTE")) -> PAGADA | U70: =IF(AND(T70<>"PAGADA", L70<TODAY()), "CRÍTICO: VENCIDA", IF(T70="PAGADA", "SOLVENTE", "EN TIEMPO")) -> SOLVENTE | V70: =IF(T70="PAGADA", 0, IF(S70 < TODAY(), TODAY() - S70, 0)) -> 0 | W70: =IF(P70=0, "Sin Pago", LET( monedaPago, Q70, descuentoAplicado, G70, limitePermitido, IFERROR(VLOOKUP(monedaPago, 'Limites de Descuento'!$A$2:$B595, 2, FALSE), 0), IF(descuentoAplicado > limitePermitido, "ALERTA: EXCESO (" & TEXT(limitePermitido, "0%") & " máx)", "OK") ) ) -> OK | X70: =IF(OR(H70=0, S70="Sin Pago"), "", IF(AND(H70 > 0, S70 > (L70 + 2)), "⚠️ REVISAR DESCUENTO", "OK")) | Y70: 226.93084 | Z70: CUMPLE
A71: S00087 | B71: 46093.742 | C71: Javier Cardenas Prato. | D71: TORO ARDILES DAVID JOSE | E71: 392.65 | F71: Pago inmediato | G71: =IF($E71=0,0,IF(SUMIF(Aux_Datos!$B:$B,$I71,Aux_Datos!$K:$K)/$E71>=VLOOKUP(IF(COUNTIFS(Aux_Datos!$B:$B,$I71,Aux_Datos!$D:$D,"<>USD")=0,"USD","VES"),'Limites de Descuento'!$A$2:$D$4,4,FALSE),MAX(0,1-SUMIF(Aux_Datos!$B:$B,$I71,Aux_Datos!$K:$K)/$E71),0)) -> 0.15191647 | I71: =VALUE(MID(A71,2,LEN(A71))) -> 87 | J71: =INT(B71) -> 46093 | K71: =IF(F71="Pago inmediato", 0, IF(F71="", "", IFERROR(VALUE(MID(F71, 1, SEARCH(" ", F71)-1)), ""))) -> 0 | L71: =J71+K71+1 -> 46094 | M71: =E71-(E71*G71)-(E71*H71) -> 333 | N71: =IF(T71="PAGADA", 0, IF(L71 < TODAY(), TODAY() - L71, 0)) -> 0 | O71: =IF(T71="PAGADA", "PAGADA", IF(L71 < TODAY(), "VENCIDA", "EN TIEMPO")) -> PAGADA | P71: =LET( idVenta, I71&"", montoTotal, M71, pagos, IFERROR(SUMIF(Aux_Datos!$B:$B, idVenta, Aux_Datos!$K:$K), 0), retenciones, IFERROR(SUMIF(Aux_Datos!$N:$N, idVenta, Aux_Datos!$R:$R), 0), pagos + retenciones ) -> 333 | Q71: =IF(P71=0, "Sin Pago", LET( idVenta, I71&"", montoTotalPagado, P71, pagoUSD, IFERROR(SUMIFS(Aux_Datos!$C:$C, Aux_Datos!$B:$B, idVenta, Aux_Datos!$D:$D, "USD"), 0), pagoVES, IFERROR(SUMIFS(Aux_Datos!$C:$C, Aux_Datos!$B:$B, idVenta, Aux_Datos!$D:$D, "VES"), 0), IF(pagoUSD >= (montoTotalPagado * 0.84), "USD", IF(pagoVES >= (montoTotalPagado * 0.84), "VES", "MIXTO")) ) ) -> USD | R71: =M71-P71 -> 0 | S71: =IF(P71=0, "Sin Pago", IFERROR( MAXIFS(Aux_Datos!$A:$A, Aux_Datos!$B:$B, I71&""), IFERROR(MAXIFS(Aux_Datos!$A:$A, Aux_Datos!$B:$B, VALUE(I71)), "Revisar ID") ) ) -> 46161 | T71: =IF(R71<=0, "PAGADA", IF(P71>0, "PAGO PARCIAL", "PENDIENTE")) -> PAGADA | U71: =IF(AND(T71<>"PAGADA", L71<TODAY()), "CRÍTICO: VENCIDA", IF(T71="PAGADA", "SOLVENTE", "EN TIEMPO")) -> SOLVENTE | V71: =IF(T71="PAGADA", 0, IF(S71 < TODAY(), TODAY() - S71, 0)) -> 0 | W71: =IF(P71=0, "Sin Pago", LET( monedaPago, Q71, descuentoAplicado, G71, limitePermitido, IFERROR(VLOOKUP(monedaPago, 'Limites de Descuento'!$A$2:$B595, 2, FALSE), 0), IF(descuentoAplicado > limitePermitido, "ALERTA: EXCESO (" & TEXT(limitePermitido, "0%") & " máx)", "OK") ) ) -> OK | X71: =IF(OR(H71=0, S71="Sin Pago"), "", IF(AND(H71 > 0, S71 > (L71 + 2)), "⚠️ REVISAR DESCUENTO", "OK")) | Y71: 333 | Z71: CUMPLE
A72: S00088 | B72: 46094.597 | C72: ALIPLUS TRASPORTE Y EQUIPOS, CA | D72: Marco Romero | E72: 286.51 | F72: 7 días | G72: =IF($E72=0,0,IF(SUMIF(Aux_Datos!$B:$B,$I72,Aux_Datos!$K:$K)/$E72>=VLOOKUP(IF(COUNTIFS(Aux_Datos!$B:$B,$I72,Aux_Datos!$D:$D,"<>USD")=0,"USD","VES"),'Limites de Descuento'!$A$2:$D$4,4,FALSE),MAX(0,1-SUMIF(Aux_Datos!$B:$B,$I72,Aux_Datos!$K:$K)/$E72),0)) -> 0 | I72: =VALUE(MID(A72,2,LEN(A72))) -> 88 | J72: =INT(B72) -> 46094 | K72: =IF(F72="Pago inmediato", 0, IF(F72="", "", IFERROR(VALUE(MID(F72, 1, SEARCH(" ", F72)-1)), ""))) -> 7 | L72: =J72+K72+1 -> 46102 | M72: =E72-(E72*G72)-(E72*H72) -> 286.51 | N72: =IF(T72="PAGADA", 0, IF(L72 < TODAY(), TODAY() - L72, 0)) -> 98 | O72: =IF(T72="PAGADA", "PAGADA", IF(L72 < TODAY(), "VENCIDA", "EN TIEMPO")) -> VENCIDA | P72: =LET( idVenta, I72&"", montoTotal, M72, pagos, IFERROR(SUMIF(Aux_Datos!$B:$B, idVenta, Aux_Datos!$K:$K), 0), retenciones, IFERROR(SUMIF(Aux_Datos!$N:$N, idVenta, Aux_Datos!$R:$R), 0), pagos + retenciones ) -> 278.15466 | Q72: =IF(P72=0, "Sin Pago", LET( idVenta, I72&"", montoTotalPagado, P72, pagoUSD, IFERROR(SUMIFS(Aux_Datos!$C:$C, Aux_Datos!$B:$B, idVenta, Aux_Datos!$D:$D, "USD"), 0), pagoVES, IFERROR(SUMIFS(Aux_Datos!$C:$C, Aux_Datos!$B:$B, idVenta, Aux_Datos!$D:$D, "VES"), 0), IF(pagoUSD >= (montoTotalPagado * 0.84), "USD", IF(pagoVES >= (montoTotalPagado * 0.84), "VES", "MIXTO")) ) ) -> VES | R72: =M72-P72 -> 8.3553425 | S72: =IF(P72=0, "Sin Pago", IFERROR( MAXIFS(Aux_Datos!$A:$A, Aux_Datos!$B:$B, I72&""), IFERROR(MAXIFS(Aux_Datos!$A:$A, Aux_Datos!$B:$B, VALUE(I72)), "Revisar ID") ) ) -> 46094 | T72: =IF(R72<=0, "PAGADA", IF(P72>0, "PAGO PARCIAL", "PENDIENTE")) -> PAGO PARCIAL | U72: =IF(AND(T72<>"PAGADA", L72<TODAY()), "CRÍTICO: VENCIDA", IF(T72="PAGADA", "SOLVENTE", "EN TIEMPO")) -> CRÍTICO: VENCIDA | V72: =IF(T72="PAGADA", 0, IF(S72 < TODAY(), TODAY() - S72, 0)) -> 106 | W72: =IF(P72=0, "Sin Pago", LET( monedaPago, Q72, descuentoAplicado, G72, limitePermitido, IFERROR(VLOOKUP(monedaPago, 'Limites de Descuento'!$A$2:$B595, 2, FALSE), 0), IF(descuentoAplicado > limitePermitido, "ALERTA: EXCESO (" & TEXT(limitePermitido, "0%") & " máx)", "OK") ) ) -> OK | X72: =IF(OR(H72=0, S72="Sin Pago"), "", IF(AND(H72 > 0, S72 > (L72 + 2)), "⚠️ REVISAR DESCUENTO", "OK")) | Y72: 240.16602 | Z72: CUMPLE
A73: S00089 | B73: 46094.573 | C73: Moto Repuestos Sanz 11. C.A. | D73: TORO ARDILES DAVID JOSE | E73: 89.99 | F73: Pago inmediato | G73: =IF($E73=0,0,IF(SUMIF(Aux_Datos!$B:$B,$I73,Aux_Datos!$K:$K)/$E73>=VLOOKUP(IF(COUNTIFS(Aux_Datos!$B:$B,$I73,Aux_Datos!$D:$D,"<>USD")=0,"USD","VES"),'Limites de Descuento'!$A$2:$D$4,4,FALSE),MAX(0,1-SUMIF(Aux_Datos!$B:$B,$I73,Aux_Datos!$K:$K)/$E73),0)) -> 0 | I73: =VALUE(MID(A73,2,LEN(A73))) -> 89 | J73: =INT(B73) -> 46094 | K73: =IF(F73="Pago inmediato", 0, IF(F73="", "", IFERROR(VALUE(MID(F73, 1, SEARCH(" ", F73)-1)), ""))) -> 0 | L73: =J73+K73+1 -> 46095 | M73: =E73-(E73*G73)-(E73*H73) -> 89.99 | N73: =IF(T73="PAGADA", 0, IF(L73 < TODAY(), TODAY() - L73, 0)) -> 0 | O73: =IF(T73="PAGADA", "PAGADA", IF(L73 < TODAY(), "VENCIDA", "EN TIEMPO")) -> PAGADA | P73: =LET( idVenta, I73&"", montoTotal, M73, pagos, IFERROR(SUMIF(Aux_Datos!$B:$B, idVenta, Aux_Datos!$K:$K), 0), retenciones, IFERROR(SUMIF(Aux_Datos!$N:$N, idVenta, Aux_Datos!$R:$R), 0), pagos + retenciones ) -> 90 | Q73: =IF(P73=0, "Sin Pago", LET( idVenta, I73&"", montoTotalPagado, P73, pagoUSD, IFERROR(SUMIFS(Aux_Datos!$C:$C, Aux_Datos!$B:$B, idVenta, Aux_Datos!$D:$D, "USD"), 0), pagoVES, IFERROR(SUMIFS(Aux_Datos!$C:$C, Aux_Datos!$B:$B, idVenta, Aux_Datos!$D:$D, "VES"), 0), IF(pagoUSD >= (montoTotalPagado * 0.84), "USD", IF(pagoVES >= (montoTotalPagado * 0.84), "VES", "MIXTO")) ) ) -> USD | R73: =M73-P73 -> -0.01 | S73: =IF(P73=0, "Sin Pago", IFERROR( MAXIFS(Aux_Datos!$A:$A, Aux_Datos!$B:$B, I73&""), IFERROR(MAXIFS(Aux_Datos!$A:$A, Aux_Datos!$B:$B, VALUE(I73)), "Revisar ID") ) ) -> 46121 | T73: =IF(R73<=0, "PAGADA", IF(P73>0, "PAGO PARCIAL", "PENDIENTE")) -> PAGADA | U73: =IF(AND(T73<>"PAGADA", L73<TODAY()), "CRÍTICO: VENCIDA", IF(T73="PAGADA", "SOLVENTE", "EN TIEMPO")) -> SOLVENTE | V73: =IF(T73="PAGADA", 0, IF(S73 < TODAY(), TODAY() - S73, 0)) -> 0 | W73: =IF(P73=0, "Sin Pago", LET( monedaPago, Q73, descuentoAplicado, G73, limitePermitido, IFERROR(VLOOKUP(monedaPago, 'Limites de Descuento'!$A$2:$B595, 2, FALSE), 0), IF(descuentoAplicado > limitePermitido, "ALERTA: EXCESO (" & TEXT(limitePermitido, "0%") & " máx)", "OK") ) ) -> OK | X73: =IF(OR(H73=0, S73="Sin Pago"), "", IF(AND(H73 > 0, S73 > (L73 + 2)), "⚠️ REVISAR DESCUENTO", "OK")) | Y73: 90 | Z73: CUMPLE
A74: S00090 | B74: 46094.573 | C74: ACCESORIOS Y REPUESTOS MOTO CAR 20-11-C.A | D74: VILLABONA CORREA ALBA ESTEFANIA | E74: 171 | F74: 7 días | G74: =IF($E74=0,0,IF(SUMIF(Aux_Datos!$B:$B,$I74,Aux_Datos!$K:$K)/$E74>=VLOOKUP(IF(COUNTIFS(Aux_Datos!$B:$B,$I74,Aux_Datos!$D:$D,"<>USD")=0,"USD","VES"),'Limites de Descuento'!$A$2:$D$4,4,FALSE),MAX(0,1-SUMIF(Aux_Datos!$B:$B,$I74,Aux_Datos!$K:$K)/$E74),0)) -> 0 | I74: =VALUE(MID(A74,2,LEN(A74))) -> 90 | J74: =INT(B74) -> 46094 | K74: =IF(F74="Pago inmediato", 0, IF(F74="", "", IFERROR(VALUE(MID(F74, 1, SEARCH(" ", F74)-1)), ""))) -> 7 | L74: =J74+K74+1 -> 46102 | M74: =E74-(E74*G74)-(E74*H74) -> 171 | N74: =IF(T74="PAGADA", 0, IF(L74 < TODAY(), TODAY() - L74, 0)) -> 0 | O74: =IF(T74="PAGADA", "PAGADA", IF(L74 < TODAY(), "VENCIDA", "EN TIEMPO")) -> PAGADA | P74: =LET( idVenta, I74&"", montoTotal, M74, pagos, IFERROR(SUMIF(Aux_Datos!$B:$B, idVenta, Aux_Datos!$K:$K), 0), retenciones, IFERROR(SUMIF(Aux_Datos!$N:$N, idVenta, Aux_Datos!$R:$R), 0), pagos + retenciones ) -> 171 | Q74: =IF(P74=0, "Sin Pago", LET( idVenta, I74&"", montoTotalPagado, P74, pagoUSD, IFERROR(SUMIFS(Aux_Datos!$C:$C, Aux_Datos!$B:$B, idVenta, Aux_Datos!$D:$D, "USD"), 0), pagoVES, IFERROR(SUMIFS(Aux_Datos!$C:$C, Aux_Datos!$B:$B, idVenta, Aux_Datos!$D:$D, "VES"), 0), IF(pagoUSD >= (montoTotalPagado * 0.84), "USD", IF(pagoVES >= (montoTotalPagado * 0.84), "VES", "MIXTO")) ) ) -> USD | R74: =M74-P74 -> 0 | S74: =IF(P74=0, "Sin Pago", IFERROR( MAXIFS(Aux_Datos!$A:$A, Aux_Datos!$B:$B, I74&""), IFERROR(MAXIFS(Aux_Datos!$A:$A, Aux_Datos!$B:$B, VALUE(I74)), "Revisar ID") ) ) -> 46127 | T74: =IF(R74<=0, "PAGADA", IF(P74>0, "PAGO PARCIAL", "PENDIENTE")) -> PAGADA | U74: =IF(AND(T74<>"PAGADA", L74<TODAY()), "CRÍTICO: VENCIDA", IF(T74="PAGADA", "SOLVENTE", "EN TIEMPO")) -> SOLVENTE | V74: =IF(T74="PAGADA", 0, IF(S74 < TODAY(), TODAY() - S74, 0)) -> 0 | W74: =IF(P74=0, "Sin Pago", LET( monedaPago, Q74, descuentoAplicado, G74, limitePermitido, IFERROR(VLOOKUP(monedaPago, 'Limites de Descuento'!$A$2:$B595, 2, FALSE), 0), IF(descuentoAplicado > limitePermitido, "ALERTA: EXCESO (" & TEXT(limitePermitido, "0%") & " máx)", "OK") ) ) -> OK | X74: =IF(OR(H74=0, S74="Sin Pago"), "", IF(AND(H74 > 0, S74 > (L74 + 2)), "⚠️ REVISAR DESCUENTO", "OK")) | Y74: 171 | Z74: CUMPLE
A75: S00092 | B75: 46094.629 | C75: EMPRENDIMIENTO IRMA RODRIGUEZ 6 | D75: TORO ARDILES DAVID JOSE | E75: 126 | F75: Pago inmediato | G75: =IF($E75=0,0,IF(SUMIF(Aux_Datos!$B:$B,$I75,Aux_Datos!$K:$K)/$E75>=VLOOKUP(IF(COUNTIFS(Aux_Datos!$B:$B,$I75,Aux_Datos!$D:$D,"<>USD")=0,"USD","VES"),'Limites de Descuento'!$A$2:$D$4,4,FALSE),MAX(0,1-SUMIF(Aux_Datos!$B:$B,$I75,Aux_Datos!$K:$K)/$E75),0)) -> 0 | I75: =VALUE(MID(A75,2,LEN(A75))) -> 92 | J75: =INT(B75) -> 46094 | K75: =IF(F75="Pago inmediato", 0, IF(F75="", "", IFERROR(VALUE(MID(F75, 1, SEARCH(" ", F75)-1)), ""))) -> 0 | L75: =J75+K75+1 -> 46095 | M75: =E75-(E75*G75)-(E75*H75) -> 126 | N75: =IF(T75="PAGADA", 0, IF(L75 < TODAY(), TODAY() - L75, 0)) -> 0 | O75: =IF(T75="PAGADA", "PAGADA", IF(L75 < TODAY(), "VENCIDA", "EN TIEMPO")) -> PAGADA | P75: =LET( idVenta, I75&"", montoTotal, M75, pagos, IFERROR(SUMIF(Aux_Datos!$B:$B, idVenta, Aux_Datos!$K:$K), 0), retenciones, IFERROR(SUMIF(Aux_Datos!$N:$N, idVenta, Aux_Datos!$R:$R), 0), pagos + retenciones ) -> 126 | Q75: =IF(P75=0, "Sin Pago", LET( idVenta, I75&"", montoTotalPagado, P75, pagoUSD, IFERROR(SUMIFS(Aux_Datos!$C:$C, Aux_Datos!$B:$B, idVenta, Aux_Datos!$D:$D, "USD"), 0), pagoVES, IFERROR(SUMIFS(Aux_Datos!$C:$C, Aux_Datos!$B:$B, idVenta, Aux_Datos!$D:$D, "VES"), 0), IF(pagoUSD >= (montoTotalPagado * 0.84), "USD", IF(pagoVES >= (montoTotalPagado * 0.84), "VES", "MIXTO")) ) ) -> USD | R75: =M75-P75 -> 0 | S75: =IF(P75=0, "Sin Pago", IFERROR( MAXIFS(Aux_Datos!$A:$A, Aux_Datos!$B:$B, I75&""), IFERROR(MAXIFS(Aux_Datos!$A:$A, Aux_Datos!$B:$B, VALUE(I75)), "Revisar ID") ) ) -> 46100 | T75: =IF(R75<=0, "PAGADA", IF(P75>0, "PAGO PARCIAL", "PENDIENTE")) -> PAGADA | U75: =IF(AND(T75<>"PAGADA", L75<TODAY()), "CRÍTICO: VENCIDA", IF(T75="PAGADA", "SOLVENTE", "EN TIEMPO")) -> SOLVENTE | V75: =IF(T75="PAGADA", 0, IF(S75 < TODAY(), TODAY() - S75, 0)) -> 0 | W75: =IF(P75=0, "Sin Pago", LET( monedaPago, Q75, descuentoAplicado, G75, limitePermitido, IFERROR(VLOOKUP(monedaPago, 'Limites de Descuento'!$A$2:$B595, 2, FALSE), 0), IF(descuentoAplicado > limitePermitido, "ALERTA: EXCESO (" & TEXT(limitePermitido, "0%") & " máx)", "OK") ) ) -> OK | X75: =IF(OR(H75=0, S75="Sin Pago"), "", IF(AND(H75 > 0, S75 > (L75 + 2)), "⚠️ REVISAR DESCUENTO", "OK")) | Y75: 126 | Z75: CUMPLE
A76: S00093 | B76: 46094.629 | C76: Emprendimiento YSKRA | D76: PEREZ DIAZ ANGEL DE DIOS | E76: 246 | F76: 30 días | G76: =IF($E76=0,0,IF(SUMIF(Aux_Datos!$B:$B,$I76,Aux_Datos!$K:$K)/$E76>=VLOOKUP(IF(COUNTIFS(Aux_Datos!$B:$B,$I76,Aux_Datos!$D:$D,"<>USD")=0,"USD","VES"),'Limites de Descuento'!$A$2:$D$4,4,FALSE),MAX(0,1-SUMIF(Aux_Datos!$B:$B,$I76,Aux_Datos!$K:$K)/$E76),0)) -> 0.11382114 | I76: =VALUE(MID(A76,2,LEN(A76))) -> 93 | J76: =INT(B76) -> 46094 | K76: =IF(F76="Pago inmediato", 0, IF(F76="", "", IFERROR(VALUE(MID(F76, 1, SEARCH(" ", F76)-1)), ""))) -> 30 | L76: =J76+K76+1 -> 46125 | M76: =E76-(E76*G76)-(E76*H76) -> 218 | N76: =IF(T76="PAGADA", 0, IF(L76 < TODAY(), TODAY() - L76, 0)) -> 0 | O76: =IF(T76="PAGADA", "PAGADA", IF(L76 < TODAY(), "VENCIDA", "EN TIEMPO")) -> PAGADA | P76: =LET( idVenta, I76&"", montoTotal, M76, pagos, IFERROR(SUMIF(Aux_Datos!$B:$B, idVenta, Aux_Datos!$K:$K), 0), retenciones, IFERROR(SUMIF(Aux_Datos!$N:$N, idVenta, Aux_Datos!$R:$R), 0), pagos + retenciones ) -> 218 | Q76: =IF(P76=0, "Sin Pago", LET( idVenta, I76&"", montoTotalPagado, P76, pagoUSD, IFERROR(SUMIFS(Aux_Datos!$C:$C, Aux_Datos!$B:$B, idVenta, Aux_Datos!$D:$D, "USD"), 0), pagoVES, IFERROR(SUMIFS(Aux_Datos!$C:$C, Aux_Datos!$B:$B, idVenta, Aux_Datos!$D:$D, "VES"), 0), IF(pagoUSD >= (montoTotalPagado * 0.84), "USD", IF(pagoVES >= (montoTotalPagado * 0.84), "VES", "MIXTO")) ) ) -> USD | R76: =M76-P76 -> 0 | S76: =IF(P76=0, "Sin Pago", IFERROR( MAXIFS(Aux_Datos!$A:$A, Aux_Datos!$B:$B, I76&""), IFERROR(MAXIFS(Aux_Datos!$A:$A, Aux_Datos!$B:$B, VALUE(I76)), "Revisar ID") ) ) -> 46190 | T76: =IF(R76<=0, "PAGADA", IF(P76>0, "PAGO PARCIAL", "PENDIENTE")) -> PAGADA | U76: =IF(AND(T76<>"PAGADA", L76<TODAY()), "CRÍTICO: VENCIDA", IF(T76="PAGADA", "SOLVENTE", "EN TIEMPO")) -> SOLVENTE | V76: =IF(T76="PAGADA", 0, IF(S76 < TODAY(), TODAY() - S76, 0)) -> 0 | W76: =IF(P76=0, "Sin Pago", LET( monedaPago, Q76, descuentoAplicado, G76, limitePermitido, IFERROR(VLOOKUP(monedaPago, 'Limites de Descuento'!$A$2:$B595, 2, FALSE), 0), IF(descuentoAplicado > limitePermitido, "ALERTA: EXCESO (" & TEXT(limitePermitido, "0%") & " máx)", "OK") ) ) -> OK | X76: =IF(OR(H76=0, S76="Sin Pago"), "", IF(AND(H76 > 0, S76 > (L76 + 2)), "⚠️ REVISAR DESCUENTO", "OK")) | Y76: 218 | Z76: CUMPLE
A77: S00094 | B77: 46094.646 | C77: Moto repuestos jj | D77: PEREZ DIAZ ANGEL DE DIOS | E77: 191.1 | F77: 30 días | G77: =IF($E77=0,0,IF(SUMIF(Aux_Datos!$B:$B,$I77,Aux_Datos!$K:$K)/$E77>=VLOOKUP(IF(COUNTIFS(Aux_Datos!$B:$B,$I77,Aux_Datos!$D:$D,"<>USD")=0,"USD","VES"),'Limites de Descuento'!$A$2:$D$4,4,FALSE),MAX(0,1-SUMIF(Aux_Datos!$B:$B,$I77,Aux_Datos!$K:$K)/$E77),0)) -> 0 | I77: =VALUE(MID(A77,2,LEN(A77))) -> 94 | J77: =INT(B77) -> 46094 | K77: =IF(F77="Pago inmediato", 0, IF(F77="", "", IFERROR(VALUE(MID(F77, 1, SEARCH(" ", F77)-1)), ""))) -> 30 | L77: =J77+K77+1 -> 46125 | M77: =E77-(E77*G77)-(E77*H77) -> 191.1 | N77: =IF(T77="PAGADA", 0, IF(L77 < TODAY(), TODAY() - L77, 0)) -> 0 | O77: =IF(T77="PAGADA", "PAGADA", IF(L77 < TODAY(), "VENCIDA", "EN TIEMPO")) -> PAGADA | P77: =LET( idVenta, I77&"", montoTotal, M77, pagos, IFERROR(SUMIF(Aux_Datos!$B:$B, idVenta, Aux_Datos!$K:$K), 0), retenciones, IFERROR(SUMIF(Aux_Datos!$N:$N, idVenta, Aux_Datos!$R:$R), 0), pagos + retenciones ) -> 204.95272 | Q77: =IF(P77=0, "Sin Pago", LET( idVenta, I77&"", montoTotalPagado, P77, pagoUSD, IFERROR(SUMIFS(Aux_Datos!$C:$C, Aux_Datos!$B:$B, idVenta, Aux_Datos!$D:$D, "USD"), 0), pagoVES, IFERROR(SUMIFS(Aux_Datos!$C:$C, Aux_Datos!$B:$B, idVenta, Aux_Datos!$D:$D, "VES"), 0), IF(pagoUSD >= (montoTotalPagado * 0.84), "USD", IF(pagoVES >= (montoTotalPagado * 0.84), "VES", "MIXTO")) ) ) -> VES | R77: =M77-P77 -> -13.852724 | S77: =IF(P77=0, "Sin Pago", IFERROR( MAXIFS(Aux_Datos!$A:$A, Aux_Datos!$B:$B, I77&""), IFERROR(MAXIFS(Aux_Datos!$A:$A, Aux_Datos!$B:$B, VALUE(I77)), "Revisar ID") ) ) -> 46171 | T77: =IF(R77<=0, "PAGADA", IF(P77>0, "PAGO PARCIAL", "PENDIENTE")) -> PAGADA | U77: =IF(AND(T77<>"PAGADA", L77<TODAY()), "CRÍTICO: VENCIDA", IF(T77="PAGADA", "SOLVENTE", "EN TIEMPO")) -> SOLVENTE | V77: =IF(T77="PAGADA", 0, IF(S77 < TODAY(), TODAY() - S77, 0)) -> 0 | W77: =IF(P77=0, "Sin Pago", LET( monedaPago, Q77, descuentoAplicado, G77, limitePermitido, IFERROR(VLOOKUP(monedaPago, 'Limites de Descuento'!$A$2:$B595, 2, FALSE), 0), IF(descuentoAplicado > limitePermitido, "ALERTA: EXCESO (" & TEXT(limitePermitido, "0%") & " máx)", "OK") ) ) -> OK | X77: =IF(OR(H77=0, S77="Sin Pago"), "", IF(AND(H77 > 0, S77 > (L77 + 2)), "⚠️ REVISAR DESCUENTO", "OK")) | Y77: 204.95272 | Z77: CUMPLE
A78: S00095 | B78: 46097.458 | C78: Multiservicios Arizona, C.A. | D78: PEREZ DIAZ ANGEL DE DIOS | E78: 368.51 | F78: 15 días | G78: =IF($E78=0,0,IF(SUMIF(Aux_Datos!$B:$B,$I78,Aux_Datos!$K:$K)/$E78>=VLOOKUP(IF(COUNTIFS(Aux_Datos!$B:$B,$I78,Aux_Datos!$D:$D,"<>USD")=0,"USD","VES"),'Limites de Descuento'!$A$2:$D$4,4,FALSE),MAX(0,1-SUMIF(Aux_Datos!$B:$B,$I78,Aux_Datos!$K:$K)/$E78),0)) -> 0.13794976 | I78: =VALUE(MID(A78,2,LEN(A78))) -> 95 | J78: =INT(B78) -> 46097 | K78: =IF(F78="Pago inmediato", 0, IF(F78="", "", IFERROR(VALUE(MID(F78, 1, SEARCH(" ", F78)-1)), ""))) -> 15 | L78: =J78+K78+1 -> 46113 | M78: =E78-(E78*G78)-(E78*H78) -> 317.67413 | N78: =IF(T78="PAGADA", 0, IF(L78 < TODAY(), TODAY() - L78, 0)) -> 0 | O78: =IF(T78="PAGADA", "PAGADA", IF(L78 < TODAY(), "VENCIDA", "EN TIEMPO")) -> PAGADA | P78: =LET( idVenta, I78&"", montoTotal, M78, pagos, IFERROR(SUMIF(Aux_Datos!$B:$B, idVenta, Aux_Datos!$K:$K), 0), retenciones, IFERROR(SUMIF(Aux_Datos!$N:$N, idVenta, Aux_Datos!$R:$R), 0), pagos + retenciones ) -> 317.67413 | Q78: =IF(P78=0, "Sin Pago", LET( idVenta, I78&"", montoTotalPagado, P78, pagoUSD, IFERROR(SUMIFS(Aux_Datos!$C:$C, Aux_Datos!$B:$B, idVenta, Aux_Datos!$D:$D, "USD"), 0), pagoVES, IFERROR(SUMIFS(Aux_Datos!$C:$C, Aux_Datos!$B:$B, idVenta, Aux_Datos!$D:$D, "VES"), 0), IF(pagoUSD >= (montoTotalPagado * 0.84), "USD", IF(pagoVES >= (montoTotalPagado * 0.84), "VES", "MIXTO")) ) ) -> VES | R78: =M78-P78 -> 0 | S78: =IF(P78=0, "Sin Pago", IFERROR( MAXIFS(Aux_Datos!$A:$A, Aux_Datos!$B:$B, I78&""), IFERROR(MAXIFS(Aux_Datos!$A:$A, Aux_Datos!$B:$B, VALUE(I78)), "Revisar ID") ) ) -> 46133 | T78: =IF(R78<=0, "PAGADA", IF(P78>0, "PAGO PARCIAL", "PENDIENTE")) -> PAGADA | U78: =IF(AND(T78<>"PAGADA", L78<TODAY()), "CRÍTICO: VENCIDA", IF(T78="PAGADA", "SOLVENTE", "EN TIEMPO")) -> SOLVENTE | V78: =IF(T78="PAGADA", 0, IF(S78 < TODAY(), TODAY() - S78, 0)) -> 0 | W78: =IF(P78=0, "Sin Pago", LET( monedaPago, Q78, descuentoAplicado, G78, limitePermitido, IFERROR(VLOOKUP(monedaPago, 'Limites de Descuento'!$A$2:$B595, 2, FALSE), 0), IF(descuentoAplicado > limitePermitido, "ALERTA: EXCESO (" & TEXT(limitePermitido, "0%") & " máx)", "OK") ) ) -> OK | X78: =IF(OR(H78=0, S78="Sin Pago"), "", IF(AND(H78 > 0, S78 > (L78 + 2)), "⚠️ REVISAR DESCUENTO", "OK")) | Y78: 317.67413 | Z78: CUMPLE
A79: S00096 | B79: 46097.457 | C79: Video Electrónica Fermat, C.A | D79: MARTINEZ MONTES JEFFREY ENRIQUE | E79: 434.94 | F79: 15 días | G79: =IF($E79=0,0,IF(SUMIF(Aux_Datos!$B:$B,$I79,Aux_Datos!$K:$K)/$E79>=VLOOKUP(IF(COUNTIFS(Aux_Datos!$B:$B,$I79,Aux_Datos!$D:$D,"<>USD")=0,"USD","VES"),'Limites de Descuento'!$A$2:$D$4,4,FALSE),MAX(0,1-SUMIF(Aux_Datos!$B:$B,$I79,Aux_Datos!$K:$K)/$E79),0)) -> 0 | I79: =VALUE(MID(A79,2,LEN(A79))) -> 96 | J79: =INT(B79) -> 46097 | K79: =IF(F79="Pago inmediato", 0, IF(F79="", "", IFERROR(VALUE(MID(F79, 1, SEARCH(" ", F79)-1)), ""))) -> 15 | L79: =J79+K79+1 -> 46113 | M79: =E79-(E79*G79)-(E79*H79) -> 434.94 | N79: =IF(T79="PAGADA", 0, IF(L79 < TODAY(), TODAY() - L79, 0)) -> 0 | O79: =IF(T79="PAGADA", "PAGADA", IF(L79 < TODAY(), "VENCIDA", "EN TIEMPO")) -> PAGADA | P79: =LET( idVenta, I79&"", montoTotal, M79, pagos, IFERROR(SUMIF(Aux_Datos!$B:$B, idVenta, Aux_Datos!$K:$K), 0), retenciones, IFERROR(SUMIF(Aux_Datos!$N:$N, idVenta, Aux_Datos!$R:$R), 0), pagos + retenciones ) -> 553.89952 | Q79: =IF(P79=0, "Sin Pago", LET( idVenta, I79&"", montoTotalPagado, P79, pagoUSD, IFERROR(SUMIFS(Aux_Datos!$C:$C, Aux_Datos!$B:$B, idVenta, Aux_Datos!$D:$D, "USD"), 0), pagoVES, IFERROR(SUMIFS(Aux_Datos!$C:$C, Aux_Datos!$B:$B, idVenta, Aux_Datos!$D:$D, "VES"), 0), IF(pagoUSD >= (montoTotalPagado * 0.84), "USD", IF(pagoVES >= (montoTotalPagado * 0.84), "VES", "MIXTO")) ) ) -> VES | R79: =M79-P79 -> -118.95952 | S79: =IF(P79=0, "Sin Pago", IFERROR( MAXIFS(Aux_Datos!$A:$A, Aux_Datos!$B:$B, I79&""), IFERROR(MAXIFS(Aux_Datos!$A:$A, Aux_Datos!$B:$B, VALUE(I79)), "Revisar ID") ) ) -> 46184 | T79: =IF(R79<=0, "PAGADA", IF(P79>0, "PAGO PARCIAL", "PENDIENTE")) -> PAGADA | U79: =IF(AND(T79<>"PAGADA", L79<TODAY()), "CRÍTICO: VENCIDA", IF(T79="PAGADA", "SOLVENTE", "EN TIEMPO")) -> SOLVENTE | V79: =IF(T79="PAGADA", 0, IF(S79 < TODAY(), TODAY() - S79, 0)) -> 0 | W79: =IF(P79=0, "Sin Pago", LET( monedaPago, Q79, descuentoAplicado, G79, limitePermitido, IFERROR(VLOOKUP(monedaPago, 'Limites de Descuento'!$A$2:$B595, 2, FALSE), 0), IF(descuentoAplicado > limitePermitido, "ALERTA: EXCESO (" & TEXT(limitePermitido, "0%") & " máx)", "OK") ) ) -> OK | X79: =IF(OR(H79=0, S79="Sin Pago"), "", IF(AND(H79 > 0, S79 > (L79 + 2)), "⚠️ REVISAR DESCUENTO", "OK")) | Y79: 553.89952 | Z79: CUMPLE
A80: S00097 | B80: 46097.457 | C80: Felipe Granja | D80: MARTINEZ MONTES JEFFREY ENRIQUE | E80: 530.98 | F80: 15 días | G80: =IF($E80=0,0,IF(SUMIF(Aux_Datos!$B:$B,$I80,Aux_Datos!$K:$K)/$E80>=VLOOKUP(IF(COUNTIFS(Aux_Datos!$B:$B,$I80,Aux_Datos!$D:$D,"<>USD")=0,"USD","VES"),'Limites de Descuento'!$A$2:$D$4,4,FALSE),MAX(0,1-SUMIF(Aux_Datos!$B:$B,$I80,Aux_Datos!$K:$K)/$E80),0)) -> 0 | I80: =VALUE(MID(A80,2,LEN(A80))) -> 97 | J80: =INT(B80) -> 46097 | K80: =IF(F80="Pago inmediato", 0, IF(F80="", "", IFERROR(VALUE(MID(F80, 1, SEARCH(" ", F80)-1)), ""))) -> 15 | L80: =J80+K80+1 -> 46113 | M80: =E80-(E80*G80)-(E80*H80) -> 530.98 | N80: =IF(T80="PAGADA", 0, IF(L80 < TODAY(), TODAY() - L80, 0)) -> 87 | O80: =IF(T80="PAGADA", "PAGADA", IF(L80 < TODAY(), "VENCIDA", "EN TIEMPO")) -> VENCIDA | P80: =LET( idVenta, I80&"", montoTotal, M80, pagos, IFERROR(SUMIF(Aux_Datos!$B:$B, idVenta, Aux_Datos!$K:$K), 0), retenciones, IFERROR(SUMIF(Aux_Datos!$N:$N, idVenta, Aux_Datos!$R:$R), 0), pagos + retenciones ) -> 129.27359 | Q80: =IF(P80=0, "Sin Pago", LET( idVenta, I80&"", montoTotalPagado, P80, pagoUSD, IFERROR(SUMIFS(Aux_Datos!$C:$C, Aux_Datos!$B:$B, idVenta, Aux_Datos!$D:$D, "USD"), 0), pagoVES, IFERROR(SUMIFS(Aux_Datos!$C:$C, Aux_Datos!$B:$B, idVenta, Aux_Datos!$D:$D, "VES"), 0), IF(pagoUSD >= (montoTotalPagado * 0.84), "USD", IF(pagoVES >= (montoTotalPagado * 0.84), "VES", "MIXTO")) ) ) -> VES | R80: =M80-P80 -> 401.70641 | S80: =IF(P80=0, "Sin Pago", IFERROR( MAXIFS(Aux_Datos!$A:$A, Aux_Datos!$B:$B, I80&""), IFERROR(MAXIFS(Aux_Datos!$A:$A, Aux_Datos!$B:$B, VALUE(I80)), "Revisar ID") ) ) -> 46168 | T80: =IF(R80<=0, "PAGADA", IF(P80>0, "PAGO PARCIAL", "PENDIENTE")) -> PAGO PARCIAL | U80: =IF(AND(T80<>"PAGADA", L80<TODAY()), "CRÍTICO: VENCIDA", IF(T80="PAGADA", "SOLVENTE", "EN TIEMPO")) -> CRÍTICO: VENCIDA | V80: =IF(T80="PAGADA", 0, IF(S80 < TODAY(), TODAY() - S80, 0)) -> 32 | W80: =IF(P80=0, "Sin Pago", LET( monedaPago, Q80, descuentoAplicado, G80, limitePermitido, IFERROR(VLOOKUP(monedaPago, 'Limites de Descuento'!$A$2:$B595, 2, FALSE), 0), IF(descuentoAplicado > limitePermitido, "ALERTA: EXCESO (" & TEXT(limitePermitido, "0%") & " máx)", "OK") ) ) -> OK | X80: =IF(OR(H80=0, S80="Sin Pago"), "", IF(AND(H80 > 0, S80 > (L80 + 2)), "⚠️ REVISAR DESCUENTO", "OK")) | Y80: 129.27359 | Z80: NO CUMPLE
A81: S00098 | B81: 46097.409 | C81: Mini Market Las Mercedes,c.a. | D81: CASERES GONZALEZ RONALD OSWALDO | E81: 1623.82 | F81: 30 días | G81: =IF($E81=0,0,IF(SUMIF(Aux_Datos!$B:$B,$I81,Aux_Datos!$K:$K)/$E81>=VLOOKUP(IF(COUNTIFS(Aux_Datos!$B:$B,$I81,Aux_Datos!$D:$D,"<>USD")=0,"USD","VES"),'Limites de Descuento'!$A$2:$D$4,4,FALSE),MAX(0,1-SUMIF(Aux_Datos!$B:$B,$I81,Aux_Datos!$K:$K)/$E81),0)) -> 0 | I81: =VALUE(MID(A81,2,LEN(A81))) -> 98 | J81: =INT(B81) -> 46097 | K81: =IF(F81="Pago inmediato", 0, IF(F81="", "", IFERROR(VALUE(MID(F81, 1, SEARCH(" ", F81)-1)), ""))) -> 30 | L81: =J81+K81+1 -> 46128 | M81: =E81-(E81*G81)-(E81*H81) -> 1623.82 | N81: =IF(T81="PAGADA", 0, IF(L81 < TODAY(), TODAY() - L81, 0)) -> 72 | O81: =IF(T81="PAGADA", "PAGADA", IF(L81 < TODAY(), "VENCIDA", "EN TIEMPO")) -> VENCIDA | P81: =LET( idVenta, I81&"", montoTotal, M81, pagos, IFERROR(SUMIF(Aux_Datos!$B:$B, idVenta, Aux_Datos!$K:$K), 0), retenciones, IFERROR(SUMIF(Aux_Datos!$N:$N, idVenta, Aux_Datos!$R:$R), 0), pagos + retenciones ) -> 0 | Q81: =IF(P81=0, "Sin Pago", LET( idVenta, I81&"", montoTotalPagado, P81, pagoUSD, IFERROR(SUMIFS(Aux_Datos!$C:$C, Aux_Datos!$B:$B, idVenta, Aux_Datos!$D:$D, "USD"), 0), pagoVES, IFERROR(SUMIFS(Aux_Datos!$C:$C, Aux_Datos!$B:$B, idVenta, Aux_Datos!$D:$D, "VES"), 0), IF(pagoUSD >= (montoTotalPagado * 0.84), "USD", IF(pagoVES >= (montoTotalPagado * 0.84), "VES", "MIXTO")) ) ) -> Sin Pago | R81: =M81-P81 -> 1623.82 | S81: =IF(P81=0, "Sin Pago", IFERROR( MAXIFS(Aux_Datos!$A:$A, Aux_Datos!$B:$B, I81&""), IFERROR(MAXIFS(Aux_Datos!$A:$A, Aux_Datos!$B:$B, VALUE(I81)), "Revisar ID") ) ) -> Sin Pago | T81: =IF(R81<=0, "PAGADA", IF(P81>0, "PAGO PARCIAL", "PENDIENTE")) -> PENDIENTE | U81: =IF(AND(T81<>"PAGADA", L81<TODAY()), "CRÍTICO: VENCIDA", IF(T81="PAGADA", "SOLVENTE", "EN TIEMPO")) -> CRÍTICO: VENCIDA | V81: =IF(T81="PAGADA", 0, IF(S81 < TODAY(), TODAY() - S81, 0)) -> 0 | W81: =IF(P81=0, "Sin Pago", LET( monedaPago, Q81, descuentoAplicado, G81, limitePermitido, IFERROR(VLOOKUP(monedaPago, 'Limites de Descuento'!$A$2:$B595, 2, FALSE), 0), IF(descuentoAplicado > limitePermitido, "ALERTA: EXCESO (" & TEXT(limitePermitido, "0%") & " máx)", "OK") ) ) -> Sin Pago | X81: =IF(OR(H81=0, S81="Sin Pago"), "", IF(AND(H81 > 0, S81 > (L81 + 2)), "⚠️ REVISAR DESCUENTO", "OK")) | Y81: 0 | Z81: SIN MONEDA VÁLIDA
A82: S00099 | B82: 46097.488 | C82: ZIP MARKET, CA | D82: QUEVEDO BASTIDAS NEYKEL DAVID | E82: 93 | F82: 15 días | G82: =IF($E82=0,0,IF(SUMIF(Aux_Datos!$B:$B,$I82,Aux_Datos!$K:$K)/$E82>=VLOOKUP(IF(COUNTIFS(Aux_Datos!$B:$B,$I82,Aux_Datos!$D:$D,"<>USD")=0,"USD","VES"),'Limites de Descuento'!$A$2:$D$4,4,FALSE),MAX(0,1-SUMIF(Aux_Datos!$B:$B,$I82,Aux_Datos!$K:$K)/$E82),0)) -> 0.00075500831 | I82: =VALUE(MID(A82,2,LEN(A82))) -> 99 | J82: =INT(B82) -> 46097 | K82: =IF(F82="Pago inmediato", 0, IF(F82="", "", IFERROR(VALUE(MID(F82, 1, SEARCH(" ", F82)-1)), ""))) -> 15 | L82: =J82+K82+1 -> 46113 | M82: =E82-(E82*G82)-(E82*H82) -> 92.929784 | N82: =IF(T82="PAGADA", 0, IF(L82 < TODAY(), TODAY() - L82, 0)) -> 0 | O82: =IF(T82="PAGADA", "PAGADA", IF(L82 < TODAY(), "VENCIDA", "EN TIEMPO")) -> PAGADA | P82: =LET( idVenta, I82&"", montoTotal, M82, pagos, IFERROR(SUMIF(Aux_Datos!$B:$B, idVenta, Aux_Datos!$K:$K), 0), retenciones, IFERROR(SUMIF(Aux_Datos!$N:$N, idVenta, Aux_Datos!$R:$R), 0), pagos + retenciones ) -> 92.929784 | Q82: =IF(P82=0, "Sin Pago", LET( idVenta, I82&"", montoTotalPagado, P82, pagoUSD, IFERROR(SUMIFS(Aux_Datos!$C:$C, Aux_Datos!$B:$B, idVenta, Aux_Datos!$D:$D, "USD"), 0), pagoVES, IFERROR(SUMIFS(Aux_Datos!$C:$C, Aux_Datos!$B:$B, idVenta, Aux_Datos!$D:$D, "VES"), 0), IF(pagoUSD >= (montoTotalPagado * 0.84), "USD", IF(pagoVES >= (montoTotalPagado * 0.84), "VES", "MIXTO")) ) ) -> VES | R82: =M82-P82 -> 0 | S82: =IF(P82=0, "Sin Pago", IFERROR( MAXIFS(Aux_Datos!$A:$A, Aux_Datos!$B:$B, I82&""), IFERROR(MAXIFS(Aux_Datos!$A:$A, Aux_Datos!$B:$B, VALUE(I82)), "Revisar ID") ) ) -> 46157 | T82: =IF(R82<=0, "PAGADA", IF(P82>0, "PAGO PARCIAL", "PENDIENTE")) -> PAGADA | U82: =IF(AND(T82<>"PAGADA", L82<TODAY()), "CRÍTICO: VENCIDA", IF(T82="PAGADA", "SOLVENTE", "EN TIEMPO")) -> SOLVENTE | V82: =IF(T82="PAGADA", 0, IF(S82 < TODAY(), TODAY() - S82, 0)) -> 0 | W82: =IF(P82=0, "Sin Pago", LET( monedaPago, Q82, descuentoAplicado, G82, limitePermitido, IFERROR(VLOOKUP(monedaPago, 'Limites de Descuento'!$A$2:$B595, 2, FALSE), 0), IF(descuentoAplicado > limitePermitido, "ALERTA: EXCESO (" & TEXT(limitePermitido, "0%") & " máx)", "OK") ) ) -> OK | X82: =IF(OR(H82=0, S82="Sin Pago"), "", IF(AND(H82 > 0, S82 > (L82 + 2)), "⚠️ REVISAR DESCUENTO", "OK")) | Y82: 92.929784 | Z82: CUMPLE
A83: S00100 | B83: 46098.657 | C83: Diana Carolina Torres | D83: VILLABONA CORREA ALBA ESTEFANIA | E83: 197.55 | F83: 7 días | G83: =IF($E83=0,0,IF(SUMIF(Aux_Datos!$B:$B,$I83,Aux_Datos!$K:$K)/$E83>=VLOOKUP(IF(COUNTIFS(Aux_Datos!$B:$B,$I83,Aux_Datos!$D:$D,"<>USD")=0,"USD","VES"),'Limites de Descuento'!$A$2:$D$4,4,FALSE),MAX(0,1-SUMIF(Aux_Datos!$B:$B,$I83,Aux_Datos!$K:$K)/$E83),0)) -> 0.018374083 | I83: =VALUE(MID(A83,2,LEN(A83))) -> 100 | J83: =INT(B83) -> 46098 | K83: =IF(F83="Pago inmediato", 0, IF(F83="", "", IFERROR(VALUE(MID(F83, 1, SEARCH(" ", F83)-1)), ""))) -> 7 | L83: =J83+K83+1 -> 46106 | M83: =E83-(E83*G83)-(E83*H83) -> 193.9202 | N83: =IF(T83="PAGADA", 0, IF(L83 < TODAY(), TODAY() - L83, 0)) -> 0 | O83: =IF(T83="PAGADA", "PAGADA", IF(L83 < TODAY(), "VENCIDA", "EN TIEMPO")) -> PAGADA | P83: =LET( idVenta, I83&"", montoTotal, M83, pagos, IFERROR(SUMIF(Aux_Datos!$B:$B, idVenta, Aux_Datos!$K:$K), 0), retenciones, IFERROR(SUMIF(Aux_Datos!$N:$N, idVenta, Aux_Datos!$R:$R), 0), pagos + retenciones ) -> 193.9202 | Q83: =IF(P83=0, "Sin Pago", LET( idVenta, I83&"", montoTotalPagado, P83, pagoUSD, IFERROR(SUMIFS(Aux_Datos!$C:$C, Aux_Datos!$B:$B, idVenta, Aux_Datos!$D:$D, "USD"), 0), pagoVES, IFERROR(SUMIFS(Aux_Datos!$C:$C, Aux_Datos!$B:$B, idVenta, Aux_Datos!$D:$D, "VES"), 0), IF(pagoUSD >= (montoTotalPagado * 0.84), "USD", IF(pagoVES >= (montoTotalPagado * 0.84), "VES", "MIXTO")) ) ) -> VES | R83: =M83-P83 -> 0 | S83: =IF(P83=0, "Sin Pago", IFERROR( MAXIFS(Aux_Datos!$A:$A, Aux_Datos!$B:$B, I83&""), IFERROR(MAXIFS(Aux_Datos!$A:$A, Aux_Datos!$B:$B, VALUE(I83)), "Revisar ID") ) ) -> 46136 | T83: =IF(R83<=0, "PAGADA", IF(P83>0, "PAGO PARCIAL", "PENDIENTE")) -> PAGADA | U83: =IF(AND(T83<>"PAGADA", L83<TODAY()), "CRÍTICO: VENCIDA", IF(T83="PAGADA", "SOLVENTE", "EN TIEMPO")) -> SOLVENTE | V83: =IF(T83="PAGADA", 0, IF(S83 < TODAY(), TODAY() - S83, 0)) -> 0 | W83: =IF(P83=0, "Sin Pago", LET( monedaPago, Q83, descuentoAplicado, G83, limitePermitido, IFERROR(VLOOKUP(monedaPago, 'Limites de Descuento'!$A$2:$B595, 2, FALSE), 0), IF(descuentoAplicado > limitePermitido, "ALERTA: EXCESO (" & TEXT(limitePermitido, "0%") & " máx)", "OK") ) ) -> OK | X83: =IF(OR(H83=0, S83="Sin Pago"), "", IF(AND(H83 > 0, S83 > (L83 + 2)), "⚠️ REVISAR DESCUENTO", "OK")) | Y83: 193.9202 | Z83: CUMPLE
A84: S00101 | B84: 46098.657 | C84: INVERSIONES JOSCAR XXI, S.A. | D84: VILLABONA CORREA ALBA ESTEFANIA | E84: 184.1 | F84: 7 días | G84: =IF($E84=0,0,IF(SUMIF(Aux_Datos!$B:$B,$I84,Aux_Datos!$K:$K)/$E84>=VLOOKUP(IF(COUNTIFS(Aux_Datos!$B:$B,$I84,Aux_Datos!$D:$D,"<>USD")=0,"USD","VES"),'Limites de Descuento'!$A$2:$D$4,4,FALSE),MAX(0,1-SUMIF(Aux_Datos!$B:$B,$I84,Aux_Datos!$K:$K)/$E84),0)) -> 0 | I84: =VALUE(MID(A84,2,LEN(A84))) -> 101 | J84: =INT(B84) -> 46098 | K84: =IF(F84="Pago inmediato", 0, IF(F84="", "", IFERROR(VALUE(MID(F84, 1, SEARCH(" ", F84)-1)), ""))) -> 7 | L84: =J84+K84+1 -> 46106 | M84: =E84-(E84*G84)-(E84*H84) -> 184.1 | N84: =IF(T84="PAGADA", 0, IF(L84 < TODAY(), TODAY() - L84, 0)) -> 94 | O84: =IF(T84="PAGADA", "PAGADA", IF(L84 < TODAY(), "VENCIDA", "EN TIEMPO")) -> VENCIDA | P84: =LET( idVenta, I84&"", montoTotal, M84, pagos, IFERROR(SUMIF(Aux_Datos!$B:$B, idVenta, Aux_Datos!$K:$K), 0), retenciones, IFERROR(SUMIF(Aux_Datos!$N:$N, idVenta, Aux_Datos!$R:$R), 0), pagos + retenciones ) -> 115 | Q84: =IF(P84=0, "Sin Pago", LET( idVenta, I84&"", montoTotalPagado, P84, pagoUSD, IFERROR(SUMIFS(Aux_Datos!$C:$C, Aux_Datos!$B:$B, idVenta, Aux_Datos!$D:$D, "USD"), 0), pagoVES, IFERROR(SUMIFS(Aux_Datos!$C:$C, Aux_Datos!$B:$B, idVenta, Aux_Datos!$D:$D, "VES"), 0), IF(pagoUSD >= (montoTotalPagado * 0.84), "USD", IF(pagoVES >= (montoTotalPagado * 0.84), "VES", "MIXTO")) ) ) -> USD | R84: =M84-P84 -> 69.1 | S84: =IF(P84=0, "Sin Pago", IFERROR( MAXIFS(Aux_Datos!$A:$A, Aux_Datos!$B:$B, I84&""), IFERROR(MAXIFS(Aux_Datos!$A:$A, Aux_Datos!$B:$B, VALUE(I84)), "Revisar ID") ) ) -> 46142 | T84: =IF(R84<=0, "PAGADA", IF(P84>0, "PAGO PARCIAL", "PENDIENTE")) -> PAGO PARCIAL | U84: =IF(AND(T84<>"PAGADA", L84<TODAY()), "CRÍTICO: VENCIDA", IF(T84="PAGADA", "SOLVENTE", "EN TIEMPO")) -> CRÍTICO: VENCIDA | V84: =IF(T84="PAGADA", 0, IF(S84 < TODAY(), TODAY() - S84, 0)) -> 58 | W84: =IF(P84=0, "Sin Pago", LET( monedaPago, Q84, descuentoAplicado, G84, limitePermitido, IFERROR(VLOOKUP(monedaPago, 'Limites de Descuento'!$A$2:$B595, 2, FALSE), 0), IF(descuentoAplicado > limitePermitido, "ALERTA: EXCESO (" & TEXT(limitePermitido, "0%") & " máx)", "OK") ) ) -> OK | X84: =IF(OR(H84=0, S84="Sin Pago"), "", IF(AND(H84 > 0, S84 > (L84 + 2)), "⚠️ REVISAR DESCUENTO", "OK")) | Y84: 115 | Z84: NO CUMPLE
A85: S00103 | B85: 46098.658 | C85: Alexis Rodríguez Fernández | D85: PEREZ DIAZ ANGEL DE DIOS | E85: 711.13 | F85: 30 días | G85: =IF($E85=0,0,IF(SUMIF(Aux_Datos!$B:$B,$I85,Aux_Datos!$K:$K)/$E85>=VLOOKUP(IF(COUNTIFS(Aux_Datos!$B:$B,$I85,Aux_Datos!$D:$D,"<>USD")=0,"USD","VES"),'Limites de Descuento'!$A$2:$D$4,4,FALSE),MAX(0,1-SUMIF(Aux_Datos!$B:$B,$I85,Aux_Datos!$K:$K)/$E85),0)) -> 0 | I85: =VALUE(MID(A85,2,LEN(A85))) -> 103 | J85: =INT(B85) -> 46098 | K85: =IF(F85="Pago inmediato", 0, IF(F85="", "", IFERROR(VALUE(MID(F85, 1, SEARCH(" ", F85)-1)), ""))) -> 30 | L85: =J85+K85+1 -> 46129 | M85: =E85-(E85*G85)-(E85*H85) -> 711.13 | N85: =IF(T85="PAGADA", 0, IF(L85 < TODAY(), TODAY() - L85, 0)) -> 71 | O85: =IF(T85="PAGADA", "PAGADA", IF(L85 < TODAY(), "VENCIDA", "EN TIEMPO")) -> VENCIDA | P85: =LET( idVenta, I85&"", montoTotal, M85, pagos, IFERROR(SUMIF(Aux_Datos!$B:$B, idVenta, Aux_Datos!$K:$K), 0), retenciones, IFERROR(SUMIF(Aux_Datos!$N:$N, idVenta, Aux_Datos!$R:$R), 0), pagos + retenciones ) -> 100 | Q85: =IF(P85=0, "Sin Pago", LET( idVenta, I85&"", montoTotalPagado, P85, pagoUSD, IFERROR(SUMIFS(Aux_Datos!$C:$C, Aux_Datos!$B:$B, idVenta, Aux_Datos!$D:$D, "USD"), 0), pagoVES, IFERROR(SUMIFS(Aux_Datos!$C:$C, Aux_Datos!$B:$B, idVenta, Aux_Datos!$D:$D, "VES"), 0), IF(pagoUSD >= (montoTotalPagado * 0.84), "USD", IF(pagoVES >= (montoTotalPagado * 0.84), "VES", "MIXTO")) ) ) -> USD | R85: =M85-P85 -> 611.13 | S85: =IF(P85=0, "Sin Pago", IFERROR( MAXIFS(Aux_Datos!$A:$A, Aux_Datos!$B:$B, I85&""), IFERROR(MAXIFS(Aux_Datos!$A:$A, Aux_Datos!$B:$B, VALUE(I85)), "Revisar ID") ) ) -> 46154 | T85: =IF(R85<=0, "PAGADA", IF(P85>0, "PAGO PARCIAL", "PENDIENTE")) -> PAGO PARCIAL | U85: =IF(AND(T85<>"PAGADA", L85<TODAY()), "CRÍTICO: VENCIDA", IF(T85="PAGADA", "SOLVENTE", "EN TIEMPO")) -> CRÍTICO: VENCIDA | V85: =IF(T85="PAGADA", 0, IF(S85 < TODAY(), TODAY() - S85, 0)) -> 46 | W85: =IF(P85=0, "Sin Pago", LET( monedaPago, Q85, descuentoAplicado, G85, limitePermitido, IFERROR(VLOOKUP(monedaPago, 'Limites de Descuento'!$A$2:$B595, 2, FALSE), 0), IF(descuentoAplicado > limitePermitido, "ALERTA: EXCESO (" & TEXT(limitePermitido, "0%") & " máx)", "OK") ) ) -> OK | X85: =IF(OR(H85=0, S85="Sin Pago"), "", IF(AND(H85 > 0, S85 > (L85 + 2)), "⚠️ REVISAR DESCUENTO", "OK")) | Y85: 100 | Z85: NO CUMPLE
A86: S00104 | B86: 46098.658 | C86: Inversiones Brayan CT C.A | D86: GRIMAN DIAZ HECTOR EDUARDO | E86: 297.02 | F86: 15 días | G86: =IF($E86=0,0,IF(SUMIF(Aux_Datos!$B:$B,$I86,Aux_Datos!$K:$K)/$E86>=VLOOKUP(IF(COUNTIFS(Aux_Datos!$B:$B,$I86,Aux_Datos!$D:$D,"<>USD")=0,"USD","VES"),'Limites de Descuento'!$A$2:$D$4,4,FALSE),MAX(0,1-SUMIF(Aux_Datos!$B:$B,$I86,Aux_Datos!$K:$K)/$E86),0)) -> 0.33337822 | I86: =VALUE(MID(A86,2,LEN(A86))) -> 104 | J86: =INT(B86) -> 46098 | K86: =IF(F86="Pago inmediato", 0, IF(F86="", "", IFERROR(VALUE(MID(F86, 1, SEARCH(" ", F86)-1)), ""))) -> 15 | L86: =J86+K86+1 -> 46114 | M86: =E86-(E86*G86)-(E86*H86) -> 198 | N86: =IF(T86="PAGADA", 0, IF(L86 < TODAY(), TODAY() - L86, 0)) -> 0 | O86: =IF(T86="PAGADA", "PAGADA", IF(L86 < TODAY(), "VENCIDA", "EN TIEMPO")) -> PAGADA | P86: =LET( idVenta, I86&"", montoTotal, M86, pagos, IFERROR(SUMIF(Aux_Datos!$B:$B, idVenta, Aux_Datos!$K:$K), 0), retenciones, IFERROR(SUMIF(Aux_Datos!$N:$N, idVenta, Aux_Datos!$R:$R), 0), pagos + retenciones ) -> 198 | Q86: =IF(P86=0, "Sin Pago", LET( idVenta, I86&"", montoTotalPagado, P86, pagoUSD, IFERROR(SUMIFS(Aux_Datos!$C:$C, Aux_Datos!$B:$B, idVenta, Aux_Datos!$D:$D, "USD"), 0), pagoVES, IFERROR(SUMIFS(Aux_Datos!$C:$C, Aux_Datos!$B:$B, idVenta, Aux_Datos!$D:$D, "VES"), 0), IF(pagoUSD >= (montoTotalPagado * 0.84), "USD", IF(pagoVES >= (montoTotalPagado * 0.84), "VES", "MIXTO")) ) ) -> USD | R86: =M86-P86 -> 0 | S86: =IF(P86=0, "Sin Pago", IFERROR( MAXIFS(Aux_Datos!$A:$A, Aux_Datos!$B:$B, I86&""), IFERROR(MAXIFS(Aux_Datos!$A:$A, Aux_Datos!$B:$B, VALUE(I86)), "Revisar ID") ) ) -> 46140 | T86: =IF(R86<=0, "PAGADA", IF(P86>0, "PAGO PARCIAL", "PENDIENTE")) -> PAGADA | U86: =IF(AND(T86<>"PAGADA", L86<TODAY()), "CRÍTICO: VENCIDA", IF(T86="PAGADA", "SOLVENTE", "EN TIEMPO")) -> SOLVENTE | V86: =IF(T86="PAGADA", 0, IF(S86 < TODAY(), TODAY() - S86, 0)) -> 0 | W86: =IF(P86=0, "Sin Pago", LET( monedaPago, Q86, descuentoAplicado, G86, limitePermitido, IFERROR(VLOOKUP(monedaPago, 'Limites de Descuento'!$A$2:$B595, 2, FALSE), 0), IF(descuentoAplicado > limitePermitido, "ALERTA: EXCESO (" & TEXT(limitePermitido, "0%") & " máx)", "OK") ) ) -> OK | X86: =IF(OR(H86=0, S86="Sin Pago"), "", IF(AND(H86 > 0, S86 > (L86 + 2)), "⚠️ REVISAR DESCUENTO", "OK")) | Y86: 198 | Z86: CUMPLE
A87: S00105 | B87: 46098.658 | C87: Ricardo A. Fernandez. | D87: MARTINEZ MONTES JEFFREY ENRIQUE | E87: 280.5 | F87: 15 días | G87: =IF($E87=0,0,IF(SUMIF(Aux_Datos!$B:$B,$I87,Aux_Datos!$K:$K)/$E87>=VLOOKUP(IF(COUNTIFS(Aux_Datos!$B:$B,$I87,Aux_Datos!$D:$D,"<>USD")=0,"USD","VES"),'Limites de Descuento'!$A$2:$D$4,4,FALSE),MAX(0,1-SUMIF(Aux_Datos!$B:$B,$I87,Aux_Datos!$K:$K)/$E87),0)) -> 0 | I87: =VALUE(MID(A87,2,LEN(A87))) -> 105 | J87: =INT(B87) -> 46098 | K87: =IF(F87="Pago inmediato", 0, IF(F87="", "", IFERROR(VALUE(MID(F87, 1, SEARCH(" ", F87)-1)), ""))) -> 15 | L87: =J87+K87+1 -> 46114 | M87: =E87-(E87*G87)-(E87*H87) -> 280.5 | N87: =IF(T87="PAGADA", 0, IF(L87 < TODAY(), TODAY() - L87, 0)) -> 0 | O87: =IF(T87="PAGADA", "PAGADA", IF(L87 < TODAY(), "VENCIDA", "EN TIEMPO")) -> PAGADA | P87: =LET( idVenta, I87&"", montoTotal, M87, pagos, IFERROR(SUMIF(Aux_Datos!$B:$B, idVenta, Aux_Datos!$K:$K), 0), retenciones, IFERROR(SUMIF(Aux_Datos!$N:$N, idVenta, Aux_Datos!$R:$R), 0), pagos + retenciones ) -> 280.90583 | Q87: =IF(P87=0, "Sin Pago", LET( idVenta, I87&"", montoTotalPagado, P87, pagoUSD, IFERROR(SUMIFS(Aux_Datos!$C:$C, Aux_Datos!$B:$B, idVenta, Aux_Datos!$D:$D, "USD"), 0), pagoVES, IFERROR(SUMIFS(Aux_Datos!$C:$C, Aux_Datos!$B:$B, idVenta, Aux_Datos!$D:$D, "VES"), 0), IF(pagoUSD >= (montoTotalPagado * 0.84), "USD", IF(pagoVES >= (montoTotalPagado * 0.84), "VES", "MIXTO")) ) ) -> VES | R87: =M87-P87 -> -0.40583351 | S87: =IF(P87=0, "Sin Pago", IFERROR( MAXIFS(Aux_Datos!$A:$A, Aux_Datos!$B:$B, I87&""), IFERROR(MAXIFS(Aux_Datos!$A:$A, Aux_Datos!$B:$B, VALUE(I87)), "Revisar ID") ) ) -> 46156 | T87: =IF(R87<=0, "PAGADA", IF(P87>0, "PAGO PARCIAL", "PENDIENTE")) -> PAGADA | U87: =IF(AND(T87<>"PAGADA", L87<TODAY()), "CRÍTICO: VENCIDA", IF(T87="PAGADA", "SOLVENTE", "EN TIEMPO")) -> SOLVENTE | V87: =IF(T87="PAGADA", 0, IF(S87 < TODAY(), TODAY() - S87, 0)) -> 0 | W87: =IF(P87=0, "Sin Pago", LET( monedaPago, Q87, descuentoAplicado, G87, limitePermitido, IFERROR(VLOOKUP(monedaPago, 'Limites de Descuento'!$A$2:$B595, 2, FALSE), 0), IF(descuentoAplicado > limitePermitido, "ALERTA: EXCESO (" & TEXT(limitePermitido, "0%") & " máx)", "OK") ) ) -> OK | X87: =IF(OR(H87=0, S87="Sin Pago"), "", IF(AND(H87 > 0, S87 > (L87 + 2)), "⚠️ REVISAR DESCUENTO", "OK")) | Y87: 280.90583 | Z87: CUMPLE
